Workbook

Sheet BB816使い方
A1: BB816 ― ボリンジャーバンド判定を切り離して、スイング用に組み直したブック
A2: 300銘柄 × 250営業日（2025-07-29〜2026-08-06）の実データで検証した結果に基づいています。
A3: 指標の計算は V815 の BBスクリーニング と突き合わせ、300銘柄すべてで一致することを確認済みです。
A5: ■ 売買ルール（これだけ守れば動く）
A6: 入口 終値が +2σ を上抜け、かつ 出来高が直近5日平均の1.5倍以上、
A7: かつ MFI14 が 55以上、かつ RSI14 が 80以下
A8: 順位 BB816スコアの高い順。1日に建てるのは最大3銘柄
A9: 建て方 翌営業日の寄付（始値）で買う
A10: 枠 資金を8等分。1銘柄あたり12.5%。同じ銘柄を重ねて持たない
A11: 損切り 建値から -8%。買えたその日に逆指値を置く
A12: 手仕舞い 10営業日たったら損益に関わらず引けで売る
A13: 置かない 利確目標・トレーリングストップ・地合いフィルタ（いずれも検証で成績を下げた）
... A73: ※ 楽天RSSアドインが入っていないパソコンでも開けます。

Sheet BB816候補
A1: 🏆 BB816 明日の買い候補
A2: 総合判定が「◎買い」の銘柄を、翌営業日の寄付で買う。1日に建てるのは上から最大3銘柄まで。1銘柄は資金の1÷枠数（既定8枠＝12.5%）。
A3: ◎買いの件数 | C3: =COUNTIF(BB816判定!$S$6:$S$505,"◎買い") | D3: SMA20より上の銘柄の割合（地合いの参考。売買条件には使いません） | H3: =IFERROR(SUMPRODUCT((BB816判定!$D$6:$D$505<>"")*(BB816判定!$D$6:$D$505>BB816判定!$E$6:$E$505))/COUNT(BB816判定!$D$6:$D$505),"") | I3: データ最終日 | K3: =終値!E3
A4: 順位 | B4: コード | C4: 銘柄名 | D4: 現在値 | E4: BB816 スコア | F4: 総合判定 | G4: 守り 分析官 | H4: 攻め 分析官 | I4: RSI14 | J4: MFI14 | K4: 出来高 倍率 | L4: 20日 騰落率 | M4: エントリー (翌日寄付) | N4: 損切り 価格 | O4: 必要資金 (100株) | P4: 資金枠に 収まるか | Q4: 株探
A5: 1 | B5: =IFERROR(INDEX(BB816判定!$B$6:$B$505,MATCH(LARGE(BB816判定!$Y$6:$Y$505,$A5),BB816判定!$Y$6:$Y$505,0)),"") | C5: =IFERROR(INDEX(BB816判定!$C$6:$C$505,MATCH(LARGE(BB816判定!$Y$6:$Y$505,$A5),BB816判定!$Y$6:$Y$505,0)),"") | D5: =IFERROR(INDEX(BB816判定!$D$6:$D$505,MATCH(LARGE(BB816判定!$Y$6:$Y$505,$A5),BB816判定!$Y$6:$Y$505,0)),"") | E5: =IFERROR(INDEX(BB816判定!$Q$6:$Q$505,MATCH(LARGE(BB816判定!$Y$6:$Y$505,$A5),BB816判定!$Y$6:$Y$505,0)),"") | F5: =IFERROR(INDEX(BB816判定!$S$6:$S$505,MATCH(LARGE(BB816判定!$Y$6:$Y$505,$A5),BB816判定!$Y$6:$Y$505,0)),"") | G5: =IFERROR(INDEX(BB816判定!$T$6:$T$505,MATCH(LARGE(BB816判定!$Y$6:$Y$505,$A5),BB816判定!$Y$6:$Y$505,0)),"") | H5: =IFERROR(INDEX(BB816判定!$U$6:$U$505,MATCH(LARGE(BB816判定!$Y$6:$Y$505,$A5),BB816判定!$Y$6:$Y$505,0)),"") | I5: =IFERROR(INDEX(BB816判定!$M$6:$M$505,MATCH(LARGE(BB816判定!$Y$6:$Y$505,$A5),BB816判定!$Y$6:$Y$505,0)),"") | J5: =IFERROR(INDEX(BB816判定!$N$6:$N$505,MATCH(LARGE(BB816判定!$Y$6:$Y$505,$A5),BB816判定!$Y$6:$Y$505,0)),"") | K5: =IFERROR(INDEX(BB816判定!$O$6:$O$505,MATCH(LARGE(BB816判定!$Y$6:$Y$505,$A5),BB816判定!$Y$6:$Y$505,0)),"") | L5: =IFERROR(INDEX(BB816判定!$P$6:$P$505,MATCH(LARGE(BB816判定!$Y$6:$Y$505,$A5),BB816判定!$Y$6:$Y$505,0)),"") | M5: =IFERROR(INDEX(BB816判定!$V$6:$V$505,MATCH(LARGE(BB816判定!$Y$6:$Y$505,$A5),BB816判定!$Y$6:$Y$505,0)),"") | N5: =IFERROR(INDEX(BB816判定!$W$6:$W$505,MATCH(LARGE(BB816判定!$Y$6:$Y$505,$A5),BB816判定!$Y$6:$Y$505,0)),"") | O5: =IFERROR(INDEX(BB816判定!$Z$6:$Z$505,MATCH(LARGE(BB816判定!$Y$6:$Y$505,$A5),BB816判定!$Y$6:$Y$505,0)),"") | P5: =IFERROR(INDEX(BB816判定!$AA$6:$AA$505,MATCH(LARGE(BB816判定!$Y$6:$Y$505,$A5),BB816判定!$Y$6:$Y$505,0)),"") | Q5: =IF($B5="","",HYPERLINK("https://kabutan.jp/stock/?code="&$B5,"📈"))
A6: 2 | B6: =IFERROR(INDEX(BB816判定!$B$6:$B$505,MATCH(LARGE(BB816判定!$Y$6:$Y$505,$A6),BB816判定!$Y$6:$Y$505,0)),"") | C6: =IFERROR(INDEX(BB816判定!$C$6:$C$505,MATCH(LARGE(BB816判定!$Y$6:$Y$505,$A6),BB816判定!$Y$6:$Y$505,0)),"") | D6: =IFERROR(INDEX(BB816判定!$D$6:$D$505,MATCH(LARGE(BB816判定!$Y$6:$Y$505,$A6),BB816判定!$Y$6:$Y$505,0)),"") | E6: =IFERROR(INDEX(BB816判定!$Q$6:$Q$505,MATCH(LARGE(BB816判定!$Y$6:$Y$505,$A6),BB816判定!$Y$6:$Y$505,0)),"") | F6: =IFERROR(INDEX(BB816判定!$S$6:$S$505,MATCH(LARGE(BB816判定!$Y$6:$Y$505,$A6),BB816判定!$Y$6:$Y$505,0)),"") | G6: =IFERROR(INDEX(BB816判定!$T$6:$T$505,MATCH(LARGE(BB816判定!$Y$6:$Y$505,$A6),BB816判定!$Y$6:$Y$505,0)),"") | H6: =IFERROR(INDEX(BB816判定!$U$6:$U$505,MATCH(LARGE(BB816判定!$Y$6:$Y$505,$A6),BB816判定!$Y$6:$Y$505,0)),"") | I6: =IFERROR(INDEX(BB816判定!$M$6:$M$505,MATCH(LARGE(BB816判定!$Y$6:$Y$505,$A6),BB816判定!$Y$6:$Y$505,0)),"") | J6: =IFERROR(INDEX(BB816判定!$N$6:$N$505,MATCH(LARGE(BB816判定!$Y$6:$Y$505,$A6),BB816判定!$Y$6:$Y$505,0)),"") | K6: =IFERROR(INDEX(BB816判定!$O$6:$O$505,MATCH(LARGE(BB816判定!$Y$6:$Y$505,$A6),BB816判定!$Y$6:$Y$505,0)),"") | L6: =IFERROR(INDEX(BB816判定!$P$6:$P$505,MATCH(LARGE(BB816判定!$Y$6:$Y$505,$A6),BB816判定!$Y$6:$Y$505,0)),"") | M6: =IFERROR(INDEX(BB816判定!$V$6:$V$505,MATCH(LARGE(BB816判定!$Y$6:$Y$505,$A6),BB816判定!$Y$6:$Y$505,0)),"") | N6: =IFERROR(INDEX(BB816判定!$W$6:$W$505,MATCH(LARGE(BB816判定!$Y$6:$Y$505,$A6),BB816判定!$Y$6:$Y$505,0)),"") | O6: =IFERROR(INDEX(BB816判定!$Z$6:$Z$505,MATCH(LARGE(BB816判定!$Y$6:$Y$505,$A6),BB816判定!$Y$6:$Y$505,0)),"") | P6: =IFERROR(INDEX(BB816判定!$AA$6:$AA$505,MATCH(LARGE(BB816判定!$Y$6:$Y$505,$A6),BB816判定!$Y$6:$Y$505,0)),"") | Q6: =IF($B6="","",HYPERLINK("https://kabutan.jp/stock/?code="&$B6,"📈"))
A7: 3 | B7: =IFERROR(INDEX(BB816判定!$B$6:$B$505,MATCH(LARGE(BB816判定!$Y$6:$Y$505,$A7),BB816判定!$Y$6:$Y$505,0)),"") | C7: =IFERROR(INDEX(BB816判定!$C$6:$C$505,MATCH(LARGE(BB816判定!$Y$6:$Y$505,$A7),BB816判定!$Y$6:$Y$505,0)),"") | D7: =IFERROR(INDEX(BB816判定!$D$6:$D$505,MATCH(LARGE(BB816判定!$Y$6:$Y$505,$A7),BB816判定!$Y$6:$Y$505,0)),"") | E7: =IFERROR(INDEX(BB816判定!$Q$6:$Q$505,MATCH(LARGE(BB816判定!$Y$6:$Y$505,$A7),BB816判定!$Y$6:$Y$505,0)),"") | F7: =IFERROR(INDEX(BB816判定!$S$6:$S$505,MATCH(LARGE(BB816判定!$Y$6:$Y$505,$A7),BB816判定!$Y$6:$Y$505,0)),"") | G7: =IFERROR(INDEX(BB816判定!$T$6:$T$505,MATCH(LARGE(BB816判定!$Y$6:$Y$505,$A7),BB816判定!$Y$6:$Y$505,0)),"") | H7: =IFERROR(INDEX(BB816判定!$U$6:$U$505,MATCH(LARGE(BB816判定!$Y$6:$Y$505,$A7),BB816判定!$Y$6:$Y$505,0)),"") | I7: =IFERROR(INDEX(BB816判定!$M$6:$M$505,MATCH(LARGE(BB816判定!$Y$6:$Y$505,$A7),BB816判定!$Y$6:$Y$505,0)),"") | J7: =IFERROR(INDEX(BB816判定!$N$6:$N$505,MATCH(LARGE(BB816判定!$Y$6:$Y$505,$A7),BB816判定!$Y$6:$Y$505,0)),"") | K7: =IFERROR(INDEX(BB816判定!$O$6:$O$505,MATCH(LARGE(BB816判定!$Y$6:$Y$505,$A7),BB816判定!$Y$6:$Y$505,0)),"") | L7: =IFERROR(INDEX(BB816判定!$P$6:$P$505,MATCH(LARGE(BB816判定!$Y$6:$Y$505,$A7),BB816判定!$Y$6:$Y$505,0)),"") | M7: =IFERROR(INDEX(BB816判定!$V$6:$V$505,MATCH(LARGE(BB816判定!$Y$6:$Y$505,$A7),BB816判定!$Y$6:$Y$505,0)),"") | N7: =IFERROR(INDEX(BB816判定!$W$6:$W$505,MATCH(LARGE(BB816判定!$Y$6:$Y$505,$A7),BB816判定!$Y$6:$Y$505,0)),"") | O7: =IFERROR(INDEX(BB816判定!$Z$6:$Z$505,MATCH(LARGE(BB816判定!$Y$6:$Y$505,$A7),BB816判定!$Y$6:$Y$505,0)),"") | P7: =IFERROR(INDEX(BB816判定!$AA$6:$AA$505,MATCH(LARGE(BB816判定!$Y$6:$Y$505,$A7),BB816判定!$Y$6:$Y$505,0)),"") | Q7: =IF($B7="","",HYPERLINK("https://kabutan.jp/stock/?code="&$B7,"📈"))
A8: 4 | B8: =IFERROR(INDEX(BB816判定!$B$6:$B$505,MATCH(LARGE(BB816判定!$Y$6:$Y$505,$A8),BB816判定!$Y$6:$Y$505,0)),"") | C8: =IFERROR(INDEX(BB816判定!$C$6:$C$505,MATCH(LARGE(BB816判定!$Y$6:$Y$505,$A8),BB816判定!$Y$6:$Y$505,0)),"") | D8: =IFERROR(INDEX(BB816判定!$D$6:$D$505,MATCH(LARGE(BB816判定!$Y$6:$Y$505,$A8),BB816判定!$Y$6:$Y$505,0)),"") | E8: =IFERROR(INDEX(BB816判定!$Q$6:$Q$505,MATCH(LARGE(BB816判定!$Y$6:$Y$505,$A8),BB816判定!$Y$6:$Y$505,0)),"") | F8: =IFERROR(INDEX(BB816判定!$S$6:$S$505,MATCH(LARGE(BB816判定!$Y$6:$Y$505,$A8),BB816判定!$Y$6:$Y$505,0)),"") | G8: =IFERROR(INDEX(BB816判定!$T$6:$T$505,MATCH(LARGE(BB816判定!$Y$6:$Y$505,$A8),BB816判定!$Y$6:$Y$505,0)),"") | H8: =IFERROR(INDEX(BB816判定!$U$6:$U$505,MATCH(LARGE(BB816判定!$Y$6:$Y$505,$A8),BB816判定!$Y$6:$Y$505,0)),"") | I8: =IFERROR(INDEX(BB816判定!$M$6:$M$505,MATCH(LARGE(BB816判定!$Y$6:$Y$505,$A8),BB816判定!$Y$6:$Y$505,0)),"") | J8: =IFERROR(INDEX(BB816判定!$N$6:$N$505,MATCH(LARGE(BB816判定!$Y$6:$Y$505,$A8),BB816判定!$Y$6:$Y$505,0)),"") | K8: =IFERROR(INDEX(BB816判定!$O$6:$O$505,MATCH(LARGE(BB816判定!$Y$6:$Y$505,$A8),BB816判定!$Y$6:$Y$505,0)),"") | L8: =IFERROR(INDEX(BB816判定!$P$6:$P$505,MATCH(LARGE(BB816判定!$Y$6:$Y$505,$A8),BB816判定!$Y$6:$Y$505,0)),"") | M8: =IFERROR(INDEX(BB816判定!$V$6:$V$505,MATCH(LARGE(BB816判定!$Y$6:$Y$505,$A8),BB816判定!$Y$6:$Y$505,0)),"") | N8: =IFERROR(INDEX(BB816判定!$W$6:$W$505,MATCH(LARGE(BB816判定!$Y$6:$Y$505,$A8),BB816判定!$Y$6:$Y$505,0)),"") | O8: =IFERROR(INDEX(BB816判定!$Z$6:$Z$505,MATCH(LARGE(BB816判定!$Y$6:$Y$505,$A8),BB816判定!$Y$6:$Y$505,0)),"") | P8: =IFERROR(INDEX(BB816判定!$AA$6:$AA$505,MATCH(LARGE(BB816判定!$Y$6:$Y$505,$A8),BB816判定!$Y$6:$Y$505,0)),"") | Q8: =IF($B8="","",HYPERLINK("https://kabutan.jp/stock/?code="&$B8,"📈"))
A9: 5 | B9: =IFERROR(INDEX(BB816判定!$B$6:$B$505,MATCH(LARGE(BB816判定!$Y$6:$Y$505,$A9),BB816判定!$Y$6:$Y$505,0)),"") | C9: =IFERROR(INDEX(BB816判定!$C$6:$C$505,MATCH(LARGE(BB816判定!$Y$6:$Y$505,$A9),BB816判定!$Y$6:$Y$505,0)),"") | D9: =IFERROR(INDEX(BB816判定!$D$6:$D$505,MATCH(LARGE(BB816判定!$Y$6:$Y$505,$A9),BB816判定!$Y$6:$Y$505,0)),"") | E9: =IFERROR(INDEX(BB816判定!$Q$6:$Q$505,MATCH(LARGE(BB816判定!$Y$6:$Y$505,$A9),BB816判定!$Y$6:$Y$505,0)),"") | F9: =IFERROR(INDEX(BB816判定!$S$6:$S$505,MATCH(LARGE(BB816判定!$Y$6:$Y$505,$A9),BB816判定!$Y$6:$Y$505,0)),"") | G9: =IFERROR(INDEX(BB816判定!$T$6:$T$505,MATCH(LARGE(BB816判定!$Y$6:$Y$505,$A9),BB816判定!$Y$6:$Y$505,0)),"") | H9: =IFERROR(INDEX(BB816判定!$U$6:$U$505,MATCH(LARGE(BB816判定!$Y$6:$Y$505,$A9),BB816判定!$Y$6:$Y$505,0)),"") | I9: =IFERROR(INDEX(BB816判定!$M$6:$M$505,MATCH(LARGE(BB816判定!$Y$6:$Y$505,$A9),BB816判定!$Y$6:$Y$505,0)),"") | J9: =IFERROR(INDEX(BB816判定!$N$6:$N$505,MATCH(LARGE(BB816判定!$Y$6:$Y$505,$A9),BB816判定!$Y$6:$Y$505,0)),"") | K9: =IFERROR(INDEX(BB816判定!$O$6:$O$505,MATCH(LARGE(BB816判定!$Y$6:$Y$505,$A9),BB816判定!$Y$6:$Y$505,0)),"") | L9: =IFERROR(INDEX(BB816判定!$P$6:$P$505,MATCH(LARGE(BB816判定!$Y$6:$Y$505,$A9),BB816判定!$Y$6:$Y$505,0)),"") | M9: =IFERROR(INDEX(BB816判定!$V$6:$V$505,MATCH(LARGE(BB816判定!$Y$6:$Y$505,$A9),BB816判定!$Y$6:$Y$505,0)),"") | N9: =IFERROR(INDEX(BB816判定!$W$6:$W$505,MATCH(LARGE(BB816判定!$Y$6:$Y$505,$A9),BB816判定!$Y$6:$Y$505,0)),"") | O9: =IFERROR(INDEX(BB816判定!$Z$6:$Z$505,MATCH(LARGE(BB816判定!$Y$6:$Y$505,$A9),BB816判定!$Y$6:$Y$505,0)),"") | P9: =IFERROR(INDEX(BB816判定!$AA$6:$AA$505,MATCH(LARGE(BB816判定!$Y$6:$Y$505,$A9),BB816判定!$Y$6:$Y$505,0)),"") | Q9: =IF($B9="","",HYPERLINK("https://kabutan.jp/stock/?code="&$B9,"📈"))
A10: 6 | B10: =IFERROR(INDEX(BB816判定!$B$6:$B$505,MATCH(LARGE(BB816判定!$Y$6:$Y$505,$A10),BB816判定!$Y$6:$Y$505,0)),"") | C10: =IFERROR(INDEX(BB816判定!$C$6:$C$505,MATCH(LARGE(BB816判定!$Y$6:$Y$505,$A10),BB816判定!$Y$6:$Y$505,0)),"") | D10: =IFERROR(INDEX(BB816判定!$D$6:$D$505,MATCH(LARGE(BB816判定!$Y$6:$Y$505,$A10),BB816判定!$Y$6:$Y$505,0)),"") | E10: =IFERROR(INDEX(BB816判定!$Q$6:$Q$505,MATCH(LARGE(BB816判定!$Y$6:$Y$505,$A10),BB816判定!$Y$6:$Y$505,0)),"") | F10: =IFERROR(INDEX(BB816判定!$S$6:$S$505,MATCH(LARGE(BB816判定!$Y$6:$Y$505,$A10),BB816判定!$Y$6:$Y$505,0)),"") | G10: =IFERROR(INDEX(BB816判定!$T$6:$T$505,MATCH(LARGE(BB816判定!$Y$6:$Y$505,$A10),BB816判定!$Y$6:$Y$505,0)),"") | H10: =IFERROR(INDEX(BB816判定!$U$6:$U$505,MATCH(LARGE(BB816判定!$Y$6:$Y$505,$A10),BB816判定!$Y$6:$Y$505,0)),"") | I10: =IFERROR(INDEX(BB816判定!$M$6:$M$505,MATCH(LARGE(BB816判定!$Y$6:$Y$505,$A10),BB816判定!$Y$6:$Y$505,0)),"") | J10: =IFERROR(INDEX(BB816判定!$N$6:$N$505,MATCH(LARGE(BB816判定!$Y$6:$Y$505,$A10),BB816判定!$Y$6:$Y$505,0)),"") | K10: =IFERROR(INDEX(BB816判定!$O$6:$O$505,MATCH(LARGE(BB816判定!$Y$6:$Y$505,$A10),BB816判定!$Y$6:$Y$505,0)),"") | L10: =IFERROR(INDEX(BB816判定!$P$6:$P$505,MATCH(LARGE(BB816判定!$Y$6:$Y$505,$A10),BB816判定!$Y$6:$Y$505,0)),"") | M10: =IFERROR(INDEX(BB816判定!$V$6:$V$505,MATCH(LARGE(BB816判定!$Y$6:$Y$505,$A10),BB816判定!$Y$6:$Y$505,0)),"") | N10: =IFERROR(INDEX(BB816判定!$W$6:$W$505,MATCH(LARGE(BB816判定!$Y$6:$Y$505,$A10),BB816判定!$Y$6:$Y$505,0)),"") | O10: =IFERROR(INDEX(BB816判定!$Z$6:$Z$505,MATCH(LARGE(BB816判定!$Y$6:$Y$505,$A10),BB816判定!$Y$6:$Y$505,0)),"") | P10: =IFERROR(INDEX(BB816判定!$AA$6:$AA$505,MATCH(LARGE(BB816判定!$Y$6:$Y$505,$A10),BB816判定!$Y$6:$Y$505,0)),"") | Q10: =IF($B10="","",HYPERLINK("https://kabutan.jp/stock/?code="&$B10,"📈"))
A11: 7 | B11: =IFERROR(INDEX(BB816判定!$B$6:$B$505,MATCH(LARGE(BB816判定!$Y$6:$Y$505,$A11),BB816判定!$Y$6:$Y$505,0)),"") | C11: =IFERROR(INDEX(BB816判定!$C$6:$C$505,MATCH(LARGE(BB816判定!$Y$6:$Y$505,$A11),BB816判定!$Y$6:$Y$505,0)),"") | D11: =IFERROR(INDEX(BB816判定!$D$6:$D$505,MATCH(LARGE(BB816判定!$Y$6:$Y$505,$A11),BB816判定!$Y$6:$Y$505,0)),"") | E11: =IFERROR(INDEX(BB816判定!$Q$6:$Q$505,MATCH(LARGE(BB816判定!$Y$6:$Y$505,$A11),BB816判定!$Y$6:$Y$505,0)),"") | F11: =IFERROR(INDEX(BB816判定!$S$6:$S$505,MATCH(LARGE(BB816判定!$Y$6:$Y$505,$A11),BB816判定!$Y$6:$Y$505,0)),"") | G11: =IFERROR(INDEX(BB816判定!$T$6:$T$505,MATCH(LARGE(BB816判定!$Y$6:$Y$505,$A11),BB816判定!$Y$6:$Y$505,0)),"") | H11: =IFERROR(INDEX(BB816判定!$U$6:$U$505,MATCH(LARGE(BB816判定!$Y$6:$Y$505,$A11),BB816判定!$Y$6:$Y$505,0)),"") | I11: =IFERROR(INDEX(BB816判定!$M$6:$M$505,MATCH(LARGE(BB816判定!$Y$6:$Y$505,$A11),BB816判定!$Y$6:$Y$505,0)),"") | J11: =IFERROR(INDEX(BB816判定!$N$6:$N$505,MATCH(LARGE(BB816判定!$Y$6:$Y$505,$A11),BB816判定!$Y$6:$Y$505,0)),"") | K11: =IFERROR(INDEX(BB816判定!$O$6:$O$505,MATCH(LARGE(BB816判定!$Y$6:$Y$505,$A11),BB816判定!$Y$6:$Y$505,0)),"") | L11: =IFERROR(INDEX(BB816判定!$P$6:$P$505,MATCH(LARGE(BB816判定!$Y$6:$Y$505,$A11),BB816判定!$Y$6:$Y$505,0)),"") | M11: =IFERROR(INDEX(BB816判定!$V$6:$V$505,MATCH(LARGE(BB816判定!$Y$6:$Y$505,$A11),BB816判定!$Y$6:$Y$505,0)),"") | N11: =IFERROR(INDEX(BB816判定!$W$6:$W$505,MATCH(LARGE(BB816判定!$Y$6:$Y$505,$A11),BB816判定!$Y$6:$Y$505,0)),"") | O11: =IFERROR(INDEX(BB816判定!$Z$6:$Z$505,MATCH(LARGE(BB816判定!$Y$6:$Y$505,$A11),BB816判定!$Y$6:$Y$505,0)),"") | P11: =IFERROR(INDEX(BB816判定!$AA$6:$AA$505,MATCH(LARGE(BB816判定!$Y$6:$Y$505,$A11),BB816判定!$Y$6:$Y$505,0)),"") | Q11: =IF($B11="","",HYPERLINK("https://kabutan.jp/stock/?code="&$B11,"📈"))
A12: 8 | B12: =IFERROR(INDEX(BB816判定!$B$6:$B$505,MATCH(LARGE(BB816判定!$Y$6:$Y$505,$A12),BB816判定!$Y$6:$Y$505,0)),"") | C12: =IFERROR(INDEX(BB816判定!$C$6:$C$505,MATCH(LARGE(BB816判定!$Y$6:$Y$505,$A12),BB816判定!$Y$6:$Y$505,0)),"") | D12: =IFERROR(INDEX(BB816判定!$D$6:$D$505,MATCH(LARGE(BB816判定!$Y$6:$Y$505,$A12),BB816判定!$Y$6:$Y$505,0)),"") | E12: =IFERROR(INDEX(BB816判定!$Q$6:$Q$505,MATCH(LARGE(BB816判定!$Y$6:$Y$505,$A12),BB816判定!$Y$6:$Y$505,0)),"") | F12: =IFERROR(INDEX(BB816判定!$S$6:$S$505,MATCH(LARGE(BB816判定!$Y$6:$Y$505,$A12),BB816判定!$Y$6:$Y$505,0)),"") | G12: =IFERROR(INDEX(BB816判定!$T$6:$T$505,MATCH(LARGE(BB816判定!$Y$6:$Y$505,$A12),BB816判定!$Y$6:$Y$505,0)),"") | H12: =IFERROR(INDEX(BB816判定!$U$6:$U$505,MATCH(LARGE(BB816判定!$Y$6:$Y$505,$A12),BB816判定!$Y$6:$Y$505,0)),"") | I12: =IFERROR(INDEX(BB816判定!$M$6:$M$505,MATCH(LARGE(BB816判定!$Y$6:$Y$505,$A12),BB816判定!$Y$6:$Y$505,0)),"") | J12: =IFERROR(INDEX(BB816判定!$N$6:$N$505,MATCH(LARGE(BB816判定!$Y$6:$Y$505,$A12),BB816判定!$Y$6:$Y$505,0)),"") | K12: =IFERROR(INDEX(BB816判定!$O$6:$O$505,MATCH(LARGE(BB816判定!$Y$6:$Y$505,$A12),BB816判定!$Y$6:$Y$505,0)),"") | L12: =IFERROR(INDEX(BB816判定!$P$6:$P$505,MATCH(LARGE(BB816判定!$Y$6:$Y$505,$A12),BB816判定!$Y$6:$Y$505,0)),"") | M12: =IFERROR(INDEX(BB816判定!$V$6:$V$505,MATCH(LARGE(BB816判定!$Y$6:$Y$505,$A12),BB816判定!$Y$6:$Y$505,0)),"") | N12: =IFERROR(INDEX(BB816判定!$W$6:$W$505,MATCH(LARGE(BB816判定!$Y$6:$Y$505,$A12),BB816判定!$Y$6:$Y$505,0)),"") | O12: =IFERROR(INDEX(BB816判定!$Z$6:$Z$505,MATCH(LARGE(BB816判定!$Y$6:$Y$505,$A12),BB816判定!$Y$6:$Y$505,0)),"") | P12: =IFERROR(INDEX(BB816判定!$AA$6:$AA$505,MATCH(LARGE(BB816判定!$Y$6:$Y$505,$A12),BB816判定!$Y$6:$Y$505,0)),"") | Q12: =IF($B12="","",HYPERLINK("https://kabutan.jp/stock/?code="&$B12,"📈"))
A13: 9 | B13: =IFERROR(INDEX(BB816判定!$B$6:$B$505,MATCH(LARGE(BB816判定!$Y$6:$Y$505,$A13),BB816判定!$Y$6:$Y$505,0)),"") | C13: =IFERROR(INDEX(BB816判定!$C$6:$C$505,MATCH(LARGE(BB816判定!$Y$6:$Y$505,$A13),BB816判定!$Y$6:$Y$505,0)),"") | D13: =IFERROR(INDEX(BB816判定!$D$6:$D$505,MATCH(LARGE(BB816判定!$Y$6:$Y$505,$A13),BB816判定!$Y$6:$Y$505,0)),"") | E13: =IFERROR(INDEX(BB816判定!$Q$6:$Q$505,MATCH(LARGE(BB816判定!$Y$6:$Y$505,$A13),BB816判定!$Y$6:$Y$505,0)),"") | F13: =IFERROR(INDEX(BB816判定!$S$6:$S$505,MATCH(LARGE(BB816判定!$Y$6:$Y$505,$A13),BB816判定!$Y$6:$Y$505,0)),"") | G13: =IFERROR(INDEX(BB816判定!$T$6:$T$505,MATCH(LARGE(BB816判定!$Y$6:$Y$505,$A13),BB816判定!$Y$6:$Y$505,0)),"") | H13: =IFERROR(INDEX(BB816判定!$U$6:$U$505,MATCH(LARGE(BB816判定!$Y$6:$Y$505,$A13),BB816判定!$Y$6:$Y$505,0)),"") | I13: =IFERROR(INDEX(BB816判定!$M$6:$M$505,MATCH(LARGE(BB816判定!$Y$6:$Y$505,$A13),BB816判定!$Y$6:$Y$505,0)),"") | J13: =IFERROR(INDEX(BB816判定!$N$6:$N$505,MATCH(LARGE(BB816判定!$Y$6:$Y$505,$A13),BB816判定!$Y$6:$Y$505,0)),"") | K13: =IFERROR(INDEX(BB816判定!$O$6:$O$505,MATCH(LARGE(BB816判定!$Y$6:$Y$505,$A13),BB816判定!$Y$6:$Y$505,0)),"") | L13: =IFERROR(INDEX(BB816判定!$P$6:$P$505,MATCH(LARGE(BB816判定!$Y$6:$Y$505,$A13),BB816判定!$Y$6:$Y$505,0)),"") | M13: =IFERROR(INDEX(BB816判定!$V$6:$V$505,MATCH(LARGE(BB816判定!$Y$6:$Y$505,$A13),BB816判定!$Y$6:$Y$505,0)),"") | N13: =IFERROR(INDEX(BB816判定!$W$6:$W$505,MATCH(LARGE(BB816判定!$Y$6:$Y$505,$A13),BB816判定!$Y$6:$Y$505,0)),"") | O13: =IFERROR(INDEX(BB816判定!$Z$6:$Z$505,MATCH(LARGE(BB816判定!$Y$6:$Y$505,$A13),BB816判定!$Y$6:$Y$505,0)),"") | P13: =IFERROR(INDEX(BB816判定!$AA$6:$AA$505,MATCH(LARGE(BB816判定!$Y$6:$Y$505,$A13),BB816判定!$Y$6:$Y$505,0)),"") | Q13: =IF($B13="","",HYPERLINK("https://kabutan.jp/stock/?code="&$B13,"📈"))
A14: 10 | B14: =IFERROR(INDEX(BB816判定!$B$6:$B$505,MATCH(LARGE(BB816判定!$Y$6:$Y$505,$A14),BB816判定!$Y$6:$Y$505,0)),"") | C14: =IFERROR(INDEX(BB816判定!$C$6:$C$505,MATCH(LARGE(BB816判定!$Y$6:$Y$505,$A14),BB816判定!$Y$6:$Y$505,0)),"") | D14: =IFERROR(INDEX(BB816判定!$D$6:$D$505,MATCH(LARGE(BB816判定!$Y$6:$Y$505,$A14),BB816判定!$Y$6:$Y$505,0)),"") | E14: =IFERROR(INDEX(BB816判定!$Q$6:$Q$505,MATCH(LARGE(BB816判定!$Y$6:$Y$505,$A14),BB816判定!$Y$6:$Y$505,0)),"") | F14: =IFERROR(INDEX(BB816判定!$S$6:$S$505,MATCH(LARGE(BB816判定!$Y$6:$Y$505,$A14),BB816判定!$Y$6:$Y$505,0)),"") | G14: =IFERROR(INDEX(BB816判定!$T$6:$T$505,MATCH(LARGE(BB816判定!$Y$6:$Y$505,$A14),BB816判定!$Y$6:$Y$505,0)),"") | H14: =IFERROR(INDEX(BB816判定!$U$6:$U$505,MATCH(LARGE(BB816判定!$Y$6:$Y$505,$A14),BB816判定!$Y$6:$Y$505,0)),"") | I14: =IFERROR(INDEX(BB816判定!$M$6:$M$505,MATCH(LARGE(BB816判定!$Y$6:$Y$505,$A14),BB816判定!$Y$6:$Y$505,0)),"") | J14: =IFERROR(INDEX(BB816判定!$N$6:$N$505,MATCH(LARGE(BB816判定!$Y$6:$Y$505,$A14),BB816判定!$Y$6:$Y$505,0)),"") | K14: =IFERROR(INDEX(BB816判定!$O$6:$O$505,MATCH(LARGE(BB816判定!$Y$6:$Y$505,$A14),BB816判定!$Y$6:$Y$505,0)),"") | L14: =IFERROR(INDEX(BB816判定!$P$6:$P$505,MATCH(LARGE(BB816判定!$Y$6:$Y$505,$A14),BB816判定!$Y$6:$Y$505,0)),"") | M14: =IFERROR(INDEX(BB816判定!$V$6:$V$505,MATCH(LARGE(BB816判定!$Y$6:$Y$505,$A14),BB816判定!$Y$6:$Y$505,0)),"") | N14: =IFERROR(INDEX(BB816判定!$W$6:$W$505,MATCH(LARGE(BB816判定!$Y$6:$Y$505,$A14),BB816判定!$Y$6:$Y$505,0)),"") | O14: =IFERROR(INDEX(BB816判定!$Z$6:$Z$505,MATCH(LARGE(BB816判定!$Y$6:$Y$505,$A14),BB816判定!$Y$6:$Y$505,0)),"") | P14: =IFERROR(INDEX(BB816判定!$AA$6:$AA$505,MATCH(LARGE(BB816判定!$Y$6:$Y$505,$A14),BB816判定!$Y$6:$Y$505,0)),"") | Q14: =IF($B14="","",HYPERLINK("https://kabutan.jp/stock/?code="&$B14,"📈"))
A15: 11 | B15: =IFERROR(INDEX(BB816判定!$B$6:$B$505,MATCH(LARGE(BB816判定!$Y$6:$Y$505,$A15),BB816判定!$Y$6:$Y$505,0)),"") | C15: =IFERROR(INDEX(BB816判定!$C$6:$C$505,MATCH(LARGE(BB816判定!$Y$6:$Y$505,$A15),BB816判定!$Y$6:$Y$505,0)),"") | D15: =IFERROR(INDEX(BB816判定!$D$6:$D$505,MATCH(LARGE(BB816判定!$Y$6:$Y$505,$A15),BB816判定!$Y$6:$Y$505,0)),"") | E15: =IFERROR(INDEX(BB816判定!$Q$6:$Q$505,MATCH(LARGE(BB816判定!$Y$6:$Y$505,$A15),BB816判定!$Y$6:$Y$505,0)),"") | F15: =IFERROR(INDEX(BB816判定!$S$6:$S$505,MATCH(LARGE(BB816判定!$Y$6:$Y$505,$A15),BB816判定!$Y$6:$Y$505,0)),"") | G15: =IFERROR(INDEX(BB816判定!$T$6:$T$505,MATCH(LARGE(BB816判定!$Y$6:$Y$505,$A15),BB816判定!$Y$6:$Y$505,0)),"") | H15: =IFERROR(INDEX(BB816判定!$U$6:$U$505,MATCH(LARGE(BB816判定!$Y$6:$Y$505,$A15),BB816判定!$Y$6:$Y$505,0)),"") | I15: =IFERROR(INDEX(BB816判定!$M$6:$M$505,MATCH(LARGE(BB816判定!$Y$6:$Y$505,$A15),BB816判定!$Y$6:$Y$505,0)),"") | J15: =IFERROR(INDEX(BB816判定!$N$6:$N$505,MATCH(LARGE(BB816判定!$Y$6:$Y$505,$A15),BB816判定!$Y$6:$Y$505,0)),"") | K15: =IFERROR(INDEX(BB816判定!$O$6:$O$505,MATCH(LARGE(BB816判定!$Y$6:$Y$505,$A15),BB816判定!$Y$6:$Y$505,0)),"") | L15: =IFERROR(INDEX(BB816判定!$P$6:$P$505,MATCH(LARGE(BB816判定!$Y$6:$Y$505,$A15),BB816判定!$Y$6:$Y$505,0)),"") | M15: =IFERROR(INDEX(BB816判定!$V$6:$V$505,MATCH(LARGE(BB816判定!$Y$6:$Y$505,$A15),BB816判定!$Y$6:$Y$505,0)),"") | N15: =IFERROR(INDEX(BB816判定!$W$6:$W$505,MATCH(LARGE(BB816判定!$Y$6:$Y$505,$A15),BB816判定!$Y$6:$Y$505,0)),"") | O15: =IFERROR(INDEX(BB816判定!$Z$6:$Z$505,MATCH(LARGE(BB816判定!$Y$6:$Y$505,$A15),BB816判定!$Y$6:$Y$505,0)),"") | P15: =IFERROR(INDEX(BB816判定!$AA$6:$AA$505,MATCH(LARGE(BB816判定!$Y$6:$Y$505,$A15),BB816判定!$Y$6:$Y$505,0)),"") | Q15: =IF($B15="","",HYPERLINK("https://kabutan.jp/stock/?code="&$B15,"📈"))
A16: 12 | B16: =IFERROR(INDEX(BB816判定!$B$6:$B$505,MATCH(LARGE(BB816判定!$Y$6:$Y$505,$A16),BB816判定!$Y$6:$Y$505,0)),"") | C16: =IFERROR(INDEX(BB816判定!$C$6:$C$505,MATCH(LARGE(BB816判定!$Y$6:$Y$505,$A16),BB816判定!$Y$6:$Y$505,0)),"") | D16: =IFERROR(INDEX(BB816判定!$D$6:$D$505,MATCH(LARGE(BB816判定!$Y$6:$Y$505,$A16),BB816判定!$Y$6:$Y$505,0)),"") | E16: =IFERROR(INDEX(BB816判定!$Q$6:$Q$505,MATCH(LARGE(BB816判定!$Y$6:$Y$505,$A16),BB816判定!$Y$6:$Y$505,0)),"") | F16: =IFERROR(INDEX(BB816判定!$S$6:$S$505,MATCH(LARGE(BB816判定!$Y$6:$Y$505,$A16),BB816判定!$Y$6:$Y$505,0)),"") | G16: =IFERROR(INDEX(BB816判定!$T$6:$T$505,MATCH(LARGE(BB816判定!$Y$6:$Y$505,$A16),BB816判定!$Y$6:$Y$505,0)),"") | H16: =IFERROR(INDEX(BB816判定!$U$6:$U$505,MATCH(LARGE(BB816判定!$Y$6:$Y$505,$A16),BB816判定!$Y$6:$Y$505,0)),"") | I16: =IFERROR(INDEX(BB816判定!$M$6:$M$505,MATCH(LARGE(BB816判定!$Y$6:$Y$505,$A16),BB816判定!$Y$6:$Y$505,0)),"") | J16: =IFERROR(INDEX(BB816判定!$N$6:$N$505,MATCH(LARGE(BB816判定!$Y$6:$Y$505,$A16),BB816判定!$Y$6:$Y$505,0)),"") | K16: =IFERROR(INDEX(BB816判定!$O$6:$O$505,MATCH(LARGE(BB816判定!$Y$6:$Y$505,$A16),BB816判定!$Y$6:$Y$505,0)),"") | L16: =IFERROR(INDEX(BB816判定!$P$6:$P$505,MATCH(LARGE(BB816判定!$Y$6:$Y$505,$A16),BB816判定!$Y$6:$Y$505,0)),"") | M16: =IFERROR(INDEX(BB816判定!$V$6:$V$505,MATCH(LARGE(BB816判定!$Y$6:$Y$505,$A16),BB816判定!$Y$6:$Y$505,0)),"") | N16: =IFERROR(INDEX(BB816判定!$W$6:$W$505,MATCH(LARGE(BB816判定!$Y$6:$Y$505,$A16),BB816判定!$Y$6:$Y$505,0)),"") | O16: =IFERROR(INDEX(BB816判定!$Z$6:$Z$505,MATCH(LARGE(BB816判定!$Y$6:$Y$505,$A16),BB816判定!$Y$6:$Y$505,0)),"") | P16: =IFERROR(INDEX(BB816判定!$AA$6:$AA$505,MATCH(LARGE(BB816判定!$Y$6:$Y$505,$A16),BB816判定!$Y$6:$Y$505,0)),"") | Q16: =IF($B16="","",HYPERLINK("https://kabutan.jp/stock/?code="&$B16,"📈"))
A17: 13 | B17: =IFERROR(INDEX(BB816判定!$B$6:$B$505,MATCH(LARGE(BB816判定!$Y$6:$Y$505,$A17),BB816判定!$Y$6:$Y$505,0)),"") | C17: =IFERROR(INDEX(BB816判定!$C$6:$C$505,MATCH(LARGE(BB816判定!$Y$6:$Y$505,$A17),BB816判定!$Y$6:$Y$505,0)),"") | D17: =IFERROR(INDEX(BB816判定!$D$6:$D$505,MATCH(LARGE(BB816判定!$Y$6:$Y$505,$A17),BB816判定!$Y$6:$Y$505,0)),"") | E17: =IFERROR(INDEX(BB816判定!$Q$6:$Q$505,MATCH(LARGE(BB816判定!$Y$6:$Y$505,$A17),BB816判定!$Y$6:$Y$505,0)),"") | F17: =IFERROR(INDEX(BB816判定!$S$6:$S$505,MATCH(LARGE(BB816判定!$Y$6:$Y$505,$A17),BB816判定!$Y$6:$Y$505,0)),"") | G17: =IFERROR(INDEX(BB816判定!$T$6:$T$505,MATCH(LARGE(BB816判定!$Y$6:$Y$505,$A17),BB816判定!$Y$6:$Y$505,0)),"") | H17: =IFERROR(INDEX(BB816判定!$U$6:$U$505,MATCH(LARGE(BB816判定!$Y$6:$Y$505,$A17),BB816判定!$Y$6:$Y$505,0)),"") | I17: =IFERROR(INDEX(BB816判定!$M$6:$M$505,MATCH(LARGE(BB816判定!$Y$6:$Y$505,$A17),BB816判定!$Y$6:$Y$505,0)),"") | J17: =IFERROR(INDEX(BB816判定!$N$6:$N$505,MATCH(LARGE(BB816判定!$Y$6:$Y$505,$A17),BB816判定!$Y$6:$Y$505,0)),"") | K17: =IFERROR(INDEX(BB816判定!$O$6:$O$505,MATCH(LARGE(BB816判定!$Y$6:$Y$505,$A17),BB816判定!$Y$6:$Y$505,0)),"") | L17: =IFERROR(INDEX(BB816判定!$P$6:$P$505,MATCH(LARGE(BB816判定!$Y$6:$Y$505,$A17),BB816判定!$Y$6:$Y$505,0)),"") | M17: =IFERROR(INDEX(BB816判定!$V$6:$V$505,MATCH(LARGE(BB816判定!$Y$6:$Y$505,$A17),BB816判定!$Y$6:$Y$505,0)),"") | N17: =IFERROR(INDEX(BB816判定!$W$6:$W$505,MATCH(LARGE(BB816判定!$Y$6:$Y$505,$A17),BB816判定!$Y$6:$Y$505,0)),"") | O17: =IFERROR(INDEX(BB816判定!$Z$6:$Z$505,MATCH(LARGE(BB816判定!$Y$6:$Y$505,$A17),BB816判定!$Y$6:$Y$505,0)),"") | P17: =IFERROR(INDEX(BB816判定!$AA$6:$AA$505,MATCH(LARGE(BB816判定!$Y$6:$Y$505,$A17),BB816判定!$Y$6:$Y$505,0)),"") | Q17: =IF($B17="","",HYPERLINK("https://kabutan.jp/stock/?code="&$B17,"📈"))
A18: 14 | B18: =IFERROR(INDEX(BB816判定!$B$6:$B$505,MATCH(LARGE(BB816判定!$Y$6:$Y$505,$A18),BB816判定!$Y$6:$Y$505,0)),"") | C18: =IFERROR(INDEX(BB816判定!$C$6:$C$505,MATCH(LARGE(BB816判定!$Y$6:$Y$505,$A18),BB816判定!$Y$6:$Y$505,0)),"") | D18: =IFERROR(INDEX(BB816判定!$D$6:$D$505,MATCH(LARGE(BB816判定!$Y$6:$Y$505,$A18),BB816判定!$Y$6:$Y$505,0)),"") | E18: =IFERROR(INDEX(BB816判定!$Q$6:$Q$505,MATCH(LARGE(BB816判定!$Y$6:$Y$505,$A18),BB816判定!$Y$6:$Y$505,0)),"") | F18: =IFERROR(INDEX(BB816判定!$S$6:$S$505,MATCH(LARGE(BB816判定!$Y$6:$Y$505,$A18),BB816判定!$Y$6:$Y$505,0)),"") | G18: =IFERROR(INDEX(BB816判定!$T$6:$T$505,MATCH(LARGE(BB816判定!$Y$6:$Y$505,$A18),BB816判定!$Y$6:$Y$505,0)),"") | H18: =IFERROR(INDEX(BB816判定!$U$6:$U$505,MATCH(LARGE(BB816判定!$Y$6:$Y$505,$A18),BB816判定!$Y$6:$Y$505,0)),"") | I18: =IFERROR(INDEX(BB816判定!$M$6:$M$505,MATCH(LARGE(BB816判定!$Y$6:$Y$505,$A18),BB816判定!$Y$6:$Y$505,0)),"") | J18: =IFERROR(INDEX(BB816判定!$N$6:$N$505,MATCH(LARGE(BB816判定!$Y$6:$Y$505,$A18),BB816判定!$Y$6:$Y$505,0)),"") | K18: =IFERROR(INDEX(BB816判定!$O$6:$O$505,MATCH(LARGE(BB816判定!$Y$6:$Y$505,$A18),BB816判定!$Y$6:$Y$505,0)),"") | L18: =IFERROR(INDEX(BB816判定!$P$6:$P$505,MATCH(LARGE(BB816判定!$Y$6:$Y$505,$A18),BB816判定!$Y$6:$Y$505,0)),"") | M18: =IFERROR(INDEX(BB816判定!$V$6:$V$505,MATCH(LARGE(BB816判定!$Y$6:$Y$505,$A18),BB816判定!$Y$6:$Y$505,0)),"") | N18: =IFERROR(INDEX(BB816判定!$W$6:$W$505,MATCH(LARGE(BB816判定!$Y$6:$Y$505,$A18),BB816判定!$Y$6:$Y$505,0)),"") | O18: =IFERROR(INDEX(BB816判定!$Z$6:$Z$505,MATCH(LARGE(BB816判定!$Y$6:$Y$505,$A18),BB816判定!$Y$6:$Y$505,0)),"") | P18: =IFERROR(INDEX(BB816判定!$AA$6:$AA$505,MATCH(LARGE(BB816判定!$Y$6:$Y$505,$A18),BB816判定!$Y$6:$Y$505,0)),"") | Q18: =IF($B18="","",HYPERLINK("https://kabutan.jp/stock/?code="&$B18,"📈"))
A19: 15 | B19: =IFERROR(INDEX(BB816判定!$B$6:$B$505,MATCH(LARGE(BB816判定!$Y$6:$Y$505,$A19),BB816判定!$Y$6:$Y$505,0)),"") | C19: =IFERROR(INDEX(BB816判定!$C$6:$C$505,MATCH(LARGE(BB816判定!$Y$6:$Y$505,$A19),BB816判定!$Y$6:$Y$505,0)),"") | D19: =IFERROR(INDEX(BB816判定!$D$6:$D$505,MATCH(LARGE(BB816判定!$Y$6:$Y$505,$A19),BB816判定!$Y$6:$Y$505,0)),"") | E19: =IFERROR(INDEX(BB816判定!$Q$6:$Q$505,MATCH(LARGE(BB816判定!$Y$6:$Y$505,$A19),BB816判定!$Y$6:$Y$505,0)),"") | F19: =IFERROR(INDEX(BB816判定!$S$6:$S$505,MATCH(LARGE(BB816判定!$Y$6:$Y$505,$A19),BB816判定!$Y$6:$Y$505,0)),"") | G19: =IFERROR(INDEX(BB816判定!$T$6:$T$505,MATCH(LARGE(BB816判定!$Y$6:$Y$505,$A19),BB816判定!$Y$6:$Y$505,0)),"") | H19: =IFERROR(INDEX(BB816判定!$U$6:$U$505,MATCH(LARGE(BB816判定!$Y$6:$Y$505,$A19),BB816判定!$Y$6:$Y$505,0)),"") | I19: =IFERROR(INDEX(BB816判定!$M$6:$M$505,MATCH(LARGE(BB816判定!$Y$6:$Y$505,$A19),BB816判定!$Y$6:$Y$505,0)),"") | J19: =IFERROR(INDEX(BB816判定!$N$6:$N$505,MATCH(LARGE(BB816判定!$Y$6:$Y$505,$A19),BB816判定!$Y$6:$Y$505,0)),"") | K19: =IFERROR(INDEX(BB816判定!$O$6:$O$505,MATCH(LARGE(BB816判定!$Y$6:$Y$505,$A19),BB816判定!$Y$6:$Y$505,0)),"") | L19: =IFERROR(INDEX(BB816判定!$P$6:$P$505,MATCH(LARGE(BB816判定!$Y$6:$Y$505,$A19),BB816判定!$Y$6:$Y$505,0)),"") | M19: =IFERROR(INDEX(BB816判定!$V$6:$V$505,MATCH(LARGE(BB816判定!$Y$6:$Y$505,$A19),BB816判定!$Y$6:$Y$505,0)),"") | N19: =IFERROR(INDEX(BB816判定!$W$6:$W$505,MATCH(LARGE(BB816判定!$Y$6:$Y$505,$A19),BB816判定!$Y$6:$Y$505,0)),"") | O19: =IFERROR(INDEX(BB816判定!$Z$6:$Z$505,MATCH(LARGE(BB816判定!$Y$6:$Y$505,$A19),BB816判定!$Y$6:$Y$505,0)),"") | P19: =IFERROR(INDEX(BB816判定!$AA$6:$AA$505,MATCH(LARGE(BB816判定!$Y$6:$Y$505,$A19),BB816判定!$Y$6:$Y$505,0)),"") | Q19: =IF($B19="","",HYPERLINK("https://kabutan.jp/stock/?code="&$B19,"📈"))
A21: ■ 発注の手順
A22: 1. 「総合判定」が ◎買い の銘柄を上から選ぶ。ただし
A23: ・空いている枠の数だけ（枠が埋まっていればその日は買わない）
A24: ・1日に建てるのは最大3件まで（枠が3〜4しかないときは1件まで）
A25: ・「資金枠に収まるか」が × の銘柄は飛ばして、次の候補を見る
A26: 2. 翌営業日の寄付（始値）で買う。指値にせず寄成でよい。
A27: 3. 買えたら、その場で損切り価格（N列）に逆指値を置く。
A28: 4. 10営業日たったら、損益に関わらず引けで手仕舞う。
A29: 5. 利確目標は置かない。含み益が伸びても途中で降りない（検証では利確を置くと期待値が6割落ちた）。
A31: ■ 1日に何件買うことになるのか
A32: 実測では250営業日で248件、つまり1日あたり平均1.0件でした。
A33: 0件の日が39.6%、1件が30.0%、2件が22.0%、3件buyできた日は8.4%（21日）だけです。
... A40: 2人とも「買い可」なら、条件としては最も堅い候補になる。

Sheet BB816判定
A1: 📊 BB816 判定 ― ボリンジャーバンド＋出来高による順張りスイング
A2: 終値シートの最新終値で自動計算。発注に使うのは「BB816候補」シート。ここは全銘柄の内訳を確認する場所です。
A3: 総合判定 ◎買い＝翌営業日の寄付で買う / ○監視＝条件待ち / ▲弱い＝買わない。守り分析官・攻め分析官の欄は、2人の分析官それぞれの基準での可否です。
A5: 🔗 | B5: コード | C5: 銘柄名 | D5: 現在値 | E5: SMA20 ミドル | F5: σ | G5: +2σ | H5: +1σ | I5: -1σ | J5: -2σ | K5: %B | L5: 帯幅% | M5: RSI14 | N5: MFI14 | O5: 出来高 倍率 | P5: 20日 騰落率 | Q5: BB816 スコア | R5: 買い条件 | S5: 総合判定 | T5: 守り分析官 | U5: 攻め分析官 | V5: エントリー 目安 | W5: 損切り 価格 | X5: 総資金への 最大損失% | Y5: sortkey
A6: =IF(終値!A6="","",HYPERLINK("https://kabutan.jp/stock/?code="&終値!A6,"📈")) | B6: =IF(終値!A6="","",終値!A6) | C6: =IF(終値!A6="","",終値!B6) | D6: =IF(終値!A6="","",終値!E6) | E6: =IF($D6="","",AVERAGE(終値!E6:X6)) | F6: =IF($D6="","",STDEVP(終値!E6:X6)) | G6: =IF($D6="","",$E6+BB816設定!$B$4*$F6) | H6: =IF($D6="","",$E6+BB816設定!$B$5*$F6) | I6: =IF($D6="","",$E6-BB816設定!$B$5*$F6) | J6: =IF($D6="","",$E6-BB816設定!$B$4*$F6) | K6: =IF($D6="","",IFERROR(($D6-$J6)/($G6-$J6),"")) | L6: =IF($D6="","",IFERROR(($G6-$J6)/$E6*100,"")) | M6: =IF($D6="","",IFERROR(100-100/(1+SUMPRODUCT((終値!E6:R6>終値!F6:S6)*(終値!E6:R6-終値!F6:S6))/SUMPRODUCT((終値!E6:R6<終値!F6:S6)*(終値!F6:S6-終値!E6:R6))),100)) | N6: =IF($D6="","",IFERROR(100-100/(1+SUMPRODUCT((((高値!E6:R6+安値!E6:R6+終値!E6:R6)/3)>((高値!F6:S6+安値!F6:S6+終値!F6:S6)/3))*((高値!E6:R6+安値!E6:R6+終値!E6:R6)/3)*出来高!E6:R6)/SUMPRODUCT((((高値!E6:R6+安値!E6:R6+終値!E6:R6)/3)<((高値!F6:S6+安値!F6:S6+終値!F6:S6)/3))*((高値!E6:R6+安値!E6:R6+終値!E6:R6)/3)*出来高!E6:R6)),50)) | O6: =IF($D6="","",IFERROR(出来高!E6/AVERAGE(出来高!E6:I6),"")) | P6: =IF($D6="","",IFERROR($D6/終値!Y6-1,"")) | Q6: =IF($D6="","",MAX(0,MIN(100,IF($D6>$G6,25,IF($D6>$H6,15,IF($D6>$E6,5,0)))+IF($O6>=2,20,IF($O6>=1.5,14,IF($O6>=1.2,8,0)))+IF($N6>=80,15,IF($N6>=60,18,IF($N6>=50,8,0)))+IF(AND($M6>70,$M6<=80),18,IF(AND($M6>60,$M6<=70),14,IF(AND($M6>50,$M6<=60),6,0)))+IF($P6>=0.1,14,IF($P6>=0.03,7,0))+IF($M6>80,-12,0)+IF($M6<40,-20,0)+IF($N6<40,-15,0)+IF($K6<0.2,-18,0)+IF($P6<=-0.1,-10,0)))) | R6: =IF($D6="","",IF(AND($D6>$G6,$O6>=BB816設定!$B$6,$N6>=BB816設定!$B$7,$M6<=BB816設定!$B$8),"○","－")) | S6: =IF($D6="","",IF(AND($R6="○",$Q6>=BB816設定!$B$9),"◎買い",IF($Q6>=BB816設定!$B$10,"○監視",IF(OR($M6<40,$K6<0.2),"▲弱い","－")))) | T6: =IF($D6="","",IF(AND($D6>$G6,$O6>=BB816設定!$B$14,$N6>=BB816設定!$B$15,$M6<=BB816設定!$B$16),"買い可","見送り")) | U6: =IF($D6="","",IF(AND($D6>$H6,$M6>=BB816設定!$B$17,$N6>=BB816設定!$B$18,$O6>=BB816設定!$B$19),"買い可","見送り")) | V6: =IF($S6="◎買い",$D6,"") | W6: =IF($S6="◎買い",ROUND($D6*(1-BB816設定!$B$11/100),1),"") | X6: =IF($S6="◎買い",BB816設定!$B$11/BB816設定!$B$13,"") | Y6: =IF($D6="","",$Q6+(10000-ROW())/100000) | Z6: =IF($D6="","",$D6*BB816設定!$B$21) | AA6: =IF($D6="","",IF($Z6<=BB816設定!$B$20/BB816設定!$B$13,"○","×（1枠に入らない）"))
A7: =IF(終値!A7="","",HYPERLINK("https://kabutan.jp/stock/?code="&終値!A7,"📈")) | B7: =IF(終値!A7="","",終値!A7) | C7: =IF(終値!A7="","",終値!B7) | D7: =IF(終値!A7="","",終値!E7) | E7: =IF($D7="","",AVERAGE(終値!E7:X7)) | F7: =IF($D7="","",STDEVP(終値!E7:X7)) | G7: =IF($D7="","",$E7+BB816設定!$B$4*$F7) | H7: =IF($D7="","",$E7+BB816設定!$B$5*$F7) | I7: =IF($D7="","",$E7-BB816設定!$B$5*$F7) | J7: =IF($D7="","",$E7-BB816設定!$B$4*$F7) | K7: =IF($D7="","",IFERROR(($D7-$J7)/($G7-$J7),"")) | L7: =IF($D7="","",IFERROR(($G7-$J7)/$E7*100,"")) | M7: =IF($D7="","",IFERROR(100-100/(1+SUMPRODUCT((終値!E7:R7>終値!F7:S7)*(終値!E7:R7-終値!F7:S7))/SUMPRODUCT((終値!E7:R7<終値!F7:S7)*(終値!F7:S7-終値!E7:R7))),100)) | N7: =IF($D7="","",IFERROR(100-100/(1+SUMPRODUCT((((高値!E7:R7+安値!E7:R7+終値!E7:R7)/3)>((高値!F7:S7+安値!F7:S7+終値!F7:S7)/3))*((高値!E7:R7+安値!E7:R7+終値!E7:R7)/3)*出来高!E7:R7)/SUMPRODUCT((((高値!E7:R7+安値!E7:R7+終値!E7:R7)/3)<((高値!F7:S7+安値!F7:S7+終値!F7:S7)/3))*((高値!E7:R7+安値!E7:R7+終値!E7:R7)/3)*出来高!E7:R7)),50)) | O7: =IF($D7="","",IFERROR(出来高!E7/AVERAGE(出来高!E7:I7),"")) | P7: =IF($D7="","",IFERROR($D7/終値!Y7-1,"")) | Q7: =IF($D7="","",MAX(0,MIN(100,IF($D7>$G7,25,IF($D7>$H7,15,IF($D7>$E7,5,0)))+IF($O7>=2,20,IF($O7>=1.5,14,IF($O7>=1.2,8,0)))+IF($N7>=80,15,IF($N7>=60,18,IF($N7>=50,8,0)))+IF(AND($M7>70,$M7<=80),18,IF(AND($M7>60,$M7<=70),14,IF(AND($M7>50,$M7<=60),6,0)))+IF($P7>=0.1,14,IF($P7>=0.03,7,0))+IF($M7>80,-12,0)+IF($M7<40,-20,0)+IF($N7<40,-15,0)+IF($K7<0.2,-18,0)+IF($P7<=-0.1,-10,0)))) | R7: =IF($D7="","",IF(AND($D7>$G7,$O7>=BB816設定!$B$6,$N7>=BB816設定!$B$7,$M7<=BB816設定!$B$8),"○","－")) | S7: =IF($D7="","",IF(AND($R7="○",$Q7>=BB816設定!$B$9),"◎買い",IF($Q7>=BB816設定!$B$10,"○監視",IF(OR($M7<40,$K7<0.2),"▲弱い","－")))) | T7: =IF($D7="","",IF(AND($D7>$G7,$O7>=BB816設定!$B$14,$N7>=BB816設定!$B$15,$M7<=BB816設定!$B$16),"買い可","見送り")) | U7: =IF($D7="","",IF(AND($D7>$H7,$M7>=BB816設定!$B$17,$N7>=BB816設定!$B$18,$O7>=BB816設定!$B$19),"買い可","見送り")) | V7: =IF($S7="◎買い",$D7,"") | W7: =IF($S7="◎買い",ROUND($D7*(1-BB816設定!$B$11/100),1),"") | X7: =IF($S7="◎買い",BB816設定!$B$11/BB816設定!$B$13,"") | Y7: =IF($D7="","",$Q7+(10000-ROW())/100000) | Z7: =IF($D7="","",$D7*BB816設定!$B$21) | AA7: =IF($D7="","",IF($Z7<=BB816設定!$B$20/BB816設定!$B$13,"○","×（1枠に入らない）"))
A8: =IF(終値!A8="","",HYPERLINK("https://kabutan.jp/stock/?code="&終値!A8,"📈")) | B8: =IF(終値!A8="","",終値!A8) | C8: =IF(終値!A8="","",終値!B8) | D8: =IF(終値!A8="","",終値!E8) | E8: =IF($D8="","",AVERAGE(終値!E8:X8)) | F8: =IF($D8="","",STDEVP(終値!E8:X8)) | G8: =IF($D8="","",$E8+BB816設定!$B$4*$F8) | H8: =IF($D8="","",$E8+BB816設定!$B$5*$F8) | I8: =IF($D8="","",$E8-BB816設定!$B$5*$F8) | J8: =IF($D8="","",$E8-BB816設定!$B$4*$F8) | K8: =IF($D8="","",IFERROR(($D8-$J8)/($G8-$J8),"")) | L8: =IF($D8="","",IFERROR(($G8-$J8)/$E8*100,"")) | M8: =IF($D8="","",IFERROR(100-100/(1+SUMPRODUCT((終値!E8:R8>終値!F8:S8)*(終値!E8:R8-終値!F8:S8))/SUMPRODUCT((終値!E8:R8<終値!F8:S8)*(終値!F8:S8-終値!E8:R8))),100)) | N8: =IF($D8="","",IFERROR(100-100/(1+SUMPRODUCT((((高値!E8:R8+安値!E8:R8+終値!E8:R8)/3)>((高値!F8:S8+安値!F8:S8+終値!F8:S8)/3))*((高値!E8:R8+安値!E8:R8+終値!E8:R8)/3)*出来高!E8:R8)/SUMPRODUCT((((高値!E8:R8+安値!E8:R8+終値!E8:R8)/3)<((高値!F8:S8+安値!F8:S8+終値!F8:S8)/3))*((高値!E8:R8+安値!E8:R8+終値!E8:R8)/3)*出来高!E8:R8)),50)) | O8: =IF($D8="","",IFERROR(出来高!E8/AVERAGE(出来高!E8:I8),"")) | P8: =IF($D8="","",IFERROR($D8/終値!Y8-1,"")) | Q8: =IF($D8="","",MAX(0,MIN(100,IF($D8>$G8,25,IF($D8>$H8,15,IF($D8>$E8,5,0)))+IF($O8>=2,20,IF($O8>=1.5,14,IF($O8>=1.2,8,0)))+IF($N8>=80,15,IF($N8>=60,18,IF($N8>=50,8,0)))+IF(AND($M8>70,$M8<=80),18,IF(AND($M8>60,$M8<=70),14,IF(AND($M8>50,$M8<=60),6,0)))+IF($P8>=0.1,14,IF($P8>=0.03,7,0))+IF($M8>80,-12,0)+IF($M8<40,-20,0)+IF($N8<40,-15,0)+IF($K8<0.2,-18,0)+IF($P8<=-0.1,-10,0)))) | R8: =IF($D8="","",IF(AND($D8>$G8,$O8>=BB816設定!$B$6,$N8>=BB816設定!$B$7,$M8<=BB816設定!$B$8),"○","－")) | S8: =IF($D8="","",IF(AND($R8="○",$Q8>=BB816設定!$B$9),"◎買い",IF($Q8>=BB816設定!$B$10,"○監視",IF(OR($M8<40,$K8<0.2),"▲弱い","－")))) | T8: =IF($D8="","",IF(AND($D8>$G8,$O8>=BB816設定!$B$14,$N8>=BB816設定!$B$15,$M8<=BB816設定!$B$16),"買い可","見送り")) | U8: =IF($D8="","",IF(AND($D8>$H8,$M8>=BB816設定!$B$17,$N8>=BB816設定!$B$18,$O8>=BB816設定!$B$19),"買い可","見送り")) | V8: =IF($S8="◎買い",$D8,"") | W8: =IF($S8="◎買い",ROUND($D8*(1-BB816設定!$B$11/100),1),"") | X8: =IF($S8="◎買い",BB816設定!$B$11/BB816設定!$B$13,"") | Y8: =IF($D8="","",$Q8+(10000-ROW())/100000) | Z8: =IF($D8="","",$D8*BB816設定!$B$21) | AA8: =IF($D8="","",IF($Z8<=BB816設定!$B$20/BB816設定!$B$13,"○","×（1枠に入らない）"))
A9: =IF(終値!A9="","",HYPERLINK("https://kabutan.jp/stock/?code="&終値!A9,"📈")) | B9: =IF(終値!A9="","",終値!A9) | C9: =IF(終値!A9="","",終値!B9) | D9: =IF(終値!A9="","",終値!E9) | E9: =IF($D9="","",AVERAGE(終値!E9:X9)) | F9: =IF($D9="","",STDEVP(終値!E9:X9)) | G9: =IF($D9="","",$E9+BB816設定!$B$4*$F9) | H9: =IF($D9="","",$E9+BB816設定!$B$5*$F9) | I9: =IF($D9="","",$E9-BB816設定!$B$5*$F9) | J9: =IF($D9="","",$E9-BB816設定!$B$4*$F9) | K9: =IF($D9="","",IFERROR(($D9-$J9)/($G9-$J9),"")) | L9: =IF($D9="","",IFERROR(($G9-$J9)/$E9*100,"")) | M9: =IF($D9="","",IFERROR(100-100/(1+SUMPRODUCT((終値!E9:R9>終値!F9:S9)*(終値!E9:R9-終値!F9:S9))/SUMPRODUCT((終値!E9:R9<終値!F9:S9)*(終値!F9:S9-終値!E9:R9))),100)) | N9: =IF($D9="","",IFERROR(100-100/(1+SUMPRODUCT((((高値!E9:R9+安値!E9:R9+終値!E9:R9)/3)>((高値!F9:S9+安値!F9:S9+終値!F9:S9)/3))*((高値!E9:R9+安値!E9:R9+終値!E9:R9)/3)*出来高!E9:R9)/SUMPRODUCT((((高値!E9:R9+安値!E9:R9+終値!E9:R9)/3)<((高値!F9:S9+安値!F9:S9+終値!F9:S9)/3))*((高値!E9:R9+安値!E9:R9+終値!E9:R9)/3)*出来高!E9:R9)),50)) | O9: =IF($D9="","",IFERROR(出来高!E9/AVERAGE(出来高!E9:I9),"")) | P9: =IF($D9="","",IFERROR($D9/終値!Y9-1,"")) | Q9: =IF($D9="","",MAX(0,MIN(100,IF($D9>$G9,25,IF($D9>$H9,15,IF($D9>$E9,5,0)))+IF($O9>=2,20,IF($O9>=1.5,14,IF($O9>=1.2,8,0)))+IF($N9>=80,15,IF($N9>=60,18,IF($N9>=50,8,0)))+IF(AND($M9>70,$M9<=80),18,IF(AND($M9>60,$M9<=70),14,IF(AND($M9>50,$M9<=60),6,0)))+IF($P9>=0.1,14,IF($P9>=0.03,7,0))+IF($M9>80,-12,0)+IF($M9<40,-20,0)+IF($N9<40,-15,0)+IF($K9<0.2,-18,0)+IF($P9<=-0.1,-10,0)))) | R9: =IF($D9="","",IF(AND($D9>$G9,$O9>=BB816設定!$B$6,$N9>=BB816設定!$B$7,$M9<=BB816設定!$B$8),"○","－")) | S9: =IF($D9="","",IF(AND($R9="○",$Q9>=BB816設定!$B$9),"◎買い",IF($Q9>=BB816設定!$B$10,"○監視",IF(OR($M9<40,$K9<0.2),"▲弱い","－")))) | T9: =IF($D9="","",IF(AND($D9>$G9,$O9>=BB816設定!$B$14,$N9>=BB816設定!$B$15,$M9<=BB816設定!$B$16),"買い可","見送り")) | U9: =IF($D9="","",IF(AND($D9>$H9,$M9>=BB816設定!$B$17,$N9>=BB816設定!$B$18,$O9>=BB816設定!$B$19),"買い可","見送り")) | V9: =IF($S9="◎買い",$D9,"") | W9: =IF($S9="◎買い",ROUND($D9*(1-BB816設定!$B$11/100),1),"") | X9: =IF($S9="◎買い",BB816設定!$B$11/BB816設定!$B$13,"") | Y9: =IF($D9="","",$Q9+(10000-ROW())/100000) | Z9: =IF($D9="","",$D9*BB816設定!$B$21) | AA9: =IF($D9="","",IF($Z9<=BB816設定!$B$20/BB816設定!$B$13,"○","×（1枠に入らない）"))
A10: =IF(終値!A10="","",HYPERLINK("https://kabutan.jp/stock/?code="&終値!A10,"📈")) | B10: =IF(終値!A10="","",終値!A10) | C10: =IF(終値!A10="","",終値!B10) | D10: =IF(終値!A10="","",終値!E10) | E10: =IF($D10="","",AVERAGE(終値!E10:X10)) | F10: =IF($D10="","",STDEVP(終値!E10:X10)) | G10: =IF($D10="","",$E10+BB816設定!$B$4*$F10) | H10: =IF($D10="","",$E10+BB816設定!$B$5*$F10) | I10: =IF($D10="","",$E10-BB816設定!$B$5*$F10) | J10: =IF($D10="","",$E10-BB816設定!$B$4*$F10) | K10: =IF($D10="","",IFERROR(($D10-$J10)/($G10-$J10),"")) | L10: =IF($D10="","",IFERROR(($G10-$J10)/$E10*100,"")) | M10: =IF($D10="","",IFERROR(100-100/(1+SUMPRODUCT((終値!E10:R10>終値!F10:S10)*(終値!E10:R10-終値!F10:S10))/SUMPRODUCT((終値!E10:R10<終値!F10:S10)*(終値!F10:S10-終値!E10:R10))),100)) | N10: =IF($D10="","",IFERROR(100-100/(1+SUMPRODUCT((((高値!E10:R10+安値!E10:R10+終値!E10:R10)/3)>((高値!F10:S10+安値!F10:S10+終値!F10:S10)/3))*((高値!E10:R10+安値!E10:R10+終値!E10:R10)/3)*出来高!E10:R10)/SUMPRODUCT((((高値!E10:R10+安値!E10:R10+終値!E10:R10)/3)<((高値!F10:S10+安値!F10:S10+終値!F10:S10)/3))*((高値!E10:R10+安値!E10:R10+終値!E10:R10)/3)*出来高!E10:R10)),50)) | O10: =IF($D10="","",IFERROR(出来高!E10/AVERAGE(出来高!E10:I10),"")) | P10: =IF($D10="","",IFERROR($D10/終値!Y10-1,"")) | Q10: =IF($D10="","",MAX(0,MIN(100,IF($D10>$G10,25,IF($D10>$H10,15,IF($D10>$E10,5,0)))+IF($O10>=2,20,IF($O10>=1.5,14,IF($O10>=1.2,8,0)))+IF($N10>=80,15,IF($N10>=60,18,IF($N10>=50,8,0)))+IF(AND($M10>70,$M10<=80),18,IF(AND($M10>60,$M10<=70),14,IF(AND($M10>50,$M10<=60),6,0)))+IF($P10>=0.1,14,IF($P10>=0.03,7,0))+IF($M10>80,-12,0)+IF($M10<40,-20,0)+IF($N10<40,-15,0)+IF($K10<0.2,-18,0)+IF($P10<=-0.1,-10,0)))) | R10: =IF($D10="","",IF(AND($D10>$G10,$O10>=BB816設定!$B$6,$N10>=BB816設定!$B$7,$M10<=BB816設定!$B$8),"○","－")) | S10: =IF($D10="","",IF(AND($R10="○",$Q10>=BB816設定!$B$9),"◎買い",IF($Q10>=BB816設定!$B$10,"○監視",IF(OR($M10<40,$K10<0.2),"▲弱い","－")))) | T10: =IF($D10="","",IF(AND($D10>$G10,$O10>=BB816設定!$B$14,$N10>=BB816設定!$B$15,$M10<=BB816設定!$B$16),"買い可","見送り")) | U10: =IF($D10="","",IF(AND($D10>$H10,$M10>=BB816設定!$B$17,$N10>=BB816設定!$B$18,$O10>=BB816設定!$B$19),"買い可","見送り")) | V10: =IF($S10="◎買い",$D10,"") | W10: =IF($S10="◎買い",ROUND($D10*(1-BB816設定!$B$11/100),1),"") | X10: =IF($S10="◎買い",BB816設定!$B$11/BB816設定!$B$13,"") | Y10: =IF($D10="","",$Q10+(10000-ROW())/100000) | Z10: =IF($D10="","",$D10*BB816設定!$B$21) | AA10: =IF($D10="","",IF($Z10<=BB816設定!$B$20/BB816設定!$B$13,"○","×（1枠に入らない）"))
A11: =IF(終値!A11="","",HYPERLINK("https://kabutan.jp/stock/?code="&終値!A11,"📈")) | B11: =IF(終値!A11="","",終値!A11) | C11: =IF(終値!A11="","",終値!B11) | D11: =IF(終値!A11="","",終値!E11) | E11: =IF($D11="","",AVERAGE(終値!E11:X11)) | F11: =IF($D11="","",STDEVP(終値!E11:X11)) | G11: =IF($D11="","",$E11+BB816設定!$B$4*$F11) | H11: =IF($D11="","",$E11+BB816設定!$B$5*$F11) | I11: =IF($D11="","",$E11-BB816設定!$B$5*$F11) | J11: =IF($D11="","",$E11-BB816設定!$B$4*$F11) | K11: =IF($D11="","",IFERROR(($D11-$J11)/($G11-$J11),"")) | L11: =IF($D11="","",IFERROR(($G11-$J11)/$E11*100,"")) | M11: =IF($D11="","",IFERROR(100-100/(1+SUMPRODUCT((終値!E11:R11>終値!F11:S11)*(終値!E11:R11-終値!F11:S11))/SUMPRODUCT((終値!E11:R11<終値!F11:S11)*(終値!F11:S11-終値!E11:R11))),100)) | N11: =IF($D11="","",IFERROR(100-100/(1+SUMPRODUCT((((高値!E11:R11+安値!E11:R11+終値!E11:R11)/3)>((高値!F11:S11+安値!F11:S11+終値!F11:S11)/3))*((高値!E11:R11+安値!E11:R11+終値!E11:R11)/3)*出来高!E11:R11)/SUMPRODUCT((((高値!E11:R11+安値!E11:R11+終値!E11:R11)/3)<((高値!F11:S11+安値!F11:S11+終値!F11:S11)/3))*((高値!E11:R11+安値!E11:R11+終値!E11:R11)/3)*出来高!E11:R11)),50)) | O11: =IF($D11="","",IFERROR(出来高!E11/AVERAGE(出来高!E11:I11),"")) | P11: =IF($D11="","",IFERROR($D11/終値!Y11-1,"")) | Q11: =IF($D11="","",MAX(0,MIN(100,IF($D11>$G11,25,IF($D11>$H11,15,IF($D11>$E11,5,0)))+IF($O11>=2,20,IF($O11>=1.5,14,IF($O11>=1.2,8,0)))+IF($N11>=80,15,IF($N11>=60,18,IF($N11>=50,8,0)))+IF(AND($M11>70,$M11<=80),18,IF(AND($M11>60,$M11<=70),14,IF(AND($M11>50,$M11<=60),6,0)))+IF($P11>=0.1,14,IF($P11>=0.03,7,0))+IF($M11>80,-12,0)+IF($M11<40,-20,0)+IF($N11<40,-15,0)+IF($K11<0.2,-18,0)+IF($P11<=-0.1,-10,0)))) | R11: =IF($D11="","",IF(AND($D11>$G11,$O11>=BB816設定!$B$6,$N11>=BB816設定!$B$7,$M11<=BB816設定!$B$8),"○","－")) | S11: =IF($D11="","",IF(AND($R11="○",$Q11>=BB816設定!$B$9),"◎買い",IF($Q11>=BB816設定!$B$10,"○監視",IF(OR($M11<40,$K11<0.2),"▲弱い","－")))) | T11: =IF($D11="","",IF(AND($D11>$G11,$O11>=BB816設定!$B$14,$N11>=BB816設定!$B$15,$M11<=BB816設定!$B$16),"買い可","見送り")) | U11: =IF($D11="","",IF(AND($D11>$H11,$M11>=BB816設定!$B$17,$N11>=BB816設定!$B$18,$O11>=BB816設定!$B$19),"買い可","見送り")) | V11: =IF($S11="◎買い",$D11,"") | W11: =IF($S11="◎買い",ROUND($D11*(1-BB816設定!$B$11/100),1),"") | X11: =IF($S11="◎買い",BB816設定!$B$11/BB816設定!$B$13,"") | Y11: =IF($D11="","",$Q11+(10000-ROW())/100000) | Z11: =IF($D11="","",$D11*BB816設定!$B$21) | AA11: =IF($D11="","",IF($Z11<=BB816設定!$B$20/BB816設定!$B$13,"○","×（1枠に入らない）"))
A12: =IF(終値!A12="","",HYPERLINK("https://kabutan.jp/stock/?code="&終値!A12,"📈")) | B12: =IF(終値!A12="","",終値!A12) | C12: =IF(終値!A12="","",終値!B12) | D12: =IF(終値!A12="","",終値!E12) | E12: =IF($D12="","",AVERAGE(終値!E12:X12)) | F12: =IF($D12="","",STDEVP(終値!E12:X12)) | G12: =IF($D12="","",$E12+BB816設定!$B$4*$F12) | H12: =IF($D12="","",$E12+BB816設定!$B$5*$F12) | I12: =IF($D12="","",$E12-BB816設定!$B$5*$F12) | J12: =IF($D12="","",$E12-BB816設定!$B$4*$F12) | K12: =IF($D12="","",IFERROR(($D12-$J12)/($G12-$J12),"")) | L12: =IF($D12="","",IFERROR(($G12-$J12)/$E12*100,"")) | M12: =IF($D12="","",IFERROR(100-100/(1+SUMPRODUCT((終値!E12:R12>終値!F12:S12)*(終値!E12:R12-終値!F12:S12))/SUMPRODUCT((終値!E12:R12<終値!F12:S12)*(終値!F12:S12-終値!E12:R12))),100)) | N12: =IF($D12="","",IFERROR(100-100/(1+SUMPRODUCT((((高値!E12:R12+安値!E12:R12+終値!E12:R12)/3)>((高値!F12:S12+安値!F12:S12+終値!F12:S12)/3))*((高値!E12:R12+安値!E12:R12+終値!E12:R12)/3)*出来高!E12:R12)/SUMPRODUCT((((高値!E12:R12+安値!E12:R12+終値!E12:R12)/3)<((高値!F12:S12+安値!F12:S12+終値!F12:S12)/3))*((高値!E12:R12+安値!E12:R12+終値!E12:R12)/3)*出来高!E12:R12)),50)) | O12: =IF($D12="","",IFERROR(出来高!E12/AVERAGE(出来高!E12:I12),"")) | P12: =IF($D12="","",IFERROR($D12/終値!Y12-1,"")) | Q12: =IF($D12="","",MAX(0,MIN(100,IF($D12>$G12,25,IF($D12>$H12,15,IF($D12>$E12,5,0)))+IF($O12>=2,20,IF($O12>=1.5,14,IF($O12>=1.2,8,0)))+IF($N12>=80,15,IF($N12>=60,18,IF($N12>=50,8,0)))+IF(AND($M12>70,$M12<=80),18,IF(AND($M12>60,$M12<=70),14,IF(AND($M12>50,$M12<=60),6,0)))+IF($P12>=0.1,14,IF($P12>=0.03,7,0))+IF($M12>80,-12,0)+IF($M12<40,-20,0)+IF($N12<40,-15,0)+IF($K12<0.2,-18,0)+IF($P12<=-0.1,-10,0)))) | R12: =IF($D12="","",IF(AND($D12>$G12,$O12>=BB816設定!$B$6,$N12>=BB816設定!$B$7,$M12<=BB816設定!$B$8),"○","－")) | S12: =IF($D12="","",IF(AND($R12="○",$Q12>=BB816設定!$B$9),"◎買い",IF($Q12>=BB816設定!$B$10,"○監視",IF(OR($M12<40,$K12<0.2),"▲弱い","－")))) | T12: =IF($D12="","",IF(AND($D12>$G12,$O12>=BB816設定!$B$14,$N12>=BB816設定!$B$15,$M12<=BB816設定!$B$16),"買い可","見送り")) | U12: =IF($D12="","",IF(AND($D12>$H12,$M12>=BB816設定!$B$17,$N12>=BB816設定!$B$18,$O12>=BB816設定!$B$19),"買い可","見送り")) | V12: =IF($S12="◎買い",$D12,"") | W12: =IF($S12="◎買い",ROUND($D12*(1-BB816設定!$B$11/100),1),"") | X12: =IF($S12="◎買い",BB816設定!$B$11/BB816設定!$B$13,"") | Y12: =IF($D12="","",$Q12+(10000-ROW())/100000) | Z12: =IF($D12="","",$D12*BB816設定!$B$21) | AA12: =IF($D12="","",IF($Z12<=BB816設定!$B$20/BB816設定!$B$13,"○","×（1枠に入らない）"))
A13: =IF(終値!A13="","",HYPERLINK("https://kabutan.jp/stock/?code="&終値!A13,"📈")) | B13: =IF(終値!A13="","",終値!A13) | C13: =IF(終値!A13="","",終値!B13) | D13: =IF(終値!A13="","",終値!E13) | E13: =IF($D13="","",AVERAGE(終値!E13:X13)) | F13: =IF($D13="","",STDEVP(終値!E13:X13)) | G13: =IF($D13="","",$E13+BB816設定!$B$4*$F13) | H13: =IF($D13="","",$E13+BB816設定!$B$5*$F13) | I13: =IF($D13="","",$E13-BB816設定!$B$5*$F13) | J13: =IF($D13="","",$E13-BB816設定!$B$4*$F13) | K13: =IF($D13="","",IFERROR(($D13-$J13)/($G13-$J13),"")) | L13: =IF($D13="","",IFERROR(($G13-$J13)/$E13*100,"")) | M13: =IF($D13="","",IFERROR(100-100/(1+SUMPRODUCT((終値!E13:R13>終値!F13:S13)*(終値!E13:R13-終値!F13:S13))/SUMPRODUCT((終値!E13:R13<終値!F13:S13)*(終値!F13:S13-終値!E13:R13))),100)) | N13: =IF($D13="","",IFERROR(100-100/(1+SUMPRODUCT((((高値!E13:R13+安値!E13:R13+終値!E13:R13)/3)>((高値!F13:S13+安値!F13:S13+終値!F13:S13)/3))*((高値!E13:R13+安値!E13:R13+終値!E13:R13)/3)*出来高!E13:R13)/SUMPRODUCT((((高値!E13:R13+安値!E13:R13+終値!E13:R13)/3)<((高値!F13:S13+安値!F13:S13+終値!F13:S13)/3))*((高値!E13:R13+安値!E13:R13+終値!E13:R13)/3)*出来高!E13:R13)),50)) | O13: =IF($D13="","",IFERROR(出来高!E13/AVERAGE(出来高!E13:I13),"")) | P13: =IF($D13="","",IFERROR($D13/終値!Y13-1,"")) | Q13: =IF($D13="","",MAX(0,MIN(100,IF($D13>$G13,25,IF($D13>$H13,15,IF($D13>$E13,5,0)))+IF($O13>=2,20,IF($O13>=1.5,14,IF($O13>=1.2,8,0)))+IF($N13>=80,15,IF($N13>=60,18,IF($N13>=50,8,0)))+IF(AND($M13>70,$M13<=80),18,IF(AND($M13>60,$M13<=70),14,IF(AND($M13>50,$M13<=60),6,0)))+IF($P13>=0.1,14,IF($P13>=0.03,7,0))+IF($M13>80,-12,0)+IF($M13<40,-20,0)+IF($N13<40,-15,0)+IF($K13<0.2,-18,0)+IF($P13<=-0.1,-10,0)))) | R13: =IF($D13="","",IF(AND($D13>$G13,$O13>=BB816設定!$B$6,$N13>=BB816設定!$B$7,$M13<=BB816設定!$B$8),"○","－")) | S13: =IF($D13="","",IF(AND($R13="○",$Q13>=BB816設定!$B$9),"◎買い",IF($Q13>=BB816設定!$B$10,"○監視",IF(OR($M13<40,$K13<0.2),"▲弱い","－")))) | T13: =IF($D13="","",IF(AND($D13>$G13,$O13>=BB816設定!$B$14,$N13>=BB816設定!$B$15,$M13<=BB816設定!$B$16),"買い可","見送り")) | U13: =IF($D13="","",IF(AND($D13>$H13,$M13>=BB816設定!$B$17,$N13>=BB816設定!$B$18,$O13>=BB816設定!$B$19),"買い可","見送り")) | V13: =IF($S13="◎買い",$D13,"") | W13: =IF($S13="◎買い",ROUND($D13*(1-BB816設定!$B$11/100),1),"") | X13: =IF($S13="◎買い",BB816設定!$B$11/BB816設定!$B$13,"") | Y13: =IF($D13="","",$Q13+(10000-ROW())/100000) | Z13: =IF($D13="","",$D13*BB816設定!$B$21) | AA13: =IF($D13="","",IF($Z13<=BB816設定!$B$20/BB816設定!$B$13,"○","×（1枠に入らない）"))
A14: =IF(終値!A14="","",HYPERLINK("https://kabutan.jp/stock/?code="&終値!A14,"📈")) | B14: =IF(終値!A14="","",終値!A14) | C14: =IF(終値!A14="","",終値!B14) | D14: =IF(終値!A14="","",終値!E14) | E14: =IF($D14="","",AVERAGE(終値!E14:X14)) | F14: =IF($D14="","",STDEVP(終値!E14:X14)) | G14: =IF($D14="","",$E14+BB816設定!$B$4*$F14) | H14: =IF($D14="","",$E14+BB816設定!$B$5*$F14) | I14: =IF($D14="","",$E14-BB816設定!$B$5*$F14) | J14: =IF($D14="","",$E14-BB816設定!$B$4*$F14) | K14: =IF($D14="","",IFERROR(($D14-$J14)/($G14-$J14),"")) | L14: =IF($D14="","",IFERROR(($G14-$J14)/$E14*100,"")) | M14: =IF($D14="","",IFERROR(100-100/(1+SUMPRODUCT((終値!E14:R14>終値!F14:S14)*(終値!E14:R14-終値!F14:S14))/SUMPRODUCT((終値!E14:R14<終値!F14:S14)*(終値!F14:S14-終値!E14:R14))),100)) | N14: =IF($D14="","",IFERROR(100-100/(1+SUMPRODUCT((((高値!E14:R14+安値!E14:R14+終値!E14:R14)/3)>((高値!F14:S14+安値!F14:S14+終値!F14:S14)/3))*((高値!E14:R14+安値!E14:R14+終値!E14:R14)/3)*出来高!E14:R14)/SUMPRODUCT((((高値!E14:R14+安値!E14:R14+終値!E14:R14)/3)<((高値!F14:S14+安値!F14:S14+終値!F14:S14)/3))*((高値!E14:R14+安値!E14:R14+終値!E14:R14)/3)*出来高!E14:R14)),50)) | O14: =IF($D14="","",IFERROR(出来高!E14/AVERAGE(出来高!E14:I14),"")) | P14: =IF($D14="","",IFERROR($D14/終値!Y14-1,"")) | Q14: =IF($D14="","",MAX(0,MIN(100,IF($D14>$G14,25,IF($D14>$H14,15,IF($D14>$E14,5,0)))+IF($O14>=2,20,IF($O14>=1.5,14,IF($O14>=1.2,8,0)))+IF($N14>=80,15,IF($N14>=60,18,IF($N14>=50,8,0)))+IF(AND($M14>70,$M14<=80),18,IF(AND($M14>60,$M14<=70),14,IF(AND($M14>50,$M14<=60),6,0)))+IF($P14>=0.1,14,IF($P14>=0.03,7,0))+IF($M14>80,-12,0)+IF($M14<40,-20,0)+IF($N14<40,-15,0)+IF($K14<0.2,-18,0)+IF($P14<=-0.1,-10,0)))) | R14: =IF($D14="","",IF(AND($D14>$G14,$O14>=BB816設定!$B$6,$N14>=BB816設定!$B$7,$M14<=BB816設定!$B$8),"○","－")) | S14: =IF($D14="","",IF(AND($R14="○",$Q14>=BB816設定!$B$9),"◎買い",IF($Q14>=BB816設定!$B$10,"○監視",IF(OR($M14<40,$K14<0.2),"▲弱い","－")))) | T14: =IF($D14="","",IF(AND($D14>$G14,$O14>=BB816設定!$B$14,$N14>=BB816設定!$B$15,$M14<=BB816設定!$B$16),"買い可","見送り")) | U14: =IF($D14="","",IF(AND($D14>$H14,$M14>=BB816設定!$B$17,$N14>=BB816設定!$B$18,$O14>=BB816設定!$B$19),"買い可","見送り")) | V14: =IF($S14="◎買い",$D14,"") | W14: =IF($S14="◎買い",ROUND($D14*(1-BB816設定!$B$11/100),1),"") | X14: =IF($S14="◎買い",BB816設定!$B$11/BB816設定!$B$13,"") | Y14: =IF($D14="","",$Q14+(10000-ROW())/100000) | Z14: =IF($D14="","",$D14*BB816設定!$B$21) | AA14: =IF($D14="","",IF($Z14<=BB816設定!$B$20/BB816設定!$B$13,"○","×（1枠に入らない）"))
A15: =IF(終値!A15="","",HYPERLINK("https://kabutan.jp/stock/?code="&終値!A15,"📈")) | B15: =IF(終値!A15="","",終値!A15) | C15: =IF(終値!A15="","",終値!B15) | D15: =IF(終値!A15="","",終値!E15) | E15: =IF($D15="","",AVERAGE(終値!E15:X15)) | F15: =IF($D15="","",STDEVP(終値!E15:X15)) | G15: =IF($D15="","",$E15+BB816設定!$B$4*$F15) | H15: =IF($D15="","",$E15+BB816設定!$B$5*$F15) | I15: =IF($D15="","",$E15-BB816設定!$B$5*$F15) | J15: =IF($D15="","",$E15-BB816設定!$B$4*$F15) | K15: =IF($D15="","",IFERROR(($D15-$J15)/($G15-$J15),"")) | L15: =IF($D15="","",IFERROR(($G15-$J15)/$E15*100,"")) | M15: =IF($D15="","",IFERROR(100-100/(1+SUMPRODUCT((終値!E15:R15>終値!F15:S15)*(終値!E15:R15-終値!F15:S15))/SUMPRODUCT((終値!E15:R15<終値!F15:S15)*(終値!F15:S15-終値!E15:R15))),100)) | N15: =IF($D15="","",IFERROR(100-100/(1+SUMPRODUCT((((高値!E15:R15+安値!E15:R15+終値!E15:R15)/3)>((高値!F15:S15+安値!F15:S15+終値!F15:S15)/3))*((高値!E15:R15+安値!E15:R15+終値!E15:R15)/3)*出来高!E15:R15)/SUMPRODUCT((((高値!E15:R15+安値!E15:R15+終値!E15:R15)/3)<((高値!F15:S15+安値!F15:S15+終値!F15:S15)/3))*((高値!E15:R15+安値!E15:R15+終値!E15:R15)/3)*出来高!E15:R15)),50)) | O15: =IF($D15="","",IFERROR(出来高!E15/AVERAGE(出来高!E15:I15),"")) | P15: =IF($D15="","",IFERROR($D15/終値!Y15-1,"")) | Q15: =IF($D15="","",MAX(0,MIN(100,IF($D15>$G15,25,IF($D15>$H15,15,IF($D15>$E15,5,0)))+IF($O15>=2,20,IF($O15>=1.5,14,IF($O15>=1.2,8,0)))+IF($N15>=80,15,IF($N15>=60,18,IF($N15>=50,8,0)))+IF(AND($M15>70,$M15<=80),18,IF(AND($M15>60,$M15<=70),14,IF(AND($M15>50,$M15<=60),6,0)))+IF($P15>=0.1,14,IF($P15>=0.03,7,0))+IF($M15>80,-12,0)+IF($M15<40,-20,0)+IF($N15<40,-15,0)+IF($K15<0.2,-18,0)+IF($P15<=-0.1,-10,0)))) | R15: =IF($D15="","",IF(AND($D15>$G15,$O15>=BB816設定!$B$6,$N15>=BB816設定!$B$7,$M15<=BB816設定!$B$8),"○","－")) | S15: =IF($D15="","",IF(AND($R15="○",$Q15>=BB816設定!$B$9),"◎買い",IF($Q15>=BB816設定!$B$10,"○監視",IF(OR($M15<40,$K15<0.2),"▲弱い","－")))) | T15: =IF($D15="","",IF(AND($D15>$G15,$O15>=BB816設定!$B$14,$N15>=BB816設定!$B$15,$M15<=BB816設定!$B$16),"買い可","見送り")) | U15: =IF($D15="","",IF(AND($D15>$H15,$M15>=BB816設定!$B$17,$N15>=BB816設定!$B$18,$O15>=BB816設定!$B$19),"買い可","見送り")) | V15: =IF($S15="◎買い",$D15,"") | W15: =IF($S15="◎買い",ROUND($D15*(1-BB816設定!$B$11/100),1),"") | X15: =IF($S15="◎買い",BB816設定!$B$11/BB816設定!$B$13,"") | Y15: =IF($D15="","",$Q15+(10000-ROW())/100000) | Z15: =IF($D15="","",$D15*BB816設定!$B$21) | AA15: =IF($D15="","",IF($Z15<=BB816設定!$B$20/BB816設定!$B$13,"○","×（1枠に入らない）"))
A16: =IF(終値!A16="","",HYPERLINK("https://kabutan.jp/stock/?code="&終値!A16,"📈")) | B16: =IF(終値!A16="","",終値!A16) | C16: =IF(終値!A16="","",終値!B16) | D16: =IF(終値!A16="","",終値!E16) | E16: =IF($D16="","",AVERAGE(終値!E16:X16)) | F16: =IF($D16="","",STDEVP(終値!E16:X16)) | G16: =IF($D16="","",$E16+BB816設定!$B$4*$F16) | H16: =IF($D16="","",$E16+BB816設定!$B$5*$F16) | I16: =IF($D16="","",$E16-BB816設定!$B$5*$F16) | J16: =IF($D16="","",$E16-BB816設定!$B$4*$F16) | K16: =IF($D16="","",IFERROR(($D16-$J16)/($G16-$J16),"")) | L16: =IF($D16="","",IFERROR(($G16-$J16)/$E16*100,"")) | M16: =IF($D16="","",IFERROR(100-100/(1+SUMPRODUCT((終値!E16:R16>終値!F16:S16)*(終値!E16:R16-終値!F16:S16))/SUMPRODUCT((終値!E16:R16<終値!F16:S16)*(終値!F16:S16-終値!E16:R16))),100)) | N16: =IF($D16="","",IFERROR(100-100/(1+SUMPRODUCT((((高値!E16:R16+安値!E16:R16+終値!E16:R16)/3)>((高値!F16:S16+安値!F16:S16+終値!F16:S16)/3))*((高値!E16:R16+安値!E16:R16+終値!E16:R16)/3)*出来高!E16:R16)/SUMPRODUCT((((高値!E16:R16+安値!E16:R16+終値!E16:R16)/3)<((高値!F16:S16+安値!F16:S16+終値!F16:S16)/3))*((高値!E16:R16+安値!E16:R16+終値!E16:R16)/3)*出来高!E16:R16)),50)) | O16: =IF($D16="","",IFERROR(出来高!E16/AVERAGE(出来高!E16:I16),"")) | P16: =IF($D16="","",IFERROR($D16/終値!Y16-1,"")) | Q16: =IF($D16="","",MAX(0,MIN(100,IF($D16>$G16,25,IF($D16>$H16,15,IF($D16>$E16,5,0)))+IF($O16>=2,20,IF($O16>=1.5,14,IF($O16>=1.2,8,0)))+IF($N16>=80,15,IF($N16>=60,18,IF($N16>=50,8,0)))+IF(AND($M16>70,$M16<=80),18,IF(AND($M16>60,$M16<=70),14,IF(AND($M16>50,$M16<=60),6,0)))+IF($P16>=0.1,14,IF($P16>=0.03,7,0))+IF($M16>80,-12,0)+IF($M16<40,-20,0)+IF($N16<40,-15,0)+IF($K16<0.2,-18,0)+IF($P16<=-0.1,-10,0)))) | R16: =IF($D16="","",IF(AND($D16>$G16,$O16>=BB816設定!$B$6,$N16>=BB816設定!$B$7,$M16<=BB816設定!$B$8),"○","－")) | S16: =IF($D16="","",IF(AND($R16="○",$Q16>=BB816設定!$B$9),"◎買い",IF($Q16>=BB816設定!$B$10,"○監視",IF(OR($M16<40,$K16<0.2),"▲弱い","－")))) | T16: =IF($D16="","",IF(AND($D16>$G16,$O16>=BB816設定!$B$14,$N16>=BB816設定!$B$15,$M16<=BB816設定!$B$16),"買い可","見送り")) | U16: =IF($D16="","",IF(AND($D16>$H16,$M16>=BB816設定!$B$17,$N16>=BB816設定!$B$18,$O16>=BB816設定!$B$19),"買い可","見送り")) | V16: =IF($S16="◎買い",$D16,"") | W16: =IF($S16="◎買い",ROUND($D16*(1-BB816設定!$B$11/100),1),"") | X16: =IF($S16="◎買い",BB816設定!$B$11/BB816設定!$B$13,"") | Y16: =IF($D16="","",$Q16+(10000-ROW())/100000) | Z16: =IF($D16="","",$D16*BB816設定!$B$21) | AA16: =IF($D16="","",IF($Z16<=BB816設定!$B$20/BB816設定!$B$13,"○","×（1枠に入らない）"))
A17: =IF(終値!A17="","",HYPERLINK("https://kabutan.jp/stock/?code="&終値!A17,"📈")) | B17: =IF(終値!A17="","",終値!A17) | C17: =IF(終値!A17="","",終値!B17) | D17: =IF(終値!A17="","",終値!E17) | E17: =IF($D17="","",AVERAGE(終値!E17:X17)) | F17: =IF($D17="","",STDEVP(終値!E17:X17)) | G17: =IF($D17="","",$E17+BB816設定!$B$4*$F17) | H17: =IF($D17="","",$E17+BB816設定!$B$5*$F17) | I17: =IF($D17="","",$E17-BB816設定!$B$5*$F17) | J17: =IF($D17="","",$E17-BB816設定!$B$4*$F17) | K17: =IF($D17="","",IFERROR(($D17-$J17)/($G17-$J17),"")) | L17: =IF($D17="","",IFERROR(($G17-$J17)/$E17*100,"")) | M17: =IF($D17="","",IFERROR(100-100/(1+SUMPRODUCT((終値!E17:R17>終値!F17:S17)*(終値!E17:R17-終値!F17:S17))/SUMPRODUCT((終値!E17:R17<終値!F17:S17)*(終値!F17:S17-終値!E17:R17))),100)) | N17: =IF($D17="","",IFERROR(100-100/(1+SUMPRODUCT((((高値!E17:R17+安値!E17:R17+終値!E17:R17)/3)>((高値!F17:S17+安値!F17:S17+終値!F17:S17)/3))*((高値!E17:R17+安値!E17:R17+終値!E17:R17)/3)*出来高!E17:R17)/SUMPRODUCT((((高値!E17:R17+安値!E17:R17+終値!E17:R17)/3)<((高値!F17:S17+安値!F17:S17+終値!F17:S17)/3))*((高値!E17:R17+安値!E17:R17+終値!E17:R17)/3)*出来高!E17:R17)),50)) | O17: =IF($D17="","",IFERROR(出来高!E17/AVERAGE(出来高!E17:I17),"")) | P17: =IF($D17="","",IFERROR($D17/終値!Y17-1,"")) | Q17: =IF($D17="","",MAX(0,MIN(100,IF($D17>$G17,25,IF($D17>$H17,15,IF($D17>$E17,5,0)))+IF($O17>=2,20,IF($O17>=1.5,14,IF($O17>=1.2,8,0)))+IF($N17>=80,15,IF($N17>=60,18,IF($N17>=50,8,0)))+IF(AND($M17>70,$M17<=80),18,IF(AND($M17>60,$M17<=70),14,IF(AND($M17>50,$M17<=60),6,0)))+IF($P17>=0.1,14,IF($P17>=0.03,7,0))+IF($M17>80,-12,0)+IF($M17<40,-20,0)+IF($N17<40,-15,0)+IF($K17<0.2,-18,0)+IF($P17<=-0.1,-10,0)))) | R17: =IF($D17="","",IF(AND($D17>$G17,$O17>=BB816設定!$B$6,$N17>=BB816設定!$B$7,$M17<=BB816設定!$B$8),"○","－")) | S17: =IF($D17="","",IF(AND($R17="○",$Q17>=BB816設定!$B$9),"◎買い",IF($Q17>=BB816設定!$B$10,"○監視",IF(OR($M17<40,$K17<0.2),"▲弱い","－")))) | T17: =IF($D17="","",IF(AND($D17>$G17,$O17>=BB816設定!$B$14,$N17>=BB816設定!$B$15,$M17<=BB816設定!$B$16),"買い可","見送り")) | U17: =IF($D17="","",IF(AND($D17>$H17,$M17>=BB816設定!$B$17,$N17>=BB816設定!$B$18,$O17>=BB816設定!$B$19),"買い可","見送り")) | V17: =IF($S17="◎買い",$D17,"") | W17: =IF($S17="◎買い",ROUND($D17*(1-BB816設定!$B$11/100),1),"") | X17: =IF($S17="◎買い",BB816設定!$B$11/BB816設定!$B$13,"") | Y17: =IF($D17="","",$Q17+(10000-ROW())/100000) | Z17: =IF($D17="","",$D17*BB816設定!$B$21) | AA17: =IF($D17="","",IF($Z17<=BB816設定!$B$20/BB816設定!$B$13,"○","×（1枠に入らない）"))
A18: =IF(終値!A18="","",HYPERLINK("https://kabutan.jp/stock/?code="&終値!A18,"📈")) | B18: =IF(終値!A18="","",終値!A18) | C18: =IF(終値!A18="","",終値!B18) | D18: =IF(終値!A18="","",終値!E18) | E18: =IF($D18="","",AVERAGE(終値!E18:X18)) | F18: =IF($D18="","",STDEVP(終値!E18:X18)) | G18: =IF($D18="","",$E18+BB816設定!$B$4*$F18) | H18: =IF($D18="","",$E18+BB816設定!$B$5*$F18) | I18: =IF($D18="","",$E18-BB816設定!$B$5*$F18) | J18: =IF($D18="","",$E18-BB816設定!$B$4*$F18) | K18: =IF($D18="","",IFERROR(($D18-$J18)/($G18-$J18),"")) | L18: =IF($D18="","",IFERROR(($G18-$J18)/$E18*100,"")) | M18: =IF($D18="","",IFERROR(100-100/(1+SUMPRODUCT((終値!E18:R18>終値!F18:S18)*(終値!E18:R18-終値!F18:S18))/SUMPRODUCT((終値!E18:R18<終値!F18:S18)*(終値!F18:S18-終値!E18:R18))),100)) | N18: =IF($D18="","",IFERROR(100-100/(1+SUMPRODUCT((((高値!E18:R18+安値!E18:R18+終値!E18:R18)/3)>((高値!F18:S18+安値!F18:S18+終値!F18:S18)/3))*((高値!E18:R18+安値!E18:R18+終値!E18:R18)/3)*出来高!E18:R18)/SUMPRODUCT((((高値!E18:R18+安値!E18:R18+終値!E18:R18)/3)<((高値!F18:S18+安値!F18:S18+終値!F18:S18)/3))*((高値!E18:R18+安値!E18:R18+終値!E18:R18)/3)*出来高!E18:R18)),50)) | O18: =IF($D18="","",IFERROR(出来高!E18/AVERAGE(出来高!E18:I18),"")) | P18: =IF($D18="","",IFERROR($D18/終値!Y18-1,"")) | Q18: =IF($D18="","",MAX(0,MIN(100,IF($D18>$G18,25,IF($D18>$H18,15,IF($D18>$E18,5,0)))+IF($O18>=2,20,IF($O18>=1.5,14,IF($O18>=1.2,8,0)))+IF($N18>=80,15,IF($N18>=60,18,IF($N18>=50,8,0)))+IF(AND($M18>70,$M18<=80),18,IF(AND($M18>60,$M18<=70),14,IF(AND($M18>50,$M18<=60),6,0)))+IF($P18>=0.1,14,IF($P18>=0.03,7,0))+IF($M18>80,-12,0)+IF($M18<40,-20,0)+IF($N18<40,-15,0)+IF($K18<0.2,-18,0)+IF($P18<=-0.1,-10,0)))) | R18: =IF($D18="","",IF(AND($D18>$G18,$O18>=BB816設定!$B$6,$N18>=BB816設定!$B$7,$M18<=BB816設定!$B$8),"○","－")) | S18: =IF($D18="","",IF(AND($R18="○",$Q18>=BB816設定!$B$9),"◎買い",IF($Q18>=BB816設定!$B$10,"○監視",IF(OR($M18<40,$K18<0.2),"▲弱い","－")))) | T18: =IF($D18="","",IF(AND($D18>$G18,$O18>=BB816設定!$B$14,$N18>=BB816設定!$B$15,$M18<=BB816設定!$B$16),"買い可","見送り")) | U18: =IF($D18="","",IF(AND($D18>$H18,$M18>=BB816設定!$B$17,$N18>=BB816設定!$B$18,$O18>=BB816設定!$B$19),"買い可","見送り")) | V18: =IF($S18="◎買い",$D18,"") | W18: =IF($S18="◎買い",ROUND($D18*(1-BB816設定!$B$11/100),1),"") | X18: =IF($S18="◎買い",BB816設定!$B$11/BB816設定!$B$13,"") | Y18: =IF($D18="","",$Q18+(10000-ROW())/100000) | Z18: =IF($D18="","",$D18*BB816設定!$B$21) | AA18: =IF($D18="","",IF($Z18<=BB816設定!$B$20/BB816設定!$B$13,"○","×（1枠に入らない）"))
A19: =IF(終値!A19="","",HYPERLINK("https://kabutan.jp/stock/?code="&終値!A19,"📈")) | B19: =IF(終値!A19="","",終値!A19) | C19: =IF(終値!A19="","",終値!B19) | D19: =IF(終値!A19="","",終値!E19) | E19: =IF($D19="","",AVERAGE(終値!E19:X19)) | F19: =IF($D19="","",STDEVP(終値!E19:X19)) | G19: =IF($D19="","",$E19+BB816設定!$B$4*$F19) | H19: =IF($D19="","",$E19+BB816設定!$B$5*$F19) | I19: =IF($D19="","",$E19-BB816設定!$B$5*$F19) | J19: =IF($D19="","",$E19-BB816設定!$B$4*$F19) | K19: =IF($D19="","",IFERROR(($D19-$J19)/($G19-$J19),"")) | L19: =IF($D19="","",IFERROR(($G19-$J19)/$E19*100,"")) | M19: =IF($D19="","",IFERROR(100-100/(1+SUMPRODUCT((終値!E19:R19>終値!F19:S19)*(終値!E19:R19-終値!F19:S19))/SUMPRODUCT((終値!E19:R19<終値!F19:S19)*(終値!F19:S19-終値!E19:R19))),100)) | N19: =IF($D19="","",IFERROR(100-100/(1+SUMPRODUCT((((高値!E19:R19+安値!E19:R19+終値!E19:R19)/3)>((高値!F19:S19+安値!F19:S19+終値!F19:S19)/3))*((高値!E19:R19+安値!E19:R19+終値!E19:R19)/3)*出来高!E19:R19)/SUMPRODUCT((((高値!E19:R19+安値!E19:R19+終値!E19:R19)/3)<((高値!F19:S19+安値!F19:S19+終値!F19:S19)/3))*((高値!E19:R19+安値!E19:R19+終値!E19:R19)/3)*出来高!E19:R19)),50)) | O19: =IF($D19="","",IFERROR(出来高!E19/AVERAGE(出来高!E19:I19),"")) | P19: =IF($D19="","",IFERROR($D19/終値!Y19-1,"")) | Q19: =IF($D19="","",MAX(0,MIN(100,IF($D19>$G19,25,IF($D19>$H19,15,IF($D19>$E19,5,0)))+IF($O19>=2,20,IF($O19>=1.5,14,IF($O19>=1.2,8,0)))+IF($N19>=80,15,IF($N19>=60,18,IF($N19>=50,8,0)))+IF(AND($M19>70,$M19<=80),18,IF(AND($M19>60,$M19<=70),14,IF(AND($M19>50,$M19<=60),6,0)))+IF($P19>=0.1,14,IF($P19>=0.03,7,0))+IF($M19>80,-12,0)+IF($M19<40,-20,0)+IF($N19<40,-15,0)+IF($K19<0.2,-18,0)+IF($P19<=-0.1,-10,0)))) | R19: =IF($D19="","",IF(AND($D19>$G19,$O19>=BB816設定!$B$6,$N19>=BB816設定!$B$7,$M19<=BB816設定!$B$8),"○","－")) | S19: =IF($D19="","",IF(AND($R19="○",$Q19>=BB816設定!$B$9),"◎買い",IF($Q19>=BB816設定!$B$10,"○監視",IF(OR($M19<40,$K19<0.2),"▲弱い","－")))) | T19: =IF($D19="","",IF(AND($D19>$G19,$O19>=BB816設定!$B$14,$N19>=BB816設定!$B$15,$M19<=BB816設定!$B$16),"買い可","見送り")) | U19: =IF($D19="","",IF(AND($D19>$H19,$M19>=BB816設定!$B$17,$N19>=BB816設定!$B$18,$O19>=BB816設定!$B$19),"買い可","見送り")) | V19: =IF($S19="◎買い",$D19,"") | W19: =IF($S19="◎買い",ROUND($D19*(1-BB816設定!$B$11/100),1),"") | X19: =IF($S19="◎買い",BB816設定!$B$11/BB816設定!$B$13,"") | Y19: =IF($D19="","",$Q19+(10000-ROW())/100000) | Z19: =IF($D19="","",$D19*BB816設定!$B$21) | AA19: =IF($D19="","",IF($Z19<=BB816設定!$B$20/BB816設定!$B$13,"○","×（1枠に入らない）"))
A20: =IF(終値!A20="","",HYPERLINK("https://kabutan.jp/stock/?code="&終値!A20,"📈")) | B20: =IF(終値!A20="","",終値!A20) | C20: =IF(終値!A20="","",終値!B20) | D20: =IF(終値!A20="","",終値!E20) | E20: =IF($D20="","",AVERAGE(終値!E20:X20)) | F20: =IF($D20="","",STDEVP(終値!E20:X20)) | G20: =IF($D20="","",$E20+BB816設定!$B$4*$F20) | H20: =IF($D20="","",$E20+BB816設定!$B$5*$F20) | I20: =IF($D20="","",$E20-BB816設定!$B$5*$F20) | J20: =IF($D20="","",$E20-BB816設定!$B$4*$F20) | K20: =IF($D20="","",IFERROR(($D20-$J20)/($G20-$J20),"")) | L20: =IF($D20="","",IFERROR(($G20-$J20)/$E20*100,"")) | M20: =IF($D20="","",IFERROR(100-100/(1+SUMPRODUCT((終値!E20:R20>終値!F20:S20)*(終値!E20:R20-終値!F20:S20))/SUMPRODUCT((終値!E20:R20<終値!F20:S20)*(終値!F20:S20-終値!E20:R20))),100)) | N20: =IF($D20="","",IFERROR(100-100/(1+SUMPRODUCT((((高値!E20:R20+安値!E20:R20+終値!E20:R20)/3)>((高値!F20:S20+安値!F20:S20+終値!F20:S20)/3))*((高値!E20:R20+安値!E20:R20+終値!E20:R20)/3)*出来高!E20:R20)/SUMPRODUCT((((高値!E20:R20+安値!E20:R20+終値!E20:R20)/3)<((高値!F20:S20+安値!F20:S20+終値!F20:S20)/3))*((高値!E20:R20+安値!E20:R20+終値!E20:R20)/3)*出来高!E20:R20)),50)) | O20: =IF($D20="","",IFERROR(出来高!E20/AVERAGE(出来高!E20:I20),"")) | P20: =IF($D20="","",IFERROR($D20/終値!Y20-1,"")) | Q20: =IF($D20="","",MAX(0,MIN(100,IF($D20>$G20,25,IF($D20>$H20,15,IF($D20>$E20,5,0)))+IF($O20>=2,20,IF($O20>=1.5,14,IF($O20>=1.2,8,0)))+IF($N20>=80,15,IF($N20>=60,18,IF($N20>=50,8,0)))+IF(AND($M20>70,$M20<=80),18,IF(AND($M20>60,$M20<=70),14,IF(AND($M20>50,$M20<=60),6,0)))+IF($P20>=0.1,14,IF($P20>=0.03,7,0))+IF($M20>80,-12,0)+IF($M20<40,-20,0)+IF($N20<40,-15,0)+IF($K20<0.2,-18,0)+IF($P20<=-0.1,-10,0)))) | R20: =IF($D20="","",IF(AND($D20>$G20,$O20>=BB816設定!$B$6,$N20>=BB816設定!$B$7,$M20<=BB816設定!$B$8),"○","－")) | S20: =IF($D20="","",IF(AND($R20="○",$Q20>=BB816設定!$B$9),"◎買い",IF($Q20>=BB816設定!$B$10,"○監視",IF(OR($M20<40,$K20<0.2),"▲弱い","－")))) | T20: =IF($D20="","",IF(AND($D20>$G20,$O20>=BB816設定!$B$14,$N20>=BB816設定!$B$15,$M20<=BB816設定!$B$16),"買い可","見送り")) | U20: =IF($D20="","",IF(AND($D20>$H20,$M20>=BB816設定!$B$17,$N20>=BB816設定!$B$18,$O20>=BB816設定!$B$19),"買い可","見送り")) | V20: =IF($S20="◎買い",$D20,"") | W20: =IF($S20="◎買い",ROUND($D20*(1-BB816設定!$B$11/100),1),"") | X20: =IF($S20="◎買い",BB816設定!$B$11/BB816設定!$B$13,"") | Y20: =IF($D20="","",$Q20+(10000-ROW())/100000) | Z20: =IF($D20="","",$D20*BB816設定!$B$21) | AA20: =IF($D20="","",IF($Z20<=BB816設定!$B$20/BB816設定!$B$13,"○","×（1枠に入らない）"))
A21: =IF(終値!A21="","",HYPERLINK("https://kabutan.jp/stock/?code="&終値!A21,"📈")) | B21: =IF(終値!A21="","",終値!A21) | C21: =IF(終値!A21="","",終値!B21) | D21: =IF(終値!A21="","",終値!E21) | E21: =IF($D21="","",AVERAGE(終値!E21:X21)) | F21: =IF($D21="","",STDEVP(終値!E21:X21)) | G21: =IF($D21="","",$E21+BB816設定!$B$4*$F21) | H21: =IF($D21="","",$E21+BB816設定!$B$5*$F21) | I21: =IF($D21="","",$E21-BB816設定!$B$5*$F21) | J21: =IF($D21="","",$E21-BB816設定!$B$4*$F21) | K21: =IF($D21="","",IFERROR(($D21-$J21)/($G21-$J21),"")) | L21: =IF($D21="","",IFERROR(($G21-$J21)/$E21*100,"")) | M21: =IF($D21="","",IFERROR(100-100/(1+SUMPRODUCT((終値!E21:R21>終値!F21:S21)*(終値!E21:R21-終値!F21:S21))/SUMPRODUCT((終値!E21:R21<終値!F21:S21)*(終値!F21:S21-終値!E21:R21))),100)) | N21: =IF($D21="","",IFERROR(100-100/(1+SUMPRODUCT((((高値!E21:R21+安値!E21:R21+終値!E21:R21)/3)>((高値!F21:S21+安値!F21:S21+終値!F21:S21)/3))*((高値!E21:R21+安値!E21:R21+終値!E21:R21)/3)*出来高!E21:R21)/SUMPRODUCT((((高値!E21:R21+安値!E21:R21+終値!E21:R21)/3)<((高値!F21:S21+安値!F21:S21+終値!F21:S21)/3))*((高値!E21:R21+安値!E21:R21+終値!E21:R21)/3)*出来高!E21:R21)),50)) | O21: =IF($D21="","",IFERROR(出来高!E21/AVERAGE(出来高!E21:I21),"")) | P21: =IF($D21="","",IFERROR($D21/終値!Y21-1,"")) | Q21: =IF($D21="","",MAX(0,MIN(100,IF($D21>$G21,25,IF($D21>$H21,15,IF($D21>$E21,5,0)))+IF($O21>=2,20,IF($O21>=1.5,14,IF($O21>=1.2,8,0)))+IF($N21>=80,15,IF($N21>=60,18,IF($N21>=50,8,0)))+IF(AND($M21>70,$M21<=80),18,IF(AND($M21>60,$M21<=70),14,IF(AND($M21>50,$M21<=60),6,0)))+IF($P21>=0.1,14,IF($P21>=0.03,7,0))+IF($M21>80,-12,0)+IF($M21<40,-20,0)+IF($N21<40,-15,0)+IF($K21<0.2,-18,0)+IF($P21<=-0.1,-10,0)))) | R21: =IF($D21="","",IF(AND($D21>$G21,$O21>=BB816設定!$B$6,$N21>=BB816設定!$B$7,$M21<=BB816設定!$B$8),"○","－")) | S21: =IF($D21="","",IF(AND($R21="○",$Q21>=BB816設定!$B$9),"◎買い",IF($Q21>=BB816設定!$B$10,"○監視",IF(OR($M21<40,$K21<0.2),"▲弱い","－")))) | T21: =IF($D21="","",IF(AND($D21>$G21,$O21>=BB816設定!$B$14,$N21>=BB816設定!$B$15,$M21<=BB816設定!$B$16),"買い可","見送り")) | U21: =IF($D21="","",IF(AND($D21>$H21,$M21>=BB816設定!$B$17,$N21>=BB816設定!$B$18,$O21>=BB816設定!$B$19),"買い可","見送り")) | V21: =IF($S21="◎買い",$D21,"") | W21: =IF($S21="◎買い",ROUND($D21*(1-BB816設定!$B$11/100),1),"") | X21: =IF($S21="◎買い",BB816設定!$B$11/BB816設定!$B$13,"") | Y21: =IF($D21="","",$Q21+(10000-ROW())/100000) | Z21: =IF($D21="","",$D21*BB816設定!$B$21) | AA21: =IF($D21="","",IF($Z21<=BB816設定!$B$20/BB816設定!$B$13,"○","×（1枠に入らない）"))
A22: =IF(終値!A22="","",HYPERLINK("https://kabutan.jp/stock/?code="&終値!A22,"📈")) | B22: =IF(終値!A22="","",終値!A22) | C22: =IF(終値!A22="","",終値!B22) | D22: =IF(終値!A22="","",終値!E22) | E22: =IF($D22="","",AVERAGE(終値!E22:X22)) | F22: =IF($D22="","",STDEVP(終値!E22:X22)) | G22: =IF($D22="","",$E22+BB816設定!$B$4*$F22) | H22: =IF($D22="","",$E22+BB816設定!$B$5*$F22) | I22: =IF($D22="","",$E22-BB816設定!$B$5*$F22) | J22: =IF($D22="","",$E22-BB816設定!$B$4*$F22) | K22: =IF($D22="","",IFERROR(($D22-$J22)/($G22-$J22),"")) | L22: =IF($D22="","",IFERROR(($G22-$J22)/$E22*100,"")) | M22: =IF($D22="","",IFERROR(100-100/(1+SUMPRODUCT((終値!E22:R22>終値!F22:S22)*(終値!E22:R22-終値!F22:S22))/SUMPRODUCT((終値!E22:R22<終値!F22:S22)*(終値!F22:S22-終値!E22:R22))),100)) | N22: =IF($D22="","",IFERROR(100-100/(1+SUMPRODUCT((((高値!E22:R22+安値!E22:R22+終値!E22:R22)/3)>((高値!F22:S22+安値!F22:S22+終値!F22:S22)/3))*((高値!E22:R22+安値!E22:R22+終値!E22:R22)/3)*出来高!E22:R22)/SUMPRODUCT((((高値!E22:R22+安値!E22:R22+終値!E22:R22)/3)<((高値!F22:S22+安値!F22:S22+終値!F22:S22)/3))*((高値!E22:R22+安値!E22:R22+終値!E22:R22)/3)*出来高!E22:R22)),50)) | O22: =IF($D22="","",IFERROR(出来高!E22/AVERAGE(出来高!E22:I22),"")) | P22: =IF($D22="","",IFERROR($D22/終値!Y22-1,"")) | Q22: =IF($D22="","",MAX(0,MIN(100,IF($D22>$G22,25,IF($D22>$H22,15,IF($D22>$E22,5,0)))+IF($O22>=2,20,IF($O22>=1.5,14,IF($O22>=1.2,8,0)))+IF($N22>=80,15,IF($N22>=60,18,IF($N22>=50,8,0)))+IF(AND($M22>70,$M22<=80),18,IF(AND($M22>60,$M22<=70),14,IF(AND($M22>50,$M22<=60),6,0)))+IF($P22>=0.1,14,IF($P22>=0.03,7,0))+IF($M22>80,-12,0)+IF($M22<40,-20,0)+IF($N22<40,-15,0)+IF($K22<0.2,-18,0)+IF($P22<=-0.1,-10,0)))) | R22: =IF($D22="","",IF(AND($D22>$G22,$O22>=BB816設定!$B$6,$N22>=BB816設定!$B$7,$M22<=BB816設定!$B$8),"○","－")) | S22: =IF($D22="","",IF(AND($R22="○",$Q22>=BB816設定!$B$9),"◎買い",IF($Q22>=BB816設定!$B$10,"○監視",IF(OR($M22<40,$K22<0.2),"▲弱い","－")))) | T22: =IF($D22="","",IF(AND($D22>$G22,$O22>=BB816設定!$B$14,$N22>=BB816設定!$B$15,$M22<=BB816設定!$B$16),"買い可","見送り")) | U22: =IF($D22="","",IF(AND($D22>$H22,$M22>=BB816設定!$B$17,$N22>=BB816設定!$B$18,$O22>=BB816設定!$B$19),"買い可","見送り")) | V22: =IF($S22="◎買い",$D22,"") | W22: =IF($S22="◎買い",ROUND($D22*(1-BB816設定!$B$11/100),1),"") | X22: =IF($S22="◎買い",BB816設定!$B$11/BB816設定!$B$13,"") | Y22: =IF($D22="","",$Q22+(10000-ROW())/100000) | Z22: =IF($D22="","",$D22*BB816設定!$B$21) | AA22: =IF($D22="","",IF($Z22<=BB816設定!$B$20/BB816設定!$B$13,"○","×（1枠に入らない）"))
A23: =IF(終値!A23="","",HYPERLINK("https://kabutan.jp/stock/?code="&終値!A23,"📈")) | B23: =IF(終値!A23="","",終値!A23) | C23: =IF(終値!A23="","",終値!B23) | D23: =IF(終値!A23="","",終値!E23) | E23: =IF($D23="","",AVERAGE(終値!E23:X23)) | F23: =IF($D23="","",STDEVP(終値!E23:X23)) | G23: =IF($D23="","",$E23+BB816設定!$B$4*$F23) | H23: =IF($D23="","",$E23+BB816設定!$B$5*$F23) | I23: =IF($D23="","",$E23-BB816設定!$B$5*$F23) | J23: =IF($D23="","",$E23-BB816設定!$B$4*$F23) | K23: =IF($D23="","",IFERROR(($D23-$J23)/($G23-$J23),"")) | L23: =IF($D23="","",IFERROR(($G23-$J23)/$E23*100,"")) | M23: =IF($D23="","",IFERROR(100-100/(1+SUMPRODUCT((終値!E23:R23>終値!F23:S23)*(終値!E23:R23-終値!F23:S23))/SUMPRODUCT((終値!E23:R23<終値!F23:S23)*(終値!F23:S23-終値!E23:R23))),100)) | N23: =IF($D23="","",IFERROR(100-100/(1+SUMPRODUCT((((高値!E23:R23+安値!E23:R23+終値!E23:R23)/3)>((高値!F23:S23+安値!F23:S23+終値!F23:S23)/3))*((高値!E23:R23+安値!E23:R23+終値!E23:R23)/3)*出来高!E23:R23)/SUMPRODUCT((((高値!E23:R23+安値!E23:R23+終値!E23:R23)/3)<((高値!F23:S23+安値!F23:S23+終値!F23:S23)/3))*((高値!E23:R23+安値!E23:R23+終値!E23:R23)/3)*出来高!E23:R23)),50)) | O23: =IF($D23="","",IFERROR(出来高!E23/AVERAGE(出来高!E23:I23),"")) | P23: =IF($D23="","",IFERROR($D23/終値!Y23-1,"")) | Q23: =IF($D23="","",MAX(0,MIN(100,IF($D23>$G23,25,IF($D23>$H23,15,IF($D23>$E23,5,0)))+IF($O23>=2,20,IF($O23>=1.5,14,IF($O23>=1.2,8,0)))+IF($N23>=80,15,IF($N23>=60,18,IF($N23>=50,8,0)))+IF(AND($M23>70,$M23<=80),18,IF(AND($M23>60,$M23<=70),14,IF(AND($M23>50,$M23<=60),6,0)))+IF($P23>=0.1,14,IF($P23>=0.03,7,0))+IF($M23>80,-12,0)+IF($M23<40,-20,0)+IF($N23<40,-15,0)+IF($K23<0.2,-18,0)+IF($P23<=-0.1,-10,0)))) | R23: =IF($D23="","",IF(AND($D23>$G23,$O23>=BB816設定!$B$6,$N23>=BB816設定!$B$7,$M23<=BB816設定!$B$8),"○","－")) | S23: =IF($D23="","",IF(AND($R23="○",$Q23>=BB816設定!$B$9),"◎買い",IF($Q23>=BB816設定!$B$10,"○監視",IF(OR($M23<40,$K23<0.2),"▲弱い","－")))) | T23: =IF($D23="","",IF(AND($D23>$G23,$O23>=BB816設定!$B$14,$N23>=BB816設定!$B$15,$M23<=BB816設定!$B$16),"買い可","見送り")) | U23: =IF($D23="","",IF(AND($D23>$H23,$M23>=BB816設定!$B$17,$N23>=BB816設定!$B$18,$O23>=BB816設定!$B$19),"買い可","見送り")) | V23: =IF($S23="◎買い",$D23,"") | W23: =IF($S23="◎買い",ROUND($D23*(1-BB816設定!$B$11/100),1),"") | X23: =IF($S23="◎買い",BB816設定!$B$11/BB816設定!$B$13,"") | Y23: =IF($D23="","",$Q23+(10000-ROW())/100000) | Z23: =IF($D23="","",$D23*BB816設定!$B$21) | AA23: =IF($D23="","",IF($Z23<=BB816設定!$B$20/BB816設定!$B$13,"○","×（1枠に入らない）"))
A24: =IF(終値!A24="","",HYPERLINK("https://kabutan.jp/stock/?code="&終値!A24,"📈")) | B24: =IF(終値!A24="","",終値!A24) | C24: =IF(終値!A24="","",終値!B24) | D24: =IF(終値!A24="","",終値!E24) | E24: =IF($D24="","",AVERAGE(終値!E24:X24)) | F24: =IF($D24="","",STDEVP(終値!E24:X24)) | G24: =IF($D24="","",$E24+BB816設定!$B$4*$F24) | H24: =IF($D24="","",$E24+BB816設定!$B$5*$F24) | I24: =IF($D24="","",$E24-BB816設定!$B$5*$F24) | J24: =IF($D24="","",$E24-BB816設定!$B$4*$F24) | K24: =IF($D24="","",IFERROR(($D24-$J24)/($G24-$J24),"")) | L24: =IF($D24="","",IFERROR(($G24-$J24)/$E24*100,"")) | M24: =IF($D24="","",IFERROR(100-100/(1+SUMPRODUCT((終値!E24:R24>終値!F24:S24)*(終値!E24:R24-終値!F24:S24))/SUMPRODUCT((終値!E24:R24<終値!F24:S24)*(終値!F24:S24-終値!E24:R24))),100)) | N24: =IF($D24="","",IFERROR(100-100/(1+SUMPRODUCT((((高値!E24:R24+安値!E24:R24+終値!E24:R24)/3)>((高値!F24:S24+安値!F24:S24+終値!F24:S24)/3))*((高値!E24:R24+安値!E24:R24+終値!E24:R24)/3)*出来高!E24:R24)/SUMPRODUCT((((高値!E24:R24+安値!E24:R24+終値!E24:R24)/3)<((高値!F24:S24+安値!F24:S24+終値!F24:S24)/3))*((高値!E24:R24+安値!E24:R24+終値!E24:R24)/3)*出来高!E24:R24)),50)) | O24: =IF($D24="","",IFERROR(出来高!E24/AVERAGE(出来高!E24:I24),"")) | P24: =IF($D24="","",IFERROR($D24/終値!Y24-1,"")) | Q24: =IF($D24="","",MAX(0,MIN(100,IF($D24>$G24,25,IF($D24>$H24,15,IF($D24>$E24,5,0)))+IF($O24>=2,20,IF($O24>=1.5,14,IF($O24>=1.2,8,0)))+IF($N24>=80,15,IF($N24>=60,18,IF($N24>=50,8,0)))+IF(AND($M24>70,$M24<=80),18,IF(AND($M24>60,$M24<=70),14,IF(AND($M24>50,$M24<=60),6,0)))+IF($P24>=0.1,14,IF($P24>=0.03,7,0))+IF($M24>80,-12,0)+IF($M24<40,-20,0)+IF($N24<40,-15,0)+IF($K24<0.2,-18,0)+IF($P24<=-0.1,-10,0)))) | R24: =IF($D24="","",IF(AND($D24>$G24,$O24>=BB816設定!$B$6,$N24>=BB816設定!$B$7,$M24<=BB816設定!$B$8),"○","－")) | S24: =IF($D24="","",IF(AND($R24="○",$Q24>=BB816設定!$B$9),"◎買い",IF($Q24>=BB816設定!$B$10,"○監視",IF(OR($M24<40,$K24<0.2),"▲弱い","－")))) | T24: =IF($D24="","",IF(AND($D24>$G24,$O24>=BB816設定!$B$14,$N24>=BB816設定!$B$15,$M24<=BB816設定!$B$16),"買い可","見送り")) | U24: =IF($D24="","",IF(AND($D24>$H24,$M24>=BB816設定!$B$17,$N24>=BB816設定!$B$18,$O24>=BB816設定!$B$19),"買い可","見送り")) | V24: =IF($S24="◎買い",$D24,"") | W24: =IF($S24="◎買い",ROUND($D24*(1-BB816設定!$B$11/100),1),"") | X24: =IF($S24="◎買い",BB816設定!$B$11/BB816設定!$B$13,"") | Y24: =IF($D24="","",$Q24+(10000-ROW())/100000) | Z24: =IF($D24="","",$D24*BB816設定!$B$21) | AA24: =IF($D24="","",IF($Z24<=BB816設定!$B$20/BB816設定!$B$13,"○","×（1枠に入らない）"))
A25: =IF(終値!A25="","",HYPERLINK("https://kabutan.jp/stock/?code="&終値!A25,"📈")) | B25: =IF(終値!A25="","",終値!A25) | C25: =IF(終値!A25="","",終値!B25) | D25: =IF(終値!A25="","",終値!E25) | E25: =IF($D25="","",AVERAGE(終値!E25:X25)) | F25: =IF($D25="","",STDEVP(終値!E25:X25)) | G25: =IF($D25="","",$E25+BB816設定!$B$4*$F25) | H25: =IF($D25="","",$E25+BB816設定!$B$5*$F25) | I25: =IF($D25="","",$E25-BB816設定!$B$5*$F25) | J25: =IF($D25="","",$E25-BB816設定!$B$4*$F25) | K25: =IF($D25="","",IFERROR(($D25-$J25)/($G25-$J25),"")) | L25: =IF($D25="","",IFERROR(($G25-$J25)/$E25*100,"")) | M25: =IF($D25="","",IFERROR(100-100/(1+SUMPRODUCT((終値!E25:R25>終値!F25:S25)*(終値!E25:R25-終値!F25:S25))/SUMPRODUCT((終値!E25:R25<終値!F25:S25)*(終値!F25:S25-終値!E25:R25))),100)) | N25: =IF($D25="","",IFERROR(100-100/(1+SUMPRODUCT((((高値!E25:R25+安値!E25:R25+終値!E25:R25)/3)>((高値!F25:S25+安値!F25:S25+終値!F25:S25)/3))*((高値!E25:R25+安値!E25:R25+終値!E25:R25)/3)*出来高!E25:R25)/SUMPRODUCT((((高値!E25:R25+安値!E25:R25+終値!E25:R25)/3)<((高値!F25:S25+安値!F25:S25+終値!F25:S25)/3))*((高値!E25:R25+安値!E25:R25+終値!E25:R25)/3)*出来高!E25:R25)),50)) | O25: =IF($D25="","",IFERROR(出来高!E25/AVERAGE(出来高!E25:I25),"")) | P25: =IF($D25="","",IFERROR($D25/終値!Y25-1,"")) | Q25: =IF($D25="","",MAX(0,MIN(100,IF($D25>$G25,25,IF($D25>$H25,15,IF($D25>$E25,5,0)))+IF($O25>=2,20,IF($O25>=1.5,14,IF($O25>=1.2,8,0)))+IF($N25>=80,15,IF($N25>=60,18,IF($N25>=50,8,0)))+IF(AND($M25>70,$M25<=80),18,IF(AND($M25>60,$M25<=70),14,IF(AND($M25>50,$M25<=60),6,0)))+IF($P25>=0.1,14,IF($P25>=0.03,7,0))+IF($M25>80,-12,0)+IF($M25<40,-20,0)+IF($N25<40,-15,0)+IF($K25<0.2,-18,0)+IF($P25<=-0.1,-10,0)))) | R25: =IF($D25="","",IF(AND($D25>$G25,$O25>=BB816設定!$B$6,$N25>=BB816設定!$B$7,$M25<=BB816設定!$B$8),"○","－")) | S25: =IF($D25="","",IF(AND($R25="○",$Q25>=BB816設定!$B$9),"◎買い",IF($Q25>=BB816設定!$B$10,"○監視",IF(OR($M25<40,$K25<0.2),"▲弱い","－")))) | T25: =IF($D25="","",IF(AND($D25>$G25,$O25>=BB816設定!$B$14,$N25>=BB816設定!$B$15,$M25<=BB816設定!$B$16),"買い可","見送り")) | U25: =IF($D25="","",IF(AND($D25>$H25,$M25>=BB816設定!$B$17,$N25>=BB816設定!$B$18,$O25>=BB816設定!$B$19),"買い可","見送り")) | V25: =IF($S25="◎買い",$D25,"") | W25: =IF($S25="◎買い",ROUND($D25*(1-BB816設定!$B$11/100),1),"") | X25: =IF($S25="◎買い",BB816設定!$B$11/BB816設定!$B$13,"") | Y25: =IF($D25="","",$Q25+(10000-ROW())/100000) | Z25: =IF($D25="","",$D25*BB816設定!$B$21) | AA25: =IF($D25="","",IF($Z25<=BB816設定!$B$20/BB816設定!$B$13,"○","×（1枠に入らない）"))
A26: =IF(終値!A26="","",HYPERLINK("https://kabutan.jp/stock/?code="&終値!A26,"📈")) | B26: =IF(終値!A26="","",終値!A26) | C26: =IF(終値!A26="","",終値!B26) | D26: =IF(終値!A26="","",終値!E26) | E26: =IF($D26="","",AVERAGE(終値!E26:X26)) | F26: =IF($D26="","",STDEVP(終値!E26:X26)) | G26: =IF($D26="","",$E26+BB816設定!$B$4*$F26) | H26: =IF($D26="","",$E26+BB816設定!$B$5*$F26) | I26: =IF($D26="","",$E26-BB816設定!$B$5*$F26) | J26: =IF($D26="","",$E26-BB816設定!$B$4*$F26) | K26: =IF($D26="","",IFERROR(($D26-$J26)/($G26-$J26),"")) | L26: =IF($D26="","",IFERROR(($G26-$J26)/$E26*100,"")) | M26: =IF($D26="","",IFERROR(100-100/(1+SUMPRODUCT((終値!E26:R26>終値!F26:S26)*(終値!E26:R26-終値!F26:S26))/SUMPRODUCT((終値!E26:R26<終値!F26:S26)*(終値!F26:S26-終値!E26:R26))),100)) | N26: =IF($D26="","",IFERROR(100-100/(1+SUMPRODUCT((((高値!E26:R26+安値!E26:R26+終値!E26:R26)/3)>((高値!F26:S26+安値!F26:S26+終値!F26:S26)/3))*((高値!E26:R26+安値!E26:R26+終値!E26:R26)/3)*出来高!E26:R26)/SUMPRODUCT((((高値!E26:R26+安値!E26:R26+終値!E26:R26)/3)<((高値!F26:S26+安値!F26:S26+終値!F26:S26)/3))*((高値!E26:R26+安値!E26:R26+終値!E26:R26)/3)*出来高!E26:R26)),50)) | O26: =IF($D26="","",IFERROR(出来高!E26/AVERAGE(出来高!E26:I26),"")) | P26: =IF($D26="","",IFERROR($D26/終値!Y26-1,"")) | Q26: =IF($D26="","",MAX(0,MIN(100,IF($D26>$G26,25,IF($D26>$H26,15,IF($D26>$E26,5,0)))+IF($O26>=2,20,IF($O26>=1.5,14,IF($O26>=1.2,8,0)))+IF($N26>=80,15,IF($N26>=60,18,IF($N26>=50,8,0)))+IF(AND($M26>70,$M26<=80),18,IF(AND($M26>60,$M26<=70),14,IF(AND($M26>50,$M26<=60),6,0)))+IF($P26>=0.1,14,IF($P26>=0.03,7,0))+IF($M26>80,-12,0)+IF($M26<40,-20,0)+IF($N26<40,-15,0)+IF($K26<0.2,-18,0)+IF($P26<=-0.1,-10,0)))) | R26: =IF($D26="","",IF(AND($D26>$G26,$O26>=BB816設定!$B$6,$N26>=BB816設定!$B$7,$M26<=BB816設定!$B$8),"○","－")) | S26: =IF($D26="","",IF(AND($R26="○",$Q26>=BB816設定!$B$9),"◎買い",IF($Q26>=BB816設定!$B$10,"○監視",IF(OR($M26<40,$K26<0.2),"▲弱い","－")))) | T26: =IF($D26="","",IF(AND($D26>$G26,$O26>=BB816設定!$B$14,$N26>=BB816設定!$B$15,$M26<=BB816設定!$B$16),"買い可","見送り")) | U26: =IF($D26="","",IF(AND($D26>$H26,$M26>=BB816設定!$B$17,$N26>=BB816設定!$B$18,$O26>=BB816設定!$B$19),"買い可","見送り")) | V26: =IF($S26="◎買い",$D26,"") | W26: =IF($S26="◎買い",ROUND($D26*(1-BB816設定!$B$11/100),1),"") | X26: =IF($S26="◎買い",BB816設定!$B$11/BB816設定!$B$13,"") | Y26: =IF($D26="","",$Q26+(10000-ROW())/100000) | Z26: =IF($D26="","",$D26*BB816設定!$B$21) | AA26: =IF($D26="","",IF($Z26<=BB816設定!$B$20/BB816設定!$B$13,"○","×（1枠に入らない）"))
A27: =IF(終値!A27="","",HYPERLINK("https://kabutan.jp/stock/?code="&終値!A27,"📈")) | B27: =IF(終値!A27="","",終値!A27) | C27: =IF(終値!A27="","",終値!B27) | D27: =IF(終値!A27="","",終値!E27) | E27: =IF($D27="","",AVERAGE(終値!E27:X27)) | F27: =IF($D27="","",STDEVP(終値!E27:X27)) | G27: =IF($D27="","",$E27+BB816設定!$B$4*$F27) | H27: =IF($D27="","",$E27+BB816設定!$B$5*$F27) | I27: =IF($D27="","",$E27-BB816設定!$B$5*$F27) | J27: =IF($D27="","",$E27-BB816設定!$B$4*$F27) | K27: =IF($D27="","",IFERROR(($D27-$J27)/($G27-$J27),"")) | L27: =IF($D27="","",IFERROR(($G27-$J27)/$E27*100,"")) | M27: =IF($D27="","",IFERROR(100-100/(1+SUMPRODUCT((終値!E27:R27>終値!F27:S27)*(終値!E27:R27-終値!F27:S27))/SUMPRODUCT((終値!E27:R27<終値!F27:S27)*(終値!F27:S27-終値!E27:R27))),100)) | N27: =IF($D27="","",IFERROR(100-100/(1+SUMPRODUCT((((高値!E27:R27+安値!E27:R27+終値!E27:R27)/3)>((高値!F27:S27+安値!F27:S27+終値!F27:S27)/3))*((高値!E27:R27+安値!E27:R27+終値!E27:R27)/3)*出来高!E27:R27)/SUMPRODUCT((((高値!E27:R27+安値!E27:R27+終値!E27:R27)/3)<((高値!F27:S27+安値!F27:S27+終値!F27:S27)/3))*((高値!E27:R27+安値!E27:R27+終値!E27:R27)/3)*出来高!E27:R27)),50)) | O27: =IF($D27="","",IFERROR(出来高!E27/AVERAGE(出来高!E27:I27),"")) | P27: =IF($D27="","",IFERROR($D27/終値!Y27-1,"")) | Q27: =IF($D27="","",MAX(0,MIN(100,IF($D27>$G27,25,IF($D27>$H27,15,IF($D27>$E27,5,0)))+IF($O27>=2,20,IF($O27>=1.5,14,IF($O27>=1.2,8,0)))+IF($N27>=80,15,IF($N27>=60,18,IF($N27>=50,8,0)))+IF(AND($M27>70,$M27<=80),18,IF(AND($M27>60,$M27<=70),14,IF(AND($M27>50,$M27<=60),6,0)))+IF($P27>=0.1,14,IF($P27>=0.03,7,0))+IF($M27>80,-12,0)+IF($M27<40,-20,0)+IF($N27<40,-15,0)+IF($K27<0.2,-18,0)+IF($P27<=-0.1,-10,0)))) | R27: =IF($D27="","",IF(AND($D27>$G27,$O27>=BB816設定!$B$6,$N27>=BB816設定!$B$7,$M27<=BB816設定!$B$8),"○","－")) | S27: =IF($D27="","",IF(AND($R27="○",$Q27>=BB816設定!$B$9),"◎買い",IF($Q27>=BB816設定!$B$10,"○監視",IF(OR($M27<40,$K27<0.2),"▲弱い","－")))) | T27: =IF($D27="","",IF(AND($D27>$G27,$O27>=BB816設定!$B$14,$N27>=BB816設定!$B$15,$M27<=BB816設定!$B$16),"買い可","見送り")) | U27: =IF($D27="","",IF(AND($D27>$H27,$M27>=BB816設定!$B$17,$N27>=BB816設定!$B$18,$O27>=BB816設定!$B$19),"買い可","見送り")) | V27: =IF($S27="◎買い",$D27,"") | W27: =IF($S27="◎買い",ROUND($D27*(1-BB816設定!$B$11/100),1),"") | X27: =IF($S27="◎買い",BB816設定!$B$11/BB816設定!$B$13,"") | Y27: =IF($D27="","",$Q27+(10000-ROW())/100000) | Z27: =IF($D27="","",$D27*BB816設定!$B$21) | AA27: =IF($D27="","",IF($Z27<=BB816設定!$B$20/BB816設定!$B$13,"○","×（1枠に入らない）"))
A28: =IF(終値!A28="","",HYPERLINK("https://kabutan.jp/stock/?code="&終値!A28,"📈")) | B28: =IF(終値!A28="","",終値!A28) | C28: =IF(終値!A28="","",終値!B28) | D28: =IF(終値!A28="","",終値!E28) | E28: =IF($D28="","",AVERAGE(終値!E28:X28)) | F28: =IF($D28="","",STDEVP(終値!E28:X28)) | G28: =IF($D28="","",$E28+BB816設定!$B$4*$F28) | H28: =IF($D28="","",$E28+BB816設定!$B$5*$F28) | I28: =IF($D28="","",$E28-BB816設定!$B$5*$F28) | J28: =IF($D28="","",$E28-BB816設定!$B$4*$F28) | K28: =IF($D28="","",IFERROR(($D28-$J28)/($G28-$J28),"")) | L28: =IF($D28="","",IFERROR(($G28-$J28)/$E28*100,"")) | M28: =IF($D28="","",IFERROR(100-100/(1+SUMPRODUCT((終値!E28:R28>終値!F28:S28)*(終値!E28:R28-終値!F28:S28))/SUMPRODUCT((終値!E28:R28<終値!F28:S28)*(終値!F28:S28-終値!E28:R28))),100)) | N28: =IF($D28="","",IFERROR(100-100/(1+SUMPRODUCT((((高値!E28:R28+安値!E28:R28+終値!E28:R28)/3)>((高値!F28:S28+安値!F28:S28+終値!F28:S28)/3))*((高値!E28:R28+安値!E28:R28+終値!E28:R28)/3)*出来高!E28:R28)/SUMPRODUCT((((高値!E28:R28+安値!E28:R28+終値!E28:R28)/3)<((高値!F28:S28+安値!F28:S28+終値!F28:S28)/3))*((高値!E28:R28+安値!E28:R28+終値!E28:R28)/3)*出来高!E28:R28)),50)) | O28: =IF($D28="","",IFERROR(出来高!E28/AVERAGE(出来高!E28:I28),"")) | P28: =IF($D28="","",IFERROR($D28/終値!Y28-1,"")) | Q28: =IF($D28="","",MAX(0,MIN(100,IF($D28>$G28,25,IF($D28>$H28,15,IF($D28>$E28,5,0)))+IF($O28>=2,20,IF($O28>=1.5,14,IF($O28>=1.2,8,0)))+IF($N28>=80,15,IF($N28>=60,18,IF($N28>=50,8,0)))+IF(AND($M28>70,$M28<=80),18,IF(AND($M28>60,$M28<=70),14,IF(AND($M28>50,$M28<=60),6,0)))+IF($P28>=0.1,14,IF($P28>=0.03,7,0))+IF($M28>80,-12,0)+IF($M28<40,-20,0)+IF($N28<40,-15,0)+IF($K28<0.2,-18,0)+IF($P28<=-0.1,-10,0)))) | R28: =IF($D28="","",IF(AND($D28>$G28,$O28>=BB816設定!$B$6,$N28>=BB816設定!$B$7,$M28<=BB816設定!$B$8),"○","－")) | S28: =IF($D28="","",IF(AND($R28="○",$Q28>=BB816設定!$B$9),"◎買い",IF($Q28>=BB816設定!$B$10,"○監視",IF(OR($M28<40,$K28<0.2),"▲弱い","－")))) | T28: =IF($D28="","",IF(AND($D28>$G28,$O28>=BB816設定!$B$14,$N28>=BB816設定!$B$15,$M28<=BB816設定!$B$16),"買い可","見送り")) | U28: =IF($D28="","",IF(AND($D28>$H28,$M28>=BB816設定!$B$17,$N28>=BB816設定!$B$18,$O28>=BB816設定!$B$19),"買い可","見送り")) | V28: =IF($S28="◎買い",$D28,"") | W28: =IF($S28="◎買い",ROUND($D28*(1-BB816設定!$B$11/100),1),"") | X28: =IF($S28="◎買い",BB816設定!$B$11/BB816設定!$B$13,"") | Y28: =IF($D28="","",$Q28+(10000-ROW())/100000) | Z28: =IF($D28="","",$D28*BB816設定!$B$21) | AA28: =IF($D28="","",IF($Z28<=BB816設定!$B$20/BB816設定!$B$13,"○","×（1枠に入らない）"))
A29: =IF(終値!A29="","",HYPERLINK("https://kabutan.jp/stock/?code="&終値!A29,"📈")) | B29: =IF(終値!A29="","",終値!A29) | C29: =IF(終値!A29="","",終値!B29) | D29: =IF(終値!A29="","",終値!E29) | E29: =IF($D29="","",AVERAGE(終値!E29:X29)) | F29: =IF($D29="","",STDEVP(終値!E29:X29)) | G29: =IF($D29="","",$E29+BB816設定!$B$4*$F29) | H29: =IF($D29="","",$E29+BB816設定!$B$5*$F29) | I29: =IF($D29="","",$E29-BB816設定!$B$5*$F29) | J29: =IF($D29="","",$E29-BB816設定!$B$4*$F29) | K29: =IF($D29="","",IFERROR(($D29-$J29)/($G29-$J29),"")) | L29: =IF($D29="","",IFERROR(($G29-$J29)/$E29*100,"")) | M29: =IF($D29="","",IFERROR(100-100/(1+SUMPRODUCT((終値!E29:R29>終値!F29:S29)*(終値!E29:R29-終値!F29:S29))/SUMPRODUCT((終値!E29:R29<終値!F29:S29)*(終値!F29:S29-終値!E29:R29))),100)) | N29: =IF($D29="","",IFERROR(100-100/(1+SUMPRODUCT((((高値!E29:R29+安値!E29:R29+終値!E29:R29)/3)>((高値!F29:S29+安値!F29:S29+終値!F29:S29)/3))*((高値!E29:R29+安値!E29:R29+終値!E29:R29)/3)*出来高!E29:R29)/SUMPRODUCT((((高値!E29:R29+安値!E29:R29+終値!E29:R29)/3)<((高値!F29:S29+安値!F29:S29+終値!F29:S29)/3))*((高値!E29:R29+安値!E29:R29+終値!E29:R29)/3)*出来高!E29:R29)),50)) | O29: =IF($D29="","",IFERROR(出来高!E29/AVERAGE(出来高!E29:I29),"")) | P29: =IF($D29="","",IFERROR($D29/終値!Y29-1,"")) | Q29: =IF($D29="","",MAX(0,MIN(100,IF($D29>$G29,25,IF($D29>$H29,15,IF($D29>$E29,5,0)))+IF($O29>=2,20,IF($O29>=1.5,14,IF($O29>=1.2,8,0)))+IF($N29>=80,15,IF($N29>=60,18,IF($N29>=50,8,0)))+IF(AND($M29>70,$M29<=80),18,IF(AND($M29>60,$M29<=70),14,IF(AND($M29>50,$M29<=60),6,0)))+IF($P29>=0.1,14,IF($P29>=0.03,7,0))+IF($M29>80,-12,0)+IF($M29<40,-20,0)+IF($N29<40,-15,0)+IF($K29<0.2,-18,0)+IF($P29<=-0.1,-10,0)))) | R29: =IF($D29="","",IF(AND($D29>$G29,$O29>=BB816設定!$B$6,$N29>=BB816設定!$B$7,$M29<=BB816設定!$B$8),"○","－")) | S29: =IF($D29="","",IF(AND($R29="○",$Q29>=BB816設定!$B$9),"◎買い",IF($Q29>=BB816設定!$B$10,"○監視",IF(OR($M29<40,$K29<0.2),"▲弱い","－")))) | T29: =IF($D29="","",IF(AND($D29>$G29,$O29>=BB816設定!$B$14,$N29>=BB816設定!$B$15,$M29<=BB816設定!$B$16),"買い可","見送り")) | U29: =IF($D29="","",IF(AND($D29>$H29,$M29>=BB816設定!$B$17,$N29>=BB816設定!$B$18,$O29>=BB816設定!$B$19),"買い可","見送り")) | V29: =IF($S29="◎買い",$D29,"") | W29: =IF($S29="◎買い",ROUND($D29*(1-BB816設定!$B$11/100),1),"") | X29: =IF($S29="◎買い",BB816設定!$B$11/BB816設定!$B$13,"") | Y29: =IF($D29="","",$Q29+(10000-ROW())/100000) | Z29: =IF($D29="","",$D29*BB816設定!$B$21) | AA29: =IF($D29="","",IF($Z29<=BB816設定!$B$20/BB816設定!$B$13,"○","×（1枠に入らない）"))
A30: =IF(終値!A30="","",HYPERLINK("https://kabutan.jp/stock/?code="&終値!A30,"📈")) | B30: =IF(終値!A30="","",終値!A30) | C30: =IF(終値!A30="","",終値!B30) | D30: =IF(終値!A30="","",終値!E30) | E30: =IF($D30="","",AVERAGE(終値!E30:X30)) | F30: =IF($D30="","",STDEVP(終値!E30:X30)) | G30: =IF($D30="","",$E30+BB816設定!$B$4*$F30) | H30: =IF($D30="","",$E30+BB816設定!$B$5*$F30) | I30: =IF($D30="","",$E30-BB816設定!$B$5*$F30) | J30: =IF($D30="","",$E30-BB816設定!$B$4*$F30) | K30: =IF($D30="","",IFERROR(($D30-$J30)/($G30-$J30),"")) | L30: =IF($D30="","",IFERROR(($G30-$J30)/$E30*100,"")) | M30: =IF($D30="","",IFERROR(100-100/(1+SUMPRODUCT((終値!E30:R30>終値!F30:S30)*(終値!E30:R30-終値!F30:S30))/SUMPRODUCT((終値!E30:R30<終値!F30:S30)*(終値!F30:S30-終値!E30:R30))),100)) | N30: =IF($D30="","",IFERROR(100-100/(1+SUMPRODUCT((((高値!E30:R30+安値!E30:R30+終値!E30:R30)/3)>((高値!F30:S30+安値!F30:S30+終値!F30:S30)/3))*((高値!E30:R30+安値!E30:R30+終値!E30:R30)/3)*出来高!E30:R30)/SUMPRODUCT((((高値!E30:R30+安値!E30:R30+終値!E30:R30)/3)<((高値!F30:S30+安値!F30:S30+終値!F30:S30)/3))*((高値!E30:R30+安値!E30:R30+終値!E30:R30)/3)*出来高!E30:R30)),50)) | O30: =IF($D30="","",IFERROR(出来高!E30/AVERAGE(出来高!E30:I30),"")) | P30: =IF($D30="","",IFERROR($D30/終値!Y30-1,"")) | Q30: =IF($D30="","",MAX(0,MIN(100,IF($D30>$G30,25,IF($D30>$H30,15,IF($D30>$E30,5,0)))+IF($O30>=2,20,IF($O30>=1.5,14,IF($O30>=1.2,8,0)))+IF($N30>=80,15,IF($N30>=60,18,IF($N30>=50,8,0)))+IF(AND($M30>70,$M30<=80),18,IF(AND($M30>60,$M30<=70),14,IF(AND($M30>50,$M30<=60),6,0)))+IF($P30>=0.1,14,IF($P30>=0.03,7,0))+IF($M30>80,-12,0)+IF($M30<40,-20,0)+IF($N30<40,-15,0)+IF($K30<0.2,-18,0)+IF($P30<=-0.1,-10,0)))) | R30: =IF($D30="","",IF(AND($D30>$G30,$O30>=BB816設定!$B$6,$N30>=BB816設定!$B$7,$M30<=BB816設定!$B$8),"○","－")) | S30: =IF($D30="","",IF(AND($R30="○",$Q30>=BB816設定!$B$9),"◎買い",IF($Q30>=BB816設定!$B$10,"○監視",IF(OR($M30<40,$K30<0.2),"▲弱い","－")))) | T30: =IF($D30="","",IF(AND($D30>$G30,$O30>=BB816設定!$B$14,$N30>=BB816設定!$B$15,$M30<=BB816設定!$B$16),"買い可","見送り")) | U30: =IF($D30="","",IF(AND($D30>$H30,$M30>=BB816設定!$B$17,$N30>=BB816設定!$B$18,$O30>=BB816設定!$B$19),"買い可","見送り")) | V30: =IF($S30="◎買い",$D30,"") | W30: =IF($S30="◎買い",ROUND($D30*(1-BB816設定!$B$11/100),1),"") | X30: =IF($S30="◎買い",BB816設定!$B$11/BB816設定!$B$13,"") | Y30: =IF($D30="","",$Q30+(10000-ROW())/100000) | Z30: =IF($D30="","",$D30*BB816設定!$B$21) | AA30: =IF($D30="","",IF($Z30<=BB816設定!$B$20/BB816設定!$B$13,"○","×（1枠に入らない）"))
A31: =IF(終値!A31="","",HYPERLINK("https://kabutan.jp/stock/?code="&終値!A31,"📈")) | B31: =IF(終値!A31="","",終値!A31) | C31: =IF(終値!A31="","",終値!B31) | D31: =IF(終値!A31="","",終値!E31) | E31: =IF($D31="","",AVERAGE(終値!E31:X31)) | F31: =IF($D31="","",STDEVP(終値!E31:X31)) | G31: =IF($D31="","",$E31+BB816設定!$B$4*$F31) | H31: =IF($D31="","",$E31+BB816設定!$B$5*$F31) | I31: =IF($D31="","",$E31-BB816設定!$B$5*$F31) | J31: =IF($D31="","",$E31-BB816設定!$B$4*$F31) | K31: =IF($D31="","",IFERROR(($D31-$J31)/($G31-$J31),"")) | L31: =IF($D31="","",IFERROR(($G31-$J31)/$E31*100,"")) | M31: =IF($D31="","",IFERROR(100-100/(1+SUMPRODUCT((終値!E31:R31>終値!F31:S31)*(終値!E31:R31-終値!F31:S31))/SUMPRODUCT((終値!E31:R31<終値!F31:S31)*(終値!F31:S31-終値!E31:R31))),100)) | N31: =IF($D31="","",IFERROR(100-100/(1+SUMPRODUCT((((高値!E31:R31+安値!E31:R31+終値!E31:R31)/3)>((高値!F31:S31+安値!F31:S31+終値!F31:S31)/3))*((高値!E31:R31+安値!E31:R31+終値!E31:R31)/3)*出来高!E31:R31)/SUMPRODUCT((((高値!E31:R31+安値!E31:R31+終値!E31:R31)/3)<((高値!F31:S31+安値!F31:S31+終値!F31:S31)/3))*((高値!E31:R31+安値!E31:R31+終値!E31:R31)/3)*出来高!E31:R31)),50)) | O31: =IF($D31="","",IFERROR(出来高!E31/AVERAGE(出来高!E31:I31),"")) | P31: =IF($D31="","",IFERROR($D31/終値!Y31-1,"")) | Q31: =IF($D31="","",MAX(0,MIN(100,IF($D31>$G31,25,IF($D31>$H31,15,IF($D31>$E31,5,0)))+IF($O31>=2,20,IF($O31>=1.5,14,IF($O31>=1.2,8,0)))+IF($N31>=80,15,IF($N31>=60,18,IF($N31>=50,8,0)))+IF(AND($M31>70,$M31<=80),18,IF(AND($M31>60,$M31<=70),14,IF(AND($M31>50,$M31<=60),6,0)))+IF($P31>=0.1,14,IF($P31>=0.03,7,0))+IF($M31>80,-12,0)+IF($M31<40,-20,0)+IF($N31<40,-15,0)+IF($K31<0.2,-18,0)+IF($P31<=-0.1,-10,0)))) | R31: =IF($D31="","",IF(AND($D31>$G31,$O31>=BB816設定!$B$6,$N31>=BB816設定!$B$7,$M31<=BB816設定!$B$8),"○","－")) | S31: =IF($D31="","",IF(AND($R31="○",$Q31>=BB816設定!$B$9),"◎買い",IF($Q31>=BB816設定!$B$10,"○監視",IF(OR($M31<40,$K31<0.2),"▲弱い","－")))) | T31: =IF($D31="","",IF(AND($D31>$G31,$O31>=BB816設定!$B$14,$N31>=BB816設定!$B$15,$M31<=BB816設定!$B$16),"買い可","見送り")) | U31: =IF($D31="","",IF(AND($D31>$H31,$M31>=BB816設定!$B$17,$N31>=BB816設定!$B$18,$O31>=BB816設定!$B$19),"買い可","見送り")) | V31: =IF($S31="◎買い",$D31,"") | W31: =IF($S31="◎買い",ROUND($D31*(1-BB816設定!$B$11/100),1),"") | X31: =IF($S31="◎買い",BB816設定!$B$11/BB816設定!$B$13,"") | Y31: =IF($D31="","",$Q31+(10000-ROW())/100000) | Z31: =IF($D31="","",$D31*BB816設定!$B$21) | AA31: =IF($D31="","",IF($Z31<=BB816設定!$B$20/BB816設定!$B$13,"○","×（1枠に入らない）"))
A32: =IF(終値!A32="","",HYPERLINK("https://kabutan.jp/stock/?code="&終値!A32,"📈")) | B32: =IF(終値!A32="","",終値!A32) | C32: =IF(終値!A32="","",終値!B32) | D32: =IF(終値!A32="","",終値!E32) | E32: =IF($D32="","",AVERAGE(終値!E32:X32)) | F32: =IF($D32="","",STDEVP(終値!E32:X32)) | G32: =IF($D32="","",$E32+BB816設定!$B$4*$F32) | H32: =IF($D32="","",$E32+BB816設定!$B$5*$F32) | I32: =IF($D32="","",$E32-BB816設定!$B$5*$F32) | J32: =IF($D32="","",$E32-BB816設定!$B$4*$F32) | K32: =IF($D32="","",IFERROR(($D32-$J32)/($G32-$J32),"")) | L32: =IF($D32="","",IFERROR(($G32-$J32)/$E32*100,"")) | M32: =IF($D32="","",IFERROR(100-100/(1+SUMPRODUCT((終値!E32:R32>終値!F32:S32)*(終値!E32:R32-終値!F32:S32))/SUMPRODUCT((終値!E32:R32<終値!F32:S32)*(終値!F32:S32-終値!E32:R32))),100)) | N32: =IF($D32="","",IFERROR(100-100/(1+SUMPRODUCT((((高値!E32:R32+安値!E32:R32+終値!E32:R32)/3)>((高値!F32:S32+安値!F32:S32+終値!F32:S32)/3))*((高値!E32:R32+安値!E32:R32+終値!E32:R32)/3)*出来高!E32:R32)/SUMPRODUCT((((高値!E32:R32+安値!E32:R32+終値!E32:R32)/3)<((高値!F32:S32+安値!F32:S32+終値!F32:S32)/3))*((高値!E32:R32+安値!E32:R32+終値!E32:R32)/3)*出来高!E32:R32)),50)) | O32: =IF($D32="","",IFERROR(出来高!E32/AVERAGE(出来高!E32:I32),"")) | P32: =IF($D32="","",IFERROR($D32/終値!Y32-1,"")) | Q32: =IF($D32="","",MAX(0,MIN(100,IF($D32>$G32,25,IF($D32>$H32,15,IF($D32>$E32,5,0)))+IF($O32>=2,20,IF($O32>=1.5,14,IF($O32>=1.2,8,0)))+IF($N32>=80,15,IF($N32>=60,18,IF($N32>=50,8,0)))+IF(AND($M32>70,$M32<=80),18,IF(AND($M32>60,$M32<=70),14,IF(AND($M32>50,$M32<=60),6,0)))+IF($P32>=0.1,14,IF($P32>=0.03,7,0))+IF($M32>80,-12,0)+IF($M32<40,-20,0)+IF($N32<40,-15,0)+IF($K32<0.2,-18,0)+IF($P32<=-0.1,-10,0)))) | R32: =IF($D32="","",IF(AND($D32>$G32,$O32>=BB816設定!$B$6,$N32>=BB816設定!$B$7,$M32<=BB816設定!$B$8),"○","－")) | S32: =IF($D32="","",IF(AND($R32="○",$Q32>=BB816設定!$B$9),"◎買い",IF($Q32>=BB816設定!$B$10,"○監視",IF(OR($M32<40,$K32<0.2),"▲弱い","－")))) | T32: =IF($D32="","",IF(AND($D32>$G32,$O32>=BB816設定!$B$14,$N32>=BB816設定!$B$15,$M32<=BB816設定!$B$16),"買い可","見送り")) | U32: =IF($D32="","",IF(AND($D32>$H32,$M32>=BB816設定!$B$17,$N32>=BB816設定!$B$18,$O32>=BB816設定!$B$19),"買い可","見送り")) | V32: =IF($S32="◎買い",$D32,"") | W32: =IF($S32="◎買い",ROUND($D32*(1-BB816設定!$B$11/100),1),"") | X32: =IF($S32="◎買い",BB816設定!$B$11/BB816設定!$B$13,"") | Y32: =IF($D32="","",$Q32+(10000-ROW())/100000) | Z32: =IF($D32="","",$D32*BB816設定!$B$21) | AA32: =IF($D32="","",IF($Z32<=BB816設定!$B$20/BB816設定!$B$13,"○","×（1枠に入らない）"))
A33: =IF(終値!A33="","",HYPERLINK("https://kabutan.jp/stock/?code="&終値!A33,"📈")) | B33: =IF(終値!A33="","",終値!A33) | C33: =IF(終値!A33="","",終値!B33) | D33: =IF(終値!A33="","",終値!E33) | E33: =IF($D33="","",AVERAGE(終値!E33:X33)) | F33: =IF($D33="","",STDEVP(終値!E33:X33)) | G33: =IF($D33="","",$E33+BB816設定!$B$4*$F33) | H33: =IF($D33="","",$E33+BB816設定!$B$5*$F33) | I33: =IF($D33="","",$E33-BB816設定!$B$5*$F33) | J33: =IF($D33="","",$E33-BB816設定!$B$4*$F33) | K33: =IF($D33="","",IFERROR(($D33-$J33)/($G33-$J33),"")) | L33: =IF($D33="","",IFERROR(($G33-$J33)/$E33*100,"")) | M33: =IF($D33="","",IFERROR(100-100/(1+SUMPRODUCT((終値!E33:R33>終値!F33:S33)*(終値!E33:R33-終値!F33:S33))/SUMPRODUCT((終値!E33:R33<終値!F33:S33)*(終値!F33:S33-終値!E33:R33))),100)) | N33: =IF($D33="","",IFERROR(100-100/(1+SUMPRODUCT((((高値!E33:R33+安値!E33:R33+終値!E33:R33)/3)>((高値!F33:S33+安値!F33:S33+終値!F33:S33)/3))*((高値!E33:R33+安値!E33:R33+終値!E33:R33)/3)*出来高!E33:R33)/SUMPRODUCT((((高値!E33:R33+安値!E33:R33+終値!E33:R33)/3)<((高値!F33:S33+安値!F33:S33+終値!F33:S33)/3))*((高値!E33:R33+安値!E33:R33+終値!E33:R33)/3)*出来高!E33:R33)),50)) | O33: =IF($D33="","",IFERROR(出来高!E33/AVERAGE(出来高!E33:I33),"")) | P33: =IF($D33="","",IFERROR($D33/終値!Y33-1,"")) | Q33: =IF($D33="","",MAX(0,MIN(100,IF($D33>$G33,25,IF($D33>$H33,15,IF($D33>$E33,5,0)))+IF($O33>=2,20,IF($O33>=1.5,14,IF($O33>=1.2,8,0)))+IF($N33>=80,15,IF($N33>=60,18,IF($N33>=50,8,0)))+IF(AND($M33>70,$M33<=80),18,IF(AND($M33>60,$M33<=70),14,IF(AND($M33>50,$M33<=60),6,0)))+IF($P33>=0.1,14,IF($P33>=0.03,7,0))+IF($M33>80,-12,0)+IF($M33<40,-20,0)+IF($N33<40,-15,0)+IF($K33<0.2,-18,0)+IF($P33<=-0.1,-10,0)))) | R33: =IF($D33="","",IF(AND($D33>$G33,$O33>=BB816設定!$B$6,$N33>=BB816設定!$B$7,$M33<=BB816設定!$B$8),"○","－")) | S33: =IF($D33="","",IF(AND($R33="○",$Q33>=BB816設定!$B$9),"◎買い",IF($Q33>=BB816設定!$B$10,"○監視",IF(OR($M33<40,$K33<0.2),"▲弱い","－")))) | T33: =IF($D33="","",IF(AND($D33>$G33,$O33>=BB816設定!$B$14,$N33>=BB816設定!$B$15,$M33<=BB816設定!$B$16),"買い可","見送り")) | U33: =IF($D33="","",IF(AND($D33>$H33,$M33>=BB816設定!$B$17,$N33>=BB816設定!$B$18,$O33>=BB816設定!$B$19),"買い可","見送り")) | V33: =IF($S33="◎買い",$D33,"") | W33: =IF($S33="◎買い",ROUND($D33*(1-BB816設定!$B$11/100),1),"") | X33: =IF($S33="◎買い",BB816設定!$B$11/BB816設定!$B$13,"") | Y33: =IF($D33="","",$Q33+(10000-ROW())/100000) | Z33: =IF($D33="","",$D33*BB816設定!$B$21) | AA33: =IF($D33="","",IF($Z33<=BB816設定!$B$20/BB816設定!$B$13,"○","×（1枠に入らない）"))
A34: =IF(終値!A34="","",HYPERLINK("https://kabutan.jp/stock/?code="&終値!A34,"📈")) | B34: =IF(終値!A34="","",終値!A34) | C34: =IF(終値!A34="","",終値!B34) | D34: =IF(終値!A34="","",終値!E34) | E34: =IF($D34="","",AVERAGE(終値!E34:X34)) | F34: =IF($D34="","",STDEVP(終値!E34:X34)) | G34: =IF($D34="","",$E34+BB816設定!$B$4*$F34) | H34: =IF($D34="","",$E34+BB816設定!$B$5*$F34) | I34: =IF($D34="","",$E34-BB816設定!$B$5*$F34) | J34: =IF($D34="","",$E34-BB816設定!$B$4*$F34) | K34: =IF($D34="","",IFERROR(($D34-$J34)/($G34-$J34),"")) | L34: =IF($D34="","",IFERROR(($G34-$J34)/$E34*100,"")) | M34: =IF($D34="","",IFERROR(100-100/(1+SUMPRODUCT((終値!E34:R34>終値!F34:S34)*(終値!E34:R34-終値!F34:S34))/SUMPRODUCT((終値!E34:R34<終値!F34:S34)*(終値!F34:S34-終値!E34:R34))),100)) | N34: =IF($D34="","",IFERROR(100-100/(1+SUMPRODUCT((((高値!E34:R34+安値!E34:R34+終値!E34:R34)/3)>((高値!F34:S34+安値!F34:S34+終値!F34:S34)/3))*((高値!E34:R34+安値!E34:R34+終値!E34:R34)/3)*出来高!E34:R34)/SUMPRODUCT((((高値!E34:R34+安値!E34:R34+終値!E34:R34)/3)<((高値!F34:S34+安値!F34:S34+終値!F34:S34)/3))*((高値!E34:R34+安値!E34:R34+終値!E34:R34)/3)*出来高!E34:R34)),50)) | O34: =IF($D34="","",IFERROR(出来高!E34/AVERAGE(出来高!E34:I34),"")) | P34: =IF($D34="","",IFERROR($D34/終値!Y34-1,"")) | Q34: =IF($D34="","",MAX(0,MIN(100,IF($D34>$G34,25,IF($D34>$H34,15,IF($D34>$E34,5,0)))+IF($O34>=2,20,IF($O34>=1.5,14,IF($O34>=1.2,8,0)))+IF($N34>=80,15,IF($N34>=60,18,IF($N34>=50,8,0)))+IF(AND($M34>70,$M34<=80),18,IF(AND($M34>60,$M34<=70),14,IF(AND($M34>50,$M34<=60),6,0)))+IF($P34>=0.1,14,IF($P34>=0.03,7,0))+IF($M34>80,-12,0)+IF($M34<40,-20,0)+IF($N34<40,-15,0)+IF($K34<0.2,-18,0)+IF($P34<=-0.1,-10,0)))) | R34: =IF($D34="","",IF(AND($D34>$G34,$O34>=BB816設定!$B$6,$N34>=BB816設定!$B$7,$M34<=BB816設定!$B$8),"○","－")) | S34: =IF($D34="","",IF(AND($R34="○",$Q34>=BB816設定!$B$9),"◎買い",IF($Q34>=BB816設定!$B$10,"○監視",IF(OR($M34<40,$K34<0.2),"▲弱い","－")))) | T34: =IF($D34="","",IF(AND($D34>$G34,$O34>=BB816設定!$B$14,$N34>=BB816設定!$B$15,$M34<=BB816設定!$B$16),"買い可","見送り")) | U34: =IF($D34="","",IF(AND($D34>$H34,$M34>=BB816設定!$B$17,$N34>=BB816設定!$B$18,$O34>=BB816設定!$B$19),"買い可","見送り")) | V34: =IF($S34="◎買い",$D34,"") | W34: =IF($S34="◎買い",ROUND($D34*(1-BB816設定!$B$11/100),1),"") | X34: =IF($S34="◎買い",BB816設定!$B$11/BB816設定!$B$13,"") | Y34: =IF($D34="","",$Q34+(10000-ROW())/100000) | Z34: =IF($D34="","",$D34*BB816設定!$B$21) | AA34: =IF($D34="","",IF($Z34<=BB816設定!$B$20/BB816設定!$B$13,"○","×（1枠に入らない）"))
A35: =IF(終値!A35="","",HYPERLINK("https://kabutan.jp/stock/?code="&終値!A35,"📈")) | B35: =IF(終値!A35="","",終値!A35) | C35: =IF(終値!A35="","",終値!B35) | D35: =IF(終値!A35="","",終値!E35) | E35: =IF($D35="","",AVERAGE(終値!E35:X35)) | F35: =IF($D35="","",STDEVP(終値!E35:X35)) | G35: =IF($D35="","",$E35+BB816設定!$B$4*$F35) | H35: =IF($D35="","",$E35+BB816設定!$B$5*$F35) | I35: =IF($D35="","",$E35-BB816設定!$B$5*$F35) | J35: =IF($D35="","",$E35-BB816設定!$B$4*$F35) | K35: =IF($D35="","",IFERROR(($D35-$J35)/($G35-$J35),"")) | L35: =IF($D35="","",IFERROR(($G35-$J35)/$E35*100,"")) | M35: =IF($D35="","",IFERROR(100-100/(1+SUMPRODUCT((終値!E35:R35>終値!F35:S35)*(終値!E35:R35-終値!F35:S35))/SUMPRODUCT((終値!E35:R35<終値!F35:S35)*(終値!F35:S35-終値!E35:R35))),100)) | N35: =IF($D35="","",IFERROR(100-100/(1+SUMPRODUCT((((高値!E35:R35+安値!E35:R35+終値!E35:R35)/3)>((高値!F35:S35+安値!F35:S35+終値!F35:S35)/3))*((高値!E35:R35+安値!E35:R35+終値!E35:R35)/3)*出来高!E35:R35)/SUMPRODUCT((((高値!E35:R35+安値!E35:R35+終値!E35:R35)/3)<((高値!F35:S35+安値!F35:S35+終値!F35:S35)/3))*((高値!E35:R35+安値!E35:R35+終値!E35:R35)/3)*出来高!E35:R35)),50)) | O35: =IF($D35="","",IFERROR(出来高!E35/AVERAGE(出来高!E35:I35),"")) | P35: =IF($D35="","",IFERROR($D35/終値!Y35-1,"")) | Q35: =IF($D35="","",MAX(0,MIN(100,IF($D35>$G35,25,IF($D35>$H35,15,IF($D35>$E35,5,0)))+IF($O35>=2,20,IF($O35>=1.5,14,IF($O35>=1.2,8,0)))+IF($N35>=80,15,IF($N35>=60,18,IF($N35>=50,8,0)))+IF(AND($M35>70,$M35<=80),18,IF(AND($M35>60,$M35<=70),14,IF(AND($M35>50,$M35<=60),6,0)))+IF($P35>=0.1,14,IF($P35>=0.03,7,0))+IF($M35>80,-12,0)+IF($M35<40,-20,0)+IF($N35<40,-15,0)+IF($K35<0.2,-18,0)+IF($P35<=-0.1,-10,0)))) | R35: =IF($D35="","",IF(AND($D35>$G35,$O35>=BB816設定!$B$6,$N35>=BB816設定!$B$7,$M35<=BB816設定!$B$8),"○","－")) | S35: =IF($D35="","",IF(AND($R35="○",$Q35>=BB816設定!$B$9),"◎買い",IF($Q35>=BB816設定!$B$10,"○監視",IF(OR($M35<40,$K35<0.2),"▲弱い","－")))) | T35: =IF($D35="","",IF(AND($D35>$G35,$O35>=BB816設定!$B$14,$N35>=BB816設定!$B$15,$M35<=BB816設定!$B$16),"買い可","見送り")) | U35: =IF($D35="","",IF(AND($D35>$H35,$M35>=BB816設定!$B$17,$N35>=BB816設定!$B$18,$O35>=BB816設定!$B$19),"買い可","見送り")) | V35: =IF($S35="◎買い",$D35,"") | W35: =IF($S35="◎買い",ROUND($D35*(1-BB816設定!$B$11/100),1),"") | X35: =IF($S35="◎買い",BB816設定!$B$11/BB816設定!$B$13,"") | Y35: =IF($D35="","",$Q35+(10000-ROW())/100000) | Z35: =IF($D35="","",$D35*BB816設定!$B$21) | AA35: =IF($D35="","",IF($Z35<=BB816設定!$B$20/BB816設定!$B$13,"○","×（1枠に入らない）"))
A36: =IF(終値!A36="","",HYPERLINK("https://kabutan.jp/stock/?code="&終値!A36,"📈")) | B36: =IF(終値!A36="","",終値!A36) | C36: =IF(終値!A36="","",終値!B36) | D36: =IF(終値!A36="","",終値!E36) | E36: =IF($D36="","",AVERAGE(終値!E36:X36)) | F36: =IF($D36="","",STDEVP(終値!E36:X36)) | G36: =IF($D36="","",$E36+BB816設定!$B$4*$F36) | H36: =IF($D36="","",$E36+BB816設定!$B$5*$F36) | I36: =IF($D36="","",$E36-BB816設定!$B$5*$F36) | J36: =IF($D36="","",$E36-BB816設定!$B$4*$F36) | K36: =IF($D36="","",IFERROR(($D36-$J36)/($G36-$J36),"")) | L36: =IF($D36="","",IFERROR(($G36-$J36)/$E36*100,"")) | M36: =IF($D36="","",IFERROR(100-100/(1+SUMPRODUCT((終値!E36:R36>終値!F36:S36)*(終値!E36:R36-終値!F36:S36))/SUMPRODUCT((終値!E36:R36<終値!F36:S36)*(終値!F36:S36-終値!E36:R36))),100)) | N36: =IF($D36="","",IFERROR(100-100/(1+SUMPRODUCT((((高値!E36:R36+安値!E36:R36+終値!E36:R36)/3)>((高値!F36:S36+安値!F36:S36+終値!F36:S36)/3))*((高値!E36:R36+安値!E36:R36+終値!E36:R36)/3)*出来高!E36:R36)/SUMPRODUCT((((高値!E36:R36+安値!E36:R36+終値!E36:R36)/3)<((高値!F36:S36+安値!F36:S36+終値!F36:S36)/3))*((高値!E36:R36+安値!E36:R36+終値!E36:R36)/3)*出来高!E36:R36)),50)) | O36: =IF($D36="","",IFERROR(出来高!E36/AVERAGE(出来高!E36:I36),"")) | P36: =IF($D36="","",IFERROR($D36/終値!Y36-1,"")) | Q36: =IF($D36="","",MAX(0,MIN(100,IF($D36>$G36,25,IF($D36>$H36,15,IF($D36>$E36,5,0)))+IF($O36>=2,20,IF($O36>=1.5,14,IF($O36>=1.2,8,0)))+IF($N36>=80,15,IF($N36>=60,18,IF($N36>=50,8,0)))+IF(AND($M36>70,$M36<=80),18,IF(AND($M36>60,$M36<=70),14,IF(AND($M36>50,$M36<=60),6,0)))+IF($P36>=0.1,14,IF($P36>=0.03,7,0))+IF($M36>80,-12,0)+IF($M36<40,-20,0)+IF($N36<40,-15,0)+IF($K36<0.2,-18,0)+IF($P36<=-0.1,-10,0)))) | R36: =IF($D36="","",IF(AND($D36>$G36,$O36>=BB816設定!$B$6,$N36>=BB816設定!$B$7,$M36<=BB816設定!$B$8),"○","－")) | S36: =IF($D36="","",IF(AND($R36="○",$Q36>=BB816設定!$B$9),"◎買い",IF($Q36>=BB816設定!$B$10,"○監視",IF(OR($M36<40,$K36<0.2),"▲弱い","－")))) | T36: =IF($D36="","",IF(AND($D36>$G36,$O36>=BB816設定!$B$14,$N36>=BB816設定!$B$15,$M36<=BB816設定!$B$16),"買い可","見送り")) | U36: =IF($D36="","",IF(AND($D36>$H36,$M36>=BB816設定!$B$17,$N36>=BB816設定!$B$18,$O36>=BB816設定!$B$19),"買い可","見送り")) | V36: =IF($S36="◎買い",$D36,"") | W36: =IF($S36="◎買い",ROUND($D36*(1-BB816設定!$B$11/100),1),"") | X36: =IF($S36="◎買い",BB816設定!$B$11/BB816設定!$B$13,"") | Y36: =IF($D36="","",$Q36+(10000-ROW())/100000) | Z36: =IF($D36="","",$D36*BB816設定!$B$21) | AA36: =IF($D36="","",IF($Z36<=BB816設定!$B$20/BB816設定!$B$13,"○","×（1枠に入らない）"))
A37: =IF(終値!A37="","",HYPERLINK("https://kabutan.jp/stock/?code="&終値!A37,"📈")) | B37: =IF(終値!A37="","",終値!A37) | C37: =IF(終値!A37="","",終値!B37) | D37: =IF(終値!A37="","",終値!E37) | E37: =IF($D37="","",AVERAGE(終値!E37:X37)) | F37: =IF($D37="","",STDEVP(終値!E37:X37)) | G37: =IF($D37="","",$E37+BB816設定!$B$4*$F37) | H37: =IF($D37="","",$E37+BB816設定!$B$5*$F37) | I37: =IF($D37="","",$E37-BB816設定!$B$5*$F37) | J37: =IF($D37="","",$E37-BB816設定!$B$4*$F37) | K37: =IF($D37="","",IFERROR(($D37-$J37)/($G37-$J37),"")) | L37: =IF($D37="","",IFERROR(($G37-$J37)/$E37*100,"")) | M37: =IF($D37="","",IFERROR(100-100/(1+SUMPRODUCT((終値!E37:R37>終値!F37:S37)*(終値!E37:R37-終値!F37:S37))/SUMPRODUCT((終値!E37:R37<終値!F37:S37)*(終値!F37:S37-終値!E37:R37))),100)) | N37: =IF($D37="","",IFERROR(100-100/(1+SUMPRODUCT((((高値!E37:R37+安値!E37:R37+終値!E37:R37)/3)>((高値!F37:S37+安値!F37:S37+終値!F37:S37)/3))*((高値!E37:R37+安値!E37:R37+終値!E37:R37)/3)*出来高!E37:R37)/SUMPRODUCT((((高値!E37:R37+安値!E37:R37+終値!E37:R37)/3)<((高値!F37:S37+安値!F37:S37+終値!F37:S37)/3))*((高値!E37:R37+安値!E37:R37+終値!E37:R37)/3)*出来高!E37:R37)),50)) | O37: =IF($D37="","",IFERROR(出来高!E37/AVERAGE(出来高!E37:I37),"")) | P37: =IF($D37="","",IFERROR($D37/終値!Y37-1,"")) | Q37: =IF($D37="","",MAX(0,MIN(100,IF($D37>$G37,25,IF($D37>$H37,15,IF($D37>$E37,5,0)))+IF($O37>=2,20,IF($O37>=1.5,14,IF($O37>=1.2,8,0)))+IF($N37>=80,15,IF($N37>=60,18,IF($N37>=50,8,0)))+IF(AND($M37>70,$M37<=80),18,IF(AND($M37>60,$M37<=70),14,IF(AND($M37>50,$M37<=60),6,0)))+IF($P37>=0.1,14,IF($P37>=0.03,7,0))+IF($M37>80,-12,0)+IF($M37<40,-20,0)+IF($N37<40,-15,0)+IF($K37<0.2,-18,0)+IF($P37<=-0.1,-10,0)))) | R37: =IF($D37="","",IF(AND($D37>$G37,$O37>=BB816設定!$B$6,$N37>=BB816設定!$B$7,$M37<=BB816設定!$B$8),"○","－")) | S37: =IF($D37="","",IF(AND($R37="○",$Q37>=BB816設定!$B$9),"◎買い",IF($Q37>=BB816設定!$B$10,"○監視",IF(OR($M37<40,$K37<0.2),"▲弱い","－")))) | T37: =IF($D37="","",IF(AND($D37>$G37,$O37>=BB816設定!$B$14,$N37>=BB816設定!$B$15,$M37<=BB816設定!$B$16),"買い可","見送り")) | U37: =IF($D37="","",IF(AND($D37>$H37,$M37>=BB816設定!$B$17,$N37>=BB816設定!$B$18,$O37>=BB816設定!$B$19),"買い可","見送り")) | V37: =IF($S37="◎買い",$D37,"") | W37: =IF($S37="◎買い",ROUND($D37*(1-BB816設定!$B$11/100),1),"") | X37: =IF($S37="◎買い",BB816設定!$B$11/BB816設定!$B$13,"") | Y37: =IF($D37="","",$Q37+(10000-ROW())/100000) | Z37: =IF($D37="","",$D37*BB816設定!$B$21) | AA37: =IF($D37="","",IF($Z37<=BB816設定!$B$20/BB816設定!$B$13,"○","×（1枠に入らない）"))
A38: =IF(終値!A38="","",HYPERLINK("https://kabutan.jp/stock/?code="&終値!A38,"📈")) | B38: =IF(終値!A38="","",終値!A38) | C38: =IF(終値!A38="","",終値!B38) | D38: =IF(終値!A38="","",終値!E38) | E38: =IF($D38="","",AVERAGE(終値!E38:X38)) | F38: =IF($D38="","",STDEVP(終値!E38:X38)) | G38: =IF($D38="","",$E38+BB816設定!$B$4*$F38) | H38: =IF($D38="","",$E38+BB816設定!$B$5*$F38) | I38: =IF($D38="","",$E38-BB816設定!$B$5*$F38) | J38: =IF($D38="","",$E38-BB816設定!$B$4*$F38) | K38: =IF($D38="","",IFERROR(($D38-$J38)/($G38-$J38),"")) | L38: =IF($D38="","",IFERROR(($G38-$J38)/$E38*100,"")) | M38: =IF($D38="","",IFERROR(100-100/(1+SUMPRODUCT((終値!E38:R38>終値!F38:S38)*(終値!E38:R38-終値!F38:S38))/SUMPRODUCT((終値!E38:R38<終値!F38:S38)*(終値!F38:S38-終値!E38:R38))),100)) | N38: =IF($D38="","",IFERROR(100-100/(1+SUMPRODUCT((((高値!E38:R38+安値!E38:R38+終値!E38:R38)/3)>((高値!F38:S38+安値!F38:S38+終値!F38:S38)/3))*((高値!E38:R38+安値!E38:R38+終値!E38:R38)/3)*出来高!E38:R38)/SUMPRODUCT((((高値!E38:R38+安値!E38:R38+終値!E38:R38)/3)<((高値!F38:S38+安値!F38:S38+終値!F38:S38)/3))*((高値!E38:R38+安値!E38:R38+終値!E38:R38)/3)*出来高!E38:R38)),50)) | O38: =IF($D38="","",IFERROR(出来高!E38/AVERAGE(出来高!E38:I38),"")) | P38: =IF($D38="","",IFERROR($D38/終値!Y38-1,"")) | Q38: =IF($D38="","",MAX(0,MIN(100,IF($D38>$G38,25,IF($D38>$H38,15,IF($D38>$E38,5,0)))+IF($O38>=2,20,IF($O38>=1.5,14,IF($O38>=1.2,8,0)))+IF($N38>=80,15,IF($N38>=60,18,IF($N38>=50,8,0)))+IF(AND($M38>70,$M38<=80),18,IF(AND($M38>60,$M38<=70),14,IF(AND($M38>50,$M38<=60),6,0)))+IF($P38>=0.1,14,IF($P38>=0.03,7,0))+IF($M38>80,-12,0)+IF($M38<40,-20,0)+IF($N38<40,-15,0)+IF($K38<0.2,-18,0)+IF($P38<=-0.1,-10,0)))) | R38: =IF($D38="","",IF(AND($D38>$G38,$O38>=BB816設定!$B$6,$N38>=BB816設定!$B$7,$M38<=BB816設定!$B$8),"○","－")) | S38: =IF($D38="","",IF(AND($R38="○",$Q38>=BB816設定!$B$9),"◎買い",IF($Q38>=BB816設定!$B$10,"○監視",IF(OR($M38<40,$K38<0.2),"▲弱い","－")))) | T38: =IF($D38="","",IF(AND($D38>$G38,$O38>=BB816設定!$B$14,$N38>=BB816設定!$B$15,$M38<=BB816設定!$B$16),"買い可","見送り")) | U38: =IF($D38="","",IF(AND($D38>$H38,$M38>=BB816設定!$B$17,$N38>=BB816設定!$B$18,$O38>=BB816設定!$B$19),"買い可","見送り")) | V38: =IF($S38="◎買い",$D38,"") | W38: =IF($S38="◎買い",ROUND($D38*(1-BB816設定!$B$11/100),1),"") | X38: =IF($S38="◎買い",BB816設定!$B$11/BB816設定!$B$13,"") | Y38: =IF($D38="","",$Q38+(10000-ROW())/100000) | Z38: =IF($D38="","",$D38*BB816設定!$B$21) | AA38: =IF($D38="","",IF($Z38<=BB816設定!$B$20/BB816設定!$B$13,"○","×（1枠に入らない）"))
A39: =IF(終値!A39="","",HYPERLINK("https://kabutan.jp/stock/?code="&終値!A39,"📈")) | B39: =IF(終値!A39="","",終値!A39) | C39: =IF(終値!A39="","",終値!B39) | D39: =IF(終値!A39="","",終値!E39) | E39: =IF($D39="","",AVERAGE(終値!E39:X39)) | F39: =IF($D39="","",STDEVP(終値!E39:X39)) | G39: =IF($D39="","",$E39+BB816設定!$B$4*$F39) | H39: =IF($D39="","",$E39+BB816設定!$B$5*$F39) | I39: =IF($D39="","",$E39-BB816設定!$B$5*$F39) | J39: =IF($D39="","",$E39-BB816設定!$B$4*$F39) | K39: =IF($D39="","",IFERROR(($D39-$J39)/($G39-$J39),"")) | L39: =IF($D39="","",IFERROR(($G39-$J39)/$E39*100,"")) | M39: =IF($D39="","",IFERROR(100-100/(1+SUMPRODUCT((終値!E39:R39>終値!F39:S39)*(終値!E39:R39-終値!F39:S39))/SUMPRODUCT((終値!E39:R39<終値!F39:S39)*(終値!F39:S39-終値!E39:R39))),100)) | N39: =IF($D39="","",IFERROR(100-100/(1+SUMPRODUCT((((高値!E39:R39+安値!E39:R39+終値!E39:R39)/3)>((高値!F39:S39+安値!F39:S39+終値!F39:S39)/3))*((高値!E39:R39+安値!E39:R39+終値!E39:R39)/3)*出来高!E39:R39)/SUMPRODUCT((((高値!E39:R39+安値!E39:R39+終値!E39:R39)/3)<((高値!F39:S39+安値!F39:S39+終値!F39:S39)/3))*((高値!E39:R39+安値!E39:R39+終値!E39:R39)/3)*出来高!E39:R39)),50)) | O39: =IF($D39="","",IFERROR(出来高!E39/AVERAGE(出来高!E39:I39),"")) | P39: =IF($D39="","",IFERROR($D39/終値!Y39-1,"")) | Q39: =IF($D39="","",MAX(0,MIN(100,IF($D39>$G39,25,IF($D39>$H39,15,IF($D39>$E39,5,0)))+IF($O39>=2,20,IF($O39>=1.5,14,IF($O39>=1.2,8,0)))+IF($N39>=80,15,IF($N39>=60,18,IF($N39>=50,8,0)))+IF(AND($M39>70,$M39<=80),18,IF(AND($M39>60,$M39<=70),14,IF(AND($M39>50,$M39<=60),6,0)))+IF($P39>=0.1,14,IF($P39>=0.03,7,0))+IF($M39>80,-12,0)+IF($M39<40,-20,0)+IF($N39<40,-15,0)+IF($K39<0.2,-18,0)+IF($P39<=-0.1,-10,0)))) | R39: =IF($D39="","",IF(AND($D39>$G39,$O39>=BB816設定!$B$6,$N39>=BB816設定!$B$7,$M39<=BB816設定!$B$8),"○","－")) | S39: =IF($D39="","",IF(AND($R39="○",$Q39>=BB816設定!$B$9),"◎買い",IF($Q39>=BB816設定!$B$10,"○監視",IF(OR($M39<40,$K39<0.2),"▲弱い","－")))) | T39: =IF($D39="","",IF(AND($D39>$G39,$O39>=BB816設定!$B$14,$N39>=BB816設定!$B$15,$M39<=BB816設定!$B$16),"買い可","見送り")) | U39: =IF($D39="","",IF(AND($D39>$H39,$M39>=BB816設定!$B$17,$N39>=BB816設定!$B$18,$O39>=BB816設定!$B$19),"買い可","見送り")) | V39: =IF($S39="◎買い",$D39,"") | W39: =IF($S39="◎買い",ROUND($D39*(1-BB816設定!$B$11/100),1),"") | X39: =IF($S39="◎買い",BB816設定!$B$11/BB816設定!$B$13,"") | Y39: =IF($D39="","",$Q39+(10000-ROW())/100000) | Z39: =IF($D39="","",$D39*BB816設定!$B$21) | AA39: =IF($D39="","",IF($Z39<=BB816設定!$B$20/BB816設定!$B$13,"○","×（1枠に入らない）"))
A40: =IF(終値!A40="","",HYPERLINK("https://kabutan.jp/stock/?code="&終値!A40,"📈")) | B40: =IF(終値!A40="","",終値!A40) | C40: =IF(終値!A40="","",終値!B40) | D40: =IF(終値!A40="","",終値!E40) | E40: =IF($D40="","",AVERAGE(終値!E40:X40)) | F40: =IF($D40="","",STDEVP(終値!E40:X40)) | G40: =IF($D40="","",$E40+BB816設定!$B$4*$F40) | H40: =IF($D40="","",$E40+BB816設定!$B$5*$F40) | I40: =IF($D40="","",$E40-BB816設定!$B$5*$F40) | J40: =IF($D40="","",$E40-BB816設定!$B$4*$F40) | K40: =IF($D40="","",IFERROR(($D40-$J40)/($G40-$J40),"")) | L40: =IF($D40="","",IFERROR(($G40-$J40)/$E40*100,"")) | M40: =IF($D40="","",IFERROR(100-100/(1+SUMPRODUCT((終値!E40:R40>終値!F40:S40)*(終値!E40:R40-終値!F40:S40))/SUMPRODUCT((終値!E40:R40<終値!F40:S40)*(終値!F40:S40-終値!E40:R40))),100)) | N40: =IF($D40="","",IFERROR(100-100/(1+SUMPRODUCT((((高値!E40:R40+安値!E40:R40+終値!E40:R40)/3)>((高値!F40:S40+安値!F40:S40+終値!F40:S40)/3))*((高値!E40:R40+安値!E40:R40+終値!E40:R40)/3)*出来高!E40:R40)/SUMPRODUCT((((高値!E40:R40+安値!E40:R40+終値!E40:R40)/3)<((高値!F40:S40+安値!F40:S40+終値!F40:S40)/3))*((高値!E40:R40+安値!E40:R40+終値!E40:R40)/3)*出来高!E40:R40)),50)) | O40: =IF($D40="","",IFERROR(出来高!E40/AVERAGE(出来高!E40:I40),"")) | P40: =IF($D40="","",IFERROR($D40/終値!Y40-1,"")) | Q40: =IF($D40="","",MAX(0,MIN(100,IF($D40>$G40,25,IF($D40>$H40,15,IF($D40>$E40,5,0)))+IF($O40>=2,20,IF($O40>=1.5,14,IF($O40>=1.2,8,0)))+IF($N40>=80,15,IF($N40>=60,18,IF($N40>=50,8,0)))+IF(AND($M40>70,$M40<=80),18,IF(AND($M40>60,$M40<=70),14,IF(AND($M40>50,$M40<=60),6,0)))+IF($P40>=0.1,14,IF($P40>=0.03,7,0))+IF($M40>80,-12,0)+IF($M40<40,-20,0)+IF($N40<40,-15,0)+IF($K40<0.2,-18,0)+IF($P40<=-0.1,-10,0)))) | R40: =IF($D40="","",IF(AND($D40>$G40,$O40>=BB816設定!$B$6,$N40>=BB816設定!$B$7,$M40<=BB816設定!$B$8),"○","－")) | S40: =IF($D40="","",IF(AND($R40="○",$Q40>=BB816設定!$B$9),"◎買い",IF($Q40>=BB816設定!$B$10,"○監視",IF(OR($M40<40,$K40<0.2),"▲弱い","－")))) | T40: =IF($D40="","",IF(AND($D40>$G40,$O40>=BB816設定!$B$14,$N40>=BB816設定!$B$15,$M40<=BB816設定!$B$16),"買い可","見送り")) | U40: =IF($D40="","",IF(AND($D40>$H40,$M40>=BB816設定!$B$17,$N40>=BB816設定!$B$18,$O40>=BB816設定!$B$19),"買い可","見送り")) | V40: =IF($S40="◎買い",$D40,"") | W40: =IF($S40="◎買い",ROUND($D40*(1-BB816設定!$B$11/100),1),"") | X40: =IF($S40="◎買い",BB816設定!$B$11/BB816設定!$B$13,"") | Y40: =IF($D40="","",$Q40+(10000-ROW())/100000) | Z40: =IF($D40="","",$D40*BB816設定!$B$21) | AA40: =IF($D40="","",IF($Z40<=BB816設定!$B$20/BB816設定!$B$13,"○","×（1枠に入らない）"))
A41: =IF(終値!A41="","",HYPERLINK("https://kabutan.jp/stock/?code="&終値!A41,"📈")) | B41: =IF(終値!A41="","",終値!A41) | C41: =IF(終値!A41="","",終値!B41) | D41: =IF(終値!A41="","",終値!E41) | E41: =IF($D41="","",AVERAGE(終値!E41:X41)) | F41: =IF($D41="","",STDEVP(終値!E41:X41)) | G41: =IF($D41="","",$E41+BB816設定!$B$4*$F41) | H41: =IF($D41="","",$E41+BB816設定!$B$5*$F41) | I41: =IF($D41="","",$E41-BB816設定!$B$5*$F41) | J41: =IF($D41="","",$E41-BB816設定!$B$4*$F41) | K41: =IF($D41="","",IFERROR(($D41-$J41)/($G41-$J41),"")) | L41: =IF($D41="","",IFERROR(($G41-$J41)/$E41*100,"")) | M41: =IF($D41="","",IFERROR(100-100/(1+SUMPRODUCT((終値!E41:R41>終値!F41:S41)*(終値!E41:R41-終値!F41:S41))/SUMPRODUCT((終値!E41:R41<終値!F41:S41)*(終値!F41:S41-終値!E41:R41))),100)) | N41: =IF($D41="","",IFERROR(100-100/(1+SUMPRODUCT((((高値!E41:R41+安値!E41:R41+終値!E41:R41)/3)>((高値!F41:S41+安値!F41:S41+終値!F41:S41)/3))*((高値!E41:R41+安値!E41:R41+終値!E41:R41)/3)*出来高!E41:R41)/SUMPRODUCT((((高値!E41:R41+安値!E41:R41+終値!E41:R41)/3)<((高値!F41:S41+安値!F41:S41+終値!F41:S41)/3))*((高値!E41:R41+安値!E41:R41+終値!E41:R41)/3)*出来高!E41:R41)),50)) | O41: =IF($D41="","",IFERROR(出来高!E41/AVERAGE(出来高!E41:I41),"")) | P41: =IF($D41="","",IFERROR($D41/終値!Y41-1,"")) | Q41: =IF($D41="","",MAX(0,MIN(100,IF($D41>$G41,25,IF($D41>$H41,15,IF($D41>$E41,5,0)))+IF($O41>=2,20,IF($O41>=1.5,14,IF($O41>=1.2,8,0)))+IF($N41>=80,15,IF($N41>=60,18,IF($N41>=50,8,0)))+IF(AND($M41>70,$M41<=80),18,IF(AND($M41>60,$M41<=70),14,IF(AND($M41>50,$M41<=60),6,0)))+IF($P41>=0.1,14,IF($P41>=0.03,7,0))+IF($M41>80,-12,0)+IF($M41<40,-20,0)+IF($N41<40,-15,0)+IF($K41<0.2,-18,0)+IF($P41<=-0.1,-10,0)))) | R41: =IF($D41="","",IF(AND($D41>$G41,$O41>=BB816設定!$B$6,$N41>=BB816設定!$B$7,$M41<=BB816設定!$B$8),"○","－")) | S41: =IF($D41="","",IF(AND($R41="○",$Q41>=BB816設定!$B$9),"◎買い",IF($Q41>=BB816設定!$B$10,"○監視",IF(OR($M41<40,$K41<0.2),"▲弱い","－")))) | T41: =IF($D41="","",IF(AND($D41>$G41,$O41>=BB816設定!$B$14,$N41>=BB816設定!$B$15,$M41<=BB816設定!$B$16),"買い可","見送り")) | U41: =IF($D41="","",IF(AND($D41>$H41,$M41>=BB816設定!$B$17,$N41>=BB816設定!$B$18,$O41>=BB816設定!$B$19),"買い可","見送り")) | V41: =IF($S41="◎買い",$D41,"") | W41: =IF($S41="◎買い",ROUND($D41*(1-BB816設定!$B$11/100),1),"") | X41: =IF($S41="◎買い",BB816設定!$B$11/BB816設定!$B$13,"") | Y41: =IF($D41="","",$Q41+(10000-ROW())/100000) | Z41: =IF($D41="","",$D41*BB816設定!$B$21) | AA41: =IF($D41="","",IF($Z41<=BB816設定!$B$20/BB816設定!$B$13,"○","×（1枠に入らない）"))
A42: =IF(終値!A42="","",HYPERLINK("https://kabutan.jp/stock/?code="&終値!A42,"📈")) | B42: =IF(終値!A42="","",終値!A42) | C42: =IF(終値!A42="","",終値!B42) | D42: =IF(終値!A42="","",終値!E42) | E42: =IF($D42="","",AVERAGE(終値!E42:X42)) | F42: =IF($D42="","",STDEVP(終値!E42:X42)) | G42: =IF($D42="","",$E42+BB816設定!$B$4*$F42) | H42: =IF($D42="","",$E42+BB816設定!$B$5*$F42) | I42: =IF($D42="","",$E42-BB816設定!$B$5*$F42) | J42: =IF($D42="","",$E42-BB816設定!$B$4*$F42) | K42: =IF($D42="","",IFERROR(($D42-$J42)/($G42-$J42),"")) | L42: =IF($D42="","",IFERROR(($G42-$J42)/$E42*100,"")) | M42: =IF($D42="","",IFERROR(100-100/(1+SUMPRODUCT((終値!E42:R42>終値!F42:S42)*(終値!E42:R42-終値!F42:S42))/SUMPRODUCT((終値!E42:R42<終値!F42:S42)*(終値!F42:S42-終値!E42:R42))),100)) | N42: =IF($D42="","",IFERROR(100-100/(1+SUMPRODUCT((((高値!E42:R42+安値!E42:R42+終値!E42:R42)/3)>((高値!F42:S42+安値!F42:S42+終値!F42:S42)/3))*((高値!E42:R42+安値!E42:R42+終値!E42:R42)/3)*出来高!E42:R42)/SUMPRODUCT((((高値!E42:R42+安値!E42:R42+終値!E42:R42)/3)<((高値!F42:S42+安値!F42:S42+終値!F42:S42)/3))*((高値!E42:R42+安値!E42:R42+終値!E42:R42)/3)*出来高!E42:R42)),50)) | O42: =IF($D42="","",IFERROR(出来高!E42/AVERAGE(出来高!E42:I42),"")) | P42: =IF($D42="","",IFERROR($D42/終値!Y42-1,"")) | Q42: =IF($D42="","",MAX(0,MIN(100,IF($D42>$G42,25,IF($D42>$H42,15,IF($D42>$E42,5,0)))+IF($O42>=2,20,IF($O42>=1.5,14,IF($O42>=1.2,8,0)))+IF($N42>=80,15,IF($N42>=60,18,IF($N42>=50,8,0)))+IF(AND($M42>70,$M42<=80),18,IF(AND($M42>60,$M42<=70),14,IF(AND($M42>50,$M42<=60),6,0)))+IF($P42>=0.1,14,IF($P42>=0.03,7,0))+IF($M42>80,-12,0)+IF($M42<40,-20,0)+IF($N42<40,-15,0)+IF($K42<0.2,-18,0)+IF($P42<=-0.1,-10,0)))) | R42: =IF($D42="","",IF(AND($D42>$G42,$O42>=BB816設定!$B$6,$N42>=BB816設定!$B$7,$M42<=BB816設定!$B$8),"○","－")) | S42: =IF($D42="","",IF(AND($R42="○",$Q42>=BB816設定!$B$9),"◎買い",IF($Q42>=BB816設定!$B$10,"○監視",IF(OR($M42<40,$K42<0.2),"▲弱い","－")))) | T42: =IF($D42="","",IF(AND($D42>$G42,$O42>=BB816設定!$B$14,$N42>=BB816設定!$B$15,$M42<=BB816設定!$B$16),"買い可","見送り")) | U42: =IF($D42="","",IF(AND($D42>$H42,$M42>=BB816設定!$B$17,$N42>=BB816設定!$B$18,$O42>=BB816設定!$B$19),"買い可","見送り")) | V42: =IF($S42="◎買い",$D42,"") | W42: =IF($S42="◎買い",ROUND($D42*(1-BB816設定!$B$11/100),1),"") | X42: =IF($S42="◎買い",BB816設定!$B$11/BB816設定!$B$13,"") | Y42: =IF($D42="","",$Q42+(10000-ROW())/100000) | Z42: =IF($D42="","",$D42*BB816設定!$B$21) | AA42: =IF($D42="","",IF($Z42<=BB816設定!$B$20/BB816設定!$B$13,"○","×（1枠に入らない）"))
A43: =IF(終値!A43="","",HYPERLINK("https://kabutan.jp/stock/?code="&終値!A43,"📈")) | B43: =IF(終値!A43="","",終値!A43) | C43: =IF(終値!A43="","",終値!B43) | D43: =IF(終値!A43="","",終値!E43) | E43: =IF($D43="","",AVERAGE(終値!E43:X43)) | F43: =IF($D43="","",STDEVP(終値!E43:X43)) | G43: =IF($D43="","",$E43+BB816設定!$B$4*$F43) | H43: =IF($D43="","",$E43+BB816設定!$B$5*$F43) | I43: =IF($D43="","",$E43-BB816設定!$B$5*$F43) | J43: =IF($D43="","",$E43-BB816設定!$B$4*$F43) | K43: =IF($D43="","",IFERROR(($D43-$J43)/($G43-$J43),"")) | L43: =IF($D43="","",IFERROR(($G43-$J43)/$E43*100,"")) | M43: =IF($D43="","",IFERROR(100-100/(1+SUMPRODUCT((終値!E43:R43>終値!F43:S43)*(終値!E43:R43-終値!F43:S43))/SUMPRODUCT((終値!E43:R43<終値!F43:S43)*(終値!F43:S43-終値!E43:R43))),100)) | N43: =IF($D43="","",IFERROR(100-100/(1+SUMPRODUCT((((高値!E43:R43+安値!E43:R43+終値!E43:R43)/3)>((高値!F43:S43+安値!F43:S43+終値!F43:S43)/3))*((高値!E43:R43+安値!E43:R43+終値!E43:R43)/3)*出来高!E43:R43)/SUMPRODUCT((((高値!E43:R43+安値!E43:R43+終値!E43:R43)/3)<((高値!F43:S43+安値!F43:S43+終値!F43:S43)/3))*((高値!E43:R43+安値!E43:R43+終値!E43:R43)/3)*出来高!E43:R43)),50)) | O43: =IF($D43="","",IFERROR(出来高!E43/AVERAGE(出来高!E43:I43),"")) | P43: =IF($D43="","",IFERROR($D43/終値!Y43-1,"")) | Q43: =IF($D43="","",MAX(0,MIN(100,IF($D43>$G43,25,IF($D43>$H43,15,IF($D43>$E43,5,0)))+IF($O43>=2,20,IF($O43>=1.5,14,IF($O43>=1.2,8,0)))+IF($N43>=80,15,IF($N43>=60,18,IF($N43>=50,8,0)))+IF(AND($M43>70,$M43<=80),18,IF(AND($M43>60,$M43<=70),14,IF(AND($M43>50,$M43<=60),6,0)))+IF($P43>=0.1,14,IF($P43>=0.03,7,0))+IF($M43>80,-12,0)+IF($M43<40,-20,0)+IF($N43<40,-15,0)+IF($K43<0.2,-18,0)+IF($P43<=-0.1,-10,0)))) | R43: =IF($D43="","",IF(AND($D43>$G43,$O43>=BB816設定!$B$6,$N43>=BB816設定!$B$7,$M43<=BB816設定!$B$8),"○","－")) | S43: =IF($D43="","",IF(AND($R43="○",$Q43>=BB816設定!$B$9),"◎買い",IF($Q43>=BB816設定!$B$10,"○監視",IF(OR($M43<40,$K43<0.2),"▲弱い","－")))) | T43: =IF($D43="","",IF(AND($D43>$G43,$O43>=BB816設定!$B$14,$N43>=BB816設定!$B$15,$M43<=BB816設定!$B$16),"買い可","見送り")) | U43: =IF($D43="","",IF(AND($D43>$H43,$M43>=BB816設定!$B$17,$N43>=BB816設定!$B$18,$O43>=BB816設定!$B$19),"買い可","見送り")) | V43: =IF($S43="◎買い",$D43,"") | W43: =IF($S43="◎買い",ROUND($D43*(1-BB816設定!$B$11/100),1),"") | X43: =IF($S43="◎買い",BB816設定!$B$11/BB816設定!$B$13,"") | Y43: =IF($D43="","",$Q43+(10000-ROW())/100000) | Z43: =IF($D43="","",$D43*BB816設定!$B$21) | AA43: =IF($D43="","",IF($Z43<=BB816設定!$B$20/BB816設定!$B$13,"○","×（1枠に入らない）"))
A44: =IF(終値!A44="","",HYPERLINK("https://kabutan.jp/stock/?code="&終値!A44,"📈")) | B44: =IF(終値!A44="","",終値!A44) | C44: =IF(終値!A44="","",終値!B44) | D44: =IF(終値!A44="","",終値!E44) | E44: =IF($D44="","",AVERAGE(終値!E44:X44)) | F44: =IF($D44="","",STDEVP(終値!E44:X44)) | G44: =IF($D44="","",$E44+BB816設定!$B$4*$F44) | H44: =IF($D44="","",$E44+BB816設定!$B$5*$F44) | I44: =IF($D44="","",$E44-BB816設定!$B$5*$F44) | J44: =IF($D44="","",$E44-BB816設定!$B$4*$F44) | K44: =IF($D44="","",IFERROR(($D44-$J44)/($G44-$J44),"")) | L44: =IF($D44="","",IFERROR(($G44-$J44)/$E44*100,"")) | M44: =IF($D44="","",IFERROR(100-100/(1+SUMPRODUCT((終値!E44:R44>終値!F44:S44)*(終値!E44:R44-終値!F44:S44))/SUMPRODUCT((終値!E44:R44<終値!F44:S44)*(終値!F44:S44-終値!E44:R44))),100)) | N44: =IF($D44="","",IFERROR(100-100/(1+SUMPRODUCT((((高値!E44:R44+安値!E44:R44+終値!E44:R44)/3)>((高値!F44:S44+安値!F44:S44+終値!F44:S44)/3))*((高値!E44:R44+安値!E44:R44+終値!E44:R44)/3)*出来高!E44:R44)/SUMPRODUCT((((高値!E44:R44+安値!E44:R44+終値!E44:R44)/3)<((高値!F44:S44+安値!F44:S44+終値!F44:S44)/3))*((高値!E44:R44+安値!E44:R44+終値!E44:R44)/3)*出来高!E44:R44)),50)) | O44: =IF($D44="","",IFERROR(出来高!E44/AVERAGE(出来高!E44:I44),"")) | P44: =IF($D44="","",IFERROR($D44/終値!Y44-1,"")) | Q44: =IF($D44="","",MAX(0,MIN(100,IF($D44>$G44,25,IF($D44>$H44,15,IF($D44>$E44,5,0)))+IF($O44>=2,20,IF($O44>=1.5,14,IF($O44>=1.2,8,0)))+IF($N44>=80,15,IF($N44>=60,18,IF($N44>=50,8,0)))+IF(AND($M44>70,$M44<=80),18,IF(AND($M44>60,$M44<=70),14,IF(AND($M44>50,$M44<=60),6,0)))+IF($P44>=0.1,14,IF($P44>=0.03,7,0))+IF($M44>80,-12,0)+IF($M44<40,-20,0)+IF($N44<40,-15,0)+IF($K44<0.2,-18,0)+IF($P44<=-0.1,-10,0)))) | R44: =IF($D44="","",IF(AND($D44>$G44,$O44>=BB816設定!$B$6,$N44>=BB816設定!$B$7,$M44<=BB816設定!$B$8),"○","－")) | S44: =IF($D44="","",IF(AND($R44="○",$Q44>=BB816設定!$B$9),"◎買い",IF($Q44>=BB816設定!$B$10,"○監視",IF(OR($M44<40,$K44<0.2),"▲弱い","－")))) | T44: =IF($D44="","",IF(AND($D44>$G44,$O44>=BB816設定!$B$14,$N44>=BB816設定!$B$15,$M44<=BB816設定!$B$16),"買い可","見送り")) | U44: =IF($D44="","",IF(AND($D44>$H44,$M44>=BB816設定!$B$17,$N44>=BB816設定!$B$18,$O44>=BB816設定!$B$19),"買い可","見送り")) | V44: =IF($S44="◎買い",$D44,"") | W44: =IF($S44="◎買い",ROUND($D44*(1-BB816設定!$B$11/100),1),"") | X44: =IF($S44="◎買い",BB816設定!$B$11/BB816設定!$B$13,"") | Y44: =IF($D44="","",$Q44+(10000-ROW())/100000) | Z44: =IF($D44="","",$D44*BB816設定!$B$21) | AA44: =IF($D44="","",IF($Z44<=BB816設定!$B$20/BB816設定!$B$13,"○","×（1枠に入らない）"))
A45: =IF(終値!A45="","",HYPERLINK("https://kabutan.jp/stock/?code="&終値!A45,"📈")) | B45: =IF(終値!A45="","",終値!A45) | C45: =IF(終値!A45="","",終値!B45) | D45: =IF(終値!A45="","",終値!E45) | E45: =IF($D45="","",AVERAGE(終値!E45:X45)) | F45: =IF($D45="","",STDEVP(終値!E45:X45)) | G45: =IF($D45="","",$E45+BB816設定!$B$4*$F45) | H45: =IF($D45="","",$E45+BB816設定!$B$5*$F45) | I45: =IF($D45="","",$E45-BB816設定!$B$5*$F45) | J45: =IF($D45="","",$E45-BB816設定!$B$4*$F45) | K45: =IF($D45="","",IFERROR(($D45-$J45)/($G45-$J45),"")) | L45: =IF($D45="","",IFERROR(($G45-$J45)/$E45*100,"")) | M45: =IF($D45="","",IFERROR(100-100/(1+SUMPRODUCT((終値!E45:R45>終値!F45:S45)*(終値!E45:R45-終値!F45:S45))/SUMPRODUCT((終値!E45:R45<終値!F45:S45)*(終値!F45:S45-終値!E45:R45))),100)) | N45: =IF($D45="","",IFERROR(100-100/(1+SUMPRODUCT((((高値!E45:R45+安値!E45:R45+終値!E45:R45)/3)>((高値!F45:S45+安値!F45:S45+終値!F45:S45)/3))*((高値!E45:R45+安値!E45:R45+終値!E45:R45)/3)*出来高!E45:R45)/SUMPRODUCT((((高値!E45:R45+安値!E45:R45+終値!E45:R45)/3)<((高値!F45:S45+安値!F45:S45+終値!F45:S45)/3))*((高値!E45:R45+安値!E45:R45+終値!E45:R45)/3)*出来高!E45:R45)),50)) | O45: =IF($D45="","",IFERROR(出来高!E45/AVERAGE(出来高!E45:I45),"")) | P45: =IF($D45="","",IFERROR($D45/終値!Y45-1,"")) | Q45: =IF($D45="","",MAX(0,MIN(100,IF($D45>$G45,25,IF($D45>$H45,15,IF($D45>$E45,5,0)))+IF($O45>=2,20,IF($O45>=1.5,14,IF($O45>=1.2,8,0)))+IF($N45>=80,15,IF($N45>=60,18,IF($N45>=50,8,0)))+IF(AND($M45>70,$M45<=80),18,IF(AND($M45>60,$M45<=70),14,IF(AND($M45>50,$M45<=60),6,0)))+IF($P45>=0.1,14,IF($P45>=0.03,7,0))+IF($M45>80,-12,0)+IF($M45<40,-20,0)+IF($N45<40,-15,0)+IF($K45<0.2,-18,0)+IF($P45<=-0.1,-10,0)))) | R45: =IF($D45="","",IF(AND($D45>$G45,$O45>=BB816設定!$B$6,$N45>=BB816設定!$B$7,$M45<=BB816設定!$B$8),"○","－")) | S45: =IF($D45="","",IF(AND($R45="○",$Q45>=BB816設定!$B$9),"◎買い",IF($Q45>=BB816設定!$B$10,"○監視",IF(OR($M45<40,$K45<0.2),"▲弱い","－")))) | T45: =IF($D45="","",IF(AND($D45>$G45,$O45>=BB816設定!$B$14,$N45>=BB816設定!$B$15,$M45<=BB816設定!$B$16),"買い可","見送り")) | U45: =IF($D45="","",IF(AND($D45>$H45,$M45>=BB816設定!$B$17,$N45>=BB816設定!$B$18,$O45>=BB816設定!$B$19),"買い可","見送り")) | V45: =IF($S45="◎買い",$D45,"") | W45: =IF($S45="◎買い",ROUND($D45*(1-BB816設定!$B$11/100),1),"") | X45: =IF($S45="◎買い",BB816設定!$B$11/BB816設定!$B$13,"") | Y45: =IF($D45="","",$Q45+(10000-ROW())/100000) | Z45: =IF($D45="","",$D45*BB816設定!$B$21) | AA45: =IF($D45="","",IF($Z45<=BB816設定!$B$20/BB816設定!$B$13,"○","×（1枠に入らない）"))
A46: =IF(終値!A46="","",HYPERLINK("https://kabutan.jp/stock/?code="&終値!A46,"📈")) | B46: =IF(終値!A46="","",終値!A46) | C46: =IF(終値!A46="","",終値!B46) | D46: =IF(終値!A46="","",終値!E46) | E46: =IF($D46="","",AVERAGE(終値!E46:X46)) | F46: =IF($D46="","",STDEVP(終値!E46:X46)) | G46: =IF($D46="","",$E46+BB816設定!$B$4*$F46) | H46: =IF($D46="","",$E46+BB816設定!$B$5*$F46) | I46: =IF($D46="","",$E46-BB816設定!$B$5*$F46) | J46: =IF($D46="","",$E46-BB816設定!$B$4*$F46) | K46: =IF($D46="","",IFERROR(($D46-$J46)/($G46-$J46),"")) | L46: =IF($D46="","",IFERROR(($G46-$J46)/$E46*100,"")) | M46: =IF($D46="","",IFERROR(100-100/(1+SUMPRODUCT((終値!E46:R46>終値!F46:S46)*(終値!E46:R46-終値!F46:S46))/SUMPRODUCT((終値!E46:R46<終値!F46:S46)*(終値!F46:S46-終値!E46:R46))),100)) | N46: =IF($D46="","",IFERROR(100-100/(1+SUMPRODUCT((((高値!E46:R46+安値!E46:R46+終値!E46:R46)/3)>((高値!F46:S46+安値!F46:S46+終値!F46:S46)/3))*((高値!E46:R46+安値!E46:R46+終値!E46:R46)/3)*出来高!E46:R46)/SUMPRODUCT((((高値!E46:R46+安値!E46:R46+終値!E46:R46)/3)<((高値!F46:S46+安値!F46:S46+終値!F46:S46)/3))*((高値!E46:R46+安値!E46:R46+終値!E46:R46)/3)*出来高!E46:R46)),50)) | O46: =IF($D46="","",IFERROR(出来高!E46/AVERAGE(出来高!E46:I46),"")) | P46: =IF($D46="","",IFERROR($D46/終値!Y46-1,"")) | Q46: =IF($D46="","",MAX(0,MIN(100,IF($D46>$G46,25,IF($D46>$H46,15,IF($D46>$E46,5,0)))+IF($O46>=2,20,IF($O46>=1.5,14,IF($O46>=1.2,8,0)))+IF($N46>=80,15,IF($N46>=60,18,IF($N46>=50,8,0)))+IF(AND($M46>70,$M46<=80),18,IF(AND($M46>60,$M46<=70),14,IF(AND($M46>50,$M46<=60),6,0)))+IF($P46>=0.1,14,IF($P46>=0.03,7,0))+IF($M46>80,-12,0)+IF($M46<40,-20,0)+IF($N46<40,-15,0)+IF($K46<0.2,-18,0)+IF($P46<=-0.1,-10,0)))) | R46: =IF($D46="","",IF(AND($D46>$G46,$O46>=BB816設定!$B$6,$N46>=BB816設定!$B$7,$M46<=BB816設定!$B$8),"○","－")) | S46: =IF($D46="","",IF(AND($R46="○",$Q46>=BB816設定!$B$9),"◎買い",IF($Q46>=BB816設定!$B$10,"○監視",IF(OR($M46<40,$K46<0.2),"▲弱い","－")))) | T46: =IF($D46="","",IF(AND($D46>$G46,$O46>=BB816設定!$B$14,$N46>=BB816設定!$B$15,$M46<=BB816設定!$B$16),"買い可","見送り")) | U46: =IF($D46="","",IF(AND($D46>$H46,$M46>=BB816設定!$B$17,$N46>=BB816設定!$B$18,$O46>=BB816設定!$B$19),"買い可","見送り")) | V46: =IF($S46="◎買い",$D46,"") | W46: =IF($S46="◎買い",ROUND($D46*(1-BB816設定!$B$11/100),1),"") | X46: =IF($S46="◎買い",BB816設定!$B$11/BB816設定!$B$13,"") | Y46: =IF($D46="","",$Q46+(10000-ROW())/100000) | Z46: =IF($D46="","",$D46*BB816設定!$B$21) | AA46: =IF($D46="","",IF($Z46<=BB816設定!$B$20/BB816設定!$B$13,"○","×（1枠に入らない）"))
A47: =IF(終値!A47="","",HYPERLINK("https://kabutan.jp/stock/?code="&終値!A47,"📈")) | B47: =IF(終値!A47="","",終値!A47) | C47: =IF(終値!A47="","",終値!B47) | D47: =IF(終値!A47="","",終値!E47) | E47: =IF($D47="","",AVERAGE(終値!E47:X47)) | F47: =IF($D47="","",STDEVP(終値!E47:X47)) | G47: =IF($D47="","",$E47+BB816設定!$B$4*$F47) | H47: =IF($D47="","",$E47+BB816設定!$B$5*$F47) | I47: =IF($D47="","",$E47-BB816設定!$B$5*$F47) | J47: =IF($D47="","",$E47-BB816設定!$B$4*$F47) | K47: =IF($D47="","",IFERROR(($D47-$J47)/($G47-$J47),"")) | L47: =IF($D47="","",IFERROR(($G47-$J47)/$E47*100,"")) | M47: =IF($D47="","",IFERROR(100-100/(1+SUMPRODUCT((終値!E47:R47>終値!F47:S47)*(終値!E47:R47-終値!F47:S47))/SUMPRODUCT((終値!E47:R47<終値!F47:S47)*(終値!F47:S47-終値!E47:R47))),100)) | N47: =IF($D47="","",IFERROR(100-100/(1+SUMPRODUCT((((高値!E47:R47+安値!E47:R47+終値!E47:R47)/3)>((高値!F47:S47+安値!F47:S47+終値!F47:S47)/3))*((高値!E47:R47+安値!E47:R47+終値!E47:R47)/3)*出来高!E47:R47)/SUMPRODUCT((((高値!E47:R47+安値!E47:R47+終値!E47:R47)/3)<((高値!F47:S47+安値!F47:S47+終値!F47:S47)/3))*((高値!E47:R47+安値!E47:R47+終値!E47:R47)/3)*出来高!E47:R47)),50)) | O47: =IF($D47="","",IFERROR(出来高!E47/AVERAGE(出来高!E47:I47),"")) | P47: =IF($D47="","",IFERROR($D47/終値!Y47-1,"")) | Q47: =IF($D47="","",MAX(0,MIN(100,IF($D47>$G47,25,IF($D47>$H47,15,IF($D47>$E47,5,0)))+IF($O47>=2,20,IF($O47>=1.5,14,IF($O47>=1.2,8,0)))+IF($N47>=80,15,IF($N47>=60,18,IF($N47>=50,8,0)))+IF(AND($M47>70,$M47<=80),18,IF(AND($M47>60,$M47<=70),14,IF(AND($M47>50,$M47<=60),6,0)))+IF($P47>=0.1,14,IF($P47>=0.03,7,0))+IF($M47>80,-12,0)+IF($M47<40,-20,0)+IF($N47<40,-15,0)+IF($K47<0.2,-18,0)+IF($P47<=-0.1,-10,0)))) | R47: =IF($D47="","",IF(AND($D47>$G47,$O47>=BB816設定!$B$6,$N47>=BB816設定!$B$7,$M47<=BB816設定!$B$8),"○","－")) | S47: =IF($D47="","",IF(AND($R47="○",$Q47>=BB816設定!$B$9),"◎買い",IF($Q47>=BB816設定!$B$10,"○監視",IF(OR($M47<40,$K47<0.2),"▲弱い","－")))) | T47: =IF($D47="","",IF(AND($D47>$G47,$O47>=BB816設定!$B$14,$N47>=BB816設定!$B$15,$M47<=BB816設定!$B$16),"買い可","見送り")) | U47: =IF($D47="","",IF(AND($D47>$H47,$M47>=BB816設定!$B$17,$N47>=BB816設定!$B$18,$O47>=BB816設定!$B$19),"買い可","見送り")) | V47: =IF($S47="◎買い",$D47,"") | W47: =IF($S47="◎買い",ROUND($D47*(1-BB816設定!$B$11/100),1),"") | X47: =IF($S47="◎買い",BB816設定!$B$11/BB816設定!$B$13,"") | Y47: =IF($D47="","",$Q47+(10000-ROW())/100000) | Z47: =IF($D47="","",$D47*BB816設定!$B$21) | AA47: =IF($D47="","",IF($Z47<=BB816設定!$B$20/BB816設定!$B$13,"○","×（1枠に入らない）"))
A48: =IF(終値!A48="","",HYPERLINK("https://kabutan.jp/stock/?code="&終値!A48,"📈")) | B48: =IF(終値!A48="","",終値!A48) | C48: =IF(終値!A48="","",終値!B48) | D48: =IF(終値!A48="","",終値!E48) | E48: =IF($D48="","",AVERAGE(終値!E48:X48)) | F48: =IF($D48="","",STDEVP(終値!E48:X48)) | G48: =IF($D48="","",$E48+BB816設定!$B$4*$F48) | H48: =IF($D48="","",$E48+BB816設定!$B$5*$F48) | I48: =IF($D48="","",$E48-BB816設定!$B$5*$F48) | J48: =IF($D48="","",$E48-BB816設定!$B$4*$F48) | K48: =IF($D48="","",IFERROR(($D48-$J48)/($G48-$J48),"")) | L48: =IF($D48="","",IFERROR(($G48-$J48)/$E48*100,"")) | M48: =IF($D48="","",IFERROR(100-100/(1+SUMPRODUCT((終値!E48:R48>終値!F48:S48)*(終値!E48:R48-終値!F48:S48))/SUMPRODUCT((終値!E48:R48<終値!F48:S48)*(終値!F48:S48-終値!E48:R48))),100)) | N48: =IF($D48="","",IFERROR(100-100/(1+SUMPRODUCT((((高値!E48:R48+安値!E48:R48+終値!E48:R48)/3)>((高値!F48:S48+安値!F48:S48+終値!F48:S48)/3))*((高値!E48:R48+安値!E48:R48+終値!E48:R48)/3)*出来高!E48:R48)/SUMPRODUCT((((高値!E48:R48+安値!E48:R48+終値!E48:R48)/3)<((高値!F48:S48+安値!F48:S48+終値!F48:S48)/3))*((高値!E48:R48+安値!E48:R48+終値!E48:R48)/3)*出来高!E48:R48)),50)) | O48: =IF($D48="","",IFERROR(出来高!E48/AVERAGE(出来高!E48:I48),"")) | P48: =IF($D48="","",IFERROR($D48/終値!Y48-1,"")) | Q48: =IF($D48="","",MAX(0,MIN(100,IF($D48>$G48,25,IF($D48>$H48,15,IF($D48>$E48,5,0)))+IF($O48>=2,20,IF($O48>=1.5,14,IF($O48>=1.2,8,0)))+IF($N48>=80,15,IF($N48>=60,18,IF($N48>=50,8,0)))+IF(AND($M48>70,$M48<=80),18,IF(AND($M48>60,$M48<=70),14,IF(AND($M48>50,$M48<=60),6,0)))+IF($P48>=0.1,14,IF($P48>=0.03,7,0))+IF($M48>80,-12,0)+IF($M48<40,-20,0)+IF($N48<40,-15,0)+IF($K48<0.2,-18,0)+IF($P48<=-0.1,-10,0)))) | R48: =IF($D48="","",IF(AND($D48>$G48,$O48>=BB816設定!$B$6,$N48>=BB816設定!$B$7,$M48<=BB816設定!$B$8),"○","－")) | S48: =IF($D48="","",IF(AND($R48="○",$Q48>=BB816設定!$B$9),"◎買い",IF($Q48>=BB816設定!$B$10,"○監視",IF(OR($M48<40,$K48<0.2),"▲弱い","－")))) | T48: =IF($D48="","",IF(AND($D48>$G48,$O48>=BB816設定!$B$14,$N48>=BB816設定!$B$15,$M48<=BB816設定!$B$16),"買い可","見送り")) | U48: =IF($D48="","",IF(AND($D48>$H48,$M48>=BB816設定!$B$17,$N48>=BB816設定!$B$18,$O48>=BB816設定!$B$19),"買い可","見送り")) | V48: =IF($S48="◎買い",$D48,"") | W48: =IF($S48="◎買い",ROUND($D48*(1-BB816設定!$B$11/100),1),"") | X48: =IF($S48="◎買い",BB816設定!$B$11/BB816設定!$B$13,"") | Y48: =IF($D48="","",$Q48+(10000-ROW())/100000) | Z48: =IF($D48="","",$D48*BB816設定!$B$21) | AA48: =IF($D48="","",IF($Z48<=BB816設定!$B$20/BB816設定!$B$13,"○","×（1枠に入らない）"))
A49: =IF(終値!A49="","",HYPERLINK("https://kabutan.jp/stock/?code="&終値!A49,"📈")) | B49: =IF(終値!A49="","",終値!A49) | C49: =IF(終値!A49="","",終値!B49) | D49: =IF(終値!A49="","",終値!E49) | E49: =IF($D49="","",AVERAGE(終値!E49:X49)) | F49: =IF($D49="","",STDEVP(終値!E49:X49)) | G49: =IF($D49="","",$E49+BB816設定!$B$4*$F49) | H49: =IF($D49="","",$E49+BB816設定!$B$5*$F49) | I49: =IF($D49="","",$E49-BB816設定!$B$5*$F49) | J49: =IF($D49="","",$E49-BB816設定!$B$4*$F49) | K49: =IF($D49="","",IFERROR(($D49-$J49)/($G49-$J49),"")) | L49: =IF($D49="","",IFERROR(($G49-$J49)/$E49*100,"")) | M49: =IF($D49="","",IFERROR(100-100/(1+SUMPRODUCT((終値!E49:R49>終値!F49:S49)*(終値!E49:R49-終値!F49:S49))/SUMPRODUCT((終値!E49:R49<終値!F49:S49)*(終値!F49:S49-終値!E49:R49))),100)) | N49: =IF($D49="","",IFERROR(100-100/(1+SUMPRODUCT((((高値!E49:R49+安値!E49:R49+終値!E49:R49)/3)>((高値!F49:S49+安値!F49:S49+終値!F49:S49)/3))*((高値!E49:R49+安値!E49:R49+終値!E49:R49)/3)*出来高!E49:R49)/SUMPRODUCT((((高値!E49:R49+安値!E49:R49+終値!E49:R49)/3)<((高値!F49:S49+安値!F49:S49+終値!F49:S49)/3))*((高値!E49:R49+安値!E49:R49+終値!E49:R49)/3)*出来高!E49:R49)),50)) | O49: =IF($D49="","",IFERROR(出来高!E49/AVERAGE(出来高!E49:I49),"")) | P49: =IF($D49="","",IFERROR($D49/終値!Y49-1,"")) | Q49: =IF($D49="","",MAX(0,MIN(100,IF($D49>$G49,25,IF($D49>$H49,15,IF($D49>$E49,5,0)))+IF($O49>=2,20,IF($O49>=1.5,14,IF($O49>=1.2,8,0)))+IF($N49>=80,15,IF($N49>=60,18,IF($N49>=50,8,0)))+IF(AND($M49>70,$M49<=80),18,IF(AND($M49>60,$M49<=70),14,IF(AND($M49>50,$M49<=60),6,0)))+IF($P49>=0.1,14,IF($P49>=0.03,7,0))+IF($M49>80,-12,0)+IF($M49<40,-20,0)+IF($N49<40,-15,0)+IF($K49<0.2,-18,0)+IF($P49<=-0.1,-10,0)))) | R49: =IF($D49="","",IF(AND($D49>$G49,$O49>=BB816設定!$B$6,$N49>=BB816設定!$B$7,$M49<=BB816設定!$B$8),"○","－")) | S49: =IF($D49="","",IF(AND($R49="○",$Q49>=BB816設定!$B$9),"◎買い",IF($Q49>=BB816設定!$B$10,"○監視",IF(OR($M49<40,$K49<0.2),"▲弱い","－")))) | T49: =IF($D49="","",IF(AND($D49>$G49,$O49>=BB816設定!$B$14,$N49>=BB816設定!$B$15,$M49<=BB816設定!$B$16),"買い可","見送り")) | U49: =IF($D49="","",IF(AND($D49>$H49,$M49>=BB816設定!$B$17,$N49>=BB816設定!$B$18,$O49>=BB816設定!$B$19),"買い可","見送り")) | V49: =IF($S49="◎買い",$D49,"") | W49: =IF($S49="◎買い",ROUND($D49*(1-BB816設定!$B$11/100),1),"") | X49: =IF($S49="◎買い",BB816設定!$B$11/BB816設定!$B$13,"") | Y49: =IF($D49="","",$Q49+(10000-ROW())/100000) | Z49: =IF($D49="","",$D49*BB816設定!$B$21) | AA49: =IF($D49="","",IF($Z49<=BB816設定!$B$20/BB816設定!$B$13,"○","×（1枠に入らない）"))
A50: =IF(終値!A50="","",HYPERLINK("https://kabutan.jp/stock/?code="&終値!A50,"📈")) | B50: =IF(終値!A50="","",終値!A50) | C50: =IF(終値!A50="","",終値!B50) | D50: =IF(終値!A50="","",終値!E50) | E50: =IF($D50="","",AVERAGE(終値!E50:X50)) | F50: =IF($D50="","",STDEVP(終値!E50:X50)) | G50: =IF($D50="","",$E50+BB816設定!$B$4*$F50) | H50: =IF($D50="","",$E50+BB816設定!$B$5*$F50) | I50: =IF($D50="","",$E50-BB816設定!$B$5*$F50) | J50: =IF($D50="","",$E50-BB816設定!$B$4*$F50) | K50: =IF($D50="","",IFERROR(($D50-$J50)/($G50-$J50),"")) | L50: =IF($D50="","",IFERROR(($G50-$J50)/$E50*100,"")) | M50: =IF($D50="","",IFERROR(100-100/(1+SUMPRODUCT((終値!E50:R50>終値!F50:S50)*(終値!E50:R50-終値!F50:S50))/SUMPRODUCT((終値!E50:R50<終値!F50:S50)*(終値!F50:S50-終値!E50:R50))),100)) | N50: =IF($D50="","",IFERROR(100-100/(1+SUMPRODUCT((((高値!E50:R50+安値!E50:R50+終値!E50:R50)/3)>((高値!F50:S50+安値!F50:S50+終値!F50:S50)/3))*((高値!E50:R50+安値!E50:R50+終値!E50:R50)/3)*出来高!E50:R50)/SUMPRODUCT((((高値!E50:R50+安値!E50:R50+終値!E50:R50)/3)<((高値!F50:S50+安値!F50:S50+終値!F50:S50)/3))*((高値!E50:R50+安値!E50:R50+終値!E50:R50)/3)*出来高!E50:R50)),50)) | O50: =IF($D50="","",IFERROR(出来高!E50/AVERAGE(出来高!E50:I50),"")) | P50: =IF($D50="","",IFERROR($D50/終値!Y50-1,"")) | Q50: =IF($D50="","",MAX(0,MIN(100,IF($D50>$G50,25,IF($D50>$H50,15,IF($D50>$E50,5,0)))+IF($O50>=2,20,IF($O50>=1.5,14,IF($O50>=1.2,8,0)))+IF($N50>=80,15,IF($N50>=60,18,IF($N50>=50,8,0)))+IF(AND($M50>70,$M50<=80),18,IF(AND($M50>60,$M50<=70),14,IF(AND($M50>50,$M50<=60),6,0)))+IF($P50>=0.1,14,IF($P50>=0.03,7,0))+IF($M50>80,-12,0)+IF($M50<40,-20,0)+IF($N50<40,-15,0)+IF($K50<0.2,-18,0)+IF($P50<=-0.1,-10,0)))) | R50: =IF($D50="","",IF(AND($D50>$G50,$O50>=BB816設定!$B$6,$N50>=BB816設定!$B$7,$M50<=BB816設定!$B$8),"○","－")) | S50: =IF($D50="","",IF(AND($R50="○",$Q50>=BB816設定!$B$9),"◎買い",IF($Q50>=BB816設定!$B$10,"○監視",IF(OR($M50<40,$K50<0.2),"▲弱い","－")))) | T50: =IF($D50="","",IF(AND($D50>$G50,$O50>=BB816設定!$B$14,$N50>=BB816設定!$B$15,$M50<=BB816設定!$B$16),"買い可","見送り")) | U50: =IF($D50="","",IF(AND($D50>$H50,$M50>=BB816設定!$B$17,$N50>=BB816設定!$B$18,$O50>=BB816設定!$B$19),"買い可","見送り")) | V50: =IF($S50="◎買い",$D50,"") | W50: =IF($S50="◎買い",ROUND($D50*(1-BB816設定!$B$11/100),1),"") | X50: =IF($S50="◎買い",BB816設定!$B$11/BB816設定!$B$13,"") | Y50: =IF($D50="","",$Q50+(10000-ROW())/100000) | Z50: =IF($D50="","",$D50*BB816設定!$B$21) | AA50: =IF($D50="","",IF($Z50<=BB816設定!$B$20/BB816設定!$B$13,"○","×（1枠に入らない）"))
A51: =IF(終値!A51="","",HYPERLINK("https://kabutan.jp/stock/?code="&終値!A51,"📈")) | B51: =IF(終値!A51="","",終値!A51) | C51: =IF(終値!A51="","",終値!B51) | D51: =IF(終値!A51="","",終値!E51) | E51: =IF($D51="","",AVERAGE(終値!E51:X51)) | F51: =IF($D51="","",STDEVP(終値!E51:X51)) | G51: =IF($D51="","",$E51+BB816設定!$B$4*$F51) | H51: =IF($D51="","",$E51+BB816設定!$B$5*$F51) | I51: =IF($D51="","",$E51-BB816設定!$B$5*$F51) | J51: =IF($D51="","",$E51-BB816設定!$B$4*$F51) | K51: =IF($D51="","",IFERROR(($D51-$J51)/($G51-$J51),"")) | L51: =IF($D51="","",IFERROR(($G51-$J51)/$E51*100,"")) | M51: =IF($D51="","",IFERROR(100-100/(1+SUMPRODUCT((終値!E51:R51>終値!F51:S51)*(終値!E51:R51-終値!F51:S51))/SUMPRODUCT((終値!E51:R51<終値!F51:S51)*(終値!F51:S51-終値!E51:R51))),100)) | N51: =IF($D51="","",IFERROR(100-100/(1+SUMPRODUCT((((高値!E51:R51+安値!E51:R51+終値!E51:R51)/3)>((高値!F51:S51+安値!F51:S51+終値!F51:S51)/3))*((高値!E51:R51+安値!E51:R51+終値!E51:R51)/3)*出来高!E51:R51)/SUMPRODUCT((((高値!E51:R51+安値!E51:R51+終値!E51:R51)/3)<((高値!F51:S51+安値!F51:S51+終値!F51:S51)/3))*((高値!E51:R51+安値!E51:R51+終値!E51:R51)/3)*出来高!E51:R51)),50)) | O51: =IF($D51="","",IFERROR(出来高!E51/AVERAGE(出来高!E51:I51),"")) | P51: =IF($D51="","",IFERROR($D51/終値!Y51-1,"")) | Q51: =IF($D51="","",MAX(0,MIN(100,IF($D51>$G51,25,IF($D51>$H51,15,IF($D51>$E51,5,0)))+IF($O51>=2,20,IF($O51>=1.5,14,IF($O51>=1.2,8,0)))+IF($N51>=80,15,IF($N51>=60,18,IF($N51>=50,8,0)))+IF(AND($M51>70,$M51<=80),18,IF(AND($M51>60,$M51<=70),14,IF(AND($M51>50,$M51<=60),6,0)))+IF($P51>=0.1,14,IF($P51>=0.03,7,0))+IF($M51>80,-12,0)+IF($M51<40,-20,0)+IF($N51<40,-15,0)+IF($K51<0.2,-18,0)+IF($P51<=-0.1,-10,0)))) | R51: =IF($D51="","",IF(AND($D51>$G51,$O51>=BB816設定!$B$6,$N51>=BB816設定!$B$7,$M51<=BB816設定!$B$8),"○","－")) | S51: =IF($D51="","",IF(AND($R51="○",$Q51>=BB816設定!$B$9),"◎買い",IF($Q51>=BB816設定!$B$10,"○監視",IF(OR($M51<40,$K51<0.2),"▲弱い","－")))) | T51: =IF($D51="","",IF(AND($D51>$G51,$O51>=BB816設定!$B$14,$N51>=BB816設定!$B$15,$M51<=BB816設定!$B$16),"買い可","見送り")) | U51: =IF($D51="","",IF(AND($D51>$H51,$M51>=BB816設定!$B$17,$N51>=BB816設定!$B$18,$O51>=BB816設定!$B$19),"買い可","見送り")) | V51: =IF($S51="◎買い",$D51,"") | W51: =IF($S51="◎買い",ROUND($D51*(1-BB816設定!$B$11/100),1),"") | X51: =IF($S51="◎買い",BB816設定!$B$11/BB816設定!$B$13,"") | Y51: =IF($D51="","",$Q51+(10000-ROW())/100000) | Z51: =IF($D51="","",$D51*BB816設定!$B$21) | AA51: =IF($D51="","",IF($Z51<=BB816設定!$B$20/BB816設定!$B$13,"○","×（1枠に入らない）"))
A52: =IF(終値!A52="","",HYPERLINK("https://kabutan.jp/stock/?code="&終値!A52,"📈")) | B52: =IF(終値!A52="","",終値!A52) | C52: =IF(終値!A52="","",終値!B52) | D52: =IF(終値!A52="","",終値!E52) | E52: =IF($D52="","",AVERAGE(終値!E52:X52)) | F52: =IF($D52="","",STDEVP(終値!E52:X52)) | G52: =IF($D52="","",$E52+BB816設定!$B$4*$F52) | H52: =IF($D52="","",$E52+BB816設定!$B$5*$F52) | I52: =IF($D52="","",$E52-BB816設定!$B$5*$F52) | J52: =IF($D52="","",$E52-BB816設定!$B$4*$F52) | K52: =IF($D52="","",IFERROR(($D52-$J52)/($G52-$J52),"")) | L52: =IF($D52="","",IFERROR(($G52-$J52)/$E52*100,"")) | M52: =IF($D52="","",IFERROR(100-100/(1+SUMPRODUCT((終値!E52:R52>終値!F52:S52)*(終値!E52:R52-終値!F52:S52))/SUMPRODUCT((終値!E52:R52<終値!F52:S52)*(終値!F52:S52-終値!E52:R52))),100)) | N52: =IF($D52="","",IFERROR(100-100/(1+SUMPRODUCT((((高値!E52:R52+安値!E52:R52+終値!E52:R52)/3)>((高値!F52:S52+安値!F52:S52+終値!F52:S52)/3))*((高値!E52:R52+安値!E52:R52+終値!E52:R52)/3)*出来高!E52:R52)/SUMPRODUCT((((高値!E52:R52+安値!E52:R52+終値!E52:R52)/3)<((高値!F52:S52+安値!F52:S52+終値!F52:S52)/3))*((高値!E52:R52+安値!E52:R52+終値!E52:R52)/3)*出来高!E52:R52)),50)) | O52: =IF($D52="","",IFERROR(出来高!E52/AVERAGE(出来高!E52:I52),"")) | P52: =IF($D52="","",IFERROR($D52/終値!Y52-1,"")) | Q52: =IF($D52="","",MAX(0,MIN(100,IF($D52>$G52,25,IF($D52>$H52,15,IF($D52>$E52,5,0)))+IF($O52>=2,20,IF($O52>=1.5,14,IF($O52>=1.2,8,0)))+IF($N52>=80,15,IF($N52>=60,18,IF($N52>=50,8,0)))+IF(AND($M52>70,$M52<=80),18,IF(AND($M52>60,$M52<=70),14,IF(AND($M52>50,$M52<=60),6,0)))+IF($P52>=0.1,14,IF($P52>=0.03,7,0))+IF($M52>80,-12,0)+IF($M52<40,-20,0)+IF($N52<40,-15,0)+IF($K52<0.2,-18,0)+IF($P52<=-0.1,-10,0)))) | R52: =IF($D52="","",IF(AND($D52>$G52,$O52>=BB816設定!$B$6,$N52>=BB816設定!$B$7,$M52<=BB816設定!$B$8),"○","－")) | S52: =IF($D52="","",IF(AND($R52="○",$Q52>=BB816設定!$B$9),"◎買い",IF($Q52>=BB816設定!$B$10,"○監視",IF(OR($M52<40,$K52<0.2),"▲弱い","－")))) | T52: =IF($D52="","",IF(AND($D52>$G52,$O52>=BB816設定!$B$14,$N52>=BB816設定!$B$15,$M52<=BB816設定!$B$16),"買い可","見送り")) | U52: =IF($D52="","",IF(AND($D52>$H52,$M52>=BB816設定!$B$17,$N52>=BB816設定!$B$18,$O52>=BB816設定!$B$19),"買い可","見送り")) | V52: =IF($S52="◎買い",$D52,"") | W52: =IF($S52="◎買い",ROUND($D52*(1-BB816設定!$B$11/100),1),"") | X52: =IF($S52="◎買い",BB816設定!$B$11/BB816設定!$B$13,"") | Y52: =IF($D52="","",$Q52+(10000-ROW())/100000) | Z52: =IF($D52="","",$D52*BB816設定!$B$21) | AA52: =IF($D52="","",IF($Z52<=BB816設定!$B$20/BB816設定!$B$13,"○","×（1枠に入らない）"))
A53: =IF(終値!A53="","",HYPERLINK("https://kabutan.jp/stock/?code="&終値!A53,"📈")) | B53: =IF(終値!A53="","",終値!A53) | C53: =IF(終値!A53="","",終値!B53) | D53: =IF(終値!A53="","",終値!E53) | E53: =IF($D53="","",AVERAGE(終値!E53:X53)) | F53: =IF($D53="","",STDEVP(終値!E53:X53)) | G53: =IF($D53="","",$E53+BB816設定!$B$4*$F53) | H53: =IF($D53="","",$E53+BB816設定!$B$5*$F53) | I53: =IF($D53="","",$E53-BB816設定!$B$5*$F53) | J53: =IF($D53="","",$E53-BB816設定!$B$4*$F53) | K53: =IF($D53="","",IFERROR(($D53-$J53)/($G53-$J53),"")) | L53: =IF($D53="","",IFERROR(($G53-$J53)/$E53*100,"")) | M53: =IF($D53="","",IFERROR(100-100/(1+SUMPRODUCT((終値!E53:R53>終値!F53:S53)*(終値!E53:R53-終値!F53:S53))/SUMPRODUCT((終値!E53:R53<終値!F53:S53)*(終値!F53:S53-終値!E53:R53))),100)) | N53: =IF($D53="","",IFERROR(100-100/(1+SUMPRODUCT((((高値!E53:R53+安値!E53:R53+終値!E53:R53)/3)>((高値!F53:S53+安値!F53:S53+終値!F53:S53)/3))*((高値!E53:R53+安値!E53:R53+終値!E53:R53)/3)*出来高!E53:R53)/SUMPRODUCT((((高値!E53:R53+安値!E53:R53+終値!E53:R53)/3)<((高値!F53:S53+安値!F53:S53+終値!F53:S53)/3))*((高値!E53:R53+安値!E53:R53+終値!E53:R53)/3)*出来高!E53:R53)),50)) | O53: =IF($D53="","",IFERROR(出来高!E53/AVERAGE(出来高!E53:I53),"")) | P53: =IF($D53="","",IFERROR($D53/終値!Y53-1,"")) | Q53: =IF($D53="","",MAX(0,MIN(100,IF($D53>$G53,25,IF($D53>$H53,15,IF($D53>$E53,5,0)))+IF($O53>=2,20,IF($O53>=1.5,14,IF($O53>=1.2,8,0)))+IF($N53>=80,15,IF($N53>=60,18,IF($N53>=50,8,0)))+IF(AND($M53>70,$M53<=80),18,IF(AND($M53>60,$M53<=70),14,IF(AND($M53>50,$M53<=60),6,0)))+IF($P53>=0.1,14,IF($P53>=0.03,7,0))+IF($M53>80,-12,0)+IF($M53<40,-20,0)+IF($N53<40,-15,0)+IF($K53<0.2,-18,0)+IF($P53<=-0.1,-10,0)))) | R53: =IF($D53="","",IF(AND($D53>$G53,$O53>=BB816設定!$B$6,$N53>=BB816設定!$B$7,$M53<=BB816設定!$B$8),"○","－")) | S53: =IF($D53="","",IF(AND($R53="○",$Q53>=BB816設定!$B$9),"◎買い",IF($Q53>=BB816設定!$B$10,"○監視",IF(OR($M53<40,$K53<0.2),"▲弱い","－")))) | T53: =IF($D53="","",IF(AND($D53>$G53,$O53>=BB816設定!$B$14,$N53>=BB816設定!$B$15,$M53<=BB816設定!$B$16),"買い可","見送り")) | U53: =IF($D53="","",IF(AND($D53>$H53,$M53>=BB816設定!$B$17,$N53>=BB816設定!$B$18,$O53>=BB816設定!$B$19),"買い可","見送り")) | V53: =IF($S53="◎買い",$D53,"") | W53: =IF($S53="◎買い",ROUND($D53*(1-BB816設定!$B$11/100),1),"") | X53: =IF($S53="◎買い",BB816設定!$B$11/BB816設定!$B$13,"") | Y53: =IF($D53="","",$Q53+(10000-ROW())/100000) | Z53: =IF($D53="","",$D53*BB816設定!$B$21) | AA53: =IF($D53="","",IF($Z53<=BB816設定!$B$20/BB816設定!$B$13,"○","×（1枠に入らない）"))
A54: =IF(終値!A54="","",HYPERLINK("https://kabutan.jp/stock/?code="&終値!A54,"📈")) | B54: =IF(終値!A54="","",終値!A54) | C54: =IF(終値!A54="","",終値!B54) | D54: =IF(終値!A54="","",終値!E54) | E54: =IF($D54="","",AVERAGE(終値!E54:X54)) | F54: =IF($D54="","",STDEVP(終値!E54:X54)) | G54: =IF($D54="","",$E54+BB816設定!$B$4*$F54) | H54: =IF($D54="","",$E54+BB816設定!$B$5*$F54) | I54: =IF($D54="","",$E54-BB816設定!$B$5*$F54) | J54: =IF($D54="","",$E54-BB816設定!$B$4*$F54) | K54: =IF($D54="","",IFERROR(($D54-$J54)/($G54-$J54),"")) | L54: =IF($D54="","",IFERROR(($G54-$J54)/$E54*100,"")) | M54: =IF($D54="","",IFERROR(100-100/(1+SUMPRODUCT((終値!E54:R54>終値!F54:S54)*(終値!E54:R54-終値!F54:S54))/SUMPRODUCT((終値!E54:R54<終値!F54:S54)*(終値!F54:S54-終値!E54:R54))),100)) | N54: =IF($D54="","",IFERROR(100-100/(1+SUMPRODUCT((((高値!E54:R54+安値!E54:R54+終値!E54:R54)/3)>((高値!F54:S54+安値!F54:S54+終値!F54:S54)/3))*((高値!E54:R54+安値!E54:R54+終値!E54:R54)/3)*出来高!E54:R54)/SUMPRODUCT((((高値!E54:R54+安値!E54:R54+終値!E54:R54)/3)<((高値!F54:S54+安値!F54:S54+終値!F54:S54)/3))*((高値!E54:R54+安値!E54:R54+終値!E54:R54)/3)*出来高!E54:R54)),50)) | O54: =IF($D54="","",IFERROR(出来高!E54/AVERAGE(出来高!E54:I54),"")) | P54: =IF($D54="","",IFERROR($D54/終値!Y54-1,"")) | Q54: =IF($D54="","",MAX(0,MIN(100,IF($D54>$G54,25,IF($D54>$H54,15,IF($D54>$E54,5,0)))+IF($O54>=2,20,IF($O54>=1.5,14,IF($O54>=1.2,8,0)))+IF($N54>=80,15,IF($N54>=60,18,IF($N54>=50,8,0)))+IF(AND($M54>70,$M54<=80),18,IF(AND($M54>60,$M54<=70),14,IF(AND($M54>50,$M54<=60),6,0)))+IF($P54>=0.1,14,IF($P54>=0.03,7,0))+IF($M54>80,-12,0)+IF($M54<40,-20,0)+IF($N54<40,-15,0)+IF($K54<0.2,-18,0)+IF($P54<=-0.1,-10,0)))) | R54: =IF($D54="","",IF(AND($D54>$G54,$O54>=BB816設定!$B$6,$N54>=BB816設定!$B$7,$M54<=BB816設定!$B$8),"○","－")) | S54: =IF($D54="","",IF(AND($R54="○",$Q54>=BB816設定!$B$9),"◎買い",IF($Q54>=BB816設定!$B$10,"○監視",IF(OR($M54<40,$K54<0.2),"▲弱い","－")))) | T54: =IF($D54="","",IF(AND($D54>$G54,$O54>=BB816設定!$B$14,$N54>=BB816設定!$B$15,$M54<=BB816設定!$B$16),"買い可","見送り")) | U54: =IF($D54="","",IF(AND($D54>$H54,$M54>=BB816設定!$B$17,$N54>=BB816設定!$B$18,$O54>=BB816設定!$B$19),"買い可","見送り")) | V54: =IF($S54="◎買い",$D54,"") | W54: =IF($S54="◎買い",ROUND($D54*(1-BB816設定!$B$11/100),1),"") | X54: =IF($S54="◎買い",BB816設定!$B$11/BB816設定!$B$13,"") | Y54: =IF($D54="","",$Q54+(10000-ROW())/100000) | Z54: =IF($D54="","",$D54*BB816設定!$B$21) | AA54: =IF($D54="","",IF($Z54<=BB816設定!$B$20/BB816設定!$B$13,"○","×（1枠に入らない）"))
A55: =IF(終値!A55="","",HYPERLINK("https://kabutan.jp/stock/?code="&終値!A55,"📈")) | B55: =IF(終値!A55="","",終値!A55) | C55: =IF(終値!A55="","",終値!B55) | D55: =IF(終値!A55="","",終値!E55) | E55: =IF($D55="","",AVERAGE(終値!E55:X55)) | F55: =IF($D55="","",STDEVP(終値!E55:X55)) | G55: =IF($D55="","",$E55+BB816設定!$B$4*$F55) | H55: =IF($D55="","",$E55+BB816設定!$B$5*$F55) | I55: =IF($D55="","",$E55-BB816設定!$B$5*$F55) | J55: =IF($D55="","",$E55-BB816設定!$B$4*$F55) | K55: =IF($D55="","",IFERROR(($D55-$J55)/($G55-$J55),"")) | L55: =IF($D55="","",IFERROR(($G55-$J55)/$E55*100,"")) | M55: =IF($D55="","",IFERROR(100-100/(1+SUMPRODUCT((終値!E55:R55>終値!F55:S55)*(終値!E55:R55-終値!F55:S55))/SUMPRODUCT((終値!E55:R55<終値!F55:S55)*(終値!F55:S55-終値!E55:R55))),100)) | N55: =IF($D55="","",IFERROR(100-100/(1+SUMPRODUCT((((高値!E55:R55+安値!E55:R55+終値!E55:R55)/3)>((高値!F55:S55+安値!F55:S55+終値!F55:S55)/3))*((高値!E55:R55+安値!E55:R55+終値!E55:R55)/3)*出来高!E55:R55)/SUMPRODUCT((((高値!E55:R55+安値!E55:R55+終値!E55:R55)/3)<((高値!F55:S55+安値!F55:S55+終値!F55:S55)/3))*((高値!E55:R55+安値!E55:R55+終値!E55:R55)/3)*出来高!E55:R55)),50)) | O55: =IF($D55="","",IFERROR(出来高!E55/AVERAGE(出来高!E55:I55),"")) | P55: =IF($D55="","",IFERROR($D55/終値!Y55-1,"")) | Q55: =IF($D55="","",MAX(0,MIN(100,IF($D55>$G55,25,IF($D55>$H55,15,IF($D55>$E55,5,0)))+IF($O55>=2,20,IF($O55>=1.5,14,IF($O55>=1.2,8,0)))+IF($N55>=80,15,IF($N55>=60,18,IF($N55>=50,8,0)))+IF(AND($M55>70,$M55<=80),18,IF(AND($M55>60,$M55<=70),14,IF(AND($M55>50,$M55<=60),6,0)))+IF($P55>=0.1,14,IF($P55>=0.03,7,0))+IF($M55>80,-12,0)+IF($M55<40,-20,0)+IF($N55<40,-15,0)+IF($K55<0.2,-18,0)+IF($P55<=-0.1,-10,0)))) | R55: =IF($D55="","",IF(AND($D55>$G55,$O55>=BB816設定!$B$6,$N55>=BB816設定!$B$7,$M55<=BB816設定!$B$8),"○","－")) | S55: =IF($D55="","",IF(AND($R55="○",$Q55>=BB816設定!$B$9),"◎買い",IF($Q55>=BB816設定!$B$10,"○監視",IF(OR($M55<40,$K55<0.2),"▲弱い","－")))) | T55: =IF($D55="","",IF(AND($D55>$G55,$O55>=BB816設定!$B$14,$N55>=BB816設定!$B$15,$M55<=BB816設定!$B$16),"買い可","見送り")) | U55: =IF($D55="","",IF(AND($D55>$H55,$M55>=BB816設定!$B$17,$N55>=BB816設定!$B$18,$O55>=BB816設定!$B$19),"買い可","見送り")) | V55: =IF($S55="◎買い",$D55,"") | W55: =IF($S55="◎買い",ROUND($D55*(1-BB816設定!$B$11/100),1),"") | X55: =IF($S55="◎買い",BB816設定!$B$11/BB816設定!$B$13,"") | Y55: =IF($D55="","",$Q55+(10000-ROW())/100000) | Z55: =IF($D55="","",$D55*BB816設定!$B$21) | AA55: =IF($D55="","",IF($Z55<=BB816設定!$B$20/BB816設定!$B$13,"○","×（1枠に入らない）"))
A56: =IF(終値!A56="","",HYPERLINK("https://kabutan.jp/stock/?code="&終値!A56,"📈")) | B56: =IF(終値!A56="","",終値!A56) | C56: =IF(終値!A56="","",終値!B56) | D56: =IF(終値!A56="","",終値!E56) | E56: =IF($D56="","",AVERAGE(終値!E56:X56)) | F56: =IF($D56="","",STDEVP(終値!E56:X56)) | G56: =IF($D56="","",$E56+BB816設定!$B$4*$F56) | H56: =IF($D56="","",$E56+BB816設定!$B$5*$F56) | I56: =IF($D56="","",$E56-BB816設定!$B$5*$F56) | J56: =IF($D56="","",$E56-BB816設定!$B$4*$F56) | K56: =IF($D56="","",IFERROR(($D56-$J56)/($G56-$J56),"")) | L56: =IF($D56="","",IFERROR(($G56-$J56)/$E56*100,"")) | M56: =IF($D56="","",IFERROR(100-100/(1+SUMPRODUCT((終値!E56:R56>終値!F56:S56)*(終値!E56:R56-終値!F56:S56))/SUMPRODUCT((終値!E56:R56<終値!F56:S56)*(終値!F56:S56-終値!E56:R56))),100)) | N56: =IF($D56="","",IFERROR(100-100/(1+SUMPRODUCT((((高値!E56:R56+安値!E56:R56+終値!E56:R56)/3)>((高値!F56:S56+安値!F56:S56+終値!F56:S56)/3))*((高値!E56:R56+安値!E56:R56+終値!E56:R56)/3)*出来高!E56:R56)/SUMPRODUCT((((高値!E56:R56+安値!E56:R56+終値!E56:R56)/3)<((高値!F56:S56+安値!F56:S56+終値!F56:S56)/3))*((高値!E56:R56+安値!E56:R56+終値!E56:R56)/3)*出来高!E56:R56)),50)) | O56: =IF($D56="","",IFERROR(出来高!E56/AVERAGE(出来高!E56:I56),"")) | P56: =IF($D56="","",IFERROR($D56/終値!Y56-1,"")) | Q56: =IF($D56="","",MAX(0,MIN(100,IF($D56>$G56,25,IF($D56>$H56,15,IF($D56>$E56,5,0)))+IF($O56>=2,20,IF($O56>=1.5,14,IF($O56>=1.2,8,0)))+IF($N56>=80,15,IF($N56>=60,18,IF($N56>=50,8,0)))+IF(AND($M56>70,$M56<=80),18,IF(AND($M56>60,$M56<=70),14,IF(AND($M56>50,$M56<=60),6,0)))+IF($P56>=0.1,14,IF($P56>=0.03,7,0))+IF($M56>80,-12,0)+IF($M56<40,-20,0)+IF($N56<40,-15,0)+IF($K56<0.2,-18,0)+IF($P56<=-0.1,-10,0)))) | R56: =IF($D56="","",IF(AND($D56>$G56,$O56>=BB816設定!$B$6,$N56>=BB816設定!$B$7,$M56<=BB816設定!$B$8),"○","－")) | S56: =IF($D56="","",IF(AND($R56="○",$Q56>=BB816設定!$B$9),"◎買い",IF($Q56>=BB816設定!$B$10,"○監視",IF(OR($M56<40,$K56<0.2),"▲弱い","－")))) | T56: =IF($D56="","",IF(AND($D56>$G56,$O56>=BB816設定!$B$14,$N56>=BB816設定!$B$15,$M56<=BB816設定!$B$16),"買い可","見送り")) | U56: =IF($D56="","",IF(AND($D56>$H56,$M56>=BB816設定!$B$17,$N56>=BB816設定!$B$18,$O56>=BB816設定!$B$19),"買い可","見送り")) | V56: =IF($S56="◎買い",$D56,"") | W56: =IF($S56="◎買い",ROUND($D56*(1-BB816設定!$B$11/100),1),"") | X56: =IF($S56="◎買い",BB816設定!$B$11/BB816設定!$B$13,"") | Y56: =IF($D56="","",$Q56+(10000-ROW())/100000) | Z56: =IF($D56="","",$D56*BB816設定!$B$21) | AA56: =IF($D56="","",IF($Z56<=BB816設定!$B$20/BB816設定!$B$13,"○","×（1枠に入らない）"))
A57: =IF(終値!A57="","",HYPERLINK("https://kabutan.jp/stock/?code="&終値!A57,"📈")) | B57: =IF(終値!A57="","",終値!A57) | C57: =IF(終値!A57="","",終値!B57) | D57: =IF(終値!A57="","",終値!E57) | E57: =IF($D57="","",AVERAGE(終値!E57:X57)) | F57: =IF($D57="","",STDEVP(終値!E57:X57)) | G57: =IF($D57="","",$E57+BB816設定!$B$4*$F57) | H57: =IF($D57="","",$E57+BB816設定!$B$5*$F57) | I57: =IF($D57="","",$E57-BB816設定!$B$5*$F57) | J57: =IF($D57="","",$E57-BB816設定!$B$4*$F57) | K57: =IF($D57="","",IFERROR(($D57-$J57)/($G57-$J57),"")) | L57: =IF($D57="","",IFERROR(($G57-$J57)/$E57*100,"")) | M57: =IF($D57="","",IFERROR(100-100/(1+SUMPRODUCT((終値!E57:R57>終値!F57:S57)*(終値!E57:R57-終値!F57:S57))/SUMPRODUCT((終値!E57:R57<終値!F57:S57)*(終値!F57:S57-終値!E57:R57))),100)) | N57: =IF($D57="","",IFERROR(100-100/(1+SUMPRODUCT((((高値!E57:R57+安値!E57:R57+終値!E57:R57)/3)>((高値!F57:S57+安値!F57:S57+終値!F57:S57)/3))*((高値!E57:R57+安値!E57:R57+終値!E57:R57)/3)*出来高!E57:R57)/SUMPRODUCT((((高値!E57:R57+安値!E57:R57+終値!E57:R57)/3)<((高値!F57:S57+安値!F57:S57+終値!F57:S57)/3))*((高値!E57:R57+安値!E57:R57+終値!E57:R57)/3)*出来高!E57:R57)),50)) | O57: =IF($D57="","",IFERROR(出来高!E57/AVERAGE(出来高!E57:I57),"")) | P57: =IF($D57="","",IFERROR($D57/終値!Y57-1,"")) | Q57: =IF($D57="","",MAX(0,MIN(100,IF($D57>$G57,25,IF($D57>$H57,15,IF($D57>$E57,5,0)))+IF($O57>=2,20,IF($O57>=1.5,14,IF($O57>=1.2,8,0)))+IF($N57>=80,15,IF($N57>=60,18,IF($N57>=50,8,0)))+IF(AND($M57>70,$M57<=80),18,IF(AND($M57>60,$M57<=70),14,IF(AND($M57>50,$M57<=60),6,0)))+IF($P57>=0.1,14,IF($P57>=0.03,7,0))+IF($M57>80,-12,0)+IF($M57<40,-20,0)+IF($N57<40,-15,0)+IF($K57<0.2,-18,0)+IF($P57<=-0.1,-10,0)))) | R57: =IF($D57="","",IF(AND($D57>$G57,$O57>=BB816設定!$B$6,$N57>=BB816設定!$B$7,$M57<=BB816設定!$B$8),"○","－")) | S57: =IF($D57="","",IF(AND($R57="○",$Q57>=BB816設定!$B$9),"◎買い",IF($Q57>=BB816設定!$B$10,"○監視",IF(OR($M57<40,$K57<0.2),"▲弱い","－")))) | T57: =IF($D57="","",IF(AND($D57>$G57,$O57>=BB816設定!$B$14,$N57>=BB816設定!$B$15,$M57<=BB816設定!$B$16),"買い可","見送り")) | U57: =IF($D57="","",IF(AND($D57>$H57,$M57>=BB816設定!$B$17,$N57>=BB816設定!$B$18,$O57>=BB816設定!$B$19),"買い可","見送り")) | V57: =IF($S57="◎買い",$D57,"") | W57: =IF($S57="◎買い",ROUND($D57*(1-BB816設定!$B$11/100),1),"") | X57: =IF($S57="◎買い",BB816設定!$B$11/BB816設定!$B$13,"") | Y57: =IF($D57="","",$Q57+(10000-ROW())/100000) | Z57: =IF($D57="","",$D57*BB816設定!$B$21) | AA57: =IF($D57="","",IF($Z57<=BB816設定!$B$20/BB816設定!$B$13,"○","×（1枠に入らない）"))
A58: =IF(終値!A58="","",HYPERLINK("https://kabutan.jp/stock/?code="&終値!A58,"📈")) | B58: =IF(終値!A58="","",終値!A58) | C58: =IF(終値!A58="","",終値!B58) | D58: =IF(終値!A58="","",終値!E58) | E58: =IF($D58="","",AVERAGE(終値!E58:X58)) | F58: =IF($D58="","",STDEVP(終値!E58:X58)) | G58: =IF($D58="","",$E58+BB816設定!$B$4*$F58) | H58: =IF($D58="","",$E58+BB816設定!$B$5*$F58) | I58: =IF($D58="","",$E58-BB816設定!$B$5*$F58) | J58: =IF($D58="","",$E58-BB816設定!$B$4*$F58) | K58: =IF($D58="","",IFERROR(($D58-$J58)/($G58-$J58),"")) | L58: =IF($D58="","",IFERROR(($G58-$J58)/$E58*100,"")) | M58: =IF($D58="","",IFERROR(100-100/(1+SUMPRODUCT((終値!E58:R58>終値!F58:S58)*(終値!E58:R58-終値!F58:S58))/SUMPRODUCT((終値!E58:R58<終値!F58:S58)*(終値!F58:S58-終値!E58:R58))),100)) | N58: =IF($D58="","",IFERROR(100-100/(1+SUMPRODUCT((((高値!E58:R58+安値!E58:R58+終値!E58:R58)/3)>((高値!F58:S58+安値!F58:S58+終値!F58:S58)/3))*((高値!E58:R58+安値!E58:R58+終値!E58:R58)/3)*出来高!E58:R58)/SUMPRODUCT((((高値!E58:R58+安値!E58:R58+終値!E58:R58)/3)<((高値!F58:S58+安値!F58:S58+終値!F58:S58)/3))*((高値!E58:R58+安値!E58:R58+終値!E58:R58)/3)*出来高!E58:R58)),50)) | O58: =IF($D58="","",IFERROR(出来高!E58/AVERAGE(出来高!E58:I58),"")) | P58: =IF($D58="","",IFERROR($D58/終値!Y58-1,"")) | Q58: =IF($D58="","",MAX(0,MIN(100,IF($D58>$G58,25,IF($D58>$H58,15,IF($D58>$E58,5,0)))+IF($O58>=2,20,IF($O58>=1.5,14,IF($O58>=1.2,8,0)))+IF($N58>=80,15,IF($N58>=60,18,IF($N58>=50,8,0)))+IF(AND($M58>70,$M58<=80),18,IF(AND($M58>60,$M58<=70),14,IF(AND($M58>50,$M58<=60),6,0)))+IF($P58>=0.1,14,IF($P58>=0.03,7,0))+IF($M58>80,-12,0)+IF($M58<40,-20,0)+IF($N58<40,-15,0)+IF($K58<0.2,-18,0)+IF($P58<=-0.1,-10,0)))) | R58: =IF($D58="","",IF(AND($D58>$G58,$O58>=BB816設定!$B$6,$N58>=BB816設定!$B$7,$M58<=BB816設定!$B$8),"○","－")) | S58: =IF($D58="","",IF(AND($R58="○",$Q58>=BB816設定!$B$9),"◎買い",IF($Q58>=BB816設定!$B$10,"○監視",IF(OR($M58<40,$K58<0.2),"▲弱い","－")))) | T58: =IF($D58="","",IF(AND($D58>$G58,$O58>=BB816設定!$B$14,$N58>=BB816設定!$B$15,$M58<=BB816設定!$B$16),"買い可","見送り")) | U58: =IF($D58="","",IF(AND($D58>$H58,$M58>=BB816設定!$B$17,$N58>=BB816設定!$B$18,$O58>=BB816設定!$B$19),"買い可","見送り")) | V58: =IF($S58="◎買い",$D58,"") | W58: =IF($S58="◎買い",ROUND($D58*(1-BB816設定!$B$11/100),1),"") | X58: =IF($S58="◎買い",BB816設定!$B$11/BB816設定!$B$13,"") | Y58: =IF($D58="","",$Q58+(10000-ROW())/100000) | Z58: =IF($D58="","",$D58*BB816設定!$B$21) | AA58: =IF($D58="","",IF($Z58<=BB816設定!$B$20/BB816設定!$B$13,"○","×（1枠に入らない）"))
A59: =IF(終値!A59="","",HYPERLINK("https://kabutan.jp/stock/?code="&終値!A59,"📈")) | B59: =IF(終値!A59="","",終値!A59) | C59: =IF(終値!A59="","",終値!B59) | D59: =IF(終値!A59="","",終値!E59) | E59: =IF($D59="","",AVERAGE(終値!E59:X59)) | F59: =IF($D59="","",STDEVP(終値!E59:X59)) | G59: =IF($D59="","",$E59+BB816設定!$B$4*$F59) | H59: =IF($D59="","",$E59+BB816設定!$B$5*$F59) | I59: =IF($D59="","",$E59-BB816設定!$B$5*$F59) | J59: =IF($D59="","",$E59-BB816設定!$B$4*$F59) | K59: =IF($D59="","",IFERROR(($D59-$J59)/($G59-$J59),"")) | L59: =IF($D59="","",IFERROR(($G59-$J59)/$E59*100,"")) | M59: =IF($D59="","",IFERROR(100-100/(1+SUMPRODUCT((終値!E59:R59>終値!F59:S59)*(終値!E59:R59-終値!F59:S59))/SUMPRODUCT((終値!E59:R59<終値!F59:S59)*(終値!F59:S59-終値!E59:R59))),100)) | N59: =IF($D59="","",IFERROR(100-100/(1+SUMPRODUCT((((高値!E59:R59+安値!E59:R59+終値!E59:R59)/3)>((高値!F59:S59+安値!F59:S59+終値!F59:S59)/3))*((高値!E59:R59+安値!E59:R59+終値!E59:R59)/3)*出来高!E59:R59)/SUMPRODUCT((((高値!E59:R59+安値!E59:R59+終値!E59:R59)/3)<((高値!F59:S59+安値!F59:S59+終値!F59:S59)/3))*((高値!E59:R59+安値!E59:R59+終値!E59:R59)/3)*出来高!E59:R59)),50)) | O59: =IF($D59="","",IFERROR(出来高!E59/AVERAGE(出来高!E59:I59),"")) | P59: =IF($D59="","",IFERROR($D59/終値!Y59-1,"")) | Q59: =IF($D59="","",MAX(0,MIN(100,IF($D59>$G59,25,IF($D59>$H59,15,IF($D59>$E59,5,0)))+IF($O59>=2,20,IF($O59>=1.5,14,IF($O59>=1.2,8,0)))+IF($N59>=80,15,IF($N59>=60,18,IF($N59>=50,8,0)))+IF(AND($M59>70,$M59<=80),18,IF(AND($M59>60,$M59<=70),14,IF(AND($M59>50,$M59<=60),6,0)))+IF($P59>=0.1,14,IF($P59>=0.03,7,0))+IF($M59>80,-12,0)+IF($M59<40,-20,0)+IF($N59<40,-15,0)+IF($K59<0.2,-18,0)+IF($P59<=-0.1,-10,0)))) | R59: =IF($D59="","",IF(AND($D59>$G59,$O59>=BB816設定!$B$6,$N59>=BB816設定!$B$7,$M59<=BB816設定!$B$8),"○","－")) | S59: =IF($D59="","",IF(AND($R59="○",$Q59>=BB816設定!$B$9),"◎買い",IF($Q59>=BB816設定!$B$10,"○監視",IF(OR($M59<40,$K59<0.2),"▲弱い","－")))) | T59: =IF($D59="","",IF(AND($D59>$G59,$O59>=BB816設定!$B$14,$N59>=BB816設定!$B$15,$M59<=BB816設定!$B$16),"買い可","見送り")) | U59: =IF($D59="","",IF(AND($D59>$H59,$M59>=BB816設定!$B$17,$N59>=BB816設定!$B$18,$O59>=BB816設定!$B$19),"買い可","見送り")) | V59: =IF($S59="◎買い",$D59,"") | W59: =IF($S59="◎買い",ROUND($D59*(1-BB816設定!$B$11/100),1),"") | X59: =IF($S59="◎買い",BB816設定!$B$11/BB816設定!$B$13,"") | Y59: =IF($D59="","",$Q59+(10000-ROW())/100000) | Z59: =IF($D59="","",$D59*BB816設定!$B$21) | AA59: =IF($D59="","",IF($Z59<=BB816設定!$B$20/BB816設定!$B$13,"○","×（1枠に入らない）"))
A60: =IF(終値!A60="","",HYPERLINK("https://kabutan.jp/stock/?code="&終値!A60,"📈")) | B60: =IF(終値!A60="","",終値!A60) | C60: =IF(終値!A60="","",終値!B60) | D60: =IF(終値!A60="","",終値!E60) | E60: =IF($D60="","",AVERAGE(終値!E60:X60)) | F60: =IF($D60="","",STDEVP(終値!E60:X60)) | G60: =IF($D60="","",$E60+BB816設定!$B$4*$F60) | H60: =IF($D60="","",$E60+BB816設定!$B$5*$F60) | I60: =IF($D60="","",$E60-BB816設定!$B$5*$F60) | J60: =IF($D60="","",$E60-BB816設定!$B$4*$F60) | K60: =IF($D60="","",IFERROR(($D60-$J60)/($G60-$J60),"")) | L60: =IF($D60="","",IFERROR(($G60-$J60)/$E60*100,"")) | M60: =IF($D60="","",IFERROR(100-100/(1+SUMPRODUCT((終値!E60:R60>終値!F60:S60)*(終値!E60:R60-終値!F60:S60))/SUMPRODUCT((終値!E60:R60<終値!F60:S60)*(終値!F60:S60-終値!E60:R60))),100)) | N60: =IF($D60="","",IFERROR(100-100/(1+SUMPRODUCT((((高値!E60:R60+安値!E60:R60+終値!E60:R60)/3)>((高値!F60:S60+安値!F60:S60+終値!F60:S60)/3))*((高値!E60:R60+安値!E60:R60+終値!E60:R60)/3)*出来高!E60:R60)/SUMPRODUCT((((高値!E60:R60+安値!E60:R60+終値!E60:R60)/3)<((高値!F60:S60+安値!F60:S60+終値!F60:S60)/3))*((高値!E60:R60+安値!E60:R60+終値!E60:R60)/3)*出来高!E60:R60)),50)) | O60: =IF($D60="","",IFERROR(出来高!E60/AVERAGE(出来高!E60:I60),"")) | P60: =IF($D60="","",IFERROR($D60/終値!Y60-1,"")) | Q60: =IF($D60="","",MAX(0,MIN(100,IF($D60>$G60,25,IF($D60>$H60,15,IF($D60>$E60,5,0)))+IF($O60>=2,20,IF($O60>=1.5,14,IF($O60>=1.2,8,0)))+IF($N60>=80,15,IF($N60>=60,18,IF($N60>=50,8,0)))+IF(AND($M60>70,$M60<=80),18,IF(AND($M60>60,$M60<=70),14,IF(AND($M60>50,$M60<=60),6,0)))+IF($P60>=0.1,14,IF($P60>=0.03,7,0))+IF($M60>80,-12,0)+IF($M60<40,-20,0)+IF($N60<40,-15,0)+IF($K60<0.2,-18,0)+IF($P60<=-0.1,-10,0)))) | R60: =IF($D60="","",IF(AND($D60>$G60,$O60>=BB816設定!$B$6,$N60>=BB816設定!$B$7,$M60<=BB816設定!$B$8),"○","－")) | S60: =IF($D60="","",IF(AND($R60="○",$Q60>=BB816設定!$B$9),"◎買い",IF($Q60>=BB816設定!$B$10,"○監視",IF(OR($M60<40,$K60<0.2),"▲弱い","－")))) | T60: =IF($D60="","",IF(AND($D60>$G60,$O60>=BB816設定!$B$14,$N60>=BB816設定!$B$15,$M60<=BB816設定!$B$16),"買い可","見送り")) | U60: =IF($D60="","",IF(AND($D60>$H60,$M60>=BB816設定!$B$17,$N60>=BB816設定!$B$18,$O60>=BB816設定!$B$19),"買い可","見送り")) | V60: =IF($S60="◎買い",$D60,"") | W60: =IF($S60="◎買い",ROUND($D60*(1-BB816設定!$B$11/100),1),"") | X60: =IF($S60="◎買い",BB816設定!$B$11/BB816設定!$B$13,"") | Y60: =IF($D60="","",$Q60+(10000-ROW())/100000) | Z60: =IF($D60="","",$D60*BB816設定!$B$21) | AA60: =IF($D60="","",IF($Z60<=BB816設定!$B$20/BB816設定!$B$13,"○","×（1枠に入らない）"))
A61: =IF(終値!A61="","",HYPERLINK("https://kabutan.jp/stock/?code="&終値!A61,"📈")) | B61: =IF(終値!A61="","",終値!A61) | C61: =IF(終値!A61="","",終値!B61) | D61: =IF(終値!A61="","",終値!E61) | E61: =IF($D61="","",AVERAGE(終値!E61:X61)) | F61: =IF($D61="","",STDEVP(終値!E61:X61)) | G61: =IF($D61="","",$E61+BB816設定!$B$4*$F61) | H61: =IF($D61="","",$E61+BB816設定!$B$5*$F61) | I61: =IF($D61="","",$E61-BB816設定!$B$5*$F61) | J61: =IF($D61="","",$E61-BB816設定!$B$4*$F61) | K61: =IF($D61="","",IFERROR(($D61-$J61)/($G61-$J61),"")) | L61: =IF($D61="","",IFERROR(($G61-$J61)/$E61*100,"")) | M61: =IF($D61="","",IFERROR(100-100/(1+SUMPRODUCT((終値!E61:R61>終値!F61:S61)*(終値!E61:R61-終値!F61:S61))/SUMPRODUCT((終値!E61:R61<終値!F61:S61)*(終値!F61:S61-終値!E61:R61))),100)) | N61: =IF($D61="","",IFERROR(100-100/(1+SUMPRODUCT((((高値!E61:R61+安値!E61:R61+終値!E61:R61)/3)>((高値!F61:S61+安値!F61:S61+終値!F61:S61)/3))*((高値!E61:R61+安値!E61:R61+終値!E61:R61)/3)*出来高!E61:R61)/SUMPRODUCT((((高値!E61:R61+安値!E61:R61+終値!E61:R61)/3)<((高値!F61:S61+安値!F61:S61+終値!F61:S61)/3))*((高値!E61:R61+安値!E61:R61+終値!E61:R61)/3)*出来高!E61:R61)),50)) | O61: =IF($D61="","",IFERROR(出来高!E61/AVERAGE(出来高!E61:I61),"")) | P61: =IF($D61="","",IFERROR($D61/終値!Y61-1,"")) | Q61: =IF($D61="","",MAX(0,MIN(100,IF($D61>$G61,25,IF($D61>$H61,15,IF($D61>$E61,5,0)))+IF($O61>=2,20,IF($O61>=1.5,14,IF($O61>=1.2,8,0)))+IF($N61>=80,15,IF($N61>=60,18,IF($N61>=50,8,0)))+IF(AND($M61>70,$M61<=80),18,IF(AND($M61>60,$M61<=70),14,IF(AND($M61>50,$M61<=60),6,0)))+IF($P61>=0.1,14,IF($P61>=0.03,7,0))+IF($M61>80,-12,0)+IF($M61<40,-20,0)+IF($N61<40,-15,0)+IF($K61<0.2,-18,0)+IF($P61<=-0.1,-10,0)))) | R61: =IF($D61="","",IF(AND($D61>$G61,$O61>=BB816設定!$B$6,$N61>=BB816設定!$B$7,$M61<=BB816設定!$B$8),"○","－")) | S61: =IF($D61="","",IF(AND($R61="○",$Q61>=BB816設定!$B$9),"◎買い",IF($Q61>=BB816設定!$B$10,"○監視",IF(OR($M61<40,$K61<0.2),"▲弱い","－")))) | T61: =IF($D61="","",IF(AND($D61>$G61,$O61>=BB816設定!$B$14,$N61>=BB816設定!$B$15,$M61<=BB816設定!$B$16),"買い可","見送り")) | U61: =IF($D61="","",IF(AND($D61>$H61,$M61>=BB816設定!$B$17,$N61>=BB816設定!$B$18,$O61>=BB816設定!$B$19),"買い可","見送り")) | V61: =IF($S61="◎買い",$D61,"") | W61: =IF($S61="◎買い",ROUND($D61*(1-BB816設定!$B$11/100),1),"") | X61: =IF($S61="◎買い",BB816設定!$B$11/BB816設定!$B$13,"") | Y61: =IF($D61="","",$Q61+(10000-ROW())/100000) | Z61: =IF($D61="","",$D61*BB816設定!$B$21) | AA61: =IF($D61="","",IF($Z61<=BB816設定!$B$20/BB816設定!$B$13,"○","×（1枠に入らない）"))
A62: =IF(終値!A62="","",HYPERLINK("https://kabutan.jp/stock/?code="&終値!A62,"📈")) | B62: =IF(終値!A62="","",終値!A62) | C62: =IF(終値!A62="","",終値!B62) | D62: =IF(終値!A62="","",終値!E62) | E62: =IF($D62="","",AVERAGE(終値!E62:X62)) | F62: =IF($D62="","",STDEVP(終値!E62:X62)) | G62: =IF($D62="","",$E62+BB816設定!$B$4*$F62) | H62: =IF($D62="","",$E62+BB816設定!$B$5*$F62) | I62: =IF($D62="","",$E62-BB816設定!$B$5*$F62) | J62: =IF($D62="","",$E62-BB816設定!$B$4*$F62) | K62: =IF($D62="","",IFERROR(($D62-$J62)/($G62-$J62),"")) | L62: =IF($D62="","",IFERROR(($G62-$J62)/$E62*100,"")) | M62: =IF($D62="","",IFERROR(100-100/(1+SUMPRODUCT((終値!E62:R62>終値!F62:S62)*(終値!E62:R62-終値!F62:S62))/SUMPRODUCT((終値!E62:R62<終値!F62:S62)*(終値!F62:S62-終値!E62:R62))),100)) | N62: =IF($D62="","",IFERROR(100-100/(1+SUMPRODUCT((((高値!E62:R62+安値!E62:R62+終値!E62:R62)/3)>((高値!F62:S62+安値!F62:S62+終値!F62:S62)/3))*((高値!E62:R62+安値!E62:R62+終値!E62:R62)/3)*出来高!E62:R62)/SUMPRODUCT((((高値!E62:R62+安値!E62:R62+終値!E62:R62)/3)<((高値!F62:S62+安値!F62:S62+終値!F62:S62)/3))*((高値!E62:R62+安値!E62:R62+終値!E62:R62)/3)*出来高!E62:R62)),50)) | O62: =IF($D62="","",IFERROR(出来高!E62/AVERAGE(出来高!E62:I62),"")) | P62: =IF($D62="","",IFERROR($D62/終値!Y62-1,"")) | Q62: =IF($D62="","",MAX(0,MIN(100,IF($D62>$G62,25,IF($D62>$H62,15,IF($D62>$E62,5,0)))+IF($O62>=2,20,IF($O62>=1.5,14,IF($O62>=1.2,8,0)))+IF($N62>=80,15,IF($N62>=60,18,IF($N62>=50,8,0)))+IF(AND($M62>70,$M62<=80),18,IF(AND($M62>60,$M62<=70),14,IF(AND($M62>50,$M62<=60),6,0)))+IF($P62>=0.1,14,IF($P62>=0.03,7,0))+IF($M62>80,-12,0)+IF($M62<40,-20,0)+IF($N62<40,-15,0)+IF($K62<0.2,-18,0)+IF($P62<=-0.1,-10,0)))) | R62: =IF($D62="","",IF(AND($D62>$G62,$O62>=BB816設定!$B$6,$N62>=BB816設定!$B$7,$M62<=BB816設定!$B$8),"○","－")) | S62: =IF($D62="","",IF(AND($R62="○",$Q62>=BB816設定!$B$9),"◎買い",IF($Q62>=BB816設定!$B$10,"○監視",IF(OR($M62<40,$K62<0.2),"▲弱い","－")))) | T62: =IF($D62="","",IF(AND($D62>$G62,$O62>=BB816設定!$B$14,$N62>=BB816設定!$B$15,$M62<=BB816設定!$B$16),"買い可","見送り")) | U62: =IF($D62="","",IF(AND($D62>$H62,$M62>=BB816設定!$B$17,$N62>=BB816設定!$B$18,$O62>=BB816設定!$B$19),"買い可","見送り")) | V62: =IF($S62="◎買い",$D62,"") | W62: =IF($S62="◎買い",ROUND($D62*(1-BB816設定!$B$11/100),1),"") | X62: =IF($S62="◎買い",BB816設定!$B$11/BB816設定!$B$13,"") | Y62: =IF($D62="","",$Q62+(10000-ROW())/100000) | Z62: =IF($D62="","",$D62*BB816設定!$B$21) | AA62: =IF($D62="","",IF($Z62<=BB816設定!$B$20/BB816設定!$B$13,"○","×（1枠に入らない）"))
A63: =IF(終値!A63="","",HYPERLINK("https://kabutan.jp/stock/?code="&終値!A63,"📈")) | B63: =IF(終値!A63="","",終値!A63) | C63: =IF(終値!A63="","",終値!B63) | D63: =IF(終値!A63="","",終値!E63) | E63: =IF($D63="","",AVERAGE(終値!E63:X63)) | F63: =IF($D63="","",STDEVP(終値!E63:X63)) | G63: =IF($D63="","",$E63+BB816設定!$B$4*$F63) | H63: =IF($D63="","",$E63+BB816設定!$B$5*$F63) | I63: =IF($D63="","",$E63-BB816設定!$B$5*$F63) | J63: =IF($D63="","",$E63-BB816設定!$B$4*$F63) | K63: =IF($D63="","",IFERROR(($D63-$J63)/($G63-$J63),"")) | L63: =IF($D63="","",IFERROR(($G63-$J63)/$E63*100,"")) | M63: =IF($D63="","",IFERROR(100-100/(1+SUMPRODUCT((終値!E63:R63>終値!F63:S63)*(終値!E63:R63-終値!F63:S63))/SUMPRODUCT((終値!E63:R63<終値!F63:S63)*(終値!F63:S63-終値!E63:R63))),100)) | N63: =IF($D63="","",IFERROR(100-100/(1+SUMPRODUCT((((高値!E63:R63+安値!E63:R63+終値!E63:R63)/3)>((高値!F63:S63+安値!F63:S63+終値!F63:S63)/3))*((高値!E63:R63+安値!E63:R63+終値!E63:R63)/3)*出来高!E63:R63)/SUMPRODUCT((((高値!E63:R63+安値!E63:R63+終値!E63:R63)/3)<((高値!F63:S63+安値!F63:S63+終値!F63:S63)/3))*((高値!E63:R63+安値!E63:R63+終値!E63:R63)/3)*出来高!E63:R63)),50)) | O63: =IF($D63="","",IFERROR(出来高!E63/AVERAGE(出来高!E63:I63),"")) | P63: =IF($D63="","",IFERROR($D63/終値!Y63-1,"")) | Q63: =IF($D63="","",MAX(0,MIN(100,IF($D63>$G63,25,IF($D63>$H63,15,IF($D63>$E63,5,0)))+IF($O63>=2,20,IF($O63>=1.5,14,IF($O63>=1.2,8,0)))+IF($N63>=80,15,IF($N63>=60,18,IF($N63>=50,8,0)))+IF(AND($M63>70,$M63<=80),18,IF(AND($M63>60,$M63<=70),14,IF(AND($M63>50,$M63<=60),6,0)))+IF($P63>=0.1,14,IF($P63>=0.03,7,0))+IF($M63>80,-12,0)+IF($M63<40,-20,0)+IF($N63<40,-15,0)+IF($K63<0.2,-18,0)+IF($P63<=-0.1,-10,0)))) | R63: =IF($D63="","",IF(AND($D63>$G63,$O63>=BB816設定!$B$6,$N63>=BB816設定!$B$7,$M63<=BB816設定!$B$8),"○","－")) | S63: =IF($D63="","",IF(AND($R63="○",$Q63>=BB816設定!$B$9),"◎買い",IF($Q63>=BB816設定!$B$10,"○監視",IF(OR($M63<40,$K63<0.2),"▲弱い","－")))) | T63: =IF($D63="","",IF(AND($D63>$G63,$O63>=BB816設定!$B$14,$N63>=BB816設定!$B$15,$M63<=BB816設定!$B$16),"買い可","見送り")) | U63: =IF($D63="","",IF(AND($D63>$H63,$M63>=BB816設定!$B$17,$N63>=BB816設定!$B$18,$O63>=BB816設定!$B$19),"買い可","見送り")) | V63: =IF($S63="◎買い",$D63,"") | W63: =IF($S63="◎買い",ROUND($D63*(1-BB816設定!$B$11/100),1),"") | X63: =IF($S63="◎買い",BB816設定!$B$11/BB816設定!$B$13,"") | Y63: =IF($D63="","",$Q63+(10000-ROW())/100000) | Z63: =IF($D63="","",$D63*BB816設定!$B$21) | AA63: =IF($D63="","",IF($Z63<=BB816設定!$B$20/BB816設定!$B$13,"○","×（1枠に入らない）"))
A64: =IF(終値!A64="","",HYPERLINK("https://kabutan.jp/stock/?code="&終値!A64,"📈")) | B64: =IF(終値!A64="","",終値!A64) | C64: =IF(終値!A64="","",終値!B64) | D64: =IF(終値!A64="","",終値!E64) | E64: =IF($D64="","",AVERAGE(終値!E64:X64)) | F64: =IF($D64="","",STDEVP(終値!E64:X64)) | G64: =IF($D64="","",$E64+BB816設定!$B$4*$F64) | H64: =IF($D64="","",$E64+BB816設定!$B$5*$F64) | I64: =IF($D64="","",$E64-BB816設定!$B$5*$F64) | J64: =IF($D64="","",$E64-BB816設定!$B$4*$F64) | K64: =IF($D64="","",IFERROR(($D64-$J64)/($G64-$J64),"")) | L64: =IF($D64="","",IFERROR(($G64-$J64)/$E64*100,"")) | M64: =IF($D64="","",IFERROR(100-100/(1+SUMPRODUCT((終値!E64:R64>終値!F64:S64)*(終値!E64:R64-終値!F64:S64))/SUMPRODUCT((終値!E64:R64<終値!F64:S64)*(終値!F64:S64-終値!E64:R64))),100)) | N64: =IF($D64="","",IFERROR(100-100/(1+SUMPRODUCT((((高値!E64:R64+安値!E64:R64+終値!E64:R64)/3)>((高値!F64:S64+安値!F64:S64+終値!F64:S64)/3))*((高値!E64:R64+安値!E64:R64+終値!E64:R64)/3)*出来高!E64:R64)/SUMPRODUCT((((高値!E64:R64+安値!E64:R64+終値!E64:R64)/3)<((高値!F64:S64+安値!F64:S64+終値!F64:S64)/3))*((高値!E64:R64+安値!E64:R64+終値!E64:R64)/3)*出来高!E64:R64)),50)) | O64: =IF($D64="","",IFERROR(出来高!E64/AVERAGE(出来高!E64:I64),"")) | P64: =IF($D64="","",IFERROR($D64/終値!Y64-1,"")) | Q64: =IF($D64="","",MAX(0,MIN(100,IF($D64>$G64,25,IF($D64>$H64,15,IF($D64>$E64,5,0)))+IF($O64>=2,20,IF($O64>=1.5,14,IF($O64>=1.2,8,0)))+IF($N64>=80,15,IF($N64>=60,18,IF($N64>=50,8,0)))+IF(AND($M64>70,$M64<=80),18,IF(AND($M64>60,$M64<=70),14,IF(AND($M64>50,$M64<=60),6,0)))+IF($P64>=0.1,14,IF($P64>=0.03,7,0))+IF($M64>80,-12,0)+IF($M64<40,-20,0)+IF($N64<40,-15,0)+IF($K64<0.2,-18,0)+IF($P64<=-0.1,-10,0)))) | R64: =IF($D64="","",IF(AND($D64>$G64,$O64>=BB816設定!$B$6,$N64>=BB816設定!$B$7,$M64<=BB816設定!$B$8),"○","－")) | S64: =IF($D64="","",IF(AND($R64="○",$Q64>=BB816設定!$B$9),"◎買い",IF($Q64>=BB816設定!$B$10,"○監視",IF(OR($M64<40,$K64<0.2),"▲弱い","－")))) | T64: =IF($D64="","",IF(AND($D64>$G64,$O64>=BB816設定!$B$14,$N64>=BB816設定!$B$15,$M64<=BB816設定!$B$16),"買い可","見送り")) | U64: =IF($D64="","",IF(AND($D64>$H64,$M64>=BB816設定!$B$17,$N64>=BB816設定!$B$18,$O64>=BB816設定!$B$19),"買い可","見送り")) | V64: =IF($S64="◎買い",$D64,"") | W64: =IF($S64="◎買い",ROUND($D64*(1-BB816設定!$B$11/100),1),"") | X64: =IF($S64="◎買い",BB816設定!$B$11/BB816設定!$B$13,"") | Y64: =IF($D64="","",$Q64+(10000-ROW())/100000) | Z64: =IF($D64="","",$D64*BB816設定!$B$21) | AA64: =IF($D64="","",IF($Z64<=BB816設定!$B$20/BB816設定!$B$13,"○","×（1枠に入らない）"))
A65: =IF(終値!A65="","",HYPERLINK("https://kabutan.jp/stock/?code="&終値!A65,"📈")) | B65: =IF(終値!A65="","",終値!A65) | C65: =IF(終値!A65="","",終値!B65) | D65: =IF(終値!A65="","",終値!E65) | E65: =IF($D65="","",AVERAGE(終値!E65:X65)) | F65: =IF($D65="","",STDEVP(終値!E65:X65)) | G65: =IF($D65="","",$E65+BB816設定!$B$4*$F65) | H65: =IF($D65="","",$E65+BB816設定!$B$5*$F65) | I65: =IF($D65="","",$E65-BB816設定!$B$5*$F65) | J65: =IF($D65="","",$E65-BB816設定!$B$4*$F65) | K65: =IF($D65="","",IFERROR(($D65-$J65)/($G65-$J65),"")) | L65: =IF($D65="","",IFERROR(($G65-$J65)/$E65*100,"")) | M65: =IF($D65="","",IFERROR(100-100/(1+SUMPRODUCT((終値!E65:R65>終値!F65:S65)*(終値!E65:R65-終値!F65:S65))/SUMPRODUCT((終値!E65:R65<終値!F65:S65)*(終値!F65:S65-終値!E65:R65))),100)) | N65: =IF($D65="","",IFERROR(100-100/(1+SUMPRODUCT((((高値!E65:R65+安値!E65:R65+終値!E65:R65)/3)>((高値!F65:S65+安値!F65:S65+終値!F65:S65)/3))*((高値!E65:R65+安値!E65:R65+終値!E65:R65)/3)*出来高!E65:R65)/SUMPRODUCT((((高値!E65:R65+安値!E65:R65+終値!E65:R65)/3)<((高値!F65:S65+安値!F65:S65+終値!F65:S65)/3))*((高値!E65:R65+安値!E65:R65+終値!E65:R65)/3)*出来高!E65:R65)),50)) | O65: =IF($D65="","",IFERROR(出来高!E65/AVERAGE(出来高!E65:I65),"")) | P65: =IF($D65="","",IFERROR($D65/終値!Y65-1,"")) | Q65: =IF($D65="","",MAX(0,MIN(100,IF($D65>$G65,25,IF($D65>$H65,15,IF($D65>$E65,5,0)))+IF($O65>=2,20,IF($O65>=1.5,14,IF($O65>=1.2,8,0)))+IF($N65>=80,15,IF($N65>=60,18,IF($N65>=50,8,0)))+IF(AND($M65>70,$M65<=80),18,IF(AND($M65>60,$M65<=70),14,IF(AND($M65>50,$M65<=60),6,0)))+IF($P65>=0.1,14,IF($P65>=0.03,7,0))+IF($M65>80,-12,0)+IF($M65<40,-20,0)+IF($N65<40,-15,0)+IF($K65<0.2,-18,0)+IF($P65<=-0.1,-10,0)))) | R65: =IF($D65="","",IF(AND($D65>$G65,$O65>=BB816設定!$B$6,$N65>=BB816設定!$B$7,$M65<=BB816設定!$B$8),"○","－")) | S65: =IF($D65="","",IF(AND($R65="○",$Q65>=BB816設定!$B$9),"◎買い",IF($Q65>=BB816設定!$B$10,"○監視",IF(OR($M65<40,$K65<0.2),"▲弱い","－")))) | T65: =IF($D65="","",IF(AND($D65>$G65,$O65>=BB816設定!$B$14,$N65>=BB816設定!$B$15,$M65<=BB816設定!$B$16),"買い可","見送り")) | U65: =IF($D65="","",IF(AND($D65>$H65,$M65>=BB816設定!$B$17,$N65>=BB816設定!$B$18,$O65>=BB816設定!$B$19),"買い可","見送り")) | V65: =IF($S65="◎買い",$D65,"") | W65: =IF($S65="◎買い",ROUND($D65*(1-BB816設定!$B$11/100),1),"") | X65: =IF($S65="◎買い",BB816設定!$B$11/BB816設定!$B$13,"") | Y65: =IF($D65="","",$Q65+(10000-ROW())/100000) | Z65: =IF($D65="","",$D65*BB816設定!$B$21) | AA65: =IF($D65="","",IF($Z65<=BB816設定!$B$20/BB816設定!$B$13,"○","×（1枠に入らない）"))
A66: =IF(終値!A66="","",HYPERLINK("https://kabutan.jp/stock/?code="&終値!A66,"📈")) | B66: =IF(終値!A66="","",終値!A66) | C66: =IF(終値!A66="","",終値!B66) | D66: =IF(終値!A66="","",終値!E66) | E66: =IF($D66="","",AVERAGE(終値!E66:X66)) | F66: =IF($D66="","",STDEVP(終値!E66:X66)) | G66: =IF($D66="","",$E66+BB816設定!$B$4*$F66) | H66: =IF($D66="","",$E66+BB816設定!$B$5*$F66) | I66: =IF($D66="","",$E66-BB816設定!$B$5*$F66) | J66: =IF($D66="","",$E66-BB816設定!$B$4*$F66) | K66: =IF($D66="","",IFERROR(($D66-$J66)/($G66-$J66),"")) | L66: =IF($D66="","",IFERROR(($G66-$J66)/$E66*100,"")) | M66: =IF($D66="","",IFERROR(100-100/(1+SUMPRODUCT((終値!E66:R66>終値!F66:S66)*(終値!E66:R66-終値!F66:S66))/SUMPRODUCT((終値!E66:R66<終値!F66:S66)*(終値!F66:S66-終値!E66:R66))),100)) | N66: =IF($D66="","",IFERROR(100-100/(1+SUMPRODUCT((((高値!E66:R66+安値!E66:R66+終値!E66:R66)/3)>((高値!F66:S66+安値!F66:S66+終値!F66:S66)/3))*((高値!E66:R66+安値!E66:R66+終値!E66:R66)/3)*出来高!E66:R66)/SUMPRODUCT((((高値!E66:R66+安値!E66:R66+終値!E66:R66)/3)<((高値!F66:S66+安値!F66:S66+終値!F66:S66)/3))*((高値!E66:R66+安値!E66:R66+終値!E66:R66)/3)*出来高!E66:R66)),50)) | O66: =IF($D66="","",IFERROR(出来高!E66/AVERAGE(出来高!E66:I66),"")) | P66: =IF($D66="","",IFERROR($D66/終値!Y66-1,"")) | Q66: =IF($D66="","",MAX(0,MIN(100,IF($D66>$G66,25,IF($D66>$H66,15,IF($D66>$E66,5,0)))+IF($O66>=2,20,IF($O66>=1.5,14,IF($O66>=1.2,8,0)))+IF($N66>=80,15,IF($N66>=60,18,IF($N66>=50,8,0)))+IF(AND($M66>70,$M66<=80),18,IF(AND($M66>60,$M66<=70),14,IF(AND($M66>50,$M66<=60),6,0)))+IF($P66>=0.1,14,IF($P66>=0.03,7,0))+IF($M66>80,-12,0)+IF($M66<40,-20,0)+IF($N66<40,-15,0)+IF($K66<0.2,-18,0)+IF($P66<=-0.1,-10,0)))) | R66: =IF($D66="","",IF(AND($D66>$G66,$O66>=BB816設定!$B$6,$N66>=BB816設定!$B$7,$M66<=BB816設定!$B$8),"○","－")) | S66: =IF($D66="","",IF(AND($R66="○",$Q66>=BB816設定!$B$9),"◎買い",IF($Q66>=BB816設定!$B$10,"○監視",IF(OR($M66<40,$K66<0.2),"▲弱い","－")))) | T66: =IF($D66="","",IF(AND($D66>$G66,$O66>=BB816設定!$B$14,$N66>=BB816設定!$B$15,$M66<=BB816設定!$B$16),"買い可","見送り")) | U66: =IF($D66="","",IF(AND($D66>$H66,$M66>=BB816設定!$B$17,$N66>=BB816設定!$B$18,$O66>=BB816設定!$B$19),"買い可","見送り")) | V66: =IF($S66="◎買い",$D66,"") | W66: =IF($S66="◎買い",ROUND($D66*(1-BB816設定!$B$11/100),1),"") | X66: =IF($S66="◎買い",BB816設定!$B$11/BB816設定!$B$13,"") | Y66: =IF($D66="","",$Q66+(10000-ROW())/100000) | Z66: =IF($D66="","",$D66*BB816設定!$B$21) | AA66: =IF($D66="","",IF($Z66<=BB816設定!$B$20/BB816設定!$B$13,"○","×（1枠に入らない）"))
A67: =IF(終値!A67="","",HYPERLINK("https://kabutan.jp/stock/?code="&終値!A67,"📈")) | B67: =IF(終値!A67="","",終値!A67) | C67: =IF(終値!A67="","",終値!B67) | D67: =IF(終値!A67="","",終値!E67) | E67: =IF($D67="","",AVERAGE(終値!E67:X67)) | F67: =IF($D67="","",STDEVP(終値!E67:X67)) | G67: =IF($D67="","",$E67+BB816設定!$B$4*$F67) | H67: =IF($D67="","",$E67+BB816設定!$B$5*$F67) | I67: =IF($D67="","",$E67-BB816設定!$B$5*$F67) | J67: =IF($D67="","",$E67-BB816設定!$B$4*$F67) | K67: =IF($D67="","",IFERROR(($D67-$J67)/($G67-$J67),"")) | L67: =IF($D67="","",IFERROR(($G67-$J67)/$E67*100,"")) | M67: =IF($D67="","",IFERROR(100-100/(1+SUMPRODUCT((終値!E67:R67>終値!F67:S67)*(終値!E67:R67-終値!F67:S67))/SUMPRODUCT((終値!E67:R67<終値!F67:S67)*(終値!F67:S67-終値!E67:R67))),100)) | N67: =IF($D67="","",IFERROR(100-100/(1+SUMPRODUCT((((高値!E67:R67+安値!E67:R67+終値!E67:R67)/3)>((高値!F67:S67+安値!F67:S67+終値!F67:S67)/3))*((高値!E67:R67+安値!E67:R67+終値!E67:R67)/3)*出来高!E67:R67)/SUMPRODUCT((((高値!E67:R67+安値!E67:R67+終値!E67:R67)/3)<((高値!F67:S67+安値!F67:S67+終値!F67:S67)/3))*((高値!E67:R67+安値!E67:R67+終値!E67:R67)/3)*出来高!E67:R67)),50)) | O67: =IF($D67="","",IFERROR(出来高!E67/AVERAGE(出来高!E67:I67),"")) | P67: =IF($D67="","",IFERROR($D67/終値!Y67-1,"")) | Q67: =IF($D67="","",MAX(0,MIN(100,IF($D67>$G67,25,IF($D67>$H67,15,IF($D67>$E67,5,0)))+IF($O67>=2,20,IF($O67>=1.5,14,IF($O67>=1.2,8,0)))+IF($N67>=80,15,IF($N67>=60,18,IF($N67>=50,8,0)))+IF(AND($M67>70,$M67<=80),18,IF(AND($M67>60,$M67<=70),14,IF(AND($M67>50,$M67<=60),6,0)))+IF($P67>=0.1,14,IF($P67>=0.03,7,0))+IF($M67>80,-12,0)+IF($M67<40,-20,0)+IF($N67<40,-15,0)+IF($K67<0.2,-18,0)+IF($P67<=-0.1,-10,0)))) | R67: =IF($D67="","",IF(AND($D67>$G67,$O67>=BB816設定!$B$6,$N67>=BB816設定!$B$7,$M67<=BB816設定!$B$8),"○","－")) | S67: =IF($D67="","",IF(AND($R67="○",$Q67>=BB816設定!$B$9),"◎買い",IF($Q67>=BB816設定!$B$10,"○監視",IF(OR($M67<40,$K67<0.2),"▲弱い","－")))) | T67: =IF($D67="","",IF(AND($D67>$G67,$O67>=BB816設定!$B$14,$N67>=BB816設定!$B$15,$M67<=BB816設定!$B$16),"買い可","見送り")) | U67: =IF($D67="","",IF(AND($D67>$H67,$M67>=BB816設定!$B$17,$N67>=BB816設定!$B$18,$O67>=BB816設定!$B$19),"買い可","見送り")) | V67: =IF($S67="◎買い",$D67,"") | W67: =IF($S67="◎買い",ROUND($D67*(1-BB816設定!$B$11/100),1),"") | X67: =IF($S67="◎買い",BB816設定!$B$11/BB816設定!$B$13,"") | Y67: =IF($D67="","",$Q67+(10000-ROW())/100000) | Z67: =IF($D67="","",$D67*BB816設定!$B$21) | AA67: =IF($D67="","",IF($Z67<=BB816設定!$B$20/BB816設定!$B$13,"○","×（1枠に入らない）"))
A68: =IF(終値!A68="","",HYPERLINK("https://kabutan.jp/stock/?code="&終値!A68,"📈")) | B68: =IF(終値!A68="","",終値!A68) | C68: =IF(終値!A68="","",終値!B68) | D68: =IF(終値!A68="","",終値!E68) | E68: =IF($D68="","",AVERAGE(終値!E68:X68)) | F68: =IF($D68="","",STDEVP(終値!E68:X68)) | G68: =IF($D68="","",$E68+BB816設定!$B$4*$F68) | H68: =IF($D68="","",$E68+BB816設定!$B$5*$F68) | I68: =IF($D68="","",$E68-BB816設定!$B$5*$F68) | J68: =IF($D68="","",$E68-BB816設定!$B$4*$F68) | K68: =IF($D68="","",IFERROR(($D68-$J68)/($G68-$J68),"")) | L68: =IF($D68="","",IFERROR(($G68-$J68)/$E68*100,"")) | M68: =IF($D68="","",IFERROR(100-100/(1+SUMPRODUCT((終値!E68:R68>終値!F68:S68)*(終値!E68:R68-終値!F68:S68))/SUMPRODUCT((終値!E68:R68<終値!F68:S68)*(終値!F68:S68-終値!E68:R68))),100)) | N68: =IF($D68="","",IFERROR(100-100/(1+SUMPRODUCT((((高値!E68:R68+安値!E68:R68+終値!E68:R68)/3)>((高値!F68:S68+安値!F68:S68+終値!F68:S68)/3))*((高値!E68:R68+安値!E68:R68+終値!E68:R68)/3)*出来高!E68:R68)/SUMPRODUCT((((高値!E68:R68+安値!E68:R68+終値!E68:R68)/3)<((高値!F68:S68+安値!F68:S68+終値!F68:S68)/3))*((高値!E68:R68+安値!E68:R68+終値!E68:R68)/3)*出来高!E68:R68)),50)) | O68: =IF($D68="","",IFERROR(出来高!E68/AVERAGE(出来高!E68:I68),"")) | P68: =IF($D68="","",IFERROR($D68/終値!Y68-1,"")) | Q68: =IF($D68="","",MAX(0,MIN(100,IF($D68>$G68,25,IF($D68>$H68,15,IF($D68>$E68,5,0)))+IF($O68>=2,20,IF($O68>=1.5,14,IF($O68>=1.2,8,0)))+IF($N68>=80,15,IF($N68>=60,18,IF($N68>=50,8,0)))+IF(AND($M68>70,$M68<=80),18,IF(AND($M68>60,$M68<=70),14,IF(AND($M68>50,$M68<=60),6,0)))+IF($P68>=0.1,14,IF($P68>=0.03,7,0))+IF($M68>80,-12,0)+IF($M68<40,-20,0)+IF($N68<40,-15,0)+IF($K68<0.2,-18,0)+IF($P68<=-0.1,-10,0)))) | R68: =IF($D68="","",IF(AND($D68>$G68,$O68>=BB816設定!$B$6,$N68>=BB816設定!$B$7,$M68<=BB816設定!$B$8),"○","－")) | S68: =IF($D68="","",IF(AND($R68="○",$Q68>=BB816設定!$B$9),"◎買い",IF($Q68>=BB816設定!$B$10,"○監視",IF(OR($M68<40,$K68<0.2),"▲弱い","－")))) | T68: =IF($D68="","",IF(AND($D68>$G68,$O68>=BB816設定!$B$14,$N68>=BB816設定!$B$15,$M68<=BB816設定!$B$16),"買い可","見送り")) | U68: =IF($D68="","",IF(AND($D68>$H68,$M68>=BB816設定!$B$17,$N68>=BB816設定!$B$18,$O68>=BB816設定!$B$19),"買い可","見送り")) | V68: =IF($S68="◎買い",$D68,"") | W68: =IF($S68="◎買い",ROUND($D68*(1-BB816設定!$B$11/100),1),"") | X68: =IF($S68="◎買い",BB816設定!$B$11/BB816設定!$B$13,"") | Y68: =IF($D68="","",$Q68+(10000-ROW())/100000) | Z68: =IF($D68="","",$D68*BB816設定!$B$21) | AA68: =IF($D68="","",IF($Z68<=BB816設定!$B$20/BB816設定!$B$13,"○","×（1枠に入らない）"))
A69: =IF(終値!A69="","",HYPERLINK("https://kabutan.jp/stock/?code="&終値!A69,"📈")) | B69: =IF(終値!A69="","",終値!A69) | C69: =IF(終値!A69="","",終値!B69) | D69: =IF(終値!A69="","",終値!E69) | E69: =IF($D69="","",AVERAGE(終値!E69:X69)) | F69: =IF($D69="","",STDEVP(終値!E69:X69)) | G69: =IF($D69="","",$E69+BB816設定!$B$4*$F69) | H69: =IF($D69="","",$E69+BB816設定!$B$5*$F69) | I69: =IF($D69="","",$E69-BB816設定!$B$5*$F69) | J69: =IF($D69="","",$E69-BB816設定!$B$4*$F69) | K69: =IF($D69="","",IFERROR(($D69-$J69)/($G69-$J69),"")) | L69: =IF($D69="","",IFERROR(($G69-$J69)/$E69*100,"")) | M69: =IF($D69="","",IFERROR(100-100/(1+SUMPRODUCT((終値!E69:R69>終値!F69:S69)*(終値!E69:R69-終値!F69:S69))/SUMPRODUCT((終値!E69:R69<終値!F69:S69)*(終値!F69:S69-終値!E69:R69))),100)) | N69: =IF($D69="","",IFERROR(100-100/(1+SUMPRODUCT((((高値!E69:R69+安値!E69:R69+終値!E69:R69)/3)>((高値!F69:S69+安値!F69:S69+終値!F69:S69)/3))*((高値!E69:R69+安値!E69:R69+終値!E69:R69)/3)*出来高!E69:R69)/SUMPRODUCT((((高値!E69:R69+安値!E69:R69+終値!E69:R69)/3)<((高値!F69:S69+安値!F69:S69+終値!F69:S69)/3))*((高値!E69:R69+安値!E69:R69+終値!E69:R69)/3)*出来高!E69:R69)),50)) | O69: =IF($D69="","",IFERROR(出来高!E69/AVERAGE(出来高!E69:I69),"")) | P69: =IF($D69="","",IFERROR($D69/終値!Y69-1,"")) | Q69: =IF($D69="","",MAX(0,MIN(100,IF($D69>$G69,25,IF($D69>$H69,15,IF($D69>$E69,5,0)))+IF($O69>=2,20,IF($O69>=1.5,14,IF($O69>=1.2,8,0)))+IF($N69>=80,15,IF($N69>=60,18,IF($N69>=50,8,0)))+IF(AND($M69>70,$M69<=80),18,IF(AND($M69>60,$M69<=70),14,IF(AND($M69>50,$M69<=60),6,0)))+IF($P69>=0.1,14,IF($P69>=0.03,7,0))+IF($M69>80,-12,0)+IF($M69<40,-20,0)+IF($N69<40,-15,0)+IF($K69<0.2,-18,0)+IF($P69<=-0.1,-10,0)))) | R69: =IF($D69="","",IF(AND($D69>$G69,$O69>=BB816設定!$B$6,$N69>=BB816設定!$B$7,$M69<=BB816設定!$B$8),"○","－")) | S69: =IF($D69="","",IF(AND($R69="○",$Q69>=BB816設定!$B$9),"◎買い",IF($Q69>=BB816設定!$B$10,"○監視",IF(OR($M69<40,$K69<0.2),"▲弱い","－")))) | T69: =IF($D69="","",IF(AND($D69>$G69,$O69>=BB816設定!$B$14,$N69>=BB816設定!$B$15,$M69<=BB816設定!$B$16),"買い可","見送り")) | U69: =IF($D69="","",IF(AND($D69>$H69,$M69>=BB816設定!$B$17,$N69>=BB816設定!$B$18,$O69>=BB816設定!$B$19),"買い可","見送り")) | V69: =IF($S69="◎買い",$D69,"") | W69: =IF($S69="◎買い",ROUND($D69*(1-BB816設定!$B$11/100),1),"") | X69: =IF($S69="◎買い",BB816設定!$B$11/BB816設定!$B$13,"") | Y69: =IF($D69="","",$Q69+(10000-ROW())/100000) | Z69: =IF($D69="","",$D69*BB816設定!$B$21) | AA69: =IF($D69="","",IF($Z69<=BB816設定!$B$20/BB816設定!$B$13,"○","×（1枠に入らない）"))
A70: =IF(終値!A70="","",HYPERLINK("https://kabutan.jp/stock/?code="&終値!A70,"📈")) | B70: =IF(終値!A70="","",終値!A70) | C70: =IF(終値!A70="","",終値!B70) | D70: =IF(終値!A70="","",終値!E70) | E70: =IF($D70="","",AVERAGE(終値!E70:X70)) | F70: =IF($D70="","",STDEVP(終値!E70:X70)) | G70: =IF($D70="","",$E70+BB816設定!$B$4*$F70) | H70: =IF($D70="","",$E70+BB816設定!$B$5*$F70) | I70: =IF($D70="","",$E70-BB816設定!$B$5*$F70) | J70: =IF($D70="","",$E70-BB816設定!$B$4*$F70) | K70: =IF($D70="","",IFERROR(($D70-$J70)/($G70-$J70),"")) | L70: =IF($D70="","",IFERROR(($G70-$J70)/$E70*100,"")) | M70: =IF($D70="","",IFERROR(100-100/(1+SUMPRODUCT((終値!E70:R70>終値!F70:S70)*(終値!E70:R70-終値!F70:S70))/SUMPRODUCT((終値!E70:R70<終値!F70:S70)*(終値!F70:S70-終値!E70:R70))),100)) | N70: =IF($D70="","",IFERROR(100-100/(1+SUMPRODUCT((((高値!E70:R70+安値!E70:R70+終値!E70:R70)/3)>((高値!F70:S70+安値!F70:S70+終値!F70:S70)/3))*((高値!E70:R70+安値!E70:R70+終値!E70:R70)/3)*出来高!E70:R70)/SUMPRODUCT((((高値!E70:R70+安値!E70:R70+終値!E70:R70)/3)<((高値!F70:S70+安値!F70:S70+終値!F70:S70)/3))*((高値!E70:R70+安値!E70:R70+終値!E70:R70)/3)*出来高!E70:R70)),50)) | O70: =IF($D70="","",IFERROR(出来高!E70/AVERAGE(出来高!E70:I70),"")) | P70: =IF($D70="","",IFERROR($D70/終値!Y70-1,"")) | Q70: =IF($D70="","",MAX(0,MIN(100,IF($D70>$G70,25,IF($D70>$H70,15,IF($D70>$E70,5,0)))+IF($O70>=2,20,IF($O70>=1.5,14,IF($O70>=1.2,8,0)))+IF($N70>=80,15,IF($N70>=60,18,IF($N70>=50,8,0)))+IF(AND($M70>70,$M70<=80),18,IF(AND($M70>60,$M70<=70),14,IF(AND($M70>50,$M70<=60),6,0)))+IF($P70>=0.1,14,IF($P70>=0.03,7,0))+IF($M70>80,-12,0)+IF($M70<40,-20,0)+IF($N70<40,-15,0)+IF($K70<0.2,-18,0)+IF($P70<=-0.1,-10,0)))) | R70: =IF($D70="","",IF(AND($D70>$G70,$O70>=BB816設定!$B$6,$N70>=BB816設定!$B$7,$M70<=BB816設定!$B$8),"○","－")) | S70: =IF($D70="","",IF(AND($R70="○",$Q70>=BB816設定!$B$9),"◎買い",IF($Q70>=BB816設定!$B$10,"○監視",IF(OR($M70<40,$K70<0.2),"▲弱い","－")))) | T70: =IF($D70="","",IF(AND($D70>$G70,$O70>=BB816設定!$B$14,$N70>=BB816設定!$B$15,$M70<=BB816設定!$B$16),"買い可","見送り")) | U70: =IF($D70="","",IF(AND($D70>$H70,$M70>=BB816設定!$B$17,$N70>=BB816設定!$B$18,$O70>=BB816設定!$B$19),"買い可","見送り")) | V70: =IF($S70="◎買い",$D70,"") | W70: =IF($S70="◎買い",ROUND($D70*(1-BB816設定!$B$11/100),1),"") | X70: =IF($S70="◎買い",BB816設定!$B$11/BB816設定!$B$13,"") | Y70: =IF($D70="","",$Q70+(10000-ROW())/100000) | Z70: =IF($D70="","",$D70*BB816設定!$B$21) | AA70: =IF($D70="","",IF($Z70<=BB816設定!$B$20/BB816設定!$B$13,"○","×（1枠に入らない）"))
A71: =IF(終値!A71="","",HYPERLINK("https://kabutan.jp/stock/?code="&終値!A71,"📈")) | B71: =IF(終値!A71="","",終値!A71) | C71: =IF(終値!A71="","",終値!B71) | D71: =IF(終値!A71="","",終値!E71) | E71: =IF($D71="","",AVERAGE(終値!E71:X71)) | F71: =IF($D71="","",STDEVP(終値!E71:X71)) | G71: =IF($D71="","",$E71+BB816設定!$B$4*$F71) | H71: =IF($D71="","",$E71+BB816設定!$B$5*$F71) | I71: =IF($D71="","",$E71-BB816設定!$B$5*$F71) | J71: =IF($D71="","",$E71-BB816設定!$B$4*$F71) | K71: =IF($D71="","",IFERROR(($D71-$J71)/($G71-$J71),"")) | L71: =IF($D71="","",IFERROR(($G71-$J71)/$E71*100,"")) | M71: =IF($D71="","",IFERROR(100-100/(1+SUMPRODUCT((終値!E71:R71>終値!F71:S71)*(終値!E71:R71-終値!F71:S71))/SUMPRODUCT((終値!E71:R71<終値!F71:S71)*(終値!F71:S71-終値!E71:R71))),100)) | N71: =IF($D71="","",IFERROR(100-100/(1+SUMPRODUCT((((高値!E71:R71+安値!E71:R71+終値!E71:R71)/3)>((高値!F71:S71+安値!F71:S71+終値!F71:S71)/3))*((高値!E71:R71+安値!E71:R71+終値!E71:R71)/3)*出来高!E71:R71)/SUMPRODUCT((((高値!E71:R71+安値!E71:R71+終値!E71:R71)/3)<((高値!F71:S71+安値!F71:S71+終値!F71:S71)/3))*((高値!E71:R71+安値!E71:R71+終値!E71:R71)/3)*出来高!E71:R71)),50)) | O71: =IF($D71="","",IFERROR(出来高!E71/AVERAGE(出来高!E71:I71),"")) | P71: =IF($D71="","",IFERROR($D71/終値!Y71-1,"")) | Q71: =IF($D71="","",MAX(0,MIN(100,IF($D71>$G71,25,IF($D71>$H71,15,IF($D71>$E71,5,0)))+IF($O71>=2,20,IF($O71>=1.5,14,IF($O71>=1.2,8,0)))+IF($N71>=80,15,IF($N71>=60,18,IF($N71>=50,8,0)))+IF(AND($M71>70,$M71<=80),18,IF(AND($M71>60,$M71<=70),14,IF(AND($M71>50,$M71<=60),6,0)))+IF($P71>=0.1,14,IF($P71>=0.03,7,0))+IF($M71>80,-12,0)+IF($M71<40,-20,0)+IF($N71<40,-15,0)+IF($K71<0.2,-18,0)+IF($P71<=-0.1,-10,0)))) | R71: =IF($D71="","",IF(AND($D71>$G71,$O71>=BB816設定!$B$6,$N71>=BB816設定!$B$7,$M71<=BB816設定!$B$8),"○","－")) | S71: =IF($D71="","",IF(AND($R71="○",$Q71>=BB816設定!$B$9),"◎買い",IF($Q71>=BB816設定!$B$10,"○監視",IF(OR($M71<40,$K71<0.2),"▲弱い","－")))) | T71: =IF($D71="","",IF(AND($D71>$G71,$O71>=BB816設定!$B$14,$N71>=BB816設定!$B$15,$M71<=BB816設定!$B$16),"買い可","見送り")) | U71: =IF($D71="","",IF(AND($D71>$H71,$M71>=BB816設定!$B$17,$N71>=BB816設定!$B$18,$O71>=BB816設定!$B$19),"買い可","見送り")) | V71: =IF($S71="◎買い",$D71,"") | W71: =IF($S71="◎買い",ROUND($D71*(1-BB816設定!$B$11/100),1),"") | X71: =IF($S71="◎買い",BB816設定!$B$11/BB816設定!$B$13,"") | Y71: =IF($D71="","",$Q71+(10000-ROW())/100000) | Z71: =IF($D71="","",$D71*BB816設定!$B$21) | AA71: =IF($D71="","",IF($Z71<=BB816設定!$B$20/BB816設定!$B$13,"○","×（1枠に入らない）"))
A72: =IF(終値!A72="","",HYPERLINK("https://kabutan.jp/stock/?code="&終値!A72,"📈")) | B72: =IF(終値!A72="","",終値!A72) | C72: =IF(終値!A72="","",終値!B72) | D72: =IF(終値!A72="","",終値!E72) | E72: =IF($D72="","",AVERAGE(終値!E72:X72)) | F72: =IF($D72="","",STDEVP(終値!E72:X72)) | G72: =IF($D72="","",$E72+BB816設定!$B$4*$F72) | H72: =IF($D72="","",$E72+BB816設定!$B$5*$F72) | I72: =IF($D72="","",$E72-BB816設定!$B$5*$F72) | J72: =IF($D72="","",$E72-BB816設定!$B$4*$F72) | K72: =IF($D72="","",IFERROR(($D72-$J72)/($G72-$J72),"")) | L72: =IF($D72="","",IFERROR(($G72-$J72)/$E72*100,"")) | M72: =IF($D72="","",IFERROR(100-100/(1+SUMPRODUCT((終値!E72:R72>終値!F72:S72)*(終値!E72:R72-終値!F72:S72))/SUMPRODUCT((終値!E72:R72<終値!F72:S72)*(終値!F72:S72-終値!E72:R72))),100)) | N72: =IF($D72="","",IFERROR(100-100/(1+SUMPRODUCT((((高値!E72:R72+安値!E72:R72+終値!E72:R72)/3)>((高値!F72:S72+安値!F72:S72+終値!F72:S72)/3))*((高値!E72:R72+安値!E72:R72+終値!E72:R72)/3)*出来高!E72:R72)/SUMPRODUCT((((高値!E72:R72+安値!E72:R72+終値!E72:R72)/3)<((高値!F72:S72+安値!F72:S72+終値!F72:S72)/3))*((高値!E72:R72+安値!E72:R72+終値!E72:R72)/3)*出来高!E72:R72)),50)) | O72: =IF($D72="","",IFERROR(出来高!E72/AVERAGE(出来高!E72:I72),"")) | P72: =IF($D72="","",IFERROR($D72/終値!Y72-1,"")) | Q72: =IF($D72="","",MAX(0,MIN(100,IF($D72>$G72,25,IF($D72>$H72,15,IF($D72>$E72,5,0)))+IF($O72>=2,20,IF($O72>=1.5,14,IF($O72>=1.2,8,0)))+IF($N72>=80,15,IF($N72>=60,18,IF($N72>=50,8,0)))+IF(AND($M72>70,$M72<=80),18,IF(AND($M72>60,$M72<=70),14,IF(AND($M72>50,$M72<=60),6,0)))+IF($P72>=0.1,14,IF($P72>=0.03,7,0))+IF($M72>80,-12,0)+IF($M72<40,-20,0)+IF($N72<40,-15,0)+IF($K72<0.2,-18,0)+IF($P72<=-0.1,-10,0)))) | R72: =IF($D72="","",IF(AND($D72>$G72,$O72>=BB816設定!$B$6,$N72>=BB816設定!$B$7,$M72<=BB816設定!$B$8),"○","－")) | S72: =IF($D72="","",IF(AND($R72="○",$Q72>=BB816設定!$B$9),"◎買い",IF($Q72>=BB816設定!$B$10,"○監視",IF(OR($M72<40,$K72<0.2),"▲弱い","－")))) | T72: =IF($D72="","",IF(AND($D72>$G72,$O72>=BB816設定!$B$14,$N72>=BB816設定!$B$15,$M72<=BB816設定!$B$16),"買い可","見送り")) | U72: =IF($D72="","",IF(AND($D72>$H72,$M72>=BB816設定!$B$17,$N72>=BB816設定!$B$18,$O72>=BB816設定!$B$19),"買い可","見送り")) | V72: =IF($S72="◎買い",$D72,"") | W72: =IF($S72="◎買い",ROUND($D72*(1-BB816設定!$B$11/100),1),"") | X72: =IF($S72="◎買い",BB816設定!$B$11/BB816設定!$B$13,"") | Y72: =IF($D72="","",$Q72+(10000-ROW())/100000) | Z72: =IF($D72="","",$D72*BB816設定!$B$21) | AA72: =IF($D72="","",IF($Z72<=BB816設定!$B$20/BB816設定!$B$13,"○","×（1枠に入らない）"))
A73: =IF(終値!A73="","",HYPERLINK("https://kabutan.jp/stock/?code="&終値!A73,"📈")) | B73: =IF(終値!A73="","",終値!A73) | C73: =IF(終値!A73="","",終値!B73) | D73: =IF(終値!A73="","",終値!E73) | E73: =IF($D73="","",AVERAGE(終値!E73:X73)) | F73: =IF($D73="","",STDEVP(終値!E73:X73)) | G73: =IF($D73="","",$E73+BB816設定!$B$4*$F73) | H73: =IF($D73="","",$E73+BB816設定!$B$5*$F73) | I73: =IF($D73="","",$E73-BB816設定!$B$5*$F73) | J73: =IF($D73="","",$E73-BB816設定!$B$4*$F73) | K73: =IF($D73="","",IFERROR(($D73-$J73)/($G73-$J73),"")) | L73: =IF($D73="","",IFERROR(($G73-$J73)/$E73*100,"")) | M73: =IF($D73="","",IFERROR(100-100/(1+SUMPRODUCT((終値!E73:R73>終値!F73:S73)*(終値!E73:R73-終値!F73:S73))/SUMPRODUCT((終値!E73:R73<終値!F73:S73)*(終値!F73:S73-終値!E73:R73))),100)) | N73: =IF($D73="","",IFERROR(100-100/(1+SUMPRODUCT((((高値!E73:R73+安値!E73:R73+終値!E73:R73)/3)>((高値!F73:S73+安値!F73:S73+終値!F73:S73)/3))*((高値!E73:R73+安値!E73:R73+終値!E73:R73)/3)*出来高!E73:R73)/SUMPRODUCT((((高値!E73:R73+安値!E73:R73+終値!E73:R73)/3)<((高値!F73:S73+安値!F73:S73+終値!F73:S73)/3))*((高値!E73:R73+安値!E73:R73+終値!E73:R73)/3)*出来高!E73:R73)),50)) | O73: =IF($D73="","",IFERROR(出来高!E73/AVERAGE(出来高!E73:I73),"")) | P73: =IF($D73="","",IFERROR($D73/終値!Y73-1,"")) | Q73: =IF($D73="","",MAX(0,MIN(100,IF($D73>$G73,25,IF($D73>$H73,15,IF($D73>$E73,5,0)))+IF($O73>=2,20,IF($O73>=1.5,14,IF($O73>=1.2,8,0)))+IF($N73>=80,15,IF($N73>=60,18,IF($N73>=50,8,0)))+IF(AND($M73>70,$M73<=80),18,IF(AND($M73>60,$M73<=70),14,IF(AND($M73>50,$M73<=60),6,0)))+IF($P73>=0.1,14,IF($P73>=0.03,7,0))+IF($M73>80,-12,0)+IF($M73<40,-20,0)+IF($N73<40,-15,0)+IF($K73<0.2,-18,0)+IF($P73<=-0.1,-10,0)))) | R73: =IF($D73="","",IF(AND($D73>$G73,$O73>=BB816設定!$B$6,$N73>=BB816設定!$B$7,$M73<=BB816設定!$B$8),"○","－")) | S73: =IF($D73="","",IF(AND($R73="○",$Q73>=BB816設定!$B$9),"◎買い",IF($Q73>=BB816設定!$B$10,"○監視",IF(OR($M73<40,$K73<0.2),"▲弱い","－")))) | T73: =IF($D73="","",IF(AND($D73>$G73,$O73>=BB816設定!$B$14,$N73>=BB816設定!$B$15,$M73<=BB816設定!$B$16),"買い可","見送り")) | U73: =IF($D73="","",IF(AND($D73>$H73,$M73>=BB816設定!$B$17,$N73>=BB816設定!$B$18,$O73>=BB816設定!$B$19),"買い可","見送り")) | V73: =IF($S73="◎買い",$D73,"") | W73: =IF($S73="◎買い",ROUND($D73*(1-BB816設定!$B$11/100),1),"") | X73: =IF($S73="◎買い",BB816設定!$B$11/BB816設定!$B$13,"") | Y73: =IF($D73="","",$Q73+(10000-ROW())/100000) | Z73: =IF($D73="","",$D73*BB816設定!$B$21) | AA73: =IF($D73="","",IF($Z73<=BB816設定!$B$20/BB816設定!$B$13,"○","×（1枠に入らない）"))
A74: =IF(終値!A74="","",HYPERLINK("https://kabutan.jp/stock/?code="&終値!A74,"📈")) | B74: =IF(終値!A74="","",終値!A74) | C74: =IF(終値!A74="","",終値!B74) | D74: =IF(終値!A74="","",終値!E74) | E74: =IF($D74="","",AVERAGE(終値!E74:X74)) | F74: =IF($D74="","",STDEVP(終値!E74:X74)) | G74: =IF($D74="","",$E74+BB816設定!$B$4*$F74) | H74: =IF($D74="","",$E74+BB816設定!$B$5*$F74) | I74: =IF($D74="","",$E74-BB816設定!$B$5*$F74) | J74: =IF($D74="","",$E74-BB816設定!$B$4*$F74) | K74: =IF($D74="","",IFERROR(($D74-$J74)/($G74-$J74),"")) | L74: =IF($D74="","",IFERROR(($G74-$J74)/$E74*100,"")) | M74: =IF($D74="","",IFERROR(100-100/(1+SUMPRODUCT((終値!E74:R74>終値!F74:S74)*(終値!E74:R74-終値!F74:S74))/SUMPRODUCT((終値!E74:R74<終値!F74:S74)*(終値!F74:S74-終値!E74:R74))),100)) | N74: =IF($D74="","",IFERROR(100-100/(1+SUMPRODUCT((((高値!E74:R74+安値!E74:R74+終値!E74:R74)/3)>((高値!F74:S74+安値!F74:S74+終値!F74:S74)/3))*((高値!E74:R74+安値!E74:R74+終値!E74:R74)/3)*出来高!E74:R74)/SUMPRODUCT((((高値!E74:R74+安値!E74:R74+終値!E74:R74)/3)<((高値!F74:S74+安値!F74:S74+終値!F74:S74)/3))*((高値!E74:R74+安値!E74:R74+終値!E74:R74)/3)*出来高!E74:R74)),50)) | O74: =IF($D74="","",IFERROR(出来高!E74/AVERAGE(出来高!E74:I74),"")) | P74: =IF($D74="","",IFERROR($D74/終値!Y74-1,"")) | Q74: =IF($D74="","",MAX(0,MIN(100,IF($D74>$G74,25,IF($D74>$H74,15,IF($D74>$E74,5,0)))+IF($O74>=2,20,IF($O74>=1.5,14,IF($O74>=1.2,8,0)))+IF($N74>=80,15,IF($N74>=60,18,IF($N74>=50,8,0)))+IF(AND($M74>70,$M74<=80),18,IF(AND($M74>60,$M74<=70),14,IF(AND($M74>50,$M74<=60),6,0)))+IF($P74>=0.1,14,IF($P74>=0.03,7,0))+IF($M74>80,-12,0)+IF($M74<40,-20,0)+IF($N74<40,-15,0)+IF($K74<0.2,-18,0)+IF($P74<=-0.1,-10,0)))) | R74: =IF($D74="","",IF(AND($D74>$G74,$O74>=BB816設定!$B$6,$N74>=BB816設定!$B$7,$M74<=BB816設定!$B$8),"○","－")) | S74: =IF($D74="","",IF(AND($R74="○",$Q74>=BB816設定!$B$9),"◎買い",IF($Q74>=BB816設定!$B$10,"○監視",IF(OR($M74<40,$K74<0.2),"▲弱い","－")))) | T74: =IF($D74="","",IF(AND($D74>$G74,$O74>=BB816設定!$B$14,$N74>=BB816設定!$B$15,$M74<=BB816設定!$B$16),"買い可","見送り")) | U74: =IF($D74="","",IF(AND($D74>$H74,$M74>=BB816設定!$B$17,$N74>=BB816設定!$B$18,$O74>=BB816設定!$B$19),"買い可","見送り")) | V74: =IF($S74="◎買い",$D74,"") | W74: =IF($S74="◎買い",ROUND($D74*(1-BB816設定!$B$11/100),1),"") | X74: =IF($S74="◎買い",BB816設定!$B$11/BB816設定!$B$13,"") | Y74: =IF($D74="","",$Q74+(10000-ROW())/100000) | Z74: =IF($D74="","",$D74*BB816設定!$B$21) | AA74: =IF($D74="","",IF($Z74<=BB816設定!$B$20/BB816設定!$B$13,"○","×（1枠に入らない）"))
A75: =IF(終値!A75="","",HYPERLINK("https://kabutan.jp/stock/?code="&終値!A75,"📈")) | B75: =IF(終値!A75="","",終値!A75) | C75: =IF(終値!A75="","",終値!B75) | D75: =IF(終値!A75="","",終値!E75) | E75: =IF($D75="","",AVERAGE(終値!E75:X75)) | F75: =IF($D75="","",STDEVP(終値!E75:X75)) | G75: =IF($D75="","",$E75+BB816設定!$B$4*$F75) | H75: =IF($D75="","",$E75+BB816設定!$B$5*$F75) | I75: =IF($D75="","",$E75-BB816設定!$B$5*$F75) | J75: =IF($D75="","",$E75-BB816設定!$B$4*$F75) | K75: =IF($D75="","",IFERROR(($D75-$J75)/($G75-$J75),"")) | L75: =IF($D75="","",IFERROR(($G75-$J75)/$E75*100,"")) | M75: =IF($D75="","",IFERROR(100-100/(1+SUMPRODUCT((終値!E75:R75>終値!F75:S75)*(終値!E75:R75-終値!F75:S75))/SUMPRODUCT((終値!E75:R75<終値!F75:S75)*(終値!F75:S75-終値!E75:R75))),100)) | N75: =IF($D75="","",IFERROR(100-100/(1+SUMPRODUCT((((高値!E75:R75+安値!E75:R75+終値!E75:R75)/3)>((高値!F75:S75+安値!F75:S75+終値!F75:S75)/3))*((高値!E75:R75+安値!E75:R75+終値!E75:R75)/3)*出来高!E75:R75)/SUMPRODUCT((((高値!E75:R75+安値!E75:R75+終値!E75:R75)/3)<((高値!F75:S75+安値!F75:S75+終値!F75:S75)/3))*((高値!E75:R75+安値!E75:R75+終値!E75:R75)/3)*出来高!E75:R75)),50)) | O75: =IF($D75="","",IFERROR(出来高!E75/AVERAGE(出来高!E75:I75),"")) | P75: =IF($D75="","",IFERROR($D75/終値!Y75-1,"")) | Q75: =IF($D75="","",MAX(0,MIN(100,IF($D75>$G75,25,IF($D75>$H75,15,IF($D75>$E75,5,0)))+IF($O75>=2,20,IF($O75>=1.5,14,IF($O75>=1.2,8,0)))+IF($N75>=80,15,IF($N75>=60,18,IF($N75>=50,8,0)))+IF(AND($M75>70,$M75<=80),18,IF(AND($M75>60,$M75<=70),14,IF(AND($M75>50,$M75<=60),6,0)))+IF($P75>=0.1,14,IF($P75>=0.03,7,0))+IF($M75>80,-12,0)+IF($M75<40,-20,0)+IF($N75<40,-15,0)+IF($K75<0.2,-18,0)+IF($P75<=-0.1,-10,0)))) | R75: =IF($D75="","",IF(AND($D75>$G75,$O75>=BB816設定!$B$6,$N75>=BB816設定!$B$7,$M75<=BB816設定!$B$8),"○","－")) | S75: =IF($D75="","",IF(AND($R75="○",$Q75>=BB816設定!$B$9),"◎買い",IF($Q75>=BB816設定!$B$10,"○監視",IF(OR($M75<40,$K75<0.2),"▲弱い","－")))) | T75: =IF($D75="","",IF(AND($D75>$G75,$O75>=BB816設定!$B$14,$N75>=BB816設定!$B$15,$M75<=BB816設定!$B$16),"買い可","見送り")) | U75: =IF($D75="","",IF(AND($D75>$H75,$M75>=BB816設定!$B$17,$N75>=BB816設定!$B$18,$O75>=BB816設定!$B$19),"買い可","見送り")) | V75: =IF($S75="◎買い",$D75,"") | W75: =IF($S75="◎買い",ROUND($D75*(1-BB816設定!$B$11/100),1),"") | X75: =IF($S75="◎買い",BB816設定!$B$11/BB816設定!$B$13,"") | Y75: =IF($D75="","",$Q75+(10000-ROW())/100000) | Z75: =IF($D75="","",$D75*BB816設定!$B$21) | AA75: =IF($D75="","",IF($Z75<=BB816設定!$B$20/BB816設定!$B$13,"○","×（1枠に入らない）"))
A76: =IF(終値!A76="","",HYPERLINK("https://kabutan.jp/stock/?code="&終値!A76,"📈")) | B76: =IF(終値!A76="","",終値!A76) | C76: =IF(終値!A76="","",終値!B76) | D76: =IF(終値!A76="","",終値!E76) | E76: =IF($D76="","",AVERAGE(終値!E76:X76)) | F76: =IF($D76="","",STDEVP(終値!E76:X76)) | G76: =IF($D76="","",$E76+BB816設定!$B$4*$F76) | H76: =IF($D76="","",$E76+BB816設定!$B$5*$F76) | I76: =IF($D76="","",$E76-BB816設定!$B$5*$F76) | J76: =IF($D76="","",$E76-BB816設定!$B$4*$F76) | K76: =IF($D76="","",IFERROR(($D76-$J76)/($G76-$J76),"")) | L76: =IF($D76="","",IFERROR(($G76-$J76)/$E76*100,"")) | M76: =IF($D76="","",IFERROR(100-100/(1+SUMPRODUCT((終値!E76:R76>終値!F76:S76)*(終値!E76:R76-終値!F76:S76))/SUMPRODUCT((終値!E76:R76<終値!F76:S76)*(終値!F76:S76-終値!E76:R76))),100)) | N76: =IF($D76="","",IFERROR(100-100/(1+SUMPRODUCT((((高値!E76:R76+安値!E76:R76+終値!E76:R76)/3)>((高値!F76:S76+安値!F76:S76+終値!F76:S76)/3))*((高値!E76:R76+安値!E76:R76+終値!E76:R76)/3)*出来高!E76:R76)/SUMPRODUCT((((高値!E76:R76+安値!E76:R76+終値!E76:R76)/3)<((高値!F76:S76+安値!F76:S76+終値!F76:S76)/3))*((高値!E76:R76+安値!E76:R76+終値!E76:R76)/3)*出来高!E76:R76)),50)) | O76: =IF($D76="","",IFERROR(出来高!E76/AVERAGE(出来高!E76:I76),"")) | P76: =IF($D76="","",IFERROR($D76/終値!Y76-1,"")) | Q76: =IF($D76="","",MAX(0,MIN(100,IF($D76>$G76,25,IF($D76>$H76,15,IF($D76>$E76,5,0)))+IF($O76>=2,20,IF($O76>=1.5,14,IF($O76>=1.2,8,0)))+IF($N76>=80,15,IF($N76>=60,18,IF($N76>=50,8,0)))+IF(AND($M76>70,$M76<=80),18,IF(AND($M76>60,$M76<=70),14,IF(AND($M76>50,$M76<=60),6,0)))+IF($P76>=0.1,14,IF($P76>=0.03,7,0))+IF($M76>80,-12,0)+IF($M76<40,-20,0)+IF($N76<40,-15,0)+IF($K76<0.2,-18,0)+IF($P76<=-0.1,-10,0)))) | R76: =IF($D76="","",IF(AND($D76>$G76,$O76>=BB816設定!$B$6,$N76>=BB816設定!$B$7,$M76<=BB816設定!$B$8),"○","－")) | S76: =IF($D76="","",IF(AND($R76="○",$Q76>=BB816設定!$B$9),"◎買い",IF($Q76>=BB816設定!$B$10,"○監視",IF(OR($M76<40,$K76<0.2),"▲弱い","－")))) | T76: =IF($D76="","",IF(AND($D76>$G76,$O76>=BB816設定!$B$14,$N76>=BB816設定!$B$15,$M76<=BB816設定!$B$16),"買い可","見送り")) | U76: =IF($D76="","",IF(AND($D76>$H76,$M76>=BB816設定!$B$17,$N76>=BB816設定!$B$18,$O76>=BB816設定!$B$19),"買い可","見送り")) | V76: =IF($S76="◎買い",$D76,"") | W76: =IF($S76="◎買い",ROUND($D76*(1-BB816設定!$B$11/100),1),"") | X76: =IF($S76="◎買い",BB816設定!$B$11/BB816設定!$B$13,"") | Y76: =IF($D76="","",$Q76+(10000-ROW())/100000) | Z76: =IF($D76="","",$D76*BB816設定!$B$21) | AA76: =IF($D76="","",IF($Z76<=BB816設定!$B$20/BB816設定!$B$13,"○","×（1枠に入らない）"))
A77: =IF(終値!A77="","",HYPERLINK("https://kabutan.jp/stock/?code="&終値!A77,"📈")) | B77: =IF(終値!A77="","",終値!A77) | C77: =IF(終値!A77="","",終値!B77) | D77: =IF(終値!A77="","",終値!E77) | E77: =IF($D77="","",AVERAGE(終値!E77:X77)) | F77: =IF($D77="","",STDEVP(終値!E77:X77)) | G77: =IF($D77="","",$E77+BB816設定!$B$4*$F77) | H77: =IF($D77="","",$E77+BB816設定!$B$5*$F77) | I77: =IF($D77="","",$E77-BB816設定!$B$5*$F77) | J77: =IF($D77="","",$E77-BB816設定!$B$4*$F77) | K77: =IF($D77="","",IFERROR(($D77-$J77)/($G77-$J77),"")) | L77: =IF($D77="","",IFERROR(($G77-$J77)/$E77*100,"")) | M77: =IF($D77="","",IFERROR(100-100/(1+SUMPRODUCT((終値!E77:R77>終値!F77:S77)*(終値!E77:R77-終値!F77:S77))/SUMPRODUCT((終値!E77:R77<終値!F77:S77)*(終値!F77:S77-終値!E77:R77))),100)) | N77: =IF($D77="","",IFERROR(100-100/(1+SUMPRODUCT((((高値!E77:R77+安値!E77:R77+終値!E77:R77)/3)>((高値!F77:S77+安値!F77:S77+終値!F77:S77)/3))*((高値!E77:R77+安値!E77:R77+終値!E77:R77)/3)*出来高!E77:R77)/SUMPRODUCT((((高値!E77:R77+安値!E77:R77+終値!E77:R77)/3)<((高値!F77:S77+安値!F77:S77+終値!F77:S77)/3))*((高値!E77:R77+安値!E77:R77+終値!E77:R77)/3)*出来高!E77:R77)),50)) | O77: =IF($D77="","",IFERROR(出来高!E77/AVERAGE(出来高!E77:I77),"")) | P77: =IF($D77="","",IFERROR($D77/終値!Y77-1,"")) | Q77: =IF($D77="","",MAX(0,MIN(100,IF($D77>$G77,25,IF($D77>$H77,15,IF($D77>$E77,5,0)))+IF($O77>=2,20,IF($O77>=1.5,14,IF($O77>=1.2,8,0)))+IF($N77>=80,15,IF($N77>=60,18,IF($N77>=50,8,0)))+IF(AND($M77>70,$M77<=80),18,IF(AND($M77>60,$M77<=70),14,IF(AND($M77>50,$M77<=60),6,0)))+IF($P77>=0.1,14,IF($P77>=0.03,7,0))+IF($M77>80,-12,0)+IF($M77<40,-20,0)+IF($N77<40,-15,0)+IF($K77<0.2,-18,0)+IF($P77<=-0.1,-10,0)))) | R77: =IF($D77="","",IF(AND($D77>$G77,$O77>=BB816設定!$B$6,$N77>=BB816設定!$B$7,$M77<=BB816設定!$B$8),"○","－")) | S77: =IF($D77="","",IF(AND($R77="○",$Q77>=BB816設定!$B$9),"◎買い",IF($Q77>=BB816設定!$B$10,"○監視",IF(OR($M77<40,$K77<0.2),"▲弱い","－")))) | T77: =IF($D77="","",IF(AND($D77>$G77,$O77>=BB816設定!$B$14,$N77>=BB816設定!$B$15,$M77<=BB816設定!$B$16),"買い可","見送り")) | U77: =IF($D77="","",IF(AND($D77>$H77,$M77>=BB816設定!$B$17,$N77>=BB816設定!$B$18,$O77>=BB816設定!$B$19),"買い可","見送り")) | V77: =IF($S77="◎買い",$D77,"") | W77: =IF($S77="◎買い",ROUND($D77*(1-BB816設定!$B$11/100),1),"") | X77: =IF($S77="◎買い",BB816設定!$B$11/BB816設定!$B$13,"") | Y77: =IF($D77="","",$Q77+(10000-ROW())/100000) | Z77: =IF($D77="","",$D77*BB816設定!$B$21) | AA77: =IF($D77="","",IF($Z77<=BB816設定!$B$20/BB816設定!$B$13,"○","×（1枠に入らない）"))
A78: =IF(終値!A78="","",HYPERLINK("https://kabutan.jp/stock/?code="&終値!A78,"📈")) | B78: =IF(終値!A78="","",終値!A78) | C78: =IF(終値!A78="","",終値!B78) | D78: =IF(終値!A78="","",終値!E78) | E78: =IF($D78="","",AVERAGE(終値!E78:X78)) | F78: =IF($D78="","",STDEVP(終値!E78:X78)) | G78: =IF($D78="","",$E78+BB816設定!$B$4*$F78) | H78: =IF($D78="","",$E78+BB816設定!$B$5*$F78) | I78: =IF($D78="","",$E78-BB816設定!$B$5*$F78) | J78: =IF($D78="","",$E78-BB816設定!$B$4*$F78) | K78: =IF($D78="","",IFERROR(($D78-$J78)/($G78-$J78),"")) | L78: =IF($D78="","",IFERROR(($G78-$J78)/$E78*100,"")) | M78: =IF($D78="","",IFERROR(100-100/(1+SUMPRODUCT((終値!E78:R78>終値!F78:S78)*(終値!E78:R78-終値!F78:S78))/SUMPRODUCT((終値!E78:R78<終値!F78:S78)*(終値!F78:S78-終値!E78:R78))),100)) | N78: =IF($D78="","",IFERROR(100-100/(1+SUMPRODUCT((((高値!E78:R78+安値!E78:R78+終値!E78:R78)/3)>((高値!F78:S78+安値!F78:S78+終値!F78:S78)/3))*((高値!E78:R78+安値!E78:R78+終値!E78:R78)/3)*出来高!E78:R78)/SUMPRODUCT((((高値!E78:R78+安値!E78:R78+終値!E78:R78)/3)<((高値!F78:S78+安値!F78:S78+終値!F78:S78)/3))*((高値!E78:R78+安値!E78:R78+終値!E78:R78)/3)*出来高!E78:R78)),50)) | O78: =IF($D78="","",IFERROR(出来高!E78/AVERAGE(出来高!E78:I78),"")) | P78: =IF($D78="","",IFERROR($D78/終値!Y78-1,"")) | Q78: =IF($D78="","",MAX(0,MIN(100,IF($D78>$G78,25,IF($D78>$H78,15,IF($D78>$E78,5,0)))+IF($O78>=2,20,IF($O78>=1.5,14,IF($O78>=1.2,8,0)))+IF($N78>=80,15,IF($N78>=60,18,IF($N78>=50,8,0)))+IF(AND($M78>70,$M78<=80),18,IF(AND($M78>60,$M78<=70),14,IF(AND($M78>50,$M78<=60),6,0)))+IF($P78>=0.1,14,IF($P78>=0.03,7,0))+IF($M78>80,-12,0)+IF($M78<40,-20,0)+IF($N78<40,-15,0)+IF($K78<0.2,-18,0)+IF($P78<=-0.1,-10,0)))) | R78: =IF($D78="","",IF(AND($D78>$G78,$O78>=BB816設定!$B$6,$N78>=BB816設定!$B$7,$M78<=BB816設定!$B$8),"○","－")) | S78: =IF($D78="","",IF(AND($R78="○",$Q78>=BB816設定!$B$9),"◎買い",IF($Q78>=BB816設定!$B$10,"○監視",IF(OR($M78<40,$K78<0.2),"▲弱い","－")))) | T78: =IF($D78="","",IF(AND($D78>$G78,$O78>=BB816設定!$B$14,$N78>=BB816設定!$B$15,$M78<=BB816設定!$B$16),"買い可","見送り")) | U78: =IF($D78="","",IF(AND($D78>$H78,$M78>=BB816設定!$B$17,$N78>=BB816設定!$B$18,$O78>=BB816設定!$B$19),"買い可","見送り")) | V78: =IF($S78="◎買い",$D78,"") | W78: =IF($S78="◎買い",ROUND($D78*(1-BB816設定!$B$11/100),1),"") | X78: =IF($S78="◎買い",BB816設定!$B$11/BB816設定!$B$13,"") | Y78: =IF($D78="","",$Q78+(10000-ROW())/100000) | Z78: =IF($D78="","",$D78*BB816設定!$B$21) | AA78: =IF($D78="","",IF($Z78<=BB816設定!$B$20/BB816設定!$B$13,"○","×（1枠に入らない）"))
