Workbook

Sheet BB使い方
B1: 📘 ボリンジャーバンド投資シート ― 使い方と戦略
B2: このブックは既存の楽天RSS株価管理システムに「ボリンジャーバンド(SMA20・±1σ/±2σ)」の
B3: 買い候補スクリーニング／バックテストを追加したものです。既存シートは一切変更していません。
B5: ■ シートの使い方
B6: ① 楽天RSS(マーケットスピードII RSS)を起動し、いつも通り「終値/高値/安値/出来高」シートを最新化する。
B7: ② 自動再計算(F9)後、「BBスクリーニング」シートを開く。全銘柄のバンド・シグナルが自動計算される。
B8: ③ 「スコア」列で降順に並べ替え、または「BB買い候補TOP」シートで上位30銘柄を確認する。
B9: ④ 「戦略シグナル」列が ◎○△ の銘柄を候補とし、利確(+1σ)・損切り(ミドル)ラインを確認する。
B10: ⑤ 「BBバックテスト」シートに銘柄コードを入れると、その銘柄の過去検証(勝率・損益)が出る。
B11: ⑥ 数値のしきい値は「BB設定」シートの青字セルで変更できる。
B13: ■ 戦略サマリー表（動画の手法をシート化）
B14: 戦略 | C14: エントリー条件 | D14: 確認フィルター | E14: 利確 | F14: 損切り | G14: 使用指標
B15: ①スクイーズブレイク | C15: 帯幅が歴史的低水準→終値が+2σを実体で突破 | D15: 帯幅が拡大に転換／ダマシ回避 | E15: +1σを実体割れ | F15: ミドル(SMA)割れ | G15: 帯幅・SMA・±2σ
B16: ②トレンドフォロー (バンドウォーク) | C16: 終値が+1σ以上を上方に歩く | D16: MFI≥80(資金流入強)。逆らわず押し目買い | E16: +1σ実体割れ | F16: ミドル／直近安値割れ | G16: ±1σ・MFI・SMA
B17: ③ダブルトップ/ボトム (厳密スイング検出) | C17: フラクタル(前後2本)で2つの谷/山を検出 →同水準＋間に戻り＝W/M型 | D17: 1回目バンド外→2回目バンド内を自動判定 ネックライン上抜け/下抜けで「確」 | E17: ネックライン到達 | F17: 直近安値割れ | G17: スイング・±2σ
B18: ④ダイバージェンス | C18: 価格は安値更新もRSIは切上げ | D18: ミドルライン上抜けでエントリー | E18: +1σ／+2σ目標 | F18: 直近安値割れ | G18: RSI・SMA
B19: 利確・損切り原則 | C19: 強いトレンドは+1σ〜+2σを歩く(バンドウォーク) | D19: +1σを実体で割ったら「宴の終わり」 | E19: +1σ割れで決済 | F19: ミドル or 直近安値割れ | G19: ±1σ・SMA
B21: ※ 移動平均は必ず SMA（単純移動平均）を使用しています（期間20日）。σは母標準偏差(STDEVP)。
B22: ※ スクイーズ=帯幅が過去40日の最小付近。ダイバージェンス=10日前とRSIを比較して逆行を検出。
B23: ※ データはすべて既存の終値/高値/安値/出来高シート（楽天RSS取得）を参照。二重入力は不要です。
B24: ※ バックテストは履歴の範囲（最大100日、履歴が増えるほど自動で検証期間も延びます）。
B25: ※ 本シートは投資助言ではありません。最終判断はご自身で行ってください。

Sheet BB設定
A1: ⚙ ボリンジャーバンド設定（青字セル＝変更可）
A3: 項目 | B3: 値 | C3: 説明
A4: 外側バンド σ倍率 | B4: 2 | C4: ±2σ。ボリンジャーバンドの外側。ブレイク判定に使用
A5: 内側バンド σ倍率 | B5: 1 | C5: ±1σ。利確ライン・バンドウォーク判定に使用
A6: SMA期間（固定20） | B6: 20 | C6: 単純移動平均SMAの期間。式はE:X=20日で固定 ※SMA使用
A7: スクイーズ許容係数 | B7: 1.1 | C7: 帯幅 ≤ 過去40日最小×この値 でスクイーズ判定
A8: スクイーズ履歴（固定40） | B8: 40 | C8: 帯幅の最小を探す期間（式で固定）
A9: RSI/MFI期間（固定14） | B9: 14 | C9: RSI・MFIの期間。式はE:R=14で固定
A10: MFI強気しきい値 | B10: 80 | C10: MFIがこの値以上＝資金流入が強い→順張り継続
A11: ダイバージェンス比較（固定10） | B11: 10 | C11: 10日前とRSIを比較して逆行を検出
A12: 二番底/天井 価格許容 | B12: 0.05 | C12: 2つのスイング安値(高値)の価格差がこの割合以内なら「同水準」
A13: ネックライン戻り | B13: 0.03 | C13: 2つの谷(山)の間の戻りがこの割合以上でW/M型と判定
A15: ■ シグナル凡例
A16: ◎スクイーズブレイク買 | B16: → | C16: スクイーズ★または収縮状態から+2σ突破＆帯3日連続拡大。最も強い買いサイン
A17: ○順張り継続(walk) | B17: → | C17: +1σ以上でMFI≥80。トレンドに乗る
A18: ○反発(ダイバ)買 | B18: → | C18: 強気ダイバージェンス＆-1σ回復。二番天井時は抑制
A19: △二番底買(確) | B19: → | C19: 厳密スイング検出のW型＋ネックライン上抜け/バンド内復帰。反転狙い
A20: △二番底形成 | B20: → | C20: W型は成立、ネックライン未上抜け。ブレイク待ち
A21: ☆スクイーズ監視 | B21: → | C21: 帯幅が最小圏。ブレイク待ちの監視銘柄
A22: ・押し目注目 | B22: → | C22: ミドル上で%B<0.6・MFI≥50。押し目買い候補
A23: ▼-2σ割れ危険 | B23: → | C23: -2σ割れ。下落継続の警戒
A24: ▼二番天井警戒 | B24: → | C24: 二番天井M形成中。買いシグナル抑制＆-15点ペナルティ

Sheet BB買い候補TOP
A1: 🏆 本日の買い候補 TOP30（スコア上位・自動抽出）
A2: 「BBスクリーニング」のスコア上位を自動表示。◎○△のシグナルを優先的にチェック。 | Q2: 最終更新 | R2: =終値!E3 -> 46240
A4: 順位 | B4: コード | C4: 銘柄名 | D4: 現在値 | E4: スクイーズ | F4: ブレイク | G4: RSI | H4: MFI | I4: ダイバ | J4: 戦略シグナル | K4: スコア | L4: 利確+1σ | M4: 損切り | N4: R:R | O4: 株探 | Q4: Ctrl+Shift+F9（全シート強制再計算）
A5: 1 | B5: =IFERROR(INDEX(BBスクリーニング!$B$6:$B$405,MATCH(LARGE(BBスクリーニング!$AE$6:$AE$405,$A5),BBスクリーニング!$AE$6:$AE$405,0)),"") -> 5243 | C5: =IFERROR(INDEX(BBスクリーニング!$C$6:$C$405,MATCH(LARGE(BBスクリーニング!$AE$6:$AE$405,$A5),BBスクリーニング!$AE$6:$AE$405,0)),"") -> ＮＯＴＥ | D5: =IFERROR(INDEX(BBスクリーニング!$D$6:$D$405,MATCH(LARGE(BBスクリーニング!$AE$6:$AE$405,$A5),BBスクリーニング!$AE$6:$AE$405,0)),"") -> 2314 | E5: =IFERROR(INDEX(BBスクリーニング!$N$6:$N$405,MATCH(LARGE(BBスクリーニング!$AE$6:$AE$405,$A5),BBスクリーニング!$AE$6:$AE$405,0)),"") -> スクイーズ★ | F5: =IFERROR(INDEX(BBスクリーニング!$P$6:$P$405,MATCH(LARGE(BBスクリーニング!$AE$6:$AE$405,$A5),BBスクリーニング!$AE$6:$AE$405,0)),"") -> ↑+2σ突破 | G5: =IFERROR(INDEX(BBスクリーニング!$Q$6:$Q$405,MATCH(LARGE(BBスクリーニング!$AE$6:$AE$405,$A5),BBスクリーニング!$AE$6:$AE$405,0)),"") -> 55.288889 | H5: =IFERROR(INDEX(BBスクリーニング!$R$6:$R$405,MATCH(LARGE(BBスクリーニング!$AE$6:$AE$405,$A5),BBスクリーニング!$AE$6:$AE$405,0)),"") -> 62.145217 | I5: =IFERROR(INDEX(BBスクリーニング!$S$6:$S$405,MATCH(LARGE(BBスクリーニング!$AE$6:$AE$405,$A5),BBスクリーニング!$AE$6:$AE$405,0)),"") -> － | J5: =IFERROR(INDEX(BBスクリーニング!$W$6:$W$405,MATCH(LARGE(BBスクリーニング!$AE$6:$AE$405,$A5),BBスクリーニング!$AE$6:$AE$405,0)),"") -> ◎スクイーズブレイク買 | K5: =IFERROR(INDEX(BBスクリーニング!$X$6:$X$405,MATCH(LARGE(BBスクリーニング!$AE$6:$AE$405,$A5),BBスクリーニング!$AE$6:$AE$405,0)),"") -> 75 | L5: =IFERROR(INDEX(BBスクリーニング!$Z$6:$Z$405,MATCH(LARGE(BBスクリーニング!$AE$6:$AE$405,$A5),BBスクリーニング!$AE$6:$AE$405,0)),"") -> 2198.5011 | M5: =IFERROR(INDEX(BBスクリーニング!$AA$6:$AA$405,MATCH(LARGE(BBスクリーニング!$AE$6:$AE$405,$A5),BBスクリーニング!$AE$6:$AE$405,0)),"") -> 2098.4 | N5: =IFERROR(INDEX(BBスクリーニング!$AC$6:$AC$405,MATCH(LARGE(BBスクリーニング!$AE$6:$AE$405,$A5),BBスクリーニング!$AE$6:$AE$405,0)),"") -> 0.39 | O5: =IF($B5="","",HYPERLINK("https://kabutan.jp/stock/?code="&$B5,"株探")) -> 株探
A6: 2 | B6: =IFERROR(INDEX(BBスクリーニング!$B$6:$B$405,MATCH(LARGE(BBスクリーニング!$AE$6:$AE$405,$A6),BBスクリーニング!$AE$6:$AE$405,0)),"") -> 4704 | C6: =IFERROR(INDEX(BBスクリーニング!$C$6:$C$405,MATCH(LARGE(BBスクリーニング!$AE$6:$AE$405,$A6),BBスクリーニング!$AE$6:$AE$405,0)),"") -> トレンドマイクロ | D6: =IFERROR(INDEX(BBスクリーニング!$D$6:$D$405,MATCH(LARGE(BBスクリーニング!$AE$6:$AE$405,$A6),BBスクリーニング!$AE$6:$AE$405,0)),"") -> 6720 | E6: =IFERROR(INDEX(BBスクリーニング!$N$6:$N$405,MATCH(LARGE(BBスクリーニング!$AE$6:$AE$405,$A6),BBスクリーニング!$AE$6:$AE$405,0)),"") -> 収縮 | F6: =IFERROR(INDEX(BBスクリーニング!$P$6:$P$405,MATCH(LARGE(BBスクリーニング!$AE$6:$AE$405,$A6),BBスクリーニング!$AE$6:$AE$405,0)),"") -> +1σ上 | G6: =IFERROR(INDEX(BBスクリーニング!$Q$6:$Q$405,MATCH(LARGE(BBスクリーニング!$AE$6:$AE$405,$A6),BBスクリーニング!$AE$6:$AE$405,0)),"") -> 56.684492 | H6: =IFERROR(INDEX(BBスクリーニング!$R$6:$R$405,MATCH(LARGE(BBスクリーニング!$AE$6:$AE$405,$A6),BBスクリーニング!$AE$6:$AE$405,0)),"") -> 73.03391 | I6: =IFERROR(INDEX(BBスクリーニング!$S$6:$S$405,MATCH(LARGE(BBスクリーニング!$AE$6:$AE$405,$A6),BBスクリーニング!$AE$6:$AE$405,0)),"") -> － | J6: =IFERROR(INDEX(BBスクリーニング!$W$6:$W$405,MATCH(LARGE(BBスクリーニング!$AE$6:$AE$405,$A6),BBスクリーニング!$AE$6:$AE$405,0)),"") -> △二番底形成 | K6: =IFERROR(INDEX(BBスクリーニング!$X$6:$X$405,MATCH(LARGE(BBスクリーニング!$AE$6:$AE$405,$A6),BBスクリーニング!$AE$6:$AE$405,0)),"") -> 67 | L6: =IFERROR(INDEX(BBスクリーニング!$Z$6:$Z$405,MATCH(LARGE(BBスクリーニング!$AE$6:$AE$405,$A6),BBスクリーニング!$AE$6:$AE$405,0)),"") -> 6594.5846 | M6: =IFERROR(INDEX(BBスクリーニング!$AA$6:$AA$405,MATCH(LARGE(BBスクリーニング!$AE$6:$AE$405,$A6),BBスクリーニング!$AE$6:$AE$405,0)),"") -> 6423.65 | N6: =IFERROR(INDEX(BBスクリーニング!$AC$6:$AC$405,MATCH(LARGE(BBスクリーニング!$AE$6:$AE$405,$A6),BBスクリーニング!$AE$6:$AE$405,0)),"") -> 0.15 | O6: =IF($B6="","",HYPERLINK("https://kabutan.jp/stock/?code="&$B6,"株探")) -> 株探 | V6: 8002の値 | W6: 意味・見方
A7: 3 | B7: =IFERROR(INDEX(BBスクリーニング!$B$6:$B$405,MATCH(LARGE(BBスクリーニング!$AE$6:$AE$405,$A7),BBスクリーニング!$AE$6:$AE$405,0)),"") -> 5711 | C7: =IFERROR(INDEX(BBスクリーニング!$C$6:$C$405,MATCH(LARGE(BBスクリーニング!$AE$6:$AE$405,$A7),BBスクリーニング!$AE$6:$AE$405,0)),"") -> 三菱マテリアル | D7: =IFERROR(INDEX(BBスクリーニング!$D$6:$D$405,MATCH(LARGE(BBスクリーニング!$AE$6:$AE$405,$A7),BBスクリーニング!$AE$6:$AE$405,0)),"") -> 4457 | E7: =IFERROR(INDEX(BBスクリーニング!$N$6:$N$405,MATCH(LARGE(BBスクリーニング!$AE$6:$AE$405,$A7),BBスクリーニング!$AE$6:$AE$405,0)),"") -> 収縮 | F7: =IFERROR(INDEX(BBスクリーニング!$P$6:$P$405,MATCH(LARGE(BBスクリーニング!$AE$6:$AE$405,$A7),BBスクリーニング!$AE$6:$AE$405,0)),"") -> ↑+2σ突破 | G7: =IFERROR(INDEX(BBスクリーニング!$Q$6:$Q$405,MATCH(LARGE(BBスクリーニング!$AE$6:$AE$405,$A7),BBスクリーニング!$AE$6:$AE$405,0)),"") -> 58.128079 | H7: =IFERROR(INDEX(BBスクリーニング!$R$6:$R$405,MATCH(LARGE(BBスクリーニング!$AE$6:$AE$405,$A7),BBスクリーニング!$AE$6:$AE$405,0)),"") -> 65.117569 | I7: =IFERROR(INDEX(BBスクリーニング!$S$6:$S$405,MATCH(LARGE(BBスクリーニング!$AE$6:$AE$405,$A7),BBスクリーニング!$AE$6:$AE$405,0)),"") -> － | J7: =IFERROR(INDEX(BBスクリーニング!$W$6:$W$405,MATCH(LARGE(BBスクリーニング!$AE$6:$AE$405,$A7),BBスクリーニング!$AE$6:$AE$405,0)),"") -> ◎スクイーズブレイク買 | K7: =IFERROR(INDEX(BBスクリーニング!$X$6:$X$405,MATCH(LARGE(BBスクリーニング!$AE$6:$AE$405,$A7),BBスクリーニング!$AE$6:$AE$405,0)),"") -> 65 | L7: =IFERROR(INDEX(BBスクリーニング!$Z$6:$Z$405,MATCH(LARGE(BBスクリーニング!$AE$6:$AE$405,$A7),BBスクリーニング!$AE$6:$AE$405,0)),"") -> 4281.7566 | M7: =IFERROR(INDEX(BBスクリーニング!$AA$6:$AA$405,MATCH(LARGE(BBスクリーニング!$AE$6:$AE$405,$A7),BBスクリーニング!$AE$6:$AE$405,0)),"") -> 4147.35 | N7: =IFERROR(INDEX(BBスクリーニング!$AC$6:$AC$405,MATCH(LARGE(BBスクリーニング!$AE$6:$AE$405,$A7),BBスクリーニング!$AE$6:$AE$405,0)),"") -> 0.3 | O7: =IF($B7="","",HYPERLINK("https://kabutan.jp/stock/?code="&$B7,"株探")) -> 株探 | V7: 3 | W7: スコアの高い順。上ほど条件がそろった銘柄
A8: 4 | B8: =IFERROR(INDEX(BBスクリーニング!$B$6:$B$405,MATCH(LARGE(BBスクリーニング!$AE$6:$AE$405,$A8),BBスクリーニング!$AE$6:$AE$405,0)),"") -> 8344 | C8: =IFERROR(INDEX(BBスクリーニング!$C$6:$C$405,MATCH(LARGE(BBスクリーニング!$AE$6:$AE$405,$A8),BBスクリーニング!$AE$6:$AE$405,0)),"") -> 山形銀行 | D8: =IFERROR(INDEX(BBスクリーニング!$D$6:$D$405,MATCH(LARGE(BBスクリーニング!$AE$6:$AE$405,$A8),BBスクリーニング!$AE$6:$AE$405,0)),"") -> 4235 | E8: =IFERROR(INDEX(BBスクリーニング!$N$6:$N$405,MATCH(LARGE(BBスクリーニング!$AE$6:$AE$405,$A8),BBスクリーニング!$AE$6:$AE$405,0)),"") -> 収縮 | F8: =IFERROR(INDEX(BBスクリーニング!$P$6:$P$405,MATCH(LARGE(BBスクリーニング!$AE$6:$AE$405,$A8),BBスクリーニング!$AE$6:$AE$405,0)),"") -> ↑+2σ突破 | G8: =IFERROR(INDEX(BBスクリーニング!$Q$6:$Q$405,MATCH(LARGE(BBスクリーニング!$AE$6:$AE$405,$A8),BBスクリーニング!$AE$6:$AE$405,0)),"") -> 58.530184 | H8: =IFERROR(INDEX(BBスクリーニング!$R$6:$R$405,MATCH(LARGE(BBスクリーニング!$AE$6:$AE$405,$A8),BBスクリーニング!$AE$6:$AE$405,0)),"") -> 63.260242 | I8: =IFERROR(INDEX(BBスクリーニング!$S$6:$S$405,MATCH(LARGE(BBスクリーニング!$AE$6:$AE$405,$A8),BBスクリーニング!$AE$6:$AE$405,0)),"") -> － | J8: =IFERROR(INDEX(BBスクリーニング!$W$6:$W$405,MATCH(LARGE(BBスクリーニング!$AE$6:$AE$405,$A8),BBスクリーニング!$AE$6:$AE$405,0)),"") -> ◎スクイーズブレイク買 | K8: =IFERROR(INDEX(BBスクリーニング!$X$6:$X$405,MATCH(LARGE(BBスクリーニング!$AE$6:$AE$405,$A8),BBスクリーニング!$AE$6:$AE$405,0)),"") -> 65 | L8: =IFERROR(INDEX(BBスクリーニング!$Z$6:$Z$405,MATCH(LARGE(BBスクリーニング!$AE$6:$AE$405,$A8),BBスクリーニング!$AE$6:$AE$405,0)),"") -> 4033.0327 | M8: =IFERROR(INDEX(BBスクリーニング!$AA$6:$AA$405,MATCH(LARGE(BBスクリーニング!$AE$6:$AE$405,$A8),BBスクリーニング!$AE$6:$AE$405,0)),"") -> 3870.75 | N8: =IFERROR(INDEX(BBスクリーニング!$AC$6:$AC$405,MATCH(LARGE(BBスクリーニング!$AE$6:$AE$405,$A8),BBスクリーニング!$AE$6:$AE$405,0)),"") -> 0.34 | O8: =IF($B8="","",HYPERLINK("https://kabutan.jp/stock/?code="&$B8,"株探")) -> 株探 | V8: 8002 | W8: 証券コード（4桁）
A9: 5 | B9: =IFERROR(INDEX(BBスクリーニング!$B$6:$B$405,MATCH(LARGE(BBスクリーニング!$AE$6:$AE$405,$A9),BBスクリーニング!$AE$6:$AE$405,0)),"") -> 3984 | C9: =IFERROR(INDEX(BBスクリーニング!$C$6:$C$405,MATCH(LARGE(BBスクリーニング!$AE$6:$AE$405,$A9),BBスクリーニング!$AE$6:$AE$405,0)),"") -> ユーザーローカル | D9: =IFERROR(INDEX(BBスクリーニング!$D$6:$D$405,MATCH(LARGE(BBスクリーニング!$AE$6:$AE$405,$A9),BBスクリーニング!$AE$6:$AE$405,0)),"") -> 1836 | E9: =IFERROR(INDEX(BBスクリーニング!$N$6:$N$405,MATCH(LARGE(BBスクリーニング!$AE$6:$AE$405,$A9),BBスクリーニング!$AE$6:$AE$405,0)),"") -> 収縮 | F9: =IFERROR(INDEX(BBスクリーニング!$P$6:$P$405,MATCH(LARGE(BBスクリーニング!$AE$6:$AE$405,$A9),BBスクリーニング!$AE$6:$AE$405,0)),"") -> +1σ上 | G9: =IFERROR(INDEX(BBスクリーニング!$Q$6:$Q$405,MATCH(LARGE(BBスクリーニング!$AE$6:$AE$405,$A9),BBスクリーニング!$AE$6:$AE$405,0)),"") -> 51.083591 | H9: =IFERROR(INDEX(BBスクリーニング!$R$6:$R$405,MATCH(LARGE(BBスクリーニング!$AE$6:$AE$405,$A9),BBスクリーニング!$AE$6:$AE$405,0)),"") -> 53.665458 | I9: =IFERROR(INDEX(BBスクリーニング!$S$6:$S$405,MATCH(LARGE(BBスクリーニング!$AE$6:$AE$405,$A9),BBスクリーニング!$AE$6:$AE$405,0)),"") -> － | J9: =IFERROR(INDEX(BBスクリーニング!$W$6:$W$405,MATCH(LARGE(BBスクリーニング!$AE$6:$AE$405,$A9),BBスクリーニング!$AE$6:$AE$405,0)),"") -> △二番底買(確) | K9: =IFERROR(INDEX(BBスクリーニング!$X$6:$X$405,MATCH(LARGE(BBスクリーニング!$AE$6:$AE$405,$A9),BBスクリーニング!$AE$6:$AE$405,0)),"") -> 62 | L9: =IFERROR(INDEX(BBスクリーニング!$Z$6:$Z$405,MATCH(LARGE(BBスクリーニング!$AE$6:$AE$405,$A9),BBスクリーニング!$AE$6:$AE$405,0)),"") -> 1827.2009 | M9: =IFERROR(INDEX(BBスクリーニング!$AA$6:$AA$405,MATCH(LARGE(BBスクリーニング!$AE$6:$AE$405,$A9),BBスクリーニング!$AE$6:$AE$405,0)),"") -> 1794.5 | N9: =IFERROR(INDEX(BBスクリーニング!$AC$6:$AC$405,MATCH(LARGE(BBスクリーニング!$AE$6:$AE$405,$A9),BBスクリーニング!$AE$6:$AE$405,0)),"") -> 0.58 | O9: =IF($B9="","",HYPERLINK("https://kabutan.jp/stock/?code="&$B9,"株探")) -> 株探 | V9: 丸紅 | W9: 会社名
A10: 6 | B10: =IFERROR(INDEX(BBスクリーニング!$B$6:$B$405,MATCH(LARGE(BBスクリーニング!$AE$6:$AE$405,$A10),BBスクリーニング!$AE$6:$AE$405,0)),"") -> 6965 | C10: =IFERROR(INDEX(BBスクリーニング!$C$6:$C$405,MATCH(LARGE(BBスクリーニング!$AE$6:$AE$405,$A10),BBスクリーニング!$AE$6:$AE$405,0)),"") -> 浜松ホトニクス | D10: =IFERROR(INDEX(BBスクリーニング!$D$6:$D$405,MATCH(LARGE(BBスクリーニング!$AE$6:$AE$405,$A10),BBスクリーニング!$AE$6:$AE$405,0)),"") -> 2505.5 | E10: =IFERROR(INDEX(BBスクリーニング!$N$6:$N$405,MATCH(LARGE(BBスクリーニング!$AE$6:$AE$405,$A10),BBスクリーニング!$AE$6:$AE$405,0)),"") -> スクイーズ★ | F10: =IFERROR(INDEX(BBスクリーニング!$P$6:$P$405,MATCH(LARGE(BBスクリーニング!$AE$6:$AE$405,$A10),BBスクリーニング!$AE$6:$AE$405,0)),"") -> +1σ上 | G10: =IFERROR(INDEX(BBスクリーニング!$Q$6:$Q$405,MATCH(LARGE(BBスクリーニング!$AE$6:$AE$405,$A10),BBスクリーニング!$AE$6:$AE$405,0)),"") -> 55.660874 | H10: =IFERROR(INDEX(BBスクリーニング!$R$6:$R$405,MATCH(LARGE(BBスクリーニング!$AE$6:$AE$405,$A10),BBスクリーニング!$AE$6:$AE$405,0)),"") -> 52.708572 | I10: =IFERROR(INDEX(BBスクリーニング!$S$6:$S$405,MATCH(LARGE(BBスクリーニング!$AE$6:$AE$405,$A10),BBスクリーニング!$AE$6:$AE$405,0)),"") -> － | J10: =IFERROR(INDEX(BBスクリーニング!$W$6:$W$405,MATCH(LARGE(BBスクリーニング!$AE$6:$AE$405,$A10),BBスクリーニング!$AE$6:$AE$405,0)),"") -> ☆スクイーズ監視 | K10: =IFERROR(INDEX(BBスクリーニング!$X$6:$X$405,MATCH(LARGE(BBスクリーニング!$AE$6:$AE$405,$A10),BBスクリーニング!$AE$6:$AE$405,0)),"") -> 62 | L10: =IFERROR(INDEX(BBスクリーニング!$Z$6:$Z$405,MATCH(LARGE(BBスクリーニング!$AE$6:$AE$405,$A10),BBスクリーニング!$AE$6:$AE$405,0)),"") -> 2486.7024 | M10: =IFERROR(INDEX(BBスクリーニング!$AA$6:$AA$405,MATCH(LARGE(BBスクリーニング!$AE$6:$AE$405,$A10),BBスクリーニング!$AE$6:$AE$405,0)),"") -> 2376.475 | N10: =IFERROR(INDEX(BBスクリーニング!$AC$6:$AC$405,MATCH(LARGE(BBスクリーニング!$AE$6:$AE$405,$A10),BBスクリーニング!$AE$6:$AE$405,0)),"") -> 0.71 | O10: =IF($B10="","",HYPERLINK("https://kabutan.jp/stock/?code="&$B10,"株探")) -> 株探 | V10: 4988 | W10: 最新の終値
A11: 7 | B11: =IFERROR(INDEX(BBスクリーニング!$B$6:$B$405,MATCH(LARGE(BBスクリーニング!$AE$6:$AE$405,$A11),BBスクリーニング!$AE$6:$AE$405,0)),"") -> 3402 | C11: =IFERROR(INDEX(BBスクリーニング!$C$6:$C$405,MATCH(LARGE(BBスクリーニング!$AE$6:$AE$405,$A11),BBスクリーニング!$AE$6:$AE$405,0)),"") -> 東レ | D11: =IFERROR(INDEX(BBスクリーニング!$D$6:$D$405,MATCH(LARGE(BBスクリーニング!$AE$6:$AE$405,$A11),BBスクリーニング!$AE$6:$AE$405,0)),"") -> 1299.5 | E11: =IFERROR(INDEX(BBスクリーニング!$N$6:$N$405,MATCH(LARGE(BBスクリーニング!$AE$6:$AE$405,$A11),BBスクリーニング!$AE$6:$AE$405,0)),"") -> － | F11: =IFERROR(INDEX(BBスクリーニング!$P$6:$P$405,MATCH(LARGE(BBスクリーニング!$AE$6:$AE$405,$A11),BBスクリーニング!$AE$6:$AE$405,0)),"") -> ↑+2σ突破 | G11: =IFERROR(INDEX(BBスクリーニング!$Q$6:$Q$405,MATCH(LARGE(BBスクリーニング!$AE$6:$AE$405,$A11),BBスクリーニング!$AE$6:$AE$405,0)),"") -> 69.054441 | H11: =IFERROR(INDEX(BBスクリーニング!$R$6:$R$405,MATCH(LARGE(BBスクリーニング!$AE$6:$AE$405,$A11),BBスクリーニング!$AE$6:$AE$405,0)),"") -> 67.01797 | I11: =IFERROR(INDEX(BBスクリーニング!$S$6:$S$405,MATCH(LARGE(BBスクリーニング!$AE$6:$AE$405,$A11),BBスクリーニング!$AE$6:$AE$405,0)),"") -> － | J11: =IFERROR(INDEX(BBスクリーニング!$W$6:$W$405,MATCH(LARGE(BBスクリーニング!$AE$6:$AE$405,$A11),BBスクリーニング!$AE$6:$AE$405,0)),"") -> △二番底買(確) | K11: =IFERROR(INDEX(BBスクリーニング!$X$6:$X$405,MATCH(LARGE(BBスクリーニング!$AE$6:$AE$405,$A11),BBスクリーニング!$AE$6:$AE$405,0)),"") -> 60 | L11: =IFERROR(INDEX(BBスクリーニング!$Z$6:$Z$405,MATCH(LARGE(BBスクリーニング!$AE$6:$AE$405,$A11),BBスクリーニング!$AE$6:$AE$405,0)),"") -> 1199.291 | M11: =IFERROR(INDEX(BBスクリーニング!$AA$6:$AA$405,MATCH(LARGE(BBスクリーニング!$AE$6:$AE$405,$A11),BBスクリーニング!$AE$6:$AE$405,0)),"") -> 1165.25 | N11: =IFERROR(INDEX(BBスクリーニング!$AC$6:$AC$405,MATCH(LARGE(BBスクリーニング!$AE$6:$AE$405,$A11),BBスクリーニング!$AE$6:$AE$405,0)),"") -> -0.24 | O11: =IF($B11="","",HYPERLINK("https://kabutan.jp/stock/?code="&$B11,"株探")) -> 株探 | V11: 収縮 | W11: バンドの幅の状態。スクイーズ★＝過去最小圏（大きく動く前兆）／収縮＝狭まり気味／－＝通常
A12: 8 | B12: =IFERROR(INDEX(BBスクリーニング!$B$6:$B$405,MATCH(LARGE(BBスクリーニング!$AE$6:$AE$405,$A12),BBスクリーニング!$AE$6:$AE$405,0)),"") -> 3103 | C12: =IFERROR(INDEX(BBスクリーニング!$C$6:$C$405,MATCH(LARGE(BBスクリーニング!$AE$6:$AE$405,$A12),BBスクリーニング!$AE$6:$AE$405,0)),"") -> ユニチカ | D12: =IFERROR(INDEX(BBスクリーニング!$D$6:$D$405,MATCH(LARGE(BBスクリーニング!$AE$6:$AE$405,$A12),BBスクリーニング!$AE$6:$AE$405,0)),"") -> 1258 | E12: =IFERROR(INDEX(BBスクリーニング!$N$6:$N$405,MATCH(LARGE(BBスクリーニング!$AE$6:$AE$405,$A12),BBスクリーニング!$AE$6:$AE$405,0)),"") -> － | F12: =IFERROR(INDEX(BBスクリーニング!$P$6:$P$405,MATCH(LARGE(BBスクリーニング!$AE$6:$AE$405,$A12),BBスクリーニング!$AE$6:$AE$405,0)),"") -> ↑+2σ突破 | G12: =IFERROR(INDEX(BBスクリーニング!$Q$6:$Q$405,MATCH(LARGE(BBスクリーニング!$AE$6:$AE$405,$A12),BBスクリーニング!$AE$6:$AE$405,0)),"") -> 68.69773 | H12: =IFERROR(INDEX(BBスクリーニング!$R$6:$R$405,MATCH(LARGE(BBスクリーニング!$AE$6:$AE$405,$A12),BBスクリーニング!$AE$6:$AE$405,0)),"") -> 75.47515 | I12: =IFERROR(INDEX(BBスクリーニング!$S$6:$S$405,MATCH(LARGE(BBスクリーニング!$AE$6:$AE$405,$A12),BBスクリーニング!$AE$6:$AE$405,0)),"") -> － | J12: =IFERROR(INDEX(BBスクリーニング!$W$6:$W$405,MATCH(LARGE(BBスクリーニング!$AE$6:$AE$405,$A12),BBスクリーニング!$AE$6:$AE$405,0)),"") -> 様子見 | K12: =IFERROR(INDEX(BBスクリーニング!$X$6:$X$405,MATCH(LARGE(BBスクリーニング!$AE$6:$AE$405,$A12),BBスクリーニング!$AE$6:$AE$405,0)),"") -> 60 | L12: =IFERROR(INDEX(BBスクリーニング!$Z$6:$Z$405,MATCH(LARGE(BBスクリーニング!$AE$6:$AE$405,$A12),BBスクリーニング!$AE$6:$AE$405,0)),"") -> 1000.4522 | M12: =IFERROR(INDEX(BBスクリーニング!$AA$6:$AA$405,MATCH(LARGE(BBスクリーニング!$AE$6:$AE$405,$A12),BBスクリーニング!$AE$6:$AE$405,0)),"") -> 898.45 | N12: =IFERROR(INDEX(BBスクリーニング!$AC$6:$AC$405,MATCH(LARGE(BBスクリーニング!$AE$6:$AE$405,$A12),BBスクリーニング!$AE$6:$AE$405,0)),"") -> -0.15 | O12: =IF($B12="","",HYPERLINK("https://kabutan.jp/stock/?code="&$B12,"株探")) -> 株探 | V12: +1σ上 | W12: 現在値がバンドのどこにいるか。↑+2σ突破＝強い上抜け／+1σ上＝上寄り／バンド内／−1σ下／↓−2σ割れ
A13: 9 | B13: =IFERROR(INDEX(BBスクリーニング!$B$6:$B$405,MATCH(LARGE(BBスクリーニング!$AE$6:$AE$405,$A13),BBスクリーニング!$AE$6:$AE$405,0)),"") -> 5801 | C13: =IFERROR(INDEX(BBスクリーニング!$C$6:$C$405,MATCH(LARGE(BBスクリーニング!$AE$6:$AE$405,$A13),BBスクリーニング!$AE$6:$AE$405,0)),"") -> 古河電工 | D13: =IFERROR(INDEX(BBスクリーニング!$D$6:$D$405,MATCH(LARGE(BBスクリーニング!$AE$6:$AE$405,$A13),BBスクリーニング!$AE$6:$AE$405,0)),"") -> 3909 | E13: =IFERROR(INDEX(BBスクリーニング!$N$6:$N$405,MATCH(LARGE(BBスクリーニング!$AE$6:$AE$405,$A13),BBスクリーニング!$AE$6:$AE$405,0)),"") -> 収縮 | F13: =IFERROR(INDEX(BBスクリーニング!$P$6:$P$405,MATCH(LARGE(BBスクリーニング!$AE$6:$AE$405,$A13),BBスクリーニング!$AE$6:$AE$405,0)),"") -> +1σ上 | G13: =IFERROR(INDEX(BBスクリーニング!$Q$6:$Q$405,MATCH(LARGE(BBスクリーニング!$AE$6:$AE$405,$A13),BBスクリーニング!$AE$6:$AE$405,0)),"") -> 59.123322 | H13: =IFERROR(INDEX(BBスクリーニング!$R$6:$R$405,MATCH(LARGE(BBスクリーニング!$AE$6:$AE$405,$A13),BBスクリーニング!$AE$6:$AE$405,0)),"") -> 40.233516 | I13: =IFERROR(INDEX(BBスクリーニング!$S$6:$S$405,MATCH(LARGE(BBスクリーニング!$AE$6:$AE$405,$A13),BBスクリーニング!$AE$6:$AE$405,0)),"") -> － | J13: =IFERROR(INDEX(BBスクリーニング!$W$6:$W$405,MATCH(LARGE(BBスクリーニング!$AE$6:$AE$405,$A13),BBスクリーニング!$AE$6:$AE$405,0)),"") -> 様子見 | K13: =IFERROR(INDEX(BBスクリーニング!$X$6:$X$405,MATCH(LARGE(BBスクリーニング!$AE$6:$AE$405,$A13),BBスクリーニング!$AE$6:$AE$405,0)),"") -> 60 | L13: =IFERROR(INDEX(BBスクリーニング!$Z$6:$Z$405,MATCH(LARGE(BBスクリーニング!$AE$6:$AE$405,$A13),BBスクリーニング!$AE$6:$AE$405,0)),"") -> 3728.7637 | M13: =IFERROR(INDEX(BBスクリーニング!$AA$6:$AA$405,MATCH(LARGE(BBスクリーニング!$AE$6:$AE$405,$A13),BBスクリーニング!$AE$6:$AE$405,0)),"") -> 3414.9 | N13: =IFERROR(INDEX(BBスクリーニング!$AC$6:$AC$405,MATCH(LARGE(BBスクリーニング!$AE$6:$AE$405,$A13),BBスクリーニング!$AE$6:$AE$405,0)),"") -> 0.27 | O13: =IF($B13="","",HYPERLINK("https://kabutan.jp/stock/?code="&$B13,"株探")) -> 株探 | V13: 68.3 | W13: 買われすぎ/売られすぎ。70以上=過熱、30以下=売られすぎ、50前後=中立
A14: 10 | B14: =IFERROR(INDEX(BBスクリーニング!$B$6:$B$405,MATCH(LARGE(BBスクリーニング!$AE$6:$AE$405,$A14),BBスクリーニング!$AE$6:$AE$405,0)),"") -> 6482 | C14: =IFERROR(INDEX(BBスクリーニング!$C$6:$C$405,MATCH(LARGE(BBスクリーニング!$AE$6:$AE$405,$A14),BBスクリーニング!$AE$6:$AE$405,0)),"") -> ＹＵＳＨＩＮ | D14: =IFERROR(INDEX(BBスクリーニング!$D$6:$D$405,MATCH(LARGE(BBスクリーニング!$AE$6:$AE$405,$A14),BBスクリーニング!$AE$6:$AE$405,0)),"") -> 682 | E14: =IFERROR(INDEX(BBスクリーニング!$N$6:$N$405,MATCH(LARGE(BBスクリーニング!$AE$6:$AE$405,$A14),BBスクリーニング!$AE$6:$AE$405,0)),"") -> スクイーズ★ | F14: =IFERROR(INDEX(BBスクリーニング!$P$6:$P$405,MATCH(LARGE(BBスクリーニング!$AE$6:$AE$405,$A14),BBスクリーニング!$AE$6:$AE$405,0)),"") -> バンド内 | G14: =IFERROR(INDEX(BBスクリーニング!$Q$6:$Q$405,MATCH(LARGE(BBスクリーニング!$AE$6:$AE$405,$A14),BBスクリーニング!$AE$6:$AE$405,0)),"") -> 56.666667 | H14: =IFERROR(INDEX(BBスクリーニング!$R$6:$R$405,MATCH(LARGE(BBスクリーニング!$AE$6:$AE$405,$A14),BBスクリーニング!$AE$6:$AE$405,0)),"") -> 70.219735 | I14: =IFERROR(INDEX(BBスクリーニング!$S$6:$S$405,MATCH(LARGE(BBスクリーニング!$AE$6:$AE$405,$A14),BBスクリーニング!$AE$6:$AE$405,0)),"") -> 強気div▲ | J14: =IFERROR(INDEX(BBスクリーニング!$W$6:$W$405,MATCH(LARGE(BBスクリーニング!$AE$6:$AE$405,$A14),BBスクリーニング!$AE$6:$AE$405,0)),"") -> ○反発(ダイバ)買 | K14: =IFERROR(INDEX(BBスクリーニング!$X$6:$X$405,MATCH(LARGE(BBスクリーニング!$AE$6:$AE$405,$A14),BBスクリーニング!$AE$6:$AE$405,0)),"") -> 60 | L14: =IFERROR(INDEX(BBスクリーニング!$Z$6:$Z$405,MATCH(LARGE(BBスクリーニング!$AE$6:$AE$405,$A14),BBスクリーニング!$AE$6:$AE$405,0)),"") -> 685.99894 | M14: =IFERROR(INDEX(BBスクリーニング!$AA$6:$AA$405,MATCH(LARGE(BBスクリーニング!$AE$6:$AE$405,$A14),BBスクリーニング!$AE$6:$AE$405,0)),"") -> 676.6 | N14: =IFERROR(INDEX(BBスクリーニング!$AC$6:$AC$405,MATCH(LARGE(BBスクリーニング!$AE$6:$AE$405,$A14),BBスクリーニング!$AE$6:$AE$405,0)),"") -> 2.48 | O14: =IF($B14="","",HYPERLINK("https://kabutan.jp/stock/?code="&$B14,"株探")) -> 株探 | V14: 59.4 | W14: お金の流入の強さ（出来高込みのRSI）。80以上=資金流入が強い、20以下=流出
A15: 11 | B15: =IFERROR(INDEX(BBスクリーニング!$B$6:$B$405,MATCH(LARGE(BBスクリーニング!$AE$6:$AE$405,$A15),BBスクリーニング!$AE$6:$AE$405,0)),"") -> 5714 | C15: =IFERROR(INDEX(BBスクリーニング!$C$6:$C$405,MATCH(LARGE(BBスクリーニング!$AE$6:$AE$405,$A15),BBスクリーニング!$AE$6:$AE$405,0)),"") -> ＤＯＷＡホールディングス | D15: =IFERROR(INDEX(BBスクリーニング!$D$6:$D$405,MATCH(LARGE(BBスクリーニング!$AE$6:$AE$405,$A15),BBスクリーニング!$AE$6:$AE$405,0)),"") -> 8907 | E15: =IFERROR(INDEX(BBスクリーニング!$N$6:$N$405,MATCH(LARGE(BBスクリーニング!$AE$6:$AE$405,$A15),BBスクリーニング!$AE$6:$AE$405,0)),"") -> 収縮 | F15: =IFERROR(INDEX(BBスクリーニング!$P$6:$P$405,MATCH(LARGE(BBスクリーニング!$AE$6:$AE$405,$A15),BBスクリーニング!$AE$6:$AE$405,0)),"") -> ↑+2σ突破 | G15: =IFERROR(INDEX(BBスクリーニング!$Q$6:$Q$405,MATCH(LARGE(BBスクリーニング!$AE$6:$AE$405,$A15),BBスクリーニング!$AE$6:$AE$405,0)),"") -> 59.00581 | H15: =IFERROR(INDEX(BBスクリーニング!$R$6:$R$405,MATCH(LARGE(BBスクリーニング!$AE$6:$AE$405,$A15),BBスクリーニング!$AE$6:$AE$405,0)),"") -> 65.398996 | I15: =IFERROR(INDEX(BBスクリーニング!$S$6:$S$405,MATCH(LARGE(BBスクリーニング!$AE$6:$AE$405,$A15),BBスクリーニング!$AE$6:$AE$405,0)),"") -> － | J15: =IFERROR(INDEX(BBスクリーニング!$W$6:$W$405,MATCH(LARGE(BBスクリーニング!$AE$6:$AE$405,$A15),BBスクリーニング!$AE$6:$AE$405,0)),"") -> △二番底買(確) | K15: =IFERROR(INDEX(BBスクリーニング!$X$6:$X$405,MATCH(LARGE(BBスクリーニング!$AE$6:$AE$405,$A15),BBスクリーニング!$AE$6:$AE$405,0)),"") -> 58 | L15: =IFERROR(INDEX(BBスクリーニング!$Z$6:$Z$405,MATCH(LARGE(BBスクリーニング!$AE$6:$AE$405,$A15),BBスクリーニング!$AE$6:$AE$405,0)),"") -> 8528.7918 | M15: =IFERROR(INDEX(BBスクリーニング!$AA$6:$AA$405,MATCH(LARGE(BBスクリーニング!$AE$6:$AE$405,$A15),BBスクリーニング!$AE$6:$AE$405,0)),"") -> 8302.05 | N15: =IFERROR(INDEX(BBスクリーニング!$AC$6:$AC$405,MATCH(LARGE(BBスクリーニング!$AE$6:$AE$405,$A15),BBスクリーニング!$AE$6:$AE$405,0)),"") -> 0.12 | O15: =IF($B15="","",HYPERLINK("https://kabutan.jp/stock/?code="&$B15,"株探")) -> 株探 | V15: なし | W15: ダイバージェンス。強気div▲＝価格は下でもRSIは上向き（反転の芽）／弱気div▼＝逆
A16: 12 | B16: =IFERROR(INDEX(BBスクリーニング!$B$6:$B$405,MATCH(LARGE(BBスクリーニング!$AE$6:$AE$405,$A16),BBスクリーニング!$AE$6:$AE$405,0)),"") -> 300A | C16: =IFERROR(INDEX(BBスクリーニング!$C$6:$C$405,MATCH(LARGE(BBスクリーニング!$AE$6:$AE$405,$A16),BBスクリーニング!$AE$6:$AE$405,0)),"") -> ＭＩＣ | D16: =IFERROR(INDEX(BBスクリーニング!$D$6:$D$405,MATCH(LARGE(BBスクリーニング!$AE$6:$AE$405,$A16),BBスクリーニング!$AE$6:$AE$405,0)),"") -> 3070 | E16: =IFERROR(INDEX(BBスクリーニング!$N$6:$N$405,MATCH(LARGE(BBスクリーニング!$AE$6:$AE$405,$A16),BBスクリーニング!$AE$6:$AE$405,0)),"") -> － | F16: =IFERROR(INDEX(BBスクリーニング!$P$6:$P$405,MATCH(LARGE(BBスクリーニング!$AE$6:$AE$405,$A16),BBスクリーニング!$AE$6:$AE$405,0)),"") -> ↑+2σ突破 | G16: =IFERROR(INDEX(BBスクリーニング!$Q$6:$Q$405,MATCH(LARGE(BBスクリーニング!$AE$6:$AE$405,$A16),BBスクリーニング!$AE$6:$AE$405,0)),"") -> 67.088608 | H16: =IFERROR(INDEX(BBスクリーニング!$R$6:$R$405,MATCH(LARGE(BBスクリーニング!$AE$6:$AE$405,$A16),BBスクリーニング!$AE$6:$AE$405,0)),"") -> 79.703525 | I16: =IFERROR(INDEX(BBスクリーニング!$S$6:$S$405,MATCH(LARGE(BBスクリーニング!$AE$6:$AE$405,$A16),BBスクリーニング!$AE$6:$AE$405,0)),"") -> － | J16: =IFERROR(INDEX(BBスクリーニング!$W$6:$W$405,MATCH(LARGE(BBスクリーニング!$AE$6:$AE$405,$A16),BBスクリーニング!$AE$6:$AE$405,0)),"") -> △二番底買(確) | K16: =IFERROR(INDEX(BBスクリーニング!$X$6:$X$405,MATCH(LARGE(BBスクリーニング!$AE$6:$AE$405,$A16),BBスクリーニング!$AE$6:$AE$405,0)),"") -> 58 | L16: =IFERROR(INDEX(BBスクリーニング!$Z$6:$Z$405,MATCH(LARGE(BBスクリーニング!$AE$6:$AE$405,$A16),BBスクリーニング!$AE$6:$AE$405,0)),"") -> 3003.5767 | M16: =IFERROR(INDEX(BBスクリーニング!$AA$6:$AA$405,MATCH(LARGE(BBスクリーニング!$AE$6:$AE$405,$A16),BBスクリーニング!$AE$6:$AE$405,0)),"") -> 2937.2 | N16: =IFERROR(INDEX(BBスクリーニング!$AC$6:$AC$405,MATCH(LARGE(BBスクリーニング!$AE$6:$AE$405,$A16),BBスクリーニング!$AE$6:$AE$405,0)),"") -> 0.5 | O16: =IF($B16="","",HYPERLINK("https://kabutan.jp/stock/?code="&$B16,"株探")) -> 株探 | V16: △二番底形成 | W16: 一番の要注目列（下に凡例）
A17: 13 | B17: =IFERROR(INDEX(BBスクリーニング!$B$6:$B$405,MATCH(LARGE(BBスクリーニング!$AE$6:$AE$405,$A17),BBスクリーニング!$AE$6:$AE$405,0)),"") -> 8570 | C17: =IFERROR(INDEX(BBスクリーニング!$C$6:$C$405,MATCH(LARGE(BBスクリーニング!$AE$6:$AE$405,$A17),BBスクリーニング!$AE$6:$AE$405,0)),"") -> イオンフィナンシャルサービス | D17: =IFERROR(INDEX(BBスクリーニング!$D$6:$D$405,MATCH(LARGE(BBスクリーニング!$AE$6:$AE$405,$A17),BBスクリーニング!$AE$6:$AE$405,0)),"") -> 1594.5 | E17: =IFERROR(INDEX(BBスクリーニング!$N$6:$N$405,MATCH(LARGE(BBスクリーニング!$AE$6:$AE$405,$A17),BBスクリーニング!$AE$6:$AE$405,0)),"") -> スクイーズ★ | F17: =IFERROR(INDEX(BBスクリーニング!$P$6:$P$405,MATCH(LARGE(BBスクリーニング!$AE$6:$AE$405,$A17),BBスクリーニング!$AE$6:$AE$405,0)),"") -> +1σ上 | G17: =IFERROR(INDEX(BBスクリーニング!$Q$6:$Q$405,MATCH(LARGE(BBスクリーニング!$AE$6:$AE$405,$A17),BBスクリーニング!$AE$6:$AE$405,0)),"") -> 61.693548 | H17: =IFERROR(INDEX(BBスクリーニング!$R$6:$R$405,MATCH(LARGE(BBスクリーニング!$AE$6:$AE$405,$A17),BBスクリーニング!$AE$6:$AE$405,0)),"") -> 61.095421 | I17: =IFERROR(INDEX(BBスクリーニング!$S$6:$S$405,MATCH(LARGE(BBスクリーニング!$AE$6:$AE$405,$A17),BBスクリーニング!$AE$6:$AE$405,0)),"") -> 弱気div▼ | J17: =IFERROR(INDEX(BBスクリーニング!$W$6:$W$405,MATCH(LARGE(BBスクリーニング!$AE$6:$AE$405,$A17),BBスクリーニング!$AE$6:$AE$405,0)),"") -> ☆スクイーズ監視 | K17: =IFERROR(INDEX(BBスクリーニング!$X$6:$X$405,MATCH(LARGE(BBスクリーニング!$AE$6:$AE$405,$A17),BBスクリーニング!$AE$6:$AE$405,0)),"") -> 57 | L17: =IFERROR(INDEX(BBスクリーニング!$Z$6:$Z$405,MATCH(LARGE(BBスクリーニング!$AE$6:$AE$405,$A17),BBスクリーニング!$AE$6:$AE$405,0)),"") -> 1577.1698 | M17: =IFERROR(INDEX(BBスクリーニング!$AA$6:$AA$405,MATCH(LARGE(BBスクリーニング!$AE$6:$AE$405,$A17),BBスクリーニング!$AE$6:$AE$405,0)),"") -> 1556.05 | N17: =IFERROR(INDEX(BBスクリーニング!$AC$6:$AC$405,MATCH(LARGE(BBスクリーニング!$AE$6:$AE$405,$A17),BBスクリーニング!$AE$6:$AE$405,0)),"") -> 0.1 | O17: =IF($B17="","",HYPERLINK("https://kabutan.jp/stock/?code="&$B17,"株探")) -> 株探 | V17: 62 | W17: 各条件の合致度を0〜100点で合計。高いほど条件がそろう
A18: 14 | B18: =IFERROR(INDEX(BBスクリーニング!$B$6:$B$405,MATCH(LARGE(BBスクリーニング!$AE$6:$AE$405,$A18),BBスクリーニング!$AE$6:$AE$405,0)),"") -> 9501 | C18: =IFERROR(INDEX(BBスクリーニング!$C$6:$C$405,MATCH(LARGE(BBスクリーニング!$AE$6:$AE$405,$A18),BBスクリーニング!$AE$6:$AE$405,0)),"") -> 東京電力ＨＤ | D18: =IFERROR(INDEX(BBスクリーニング!$D$6:$D$405,MATCH(LARGE(BBスクリーニング!$AE$6:$AE$405,$A18),BBスクリーニング!$AE$6:$AE$405,0)),"") -> 537 | E18: =IFERROR(INDEX(BBスクリーニング!$N$6:$N$405,MATCH(LARGE(BBスクリーニング!$AE$6:$AE$405,$A18),BBスクリーニング!$AE$6:$AE$405,0)),"") -> スクイーズ★ | F18: =IFERROR(INDEX(BBスクリーニング!$P$6:$P$405,MATCH(LARGE(BBスクリーニング!$AE$6:$AE$405,$A18),BBスクリーニング!$AE$6:$AE$405,0)),"") -> +1σ上 | G18: =IFERROR(INDEX(BBスクリーニング!$Q$6:$Q$405,MATCH(LARGE(BBスクリーニング!$AE$6:$AE$405,$A18),BBスクリーニング!$AE$6:$AE$405,0)),"") -> 67.251462 | H18: =IFERROR(INDEX(BBスクリーニング!$R$6:$R$405,MATCH(LARGE(BBスクリーニング!$AE$6:$AE$405,$A18),BBスクリーニング!$AE$6:$AE$405,0)),"") -> 60.765493 | I18: =IFERROR(INDEX(BBスクリーニング!$S$6:$S$405,MATCH(LARGE(BBスクリーニング!$AE$6:$AE$405,$A18),BBスクリーニング!$AE$6:$AE$405,0)),"") -> 弱気div▼ | J18: =IFERROR(INDEX(BBスクリーニング!$W$6:$W$405,MATCH(LARGE(BBスクリーニング!$AE$6:$AE$405,$A18),BBスクリーニング!$AE$6:$AE$405,0)),"") -> △二番底形成 | K18: =IFERROR(INDEX(BBスクリーニング!$X$6:$X$405,MATCH(LARGE(BBスクリーニング!$AE$6:$AE$405,$A18),BBスクリーニング!$AE$6:$AE$405,0)),"") -> 57 | L18: =IFERROR(INDEX(BBスクリーニング!$Z$6:$Z$405,MATCH(LARGE(BBスクリーニング!$AE$6:$AE$405,$A18),BBスクリーニング!$AE$6:$AE$405,0)),"") -> 529.79673 | M18: =IFERROR(INDEX(BBスクリーニング!$AA$6:$AA$405,MATCH(LARGE(BBスクリーニング!$AE$6:$AE$405,$A18),BBスクリーニング!$AE$6:$AE$405,0)),"") -> 512.85 | N18: =IFERROR(INDEX(BBスクリーニング!$AC$6:$AC$405,MATCH(LARGE(BBスクリーニング!$AE$6:$AE$405,$A18),BBスクリーニング!$AE$6:$AE$405,0)),"") -> 0.4 | O18: =IF($B18="","",HYPERLINK("https://kabutan.jp/stock/?code="&$B18,"株探")) -> 株探 | V18: 4987 | W18: 利確の目安ライン。現在値がここを実体で割ったら手仕舞い（＝+1σ）
A19: 15 | B19: =IFERROR(INDEX(BBスクリーニング!$B$6:$B$405,MATCH(LARGE(BBスクリーニング!$AE$6:$AE$405,$A19),BBスクリーニング!$AE$6:$AE$405,0)),"") -> 8704 | C19: =IFERROR(INDEX(BBスクリーニング!$C$6:$C$405,MATCH(LARGE(BBスクリーニング!$AE$6:$AE$405,$A19),BBスクリーニング!$AE$6:$AE$405,0)),"") -> トレイダーズＨＬＤＧＳ | D19: =IFERROR(INDEX(BBスクリーニング!$D$6:$D$405,MATCH(LARGE(BBスクリーニング!$AE$6:$AE$405,$A19),BBスクリーニング!$AE$6:$AE$405,0)),"") -> 1323 | E19: =IFERROR(INDEX(BBスクリーニング!$N$6:$N$405,MATCH(LARGE(BBスクリーニング!$AE$6:$AE$405,$A19),BBスクリーニング!$AE$6:$AE$405,0)),"") -> 収縮 | F19: =IFERROR(INDEX(BBスクリーニング!$P$6:$P$405,MATCH(LARGE(BBスクリーニング!$AE$6:$AE$405,$A19),BBスクリーニング!$AE$6:$AE$405,0)),"") -> +1σ上 | G19: =IFERROR(INDEX(BBスクリーニング!$Q$6:$Q$405,MATCH(LARGE(BBスクリーニング!$AE$6:$AE$405,$A19),BBスクリーニング!$AE$6:$AE$405,0)),"") -> 53.395785 | H19: =IFERROR(INDEX(BBスクリーニング!$R$6:$R$405,MATCH(LARGE(BBスクリーニング!$AE$6:$AE$405,$A19),BBスクリーニング!$AE$6:$AE$405,0)),"") -> 61.072707 | I19: =IFERROR(INDEX(BBスクリーニング!$S$6:$S$405,MATCH(LARGE(BBスクリーニング!$AE$6:$AE$405,$A19),BBスクリーニング!$AE$6:$AE$405,0)),"") -> 弱気div▼ | J19: =IFERROR(INDEX(BBスクリーニング!$W$6:$W$405,MATCH(LARGE(BBスクリーニング!$AE$6:$AE$405,$A19),BBスクリーニング!$AE$6:$AE$405,0)),"") -> △二番底買(確) | K19: =IFERROR(INDEX(BBスクリーニング!$X$6:$X$405,MATCH(LARGE(BBスクリーニング!$AE$6:$AE$405,$A19),BBスクリーニング!$AE$6:$AE$405,0)),"") -> 57 | L19: =IFERROR(INDEX(BBスクリーニング!$Z$6:$Z$405,MATCH(LARGE(BBスクリーニング!$AE$6:$AE$405,$A19),BBスクリーニング!$AE$6:$AE$405,0)),"") -> 1306.5797 | M19: =IFERROR(INDEX(BBスクリーニング!$AA$6:$AA$405,MATCH(LARGE(BBスクリーニング!$AE$6:$AE$405,$A19),BBスクリーニング!$AE$6:$AE$405,0)),"") -> 1268.75 | N19: =IFERROR(INDEX(BBスクリーニング!$AC$6:$AC$405,MATCH(LARGE(BBスクリーニング!$AE$6:$AE$405,$A19),BBスクリーニング!$AE$6:$AE$405,0)),"") -> 0.39 | O19: =IF($B19="","",HYPERLINK("https://kabutan.jp/stock/?code="&$B19,"株探")) -> 株探 | V19: 4852 | W19: 損切りの目安ライン（＝ミドル/SMA20割れ）
A20: 16 | B20: =IFERROR(INDEX(BBスクリーニング!$B$6:$B$405,MATCH(LARGE(BBスクリーニング!$AE$6:$AE$405,$A20),BBスクリーニング!$AE$6:$AE$405,0)),"") -> 7011 | C20: =IFERROR(INDEX(BBスクリーニング!$C$6:$C$405,MATCH(LARGE(BBスクリーニング!$AE$6:$AE$405,$A20),BBスクリーニング!$AE$6:$AE$405,0)),"") -> 三菱重工業 | D20: =IFERROR(INDEX(BBスクリーニング!$D$6:$D$405,MATCH(LARGE(BBスクリーニング!$AE$6:$AE$405,$A20),BBスクリーニング!$AE$6:$AE$405,0)),"") -> 3998 | E20: =IFERROR(INDEX(BBスクリーニング!$N$6:$N$405,MATCH(LARGE(BBスクリーニング!$AE$6:$AE$405,$A20),BBスクリーニング!$AE$6:$AE$405,0)),"") -> スクイーズ★ | F20: =IFERROR(INDEX(BBスクリーニング!$P$6:$P$405,MATCH(LARGE(BBスクリーニング!$AE$6:$AE$405,$A20),BBスクリーニング!$AE$6:$AE$405,0)),"") -> +1σ上 | G20: =IFERROR(INDEX(BBスクリーニング!$Q$6:$Q$405,MATCH(LARGE(BBスクリーニング!$AE$6:$AE$405,$A20),BBスクリーニング!$AE$6:$AE$405,0)),"") -> 58.231421 | H20: =IFERROR(INDEX(BBスクリーニング!$R$6:$R$405,MATCH(LARGE(BBスクリーニング!$AE$6:$AE$405,$A20),BBスクリーニング!$AE$6:$AE$405,0)),"") -> 71.015229 | I20: =IFERROR(INDEX(BBスクリーニング!$S$6:$S$405,MATCH(LARGE(BBスクリーニング!$AE$6:$AE$405,$A20),BBスクリーニング!$AE$6:$AE$405,0)),"") -> － | J20: =IFERROR(INDEX(BBスクリーニング!$W$6:$W$405,MATCH(LARGE(BBスクリーニング!$AE$6:$AE$405,$A20),BBスクリーニング!$AE$6:$AE$405,0)),"") -> △二番底買(確) | K20: =IFERROR(INDEX(BBスクリーニング!$X$6:$X$405,MATCH(LARGE(BBスクリーニング!$AE$6:$AE$405,$A20),BBスクリーニング!$AE$6:$AE$405,0)),"") -> 57 | L20: =IFERROR(INDEX(BBスクリーニング!$Z$6:$Z$405,MATCH(LARGE(BBスクリーニング!$AE$6:$AE$405,$A20),BBスクリーニング!$AE$6:$AE$405,0)),"") -> 3947.5939 | M20: =IFERROR(INDEX(BBスクリーニング!$AA$6:$AA$405,MATCH(LARGE(BBスクリーニング!$AE$6:$AE$405,$A20),BBスクリーニング!$AE$6:$AE$405,0)),"") -> 3845.1 | N20: =IFERROR(INDEX(BBスクリーニング!$AC$6:$AC$405,MATCH(LARGE(BBスクリーニング!$AE$6:$AE$405,$A20),BBスクリーニング!$AE$6:$AE$405,0)),"") -> 0.34 | O20: =IF($B20="","",HYPERLINK("https://kabutan.jp/stock/?code="&$B20,"株探")) -> 株探 | V20: 0.99倍 | W20: リスクリワード。1倍超なら利益幅>損失幅で有利、1未満は妙味小
A21: 17 | B21: =IFERROR(INDEX(BBスクリーニング!$B$6:$B$405,MATCH(LARGE(BBスクリーニング!$AE$6:$AE$405,$A21),BBスクリーニング!$AE$6:$AE$405,0)),"") -> 6135 | C21: =IFERROR(INDEX(BBスクリーニング!$C$6:$C$405,MATCH(LARGE(BBスクリーニング!$AE$6:$AE$405,$A21),BBスクリーニング!$AE$6:$AE$405,0)),"") -> 牧野フライス | D21: =IFERROR(INDEX(BBスクリーニング!$D$6:$D$405,MATCH(LARGE(BBスクリーニング!$AE$6:$AE$405,$A21),BBスクリーニング!$AE$6:$AE$405,0)),"") -> 15070 | E21: =IFERROR(INDEX(BBスクリーニング!$N$6:$N$405,MATCH(LARGE(BBスクリーニング!$AE$6:$AE$405,$A21),BBスクリーニング!$AE$6:$AE$405,0)),"") -> 収縮 | F21: =IFERROR(INDEX(BBスクリーニング!$P$6:$P$405,MATCH(LARGE(BBスクリーニング!$AE$6:$AE$405,$A21),BBスクリーニング!$AE$6:$AE$405,0)),"") -> +1σ上 | G21: =IFERROR(INDEX(BBスクリーニング!$Q$6:$Q$405,MATCH(LARGE(BBスクリーニング!$AE$6:$AE$405,$A21),BBスクリーニング!$AE$6:$AE$405,0)),"") -> 57.183908 | H21: =IFERROR(INDEX(BBスクリーニング!$R$6:$R$405,MATCH(LARGE(BBスクリーニング!$AE$6:$AE$405,$A21),BBスクリーニング!$AE$6:$AE$405,0)),"") -> 60.271007 | I21: =IFERROR(INDEX(BBスクリーニング!$S$6:$S$405,MATCH(LARGE(BBスクリーニング!$AE$6:$AE$405,$A21),BBスクリーニング!$AE$6:$AE$405,0)),"") -> － | J21: =IFERROR(INDEX(BBスクリーニング!$W$6:$W$405,MATCH(LARGE(BBスクリーニング!$AE$6:$AE$405,$A21),BBスクリーニング!$AE$6:$AE$405,0)),"") -> 様子見 | K21: =IFERROR(INDEX(BBスクリーニング!$X$6:$X$405,MATCH(LARGE(BBスクリーニング!$AE$6:$AE$405,$A21),BBスクリーニング!$AE$6:$AE$405,0)),"") -> 57 | L21: =IFERROR(INDEX(BBスクリーニング!$Z$6:$Z$405,MATCH(LARGE(BBスクリーニング!$AE$6:$AE$405,$A21),BBスクリーニング!$AE$6:$AE$405,0)),"") -> 14977.458 | M21: =IFERROR(INDEX(BBスクリーニング!$AA$6:$AA$405,MATCH(LARGE(BBスクリーニング!$AE$6:$AE$405,$A21),BBスクリーニング!$AE$6:$AE$405,0)),"") -> 14625.5 | N21: =IFERROR(INDEX(BBスクリーニング!$AC$6:$AC$405,MATCH(LARGE(BBスクリーニング!$AE$6:$AE$405,$A21),BBスクリーニング!$AE$6:$AE$405,0)),"") -> 0.58 | O21: =IF($B21="","",HYPERLINK("https://kabutan.jp/stock/?code="&$B21,"株探")) -> 株探
A22: 18 | B22: =IFERROR(INDEX(BBスクリーニング!$B$6:$B$405,MATCH(LARGE(BBスクリーニング!$AE$6:$AE$405,$A22),BBスクリーニング!$AE$6:$AE$405,0)),"") -> 186A | C22: =IFERROR(INDEX(BBスクリーニング!$C$6:$C$405,MATCH(LARGE(BBスクリーニング!$AE$6:$AE$405,$A22),BBスクリーニング!$AE$6:$AE$405,0)),"") -> アストロスケールホールディンク | D22: =IFERROR(INDEX(BBスクリーニング!$D$6:$D$405,MATCH(LARGE(BBスクリーニング!$AE$6:$AE$405,$A22),BBスクリーニング!$AE$6:$AE$405,0)),"") -> 1176 | E22: =IFERROR(INDEX(BBスクリーニング!$N$6:$N$405,MATCH(LARGE(BBスクリーニング!$AE$6:$AE$405,$A22),BBスクリーニング!$AE$6:$AE$405,0)),"") -> 収縮 | F22: =IFERROR(INDEX(BBスクリーニング!$P$6:$P$405,MATCH(LARGE(BBスクリーニング!$AE$6:$AE$405,$A22),BBスクリーニング!$AE$6:$AE$405,0)),"") -> +1σ上 | G22: =IFERROR(INDEX(BBスクリーニング!$Q$6:$Q$405,MATCH(LARGE(BBスクリーニング!$AE$6:$AE$405,$A22),BBスクリーニング!$AE$6:$AE$405,0)),"") -> 64.473684 | H22: =IFERROR(INDEX(BBスクリーニング!$R$6:$R$405,MATCH(LARGE(BBスクリーニング!$AE$6:$AE$405,$A22),BBスクリーニング!$AE$6:$AE$405,0)),"") -> 64.573001 | I22: =IFERROR(INDEX(BBスクリーニング!$S$6:$S$405,MATCH(LARGE(BBスクリーニング!$AE$6:$AE$405,$A22),BBスクリーニング!$AE$6:$AE$405,0)),"") -> － | J22: =IFERROR(INDEX(BBスクリーニング!$W$6:$W$405,MATCH(LARGE(BBスクリーニング!$AE$6:$AE$405,$A22),BBスクリーニング!$AE$6:$AE$405,0)),"") -> 様子見 | K22: =IFERROR(INDEX(BBスクリーニング!$X$6:$X$405,MATCH(LARGE(BBスクリーニング!$AE$6:$AE$405,$A22),BBスクリーニング!$AE$6:$AE$405,0)),"") -> 57 | L22: =IFERROR(INDEX(BBスクリーニング!$Z$6:$Z$405,MATCH(LARGE(BBスクリーニング!$AE$6:$AE$405,$A22),BBスクリーニング!$AE$6:$AE$405,0)),"") -> 1118.0232 | M22: =IFERROR(INDEX(BBスクリーニング!$AA$6:$AA$405,MATCH(LARGE(BBスクリーニング!$AE$6:$AE$405,$A22),BBスクリーニング!$AE$6:$AE$405,0)),"") -> 1048.7 | N22: =IFERROR(INDEX(BBスクリーニング!$AC$6:$AC$405,MATCH(LARGE(BBスクリーニング!$AE$6:$AE$405,$A22),BBスクリーニング!$AE$6:$AE$405,0)),"") -> 0.09 | O22: =IF($B22="","",HYPERLINK("https://kabutan.jp/stock/?code="&$B22,"株探")) -> 株探
A23: 19 | B23: =IFERROR(INDEX(BBスクリーニング!$B$6:$B$405,MATCH(LARGE(BBスクリーニング!$AE$6:$AE$405,$A23),BBスクリーニング!$AE$6:$AE$405,0)),"") -> 5713 | C23: =IFERROR(INDEX(BBスクリーニング!$C$6:$C$405,MATCH(LARGE(BBスクリーニング!$AE$6:$AE$405,$A23),BBスクリーニング!$AE$6:$AE$405,0)),"") -> 住友鉱山 | D23: =IFERROR(INDEX(BBスクリーニング!$D$6:$D$405,MATCH(LARGE(BBスクリーニング!$AE$6:$AE$405,$A23),BBスクリーニング!$AE$6:$AE$405,0)),"") -> 9088 | E23: =IFERROR(INDEX(BBスクリーニング!$N$6:$N$405,MATCH(LARGE(BBスクリーニング!$AE$6:$AE$405,$A23),BBスクリーニング!$AE$6:$AE$405,0)),"") -> － | F23: =IFERROR(INDEX(BBスクリーニング!$P$6:$P$405,MATCH(LARGE(BBスクリーニング!$AE$6:$AE$405,$A23),BBスクリーニング!$AE$6:$AE$405,0)),"") -> ↑+2σ突破 | G23: =IFERROR(INDEX(BBスクリーニング!$Q$6:$Q$405,MATCH(LARGE(BBスクリーニング!$AE$6:$AE$405,$A23),BBスクリーニング!$AE$6:$AE$405,0)),"") -> 67.947702 | H23: =IFERROR(INDEX(BBスクリーニング!$R$6:$R$405,MATCH(LARGE(BBスクリーニング!$AE$6:$AE$405,$A23),BBスクリーニング!$AE$6:$AE$405,0)),"") -> 67.781042 | I23: =IFERROR(INDEX(BBスクリーニング!$S$6:$S$405,MATCH(LARGE(BBスクリーニング!$AE$6:$AE$405,$A23),BBスクリーニング!$AE$6:$AE$405,0)),"") -> － | J23: =IFERROR(INDEX(BBスクリーニング!$W$6:$W$405,MATCH(LARGE(BBスクリーニング!$AE$6:$AE$405,$A23),BBスクリーニング!$AE$6:$AE$405,0)),"") -> 様子見 | K23: =IFERROR(INDEX(BBスクリーニング!$X$6:$X$405,MATCH(LARGE(BBスクリーニング!$AE$6:$AE$405,$A23),BBスクリーニング!$AE$6:$AE$405,0)),"") -> 55 | L23: =IFERROR(INDEX(BBスクリーニング!$Z$6:$Z$405,MATCH(LARGE(BBスクリーニング!$AE$6:$AE$405,$A23),BBスクリーニング!$AE$6:$AE$405,0)),"") -> 8145.498 | M23: =IFERROR(INDEX(BBスクリーニング!$AA$6:$AA$405,MATCH(LARGE(BBスクリーニング!$AE$6:$AE$405,$A23),BBスクリーニング!$AE$6:$AE$405,0)),"") -> 7618.65 | N23: =IFERROR(INDEX(BBスクリーニング!$AC$6:$AC$405,MATCH(LARGE(BBスクリーニング!$AE$6:$AE$405,$A23),BBスクリーニング!$AE$6:$AE$405,0)),"") -> 0.08 | O23: =IF($B23="","",HYPERLINK("https://kabutan.jp/stock/?code="&$B23,"株探")) -> 株探
A24: 20 | B24: =IFERROR(INDEX(BBスクリーニング!$B$6:$B$405,MATCH(LARGE(BBスクリーニング!$AE$6:$AE$405,$A24),BBスクリーニング!$AE$6:$AE$405,0)),"") -> 5703 | C24: =IFERROR(INDEX(BBスクリーニング!$C$6:$C$405,MATCH(LARGE(BBスクリーニング!$AE$6:$AE$405,$A24),BBスクリーニング!$AE$6:$AE$405,0)),"") -> 日本軽金属ＨＤ | D24: =IFERROR(INDEX(BBスクリーニング!$D$6:$D$405,MATCH(LARGE(BBスクリーニング!$AE$6:$AE$405,$A24),BBスクリーニング!$AE$6:$AE$405,0)),"") -> 2936 | E24: =IFERROR(INDEX(BBスクリーニング!$N$6:$N$405,MATCH(LARGE(BBスクリーニング!$AE$6:$AE$405,$A24),BBスクリーニング!$AE$6:$AE$405,0)),"") -> － | F24: =IFERROR(INDEX(BBスクリーニング!$P$6:$P$405,MATCH(LARGE(BBスクリーニング!$AE$6:$AE$405,$A24),BBスクリーニング!$AE$6:$AE$405,0)),"") -> ↑+2σ突破 | G24: =IFERROR(INDEX(BBスクリーニング!$Q$6:$Q$405,MATCH(LARGE(BBスクリーニング!$AE$6:$AE$405,$A24),BBスクリーニング!$AE$6:$AE$405,0)),"") -> 62.139423 | H24: =IFERROR(INDEX(BBスクリーニング!$R$6:$R$405,MATCH(LARGE(BBスクリーニング!$AE$6:$AE$405,$A24),BBスクリーニング!$AE$6:$AE$405,0)),"") -> 60.290027 | I24: =IFERROR(INDEX(BBスクリーニング!$S$6:$S$405,MATCH(LARGE(BBスクリーニング!$AE$6:$AE$405,$A24),BBスクリーニング!$AE$6:$AE$405,0)),"") -> － | J24: =IFERROR(INDEX(BBスクリーニング!$W$6:$W$405,MATCH(LARGE(BBスクリーニング!$AE$6:$AE$405,$A24),BBスクリーニング!$AE$6:$AE$405,0)),"") -> △二番底買(確) | K24: =IFERROR(INDEX(BBスクリーニング!$X$6:$X$405,MATCH(LARGE(BBスクリーニング!$AE$6:$AE$405,$A24),BBスクリーニング!$AE$6:$AE$405,0)),"") -> 55 | L24: =IFERROR(INDEX(BBスクリーニング!$Z$6:$Z$405,MATCH(LARGE(BBスクリーニング!$AE$6:$AE$405,$A24),BBスクリーニング!$AE$6:$AE$405,0)),"") -> 2810.742 | M24: =IFERROR(INDEX(BBスクリーニング!$AA$6:$AA$405,MATCH(LARGE(BBスクリーニング!$AE$6:$AE$405,$A24),BBスクリーニング!$AE$6:$AE$405,0)),"") -> 2717.3 | N24: =IFERROR(INDEX(BBスクリーニング!$AC$6:$AC$405,MATCH(LARGE(BBスクリーニング!$AE$6:$AE$405,$A24),BBスクリーニング!$AE$6:$AE$405,0)),"") -> 0.28 | O24: =IF($B24="","",HYPERLINK("https://kabutan.jp/stock/?code="&$B24,"株探")) -> 株探
A25: 21 | B25: =IFERROR(INDEX(BBスクリーニング!$B$6:$B$405,MATCH(LARGE(BBスクリーニング!$AE$6:$AE$405,$A25),BBスクリーニング!$AE$6:$AE$405,0)),"") -> 8053 | C25: =IFERROR(INDEX(BBスクリーニング!$C$6:$C$405,MATCH(LARGE(BBスクリーニング!$AE$6:$AE$405,$A25),BBスクリーニング!$AE$6:$AE$405,0)),"") -> 住友商事 | D25: =IFERROR(INDEX(BBスクリーニング!$D$6:$D$405,MATCH(LARGE(BBスクリーニング!$AE$6:$AE$405,$A25),BBスクリーニング!$AE$6:$AE$405,0)),"") -> 1748.5 | E25: =IFERROR(INDEX(BBスクリーニング!$N$6:$N$405,MATCH(LARGE(BBスクリーニング!$AE$6:$AE$405,$A25),BBスクリーニング!$AE$6:$AE$405,0)),"") -> － | F25: =IFERROR(INDEX(BBスクリーニング!$P$6:$P$405,MATCH(LARGE(BBスクリーニング!$AE$6:$AE$405,$A25),BBスクリーニング!$AE$6:$AE$405,0)),"") -> ↑+2σ突破 | G25: =IFERROR(INDEX(BBスクリーニング!$Q$6:$Q$405,MATCH(LARGE(BBスクリーニング!$AE$6:$AE$405,$A25),BBスクリーニング!$AE$6:$AE$405,0)),"") -> 69.40211 | H25: =IFERROR(INDEX(BBスクリーニング!$R$6:$R$405,MATCH(LARGE(BBスクリーニング!$AE$6:$AE$405,$A25),BBスクリーニング!$AE$6:$AE$405,0)),"") -> 74.55349 | I25: =IFERROR(INDEX(BBスクリーニング!$S$6:$S$405,MATCH(LARGE(BBスクリーニング!$AE$6:$AE$405,$A25),BBスクリーニング!$AE$6:$AE$405,0)),"") -> － | J25: =IFERROR(INDEX(BBスクリーニング!$W$6:$W$405,MATCH(LARGE(BBスクリーニング!$AE$6:$AE$405,$A25),BBスクリーニング!$AE$6:$AE$405,0)),"") -> △二番底買(確) | K25: =IFERROR(INDEX(BBスクリーニング!$X$6:$X$405,MATCH(LARGE(BBスクリーニング!$AE$6:$AE$405,$A25),BBスクリーニング!$AE$6:$AE$405,0)),"") -> 55 | L25: =IFERROR(INDEX(BBスクリーニング!$Z$6:$Z$405,MATCH(LARGE(BBスクリーニング!$AE$6:$AE$405,$A25),BBスクリーニング!$AE$6:$AE$405,0)),"") -> 1665.9199 | M25: =IFERROR(INDEX(BBスクリーニング!$AA$6:$AA$405,MATCH(LARGE(BBスクリーニング!$AE$6:$AE$405,$A25),BBスクリーニング!$AE$6:$AE$405,0)),"") -> 1609.65 | N25: =IFERROR(INDEX(BBスクリーニング!$AC$6:$AC$405,MATCH(LARGE(BBスクリーニング!$AE$6:$AE$405,$A25),BBスクリーニング!$AE$6:$AE$405,0)),"") -> 0.22 | O25: =IF($B25="","",HYPERLINK("https://kabutan.jp/stock/?code="&$B25,"株探")) -> 株探
A26: 22 | B26: =IFERROR(INDEX(BBスクリーニング!$B$6:$B$405,MATCH(LARGE(BBスクリーニング!$AE$6:$AE$405,$A26),BBスクリーニング!$AE$6:$AE$405,0)),"") -> 8750 | C26: =IFERROR(INDEX(BBスクリーニング!$C$6:$C$405,MATCH(LARGE(BBスクリーニング!$AE$6:$AE$405,$A26),BBスクリーニング!$AE$6:$AE$405,0)),"") -> 第一ライフグループ | D26: =IFERROR(INDEX(BBスクリーニング!$D$6:$D$405,MATCH(LARGE(BBスクリーニング!$AE$6:$AE$405,$A26),BBスクリーニング!$AE$6:$AE$405,0)),"") -> 1921 | E26: =IFERROR(INDEX(BBスクリーニング!$N$6:$N$405,MATCH(LARGE(BBスクリーニング!$AE$6:$AE$405,$A26),BBスクリーニング!$AE$6:$AE$405,0)),"") -> スクイーズ★ | F26: =IFERROR(INDEX(BBスクリーニング!$P$6:$P$405,MATCH(LARGE(BBスクリーニング!$AE$6:$AE$405,$A26),BBスクリーニング!$AE$6:$AE$405,0)),"") -> バンド内 | G26: =IFERROR(INDEX(BBスクリーニング!$Q$6:$Q$405,MATCH(LARGE(BBスクリーニング!$AE$6:$AE$405,$A26),BBスクリーニング!$AE$6:$AE$405,0)),"") -> 59.976387 | H26: =IFERROR(INDEX(BBスクリーニング!$R$6:$R$405,MATCH(LARGE(BBスクリーニング!$AE$6:$AE$405,$A26),BBスクリーニング!$AE$6:$AE$405,0)),"") -> 69.012583 | I26: =IFERROR(INDEX(BBスクリーニング!$S$6:$S$405,MATCH(LARGE(BBスクリーニング!$AE$6:$AE$405,$A26),BBスクリーニング!$AE$6:$AE$405,0)),"") -> 弱気div▼ | J26: =IFERROR(INDEX(BBスクリーニング!$W$6:$W$405,MATCH(LARGE(BBスクリーニング!$AE$6:$AE$405,$A26),BBスクリーニング!$AE$6:$AE$405,0)),"") -> △二番底形成 | K26: =IFERROR(INDEX(BBスクリーニング!$X$6:$X$405,MATCH(LARGE(BBスクリーニング!$AE$6:$AE$405,$A26),BBスクリーニング!$AE$6:$AE$405,0)),"") -> 55 | L26: =IFERROR(INDEX(BBスクリーニング!$Z$6:$Z$405,MATCH(LARGE(BBスクリーニング!$AE$6:$AE$405,$A26),BBスクリーニング!$AE$6:$AE$405,0)),"") -> 1925.8433 | M26: =IFERROR(INDEX(BBスクリーニング!$AA$6:$AA$405,MATCH(LARGE(BBスクリーニング!$AE$6:$AE$405,$A26),BBスクリーニング!$AE$6:$AE$405,0)),"") -> 1888.225 | N26: =IFERROR(INDEX(BBスクリーニング!$AC$6:$AC$405,MATCH(LARGE(BBスクリーニング!$AE$6:$AE$405,$A26),BBスクリーニング!$AE$6:$AE$405,0)),"") -> 1.3 | O26: =IF($B26="","",HYPERLINK("https://kabutan.jp/stock/?code="&$B26,"株探")) -> 株探
A27: 23 | B27: =IFERROR(INDEX(BBスクリーニング!$B$6:$B$405,MATCH(LARGE(BBスクリーニング!$AE$6:$AE$405,$A27),BBスクリーニング!$AE$6:$AE$405,0)),"") -> 5901 | C27: =IFERROR(INDEX(BBスクリーニング!$C$6:$C$405,MATCH(LARGE(BBスクリーニング!$AE$6:$AE$405,$A27),BBスクリーニング!$AE$6:$AE$405,0)),"") -> 東洋製罐グループＨＤ | D27: =IFERROR(INDEX(BBスクリーニング!$D$6:$D$405,MATCH(LARGE(BBスクリーニング!$AE$6:$AE$405,$A27),BBスクリーニング!$AE$6:$AE$405,0)),"") -> 4250 | E27: =IFERROR(INDEX(BBスクリーニング!$N$6:$N$405,MATCH(LARGE(BBスクリーニング!$AE$6:$AE$405,$A27),BBスクリーニング!$AE$6:$AE$405,0)),"") -> － | F27: =IFERROR(INDEX(BBスクリーニング!$P$6:$P$405,MATCH(LARGE(BBスクリーニング!$AE$6:$AE$405,$A27),BBスクリーニング!$AE$6:$AE$405,0)),"") -> ↑+2σ突破 | G27: =IFERROR(INDEX(BBスクリーニング!$Q$6:$Q$405,MATCH(LARGE(BBスクリーニング!$AE$6:$AE$405,$A27),BBスクリーニング!$AE$6:$AE$405,0)),"") -> 63.948498 | H27: =IFERROR(INDEX(BBスクリーニング!$R$6:$R$405,MATCH(LARGE(BBスクリーニング!$AE$6:$AE$405,$A27),BBスクリーニング!$AE$6:$AE$405,0)),"") -> 67.94622 | I27: =IFERROR(INDEX(BBスクリーニング!$S$6:$S$405,MATCH(LARGE(BBスクリーニング!$AE$6:$AE$405,$A27),BBスクリーニング!$AE$6:$AE$405,0)),"") -> － | J27: =IFERROR(INDEX(BBスクリーニング!$W$6:$W$405,MATCH(LARGE(BBスクリーニング!$AE$6:$AE$405,$A27),BBスクリーニング!$AE$6:$AE$405,0)),"") -> △二番底買(確) | K27: =IFERROR(INDEX(BBスクリーニング!$X$6:$X$405,MATCH(LARGE(BBスクリーニング!$AE$6:$AE$405,$A27),BBスクリーニング!$AE$6:$AE$405,0)),"") -> 55 | L27: =IFERROR(INDEX(BBスクリーニング!$Z$6:$Z$405,MATCH(LARGE(BBスクリーニング!$AE$6:$AE$405,$A27),BBスクリーニング!$AE$6:$AE$405,0)),"") -> 4162.4218 | M27: =IFERROR(INDEX(BBスクリーニング!$AA$6:$AA$405,MATCH(LARGE(BBスクリーニング!$AE$6:$AE$405,$A27),BBスクリーニング!$AE$6:$AE$405,0)),"") -> 4088 | N27: =IFERROR(INDEX(BBスクリーニング!$AC$6:$AC$405,MATCH(LARGE(BBスクリーニング!$AE$6:$AE$405,$A27),BBスクリーニング!$AE$6:$AE$405,0)),"") -> 0.38 | O27: =IF($B27="","",HYPERLINK("https://kabutan.jp/stock/?code="&$B27,"株探")) -> 株探
A28: 24 | B28: =IFERROR(INDEX(BBスクリーニング!$B$6:$B$405,MATCH(LARGE(BBスクリーニング!$AE$6:$AE$405,$A28),BBスクリーニング!$AE$6:$AE$405,0)),"") -> 5857 | C28: =IFERROR(INDEX(BBスクリーニング!$C$6:$C$405,MATCH(LARGE(BBスクリーニング!$AE$6:$AE$405,$A28),BBスクリーニング!$AE$6:$AE$405,0)),"") -> ＡＲＥホールディングス | D28: =IFERROR(INDEX(BBスクリーニング!$D$6:$D$405,MATCH(LARGE(BBスクリーニング!$AE$6:$AE$405,$A28),BBスクリーニング!$AE$6:$AE$405,0)),"") -> 3460 | E28: =IFERROR(INDEX(BBスクリーニング!$N$6:$N$405,MATCH(LARGE(BBスクリーニング!$AE$6:$AE$405,$A28),BBスクリーニング!$AE$6:$AE$405,0)),"") -> － | F28: =IFERROR(INDEX(BBスクリーニング!$P$6:$P$405,MATCH(LARGE(BBスクリーニング!$AE$6:$AE$405,$A28),BBスクリーニング!$AE$6:$AE$405,0)),"") -> ↑+2σ突破 | G28: =IFERROR(INDEX(BBスクリーニング!$Q$6:$Q$405,MATCH(LARGE(BBスクリーニング!$AE$6:$AE$405,$A28),BBスクリーニング!$AE$6:$AE$405,0)),"") -> 66.723116 | H28: =IFERROR(INDEX(BBスクリーニング!$R$6:$R$405,MATCH(LARGE(BBスクリーニング!$AE$6:$AE$405,$A28),BBスクリーニング!$AE$6:$AE$405,0)),"") -> 60.433012 | I28: =IFERROR(INDEX(BBスクリーニング!$S$6:$S$405,MATCH(LARGE(BBスクリーニング!$AE$6:$AE$405,$A28),BBスクリーニング!$AE$6:$AE$405,0)),"") -> － | J28: =IFERROR(INDEX(BBスクリーニング!$W$6:$W$405,MATCH(LARGE(BBスクリーニング!$AE$6:$AE$405,$A28),BBスクリーニング!$AE$6:$AE$405,0)),"") -> △二番底買(確) | K28: =IFERROR(INDEX(BBスクリーニング!$X$6:$X$405,MATCH(LARGE(BBスクリーニング!$AE$6:$AE$405,$A28),BBスクリーニング!$AE$6:$AE$405,0)),"") -> 55 | L28: =IFERROR(INDEX(BBスクリーニング!$Z$6:$Z$405,MATCH(LARGE(BBスクリーニング!$AE$6:$AE$405,$A28),BBスクリーニング!$AE$6:$AE$405,0)),"") -> 3193.4422 | M28: =IFERROR(INDEX(BBスクリーニング!$AA$6:$AA$405,MATCH(LARGE(BBスクリーニング!$AE$6:$AE$405,$A28),BBスクリーニング!$AE$6:$AE$405,0)),"") -> 3074.25 | N28: =IFERROR(INDEX(BBスクリーニング!$AC$6:$AC$405,MATCH(LARGE(BBスクリーニング!$AE$6:$AE$405,$A28),BBスクリーニング!$AE$6:$AE$405,0)),"") -> -0.07 | O28: =IF($B28="","",HYPERLINK("https://kabutan.jp/stock/?code="&$B28,"株探")) -> 株探
A29: 25 | B29: =IFERROR(INDEX(BBスクリーニング!$B$6:$B$405,MATCH(LARGE(BBスクリーニング!$AE$6:$AE$405,$A29),BBスクリーニング!$AE$6:$AE$405,0)),"") -> 7167 | C29: =IFERROR(INDEX(BBスクリーニング!$C$6:$C$405,MATCH(LARGE(BBスクリーニング!$AE$6:$AE$405,$A29),BBスクリーニング!$AE$6:$AE$405,0)),"") -> めぶきフィナンシャルＧ | D29: =IFERROR(INDEX(BBスクリーニング!$D$6:$D$405,MATCH(LARGE(BBスクリーニング!$AE$6:$AE$405,$A29),BBスクリーニング!$AE$6:$AE$405,0)),"") -> 1628 | E29: =IFERROR(INDEX(BBスクリーニング!$N$6:$N$405,MATCH(LARGE(BBスクリーニング!$AE$6:$AE$405,$A29),BBスクリーニング!$AE$6:$AE$405,0)),"") -> － | F29: =IFERROR(INDEX(BBスクリーニング!$P$6:$P$405,MATCH(LARGE(BBスクリーニング!$AE$6:$AE$405,$A29),BBスクリーニング!$AE$6:$AE$405,0)),"") -> ↑+2σ突破 | G29: =IFERROR(INDEX(BBスクリーニング!$Q$6:$Q$405,MATCH(LARGE(BBスクリーニング!$AE$6:$AE$405,$A29),BBスクリーニング!$AE$6:$AE$405,0)),"") -> 62.295082 | H29: =IFERROR(INDEX(BBスクリーニング!$R$6:$R$405,MATCH(LARGE(BBスクリーニング!$AE$6:$AE$405,$A29),BBスクリーニング!$AE$6:$AE$405,0)),"") -> 67.002091 | I29: =IFERROR(INDEX(BBスクリーニング!$S$6:$S$405,MATCH(LARGE(BBスクリーニング!$AE$6:$AE$405,$A29),BBスクリーニング!$AE$6:$AE$405,0)),"") -> － | J29: =IFERROR(INDEX(BBスクリーニング!$W$6:$W$405,MATCH(LARGE(BBスクリーニング!$AE$6:$AE$405,$A29),BBスクリーニング!$AE$6:$AE$405,0)),"") -> △二番底買(確) | K29: =IFERROR(INDEX(BBスクリーニング!$X$6:$X$405,MATCH(LARGE(BBスクリーニング!$AE$6:$AE$405,$A29),BBスクリーニング!$AE$6:$AE$405,0)),"") -> 55 | L29: =IFERROR(INDEX(BBスクリーニング!$Z$6:$Z$405,MATCH(LARGE(BBスクリーニング!$AE$6:$AE$405,$A29),BBスクリーニング!$AE$6:$AE$405,0)),"") -> 1555.6154 | M29: =IFERROR(INDEX(BBスクリーニング!$AA$6:$AA$405,MATCH(LARGE(BBスクリーニング!$AE$6:$AE$405,$A29),BBスクリーニング!$AE$6:$AE$405,0)),"") -> 1515.575 | N29: =IFERROR(INDEX(BBスクリーニング!$AC$6:$AC$405,MATCH(LARGE(BBスクリーニング!$AE$6:$AE$405,$A29),BBスクリーニング!$AE$6:$AE$405,0)),"") -> 0.07 | O29: =IF($B29="","",HYPERLINK("https://kabutan.jp/stock/?code="&$B29,"株探")) -> 株探
A30: 26 | B30: =IFERROR(INDEX(BBスクリーニング!$B$6:$B$405,MATCH(LARGE(BBスクリーニング!$AE$6:$AE$405,$A30),BBスクリーニング!$AE$6:$AE$405,0)),"") -> 6809 | C30: =IFERROR(INDEX(BBスクリーニング!$C$6:$C$405,MATCH(LARGE(BBスクリーニング!$AE$6:$AE$405,$A30),BBスクリーニング!$AE$6:$AE$405,0)),"") -> ＴＯＡ | D30: =IFERROR(INDEX(BBスクリーニング!$D$6:$D$405,MATCH(LARGE(BBスクリーニング!$AE$6:$AE$405,$A30),BBスクリーニング!$AE$6:$AE$405,0)),"") -> 1669 | E30: =IFERROR(INDEX(BBスクリーニング!$N$6:$N$405,MATCH(LARGE(BBスクリーニング!$AE$6:$AE$405,$A30),BBスクリーニング!$AE$6:$AE$405,0)),"") -> － | F30: =IFERROR(INDEX(BBスクリーニング!$P$6:$P$405,MATCH(LARGE(BBスクリーニング!$AE$6:$AE$405,$A30),BBスクリーニング!$AE$6:$AE$405,0)),"") -> ↑+2σ突破 | G30: =IFERROR(INDEX(BBスクリーニング!$Q$6:$Q$405,MATCH(LARGE(BBスクリーニング!$AE$6:$AE$405,$A30),BBスクリーニング!$AE$6:$AE$405,0)),"") -> 69.811321 | H30: =IFERROR(INDEX(BBスクリーニング!$R$6:$R$405,MATCH(LARGE(BBスクリーニング!$AE$6:$AE$405,$A30),BBスクリーニング!$AE$6:$AE$405,0)),"") -> 63.738088 | I30: =IFERROR(INDEX(BBスクリーニング!$S$6:$S$405,MATCH(LARGE(BBスクリーニング!$AE$6:$AE$405,$A30),BBスクリーニング!$AE$6:$AE$405,0)),"") -> － | J30: =IFERROR(INDEX(BBスクリーニング!$W$6:$W$405,MATCH(LARGE(BBスクリーニング!$AE$6:$AE$405,$A30),BBスクリーニング!$AE$6:$AE$405,0)),"") -> 様子見 | K30: =IFERROR(INDEX(BBスクリーニング!$X$6:$X$405,MATCH(LARGE(BBスクリーニング!$AE$6:$AE$405,$A30),BBスクリーニング!$AE$6:$AE$405,0)),"") -> 55 | L30: =IFERROR(INDEX(BBスクリーニング!$Z$6:$Z$405,MATCH(LARGE(BBスクリーニング!$AE$6:$AE$405,$A30),BBスクリーニング!$AE$6:$AE$405,0)),"") -> 1641.2768 | M30: =IFERROR(INDEX(BBスクリーニング!$AA$6:$AA$405,MATCH(LARGE(BBスクリーニング!$AE$6:$AE$405,$A30),BBスクリーニング!$AE$6:$AE$405,0)),"") -> 1617.65 | N30: =IFERROR(INDEX(BBスクリーニング!$AC$6:$AC$405,MATCH(LARGE(BBスクリーニング!$AE$6:$AE$405,$A30),BBスクリーニング!$AE$6:$AE$405,0)),"") -> 0.38 | O30: =IF($B30="","",HYPERLINK("https://kabutan.jp/stock/?code="&$B30,"株探")) -> 株探
A31: 27 | B31: =IFERROR(INDEX(BBスクリーニング!$B$6:$B$405,MATCH(LARGE(BBスクリーニング!$AE$6:$AE$405,$A31),BBスクリーニング!$AE$6:$AE$405,0)),"") -> 7609 | C31: =IFERROR(INDEX(BBスクリーニング!$C$6:$C$405,MATCH(LARGE(BBスクリーニング!$AE$6:$AE$405,$A31),BBスクリーニング!$AE$6:$AE$405,0)),"") -> ダイトロン | D31: =IFERROR(INDEX(BBスクリーニング!$D$6:$D$405,MATCH(LARGE(BBスクリーニング!$AE$6:$AE$405,$A31),BBスクリーニング!$AE$6:$AE$405,0)),"") -> 4215 | E31: =IFERROR(INDEX(BBスクリーニング!$N$6:$N$405,MATCH(LARGE(BBスクリーニング!$AE$6:$AE$405,$A31),BBスクリーニング!$AE$6:$AE$405,0)),"") -> － | F31: =IFERROR(INDEX(BBスクリーニング!$P$6:$P$405,MATCH(LARGE(BBスクリーニング!$AE$6:$AE$405,$A31),BBスクリーニング!$AE$6:$AE$405,0)),"") -> ↑+2σ突破 | G31: =IFERROR(INDEX(BBスクリーニング!$Q$6:$Q$405,MATCH(LARGE(BBスクリーニング!$AE$6:$AE$405,$A31),BBスクリーニング!$AE$6:$AE$405,0)),"") -> 67.19457 | H31: =IFERROR(INDEX(BBスクリーニング!$R$6:$R$405,MATCH(LARGE(BBスクリーニング!$AE$6:$AE$405,$A31),BBスクリーニング!$AE$6:$AE$405,0)),"") -> 70.687012 | I31: =IFERROR(INDEX(BBスクリーニング!$S$6:$S$405,MATCH(LARGE(BBスクリーニング!$AE$6:$AE$405,$A31),BBスクリーニング!$AE$6:$AE$405,0)),"") -> － | J31: =IFERROR(INDEX(BBスクリーニング!$W$6:$W$405,MATCH(LARGE(BBスクリーニング!$AE$6:$AE$405,$A31),BBスクリーニング!$AE$6:$AE$405,0)),"") -> △二番底買(確) | K31: =IFERROR(INDEX(BBスクリーニング!$X$6:$X$405,MATCH(LARGE(BBスクリーニング!$AE$6:$AE$405,$A31),BBスクリーニング!$AE$6:$AE$405,0)),"") -> 55 | L31: =IFERROR(INDEX(BBスクリーニング!$Z$6:$Z$405,MATCH(LARGE(BBスクリーニング!$AE$6:$AE$405,$A31),BBスクリーニング!$AE$6:$AE$405,0)),"") -> 3850.8617 | M31: =IFERROR(INDEX(BBスクリーニング!$AA$6:$AA$405,MATCH(LARGE(BBスクリーニング!$AE$6:$AE$405,$A31),BBスクリーニング!$AE$6:$AE$405,0)),"") -> 3527.75 | N31: =IFERROR(INDEX(BBスクリーニング!$AC$6:$AC$405,MATCH(LARGE(BBスクリーニング!$AE$6:$AE$405,$A31),BBスクリーニング!$AE$6:$AE$405,0)),"") -> 0.41 | O31: =IF($B31="","",HYPERLINK("https://kabutan.jp/stock/?code="&$B31,"株探")) -> 株探
A32: 28 | B32: =IFERROR(INDEX(BBスクリーニング!$B$6:$B$405,MATCH(LARGE(BBスクリーニング!$AE$6:$AE$405,$A32),BBスクリーニング!$AE$6:$AE$405,0)),"") -> 5632 | C32: =IFERROR(INDEX(BBスクリーニング!$C$6:$C$405,MATCH(LARGE(BBスクリーニング!$AE$6:$AE$405,$A32),BBスクリーニング!$AE$6:$AE$405,0)),"") -> 三菱製鋼 | D32: =IFERROR(INDEX(BBスクリーニング!$D$6:$D$405,MATCH(LARGE(BBスクリーニング!$AE$6:$AE$405,$A32),BBスクリーニング!$AE$6:$AE$405,0)),"") -> 2307 | E32: =IFERROR(INDEX(BBスクリーニング!$N$6:$N$405,MATCH(LARGE(BBスクリーニング!$AE$6:$AE$405,$A32),BBスクリーニング!$AE$6:$AE$405,0)),"") -> － | F32: =IFERROR(INDEX(BBスクリーニング!$P$6:$P$405,MATCH(LARGE(BBスクリーニング!$AE$6:$AE$405,$A32),BBスクリーニング!$AE$6:$AE$405,0)),"") -> ↑+2σ突破 | G32: =IFERROR(INDEX(BBスクリーニング!$Q$6:$Q$405,MATCH(LARGE(BBスクリーニング!$AE$6:$AE$405,$A32),BBスクリーニング!$AE$6:$AE$405,0)),"") -> 68.957346 | H32: =IFERROR(INDEX(BBスクリーニング!$R$6:$R$405,MATCH(LARGE(BBスクリーニング!$AE$6:$AE$405,$A32),BBスクリーニング!$AE$6:$AE$405,0)),"") -> 61.352306 | I32: =IFERROR(INDEX(BBスクリーニング!$S$6:$S$405,MATCH(LARGE(BBスクリーニング!$AE$6:$AE$405,$A32),BBスクリーニング!$AE$6:$AE$405,0)),"") -> － | J32: =IFERROR(INDEX(BBスクリーニング!$W$6:$W$405,MATCH(LARGE(BBスクリーニング!$AE$6:$AE$405,$A32),BBスクリーニング!$AE$6:$AE$405,0)),"") -> △二番底買(確) | K32: =IFERROR(INDEX(BBスクリーニング!$X$6:$X$405,MATCH(LARGE(BBスクリーニング!$AE$6:$AE$405,$A32),BBスクリーニング!$AE$6:$AE$405,0)),"") -> 55 | L32: =IFERROR(INDEX(BBスクリーニング!$Z$6:$Z$405,MATCH(LARGE(BBスクリーニング!$AE$6:$AE$405,$A32),BBスクリーニング!$AE$6:$AE$405,0)),"") -> 2212.1832 | M32: =IFERROR(INDEX(BBスクリーニング!$AA$6:$AA$405,MATCH(LARGE(BBスクリーニング!$AE$6:$AE$405,$A32),BBスクリーニング!$AE$6:$AE$405,0)),"") -> 2158.1 | N32: =IFERROR(INDEX(BBスクリーニング!$AC$6:$AC$405,MATCH(LARGE(BBスクリーニング!$AE$6:$AE$405,$A32),BBスクリーニング!$AE$6:$AE$405,0)),"") -> 0.09 | O32: =IF($B32="","",HYPERLINK("https://kabutan.jp/stock/?code="&$B32,"株探")) -> 株探
... A34: 30 | B34: =IFERROR(INDEX(BBスクリーニング!$B$6:$B$405,MATCH(LARGE(BBスクリーニング!$AE$6:$AE$405,$A34),BBスクリーニング!$AE$6:$AE$405,0)),"") -> 6366 | C34: =IFERROR(INDEX(BBスクリーニング!$C$6:$C$405,MATCH(LARGE(BBスクリーニング!$AE$6:$AE$405,$A34),BBスクリーニング!$AE$6:$AE$405,0)),"") -> 千代田化工建 | D34: =IFERROR(INDEX(BBスクリーニング!$D$6:$D$405,MATCH(LARGE(BBスクリーニング!$AE$6:$AE$405,$A34),BBスクリーニング!$AE$6:$AE$405,0)),"") -> 695 | E34: =IFERROR(INDEX(BBスクリーニング!$N$6:$N$405,MATCH(LARGE(BBスクリーニング!$AE$6:$AE$405,$A34),BBスクリーニング!$AE$6:$AE$405,0)),"") -> スクイーズ★ | F34: =IFERROR(INDEX(BBスクリーニング!$P$6:$P$405,MATCH(LARGE(BBスクリーニング!$AE$6:$AE$405,$A34),BBスクリーニング!$AE$6:$AE$405,0)),"") -> バンド内 | G34: =IFERROR(INDEX(BBスクリーニング!$Q$6:$Q$405,MATCH(LARGE(BBスクリーニング!$AE$6:$AE$405,$A34),BBスクリーニング!$AE$6:$AE$405,0)),"") -> 53.636364 | H34: =IFERROR(INDEX(BBスクリーニング!$R$6:$R$405,MATCH(LARGE(BBスクリーニング!$AE$6:$AE$405,$A34),BBスクリーニング!$AE$6:$AE$405,0)),"") -> 56.532528 | I34: =IFERROR(INDEX(BBスクリーニング!$S$6:$S$405,MATCH(LARGE(BBスクリーニング!$AE$6:$AE$405,$A34),BBスクリーニング!$AE$6:$AE$405,0)),"") -> 強気div▲ | J34: =IFERROR(INDEX(BBスクリーニング!$W$6:$W$405,MATCH(LARGE(BBスクリーニング!$AE$6:$AE$405,$A34),BBスクリーニング!$AE$6:$AE$405,0)),"") -> ○反発(ダイバ)買 | K34: =IFERROR(INDEX(BBスクリーニング!$X$6:$X$405,MATCH(LARGE(BBスクリーニング!$AE$6:$AE$405,$A34),BBスクリーニング!$AE$6:$AE$405,0)),"") -> 55 | L34: =IFERROR(INDEX(BBスクリーニング!$Z$6:$Z$405,MATCH(LARGE(BBスクリーニング!$AE$6:$AE$405,$A34),BBスクリーニング!$AE$6:$AE$405,0)),"") -> 706.02242 | M34: =IFERROR(INDEX(BBスクリーニング!$AA$6:$AA$405,MATCH(LARGE(BBスクリーニング!$AE$6:$AE$405,$A34),BBスクリーニング!$AE$6:$AE$405,0)),"") -> 678.8 | N34: =IFERROR(INDEX(BBスクリーニング!$AC$6:$AC$405,MATCH(LARGE(BBスクリーニング!$AE$6:$AE$405,$A34),BBスクリーニング!$AE$6:$AE$405,0)),"") -> 2.36 | O34: =IF($B34="","",HYPERLINK("https://kabutan.jp/stock/?code="&$B34,"株探")) -> 株探

Sheet BBスクリーニング
A1: 📊 ボリンジャーバンド 買い候補スクリーニング（SMA20・±1σ/±2σ）
A2: 終値シートの最新終値を基準に自動計算。スコア降順に並べ替え、または「BB買い候補TOP」を参照。
A3: ◎スクイーズブレイク ○順張り/反発 △二番底 ☆スクイーズ監視 ・押し目 ▼危険（凡例はBB設定シート）
A5: 🔗 | B5: コード | C5: 銘柄名 | D5: 現在値 | E5: SMA20 ミドル | F5: σ | G5: +2σ | H5: +1σ | I5: -1σ | J5: -2σ | K5: %B | L5: 帯幅% | M5: 帯幅25日 最小% | N5: スクイーズ | O5: 帯拡大 | P5: ブレイク | Q5: RSI14 | R5: MFI14 | S5: ダイバー ジェンス | T5: バンド ウォーク | U5: 二番底/天井 | V5: 出来高 倍率 | W5: 戦略シグナル | X5: スコア | Y5: エントリー 目安 | Z5: 利確 (+1σ) | AA5: 損切り (ミドル) | AB5: 目標 (+2σ) | AC5: R:R | AD5: 直近5日 安値 | AE5: sortkey
A6: =IF(終値!A6="","",HYPERLINK("https://kabutan.jp/stock/?code="&終値!A6,"📈")) -> 📈 | B6: =IF(終値!A6="","",終値!A6) -> 5706 | C6: =IF(終値!A6="","",終値!B6) -> 三井金属 | D6: =IF(終値!A6="","",終値!E6) -> 31970 | E6: =IF($D6="","",AVERAGE(終値!E6:X6)) -> 32112.5 | F6: =IF($D6="","",STDEVP(終値!E6:X6)) -> 2827.1242 | G6: =IF($D6="","",$E6+BB設定!$B$4*$F6) -> 37766.748 | H6: =IF($D6="","",$E6+BB設定!$B$5*$F6) -> 34939.624 | I6: =IF($D6="","",$E6-BB設定!$B$5*$F6) -> 29285.376 | J6: =IF($D6="","",$E6-BB設定!$B$4*$F6) -> 26458.252 | K6: =IF($D6="","",IFERROR(($D6-$J6)/($G6-$J6),"")) -> 0.48739886 | L6: =IF($D6="","",IFERROR(($G6-$J6)/$E6*100,"")) -> 35.215249 | M6: =IF($D6="","",IFERROR(MIN(BB_帯幅!B6:AP6)*100,"")) -> 34.851626 | N6: =IF($L6="","",IF($L6<=$M6*BB設定!$B$7,"スクイーズ★",IF($L6<=$M6*1.3,"収縮","－"))) -> スクイーズ★ | O6: =IF($D6="","",IF(AND(BB_帯幅!B6>BB_帯幅!C6,BB_帯幅!C6>BB_帯幅!D6),"拡大↑","縮小↓")) -> 縮小↓ | P6: =IF($D6="","",IF($D6>$G6,"↑+2σ突破",IF($D6<$J6,"↓-2σ割れ",IF($D6>$H6,"+1σ上",IF($D6<$I6,"-1σ下","バンド内"))))) -> バンド内 | Q6: =IF($D6="","",IFERROR(100-100/(1+SUMPRODUCT((終値!E6:R6>終値!F6:S6)*(終値!E6:R6-終値!F6:S6))/SUMPRODUCT((終値!E6:R6<終値!F6:S6)*(終値!F6:S6-終値!E6:R6))),100)) -> 49.440433 | R6: =IF($D6="","",IFERROR(100-100/(1+SUMPRODUCT((((高値!E6:R6+安値!E6:R6+終値!E6:R6)/3)>((高値!F6:S6+安値!F6:S6+終値!F6:S6)/3))*((高値!E6:R6+安値!E6:R6+終値!E6:R6)/3)*出来高!E6:R6)/SUMPRODUCT((((高値!E6:R6+安値!E6:R6+終値!E6:R6)/3)<((高値!F6:S6+安値!F6:S6+終値!F6:S6)/3))*((高値!E6:R6+安値!E6:R6+終値!E6:R6)/3)*出来高!E6:R6)),50)) -> 56.165379 | S6: =IF($D6="","",IF(AND(終値!E6<終値!O6,$Q6>(IFERROR(100-100/(1+SUMPRODUCT((終値!O6:AB6>終値!P6:AC6)*(終値!O6:AB6-終値!P6:AC6))/SUMPRODUCT((終値!O6:AB6<終値!P6:AC6)*(終値!P6:AC6-終値!O6:AB6))),100))),"強気div▲",IF(AND(終値!E6>終値!O6,$Q6<(IFERROR(100-100/(1+SUMPRODUCT((終値!O6:AB6>終値!P6:AC6)*(終値!O6:AB6-終値!P6:AC6))/SUMPRODUCT((終値!O6:AB6<終値!P6:AC6)*(終値!P6:AC6-終値!O6:AB6))),100))),"弱気div▼","－"))) -> 強気div▲ | T6: =IF($D6="","",IF($D6>=$H6,"上walk▲",IF($D6<=$I6,"下walk▼","－"))) -> － | U6: =IF(終値!A6="","",BB_スイング!BT6) -> － | V6: =IF($D6="","",IFERROR(出来高!E6/AVERAGE(出来高!E6:I6),"")) -> 0.97157509 | W6: =IF($D6="","",IF(AND($D6>$G6,$O6="拡大↑",OR($N6="スクイーズ★",$N6="収縮")),"◎スクイーズブレイク買",IF(AND($D6>=$H6,$R6>=BB設定!$B$10),"○順張り継続(walk)",IF(AND($S6="強気div▲",$D6>$I6,LEFT($U6,4)<>"二番天井"),"○反発(ダイバ)買",IF($U6="二番底W▲","△二番底買(確)",IF($U6="二番底W形成","△二番底形成",IF(LEFT($U6,4)="二番天井","▼二番天井警戒",IF($D6<$J6,"▼-2σ割れ危険",IF(AND($D6>$E6,$K6<0.6,$R6>=50),"・押し目注目",IF($N6="スクイーズ★","☆スクイーズ監視","様子見")))))))))) -> ○反発(ダイバ)買 | X6: =IF($D6="","",MAX(0,MIN(100,IF($L6<=$M6*1.15,20,IF($L6<=$M6*1.4,10,0))+IF($D6>$G6,20,IF($D6>$H6,12,IF($D6>$E6,5,0)))+IF($O6="拡大↑",10,0)+IF($R6>=80,15,IF($R6>=60,10,IF($R6>=50,5,0)))+IF(AND($Q6>=50,$Q6<=70),10,IF($Q6>70,3,IF($Q6>=40,5,0)))+IF(AND($S6="強気div▲",$T6<>"下walk▼"),15,IF(AND($S6="強気div▲",$T6="下walk▼"),5,0))+IF($T6="上walk▲",5,0)+IF($V6>=2,5,IF($V6>=1.5,3,0))+IF(LEFT($U6,4)="二番天井",-15,0)+IF($D6<$E6,-10,0)+IF($T6="下walk▼",-10,0)+IF($K6<0.2,-5,0)))) -> 35 | Y6: =IF($D6="","",$D6) -> 31970 | Z6: =IF($D6="","",$H6) -> 34939.624 | AA6: =IF($D6="","",IF($D6>$E6,$E6,$AD6)) -> 30890 | AB6: =IF($D6="","",IF($D6>$G6,$E6+3*$F6,$G6)) -> 37766.748 | AC6: =IF($D6="","",IF(($Y6-$AA6)<=0,"－",IFERROR(ROUND(MIN(20,($AB6-$Y6)/($Y6-$AA6)),2),"－"))) -> 5.37 | AD6: =IF($D6="","",MIN(終値!E6:I6)) -> 30890 | AE6: =IF($D6="","",$X6+(10000-ROW())/100000) -> 35.09994
A7: =IF(終値!A7="","",HYPERLINK("https://kabutan.jp/stock/?code="&終値!A7,"📈")) -> 📈 | B7: =IF(終値!A7="","",終値!A7) -> 5423 | C7: =IF(終値!A7="","",終値!B7) -> 東京製鐵 | D7: =IF(終値!A7="","",終値!E7) -> 1752 | E7: =IF($D7="","",AVERAGE(終値!E7:X7)) -> 1737.2 | F7: =IF($D7="","",STDEVP(終値!E7:X7)) -> 30.134034 | G7: =IF($D7="","",$E7+BB設定!$B$4*$F7) -> 1797.4681 | H7: =IF($D7="","",$E7+BB設定!$B$5*$F7) -> 1767.334 | I7: =IF($D7="","",$E7-BB設定!$B$5*$F7) -> 1707.066 | J7: =IF($D7="","",$E7-BB設定!$B$4*$F7) -> 1676.9319 | K7: =IF($D7="","",IFERROR(($D7-$J7)/($G7-$J7),"")) -> 0.62278476 | L7: =IF($D7="","",IFERROR(($G7-$J7)/$E7*100,"")) -> 6.9385296 | M7: =IF($D7="","",IFERROR(MIN(BB_帯幅!B7:AP7)*100,"")) -> 5.5192894 | N7: =IF($L7="","",IF($L7<=$M7*BB設定!$B$7,"スクイーズ★",IF($L7<=$M7*1.3,"収縮","－"))) -> 収縮 | O7: =IF($D7="","",IF(AND(BB_帯幅!B7>BB_帯幅!C7,BB_帯幅!C7>BB_帯幅!D7),"拡大↑","縮小↓")) -> 拡大↑ | P7: =IF($D7="","",IF($D7>$G7,"↑+2σ突破",IF($D7<$J7,"↓-2σ割れ",IF($D7>$H7,"+1σ上",IF($D7<$I7,"-1σ下","バンド内"))))) -> バンド内 | Q7: =IF($D7="","",IFERROR(100-100/(1+SUMPRODUCT((終値!E7:R7>終値!F7:S7)*(終値!E7:R7-終値!F7:S7))/SUMPRODUCT((終値!E7:R7<終値!F7:S7)*(終値!F7:S7-終値!E7:R7))),100)) -> 47.593583 | R7: =IF($D7="","",IFERROR(100-100/(1+SUMPRODUCT((((高値!E7:R7+安値!E7:R7+終値!E7:R7)/3)>((高値!F7:S7+安値!F7:S7+終値!F7:S7)/3))*((高値!E7:R7+安値!E7:R7+終値!E7:R7)/3)*出来高!E7:R7)/SUMPRODUCT((((高値!E7:R7+安値!E7:R7+終値!E7:R7)/3)<((高値!F7:S7+安値!F7:S7+終値!F7:S7)/3))*((高値!E7:R7+安値!E7:R7+終値!E7:R7)/3)*出来高!E7:R7)),50)) -> 50.386124 | S7: =IF($D7="","",IF(AND(終値!E7<終値!O7,$Q7>(IFERROR(100-100/(1+SUMPRODUCT((終値!O7:AB7>終値!P7:AC7)*(終値!O7:AB7-終値!P7:AC7))/SUMPRODUCT((終値!O7:AB7<終値!P7:AC7)*(終値!P7:AC7-終値!O7:AB7))),100))),"強気div▲",IF(AND(終値!E7>終値!O7,$Q7<(IFERROR(100-100/(1+SUMPRODUCT((終値!O7:AB7>終値!P7:AC7)*(終値!O7:AB7-終値!P7:AC7))/SUMPRODUCT((終値!O7:AB7<終値!P7:AC7)*(終値!P7:AC7-終値!O7:AB7))),100))),"弱気div▼","－"))) -> 弱気div▼ | T7: =IF($D7="","",IF($D7>=$H7,"上walk▲",IF($D7<=$I7,"下walk▼","－"))) -> － | U7: =IF(終値!A7="","",BB_スイング!BT7) -> 二番底W形成 | V7: =IF($D7="","",IFERROR(出来高!E7/AVERAGE(出来高!E7:I7),"")) -> 1.045045 | W7: =IF($D7="","",IF(AND($D7>$G7,$O7="拡大↑",OR($N7="スクイーズ★",$N7="収縮")),"◎スクイーズブレイク買",IF(AND($D7>=$H7,$R7>=BB設定!$B$10),"○順張り継続(walk)",IF(AND($S7="強気div▲",$D7>$I7,LEFT($U7,4)<>"二番天井"),"○反発(ダイバ)買",IF($U7="二番底W▲","△二番底買(確)",IF($U7="二番底W形成","△二番底形成",IF(LEFT($U7,4)="二番天井","▼二番天井警戒",IF($D7<$J7,"▼-2σ割れ危険",IF(AND($D7>$E7,$K7<0.6,$R7>=50),"・押し目注目",IF($N7="スクイーズ★","☆スクイーズ監視","様子見")))))))))) -> △二番底形成 | X7: =IF($D7="","",MAX(0,MIN(100,IF($L7<=$M7*1.15,20,IF($L7<=$M7*1.4,10,0))+IF($D7>$G7,20,IF($D7>$H7,12,IF($D7>$E7,5,0)))+IF($O7="拡大↑",10,0)+IF($R7>=80,15,IF($R7>=60,10,IF($R7>=50,5,0)))+IF(AND($Q7>=50,$Q7<=70),10,IF($Q7>70,3,IF($Q7>=40,5,0)))+IF(AND($S7="強気div▲",$T7<>"下walk▼"),15,IF(AND($S7="強気div▲",$T7="下walk▼"),5,0))+IF($T7="上walk▲",5,0)+IF($V7>=2,5,IF($V7>=1.5,3,0))+IF(LEFT($U7,4)="二番天井",-15,0)+IF($D7<$E7,-10,0)+IF($T7="下walk▼",-10,0)+IF($K7<0.2,-5,0)))) -> 35 | Y7: =IF($D7="","",$D7) -> 1752 | Z7: =IF($D7="","",$H7) -> 1767.334 | AA7: =IF($D7="","",IF($D7>$E7,$E7,$AD7)) -> 1737.2 | AB7: =IF($D7="","",IF($D7>$G7,$E7+3*$F7,$G7)) -> 1797.4681 | AC7: =IF($D7="","",IF(($Y7-$AA7)<=0,"－",IFERROR(ROUND(MIN(20,($AB7-$Y7)/($Y7-$AA7)),2),"－"))) -> 3.07 | AD7: =IF($D7="","",MIN(終値!E7:I7)) -> 1689 | AE7: =IF($D7="","",$X7+(10000-ROW())/100000) -> 35.09993
A8: =IF(終値!A8="","",HYPERLINK("https://kabutan.jp/stock/?code="&終値!A8,"📈")) -> 📈 | B8: =IF(終値!A8="","",終値!A8) -> 5713 | C8: =IF(終値!A8="","",終値!B8) -> 住友鉱山 | D8: =IF(終値!A8="","",終値!E8) -> 9088 | E8: =IF($D8="","",AVERAGE(終値!E8:X8)) -> 7618.65 | F8: =IF($D8="","",STDEVP(終値!E8:X8)) -> 526.84801 | G8: =IF($D8="","",$E8+BB設定!$B$4*$F8) -> 8672.346 | H8: =IF($D8="","",$E8+BB設定!$B$5*$F8) -> 8145.498 | I8: =IF($D8="","",$E8-BB設定!$B$5*$F8) -> 7091.802 | J8: =IF($D8="","",$E8-BB設定!$B$4*$F8) -> 6564.954 | K8: =IF($D8="","",IFERROR(($D8-$J8)/($G8-$J8),"")) -> 1.1972362 | L8: =IF($D8="","",IFERROR(($G8-$J8)/$E8*100,"")) -> 27.660964 | M8: =IF($D8="","",IFERROR(MIN(BB_帯幅!B8:AP8)*100,"")) -> 14.311471 | N8: =IF($L8="","",IF($L8<=$M8*BB設定!$B$7,"スクイーズ★",IF($L8<=$M8*1.3,"収縮","－"))) -> － | O8: =IF($D8="","",IF(AND(BB_帯幅!B8>BB_帯幅!C8,BB_帯幅!C8>BB_帯幅!D8),"拡大↑","縮小↓")) -> 拡大↑ | P8: =IF($D8="","",IF($D8>$G8,"↑+2σ突破",IF($D8<$J8,"↓-2σ割れ",IF($D8>$H8,"+1σ上",IF($D8<$I8,"-1σ下","バンド内"))))) -> ↑+2σ突破 | Q8: =IF($D8="","",IFERROR(100-100/(1+SUMPRODUCT((終値!E8:R8>終値!F8:S8)*(終値!E8:R8-終値!F8:S8))/SUMPRODUCT((終値!E8:R8<終値!F8:S8)*(終値!F8:S8-終値!E8:R8))),100)) -> 67.947702 | R8: =IF($D8="","",IFERROR(100-100/(1+SUMPRODUCT((((高値!E8:R8+安値!E8:R8+終値!E8:R8)/3)>((高値!F8:S8+安値!F8:S8+終値!F8:S8)/3))*((高値!E8:R8+安値!E8:R8+終値!E8:R8)/3)*出来高!E8:R8)/SUMPRODUCT((((高値!E8:R8+安値!E8:R8+終値!E8:R8)/3)<((高値!F8:S8+安値!F8:S8+終値!F8:S8)/3))*((高値!E8:R8+安値!E8:R8+終値!E8:R8)/3)*出来高!E8:R8)),50)) -> 67.781042 | S8: =IF($D8="","",IF(AND(終値!E8<終値!O8,$Q8>(IFERROR(100-100/(1+SUMPRODUCT((終値!O8:AB8>終値!P8:AC8)*(終値!O8:AB8-終値!P8:AC8))/SUMPRODUCT((終値!O8:AB8<終値!P8:AC8)*(終値!P8:AC8-終値!O8:AB8))),100))),"強気div▲",IF(AND(終値!E8>終値!O8,$Q8<(IFERROR(100-100/(1+SUMPRODUCT((終値!O8:AB8>終値!P8:AC8)*(終値!O8:AB8-終値!P8:AC8))/SUMPRODUCT((終値!O8:AB8<終値!P8:AC8)*(終値!P8:AC8-終値!O8:AB8))),100))),"弱気div▼","－"))) -> － | T8: =IF($D8="","",IF($D8>=$H8,"上walk▲",IF($D8<=$I8,"下walk▼","－"))) -> 上walk▲ | U8: =IF(終値!A8="","",BB_スイング!BT8) -> － | V8: =IF($D8="","",IFERROR(出来高!E8/AVERAGE(出来高!E8:I8),"")) -> 1.314457 | W8: =IF($D8="","",IF(AND($D8>$G8,$O8="拡大↑",OR($N8="スクイーズ★",$N8="収縮")),"◎スクイーズブレイク買",IF(AND($D8>=$H8,$R8>=BB設定!$B$10),"○順張り継続(walk)",IF(AND($S8="強気div▲",$D8>$I8,LEFT($U8,4)<>"二番天井"),"○反発(ダイバ)買",IF($U8="二番底W▲","△二番底買(確)",IF($U8="二番底W形成","△二番底形成",IF(LEFT($U8,4)="二番天井","▼二番天井警戒",IF($D8<$J8,"▼-2σ割れ危険",IF(AND($D8>$E8,$K8<0.6,$R8>=50),"・押し目注目",IF($N8="スクイーズ★","☆スクイーズ監視","様子見")))))))))) -> 様子見 | X8: =IF($D8="","",MAX(0,MIN(100,IF($L8<=$M8*1.15,20,IF($L8<=$M8*1.4,10,0))+IF($D8>$G8,20,IF($D8>$H8,12,IF($D8>$E8,5,0)))+IF($O8="拡大↑",10,0)+IF($R8>=80,15,IF($R8>=60,10,IF($R8>=50,5,0)))+IF(AND($Q8>=50,$Q8<=70),10,IF($Q8>70,3,IF($Q8>=40,5,0)))+IF(AND($S8="強気div▲",$T8<>"下walk▼"),15,IF(AND($S8="強気div▲",$T8="下walk▼"),5,0))+IF($T8="上walk▲",5,0)+IF($V8>=2,5,IF($V8>=1.5,3,0))+IF(LEFT($U8,4)="二番天井",-15,0)+IF($D8<$E8,-10,0)+IF($T8="下walk▼",-10,0)+IF($K8<0.2,-5,0)))) -> 55 | Y8: =IF($D8="","",$D8) -> 9088 | Z8: =IF($D8="","",$H8) -> 8145.498 | AA8: =IF($D8="","",IF($D8>$E8,$E8,$AD8)) -> 7618.65 | AB8: =IF($D8="","",IF($D8>$G8,$E8+3*$F8,$G8)) -> 9199.194 | AC8: =IF($D8="","",IF(($Y8-$AA8)<=0,"－",IFERROR(ROUND(MIN(20,($AB8-$Y8)/($Y8-$AA8)),2),"－"))) -> 0.08 | AD8: =IF($D8="","",MIN(終値!E8:I8)) -> 7961 | AE8: =IF($D8="","",$X8+(10000-ROW())/100000) -> 55.09992
A9: =IF(終値!A9="","",HYPERLINK("https://kabutan.jp/stock/?code="&終値!A9,"📈")) -> 📈 | B9: =IF(終値!A9="","",終値!A9) -> 5711 | C9: =IF(終値!A9="","",終値!B9) -> 三菱マテリアル | D9: =IF(終値!A9="","",終値!E9) -> 4457 | E9: =IF($D9="","",AVERAGE(終値!E9:X9)) -> 4147.35 | F9: =IF($D9="","",STDEVP(終値!E9:X9)) -> 134.40658 | G9: =IF($D9="","",$E9+BB設定!$B$4*$F9) -> 4416.1632 | H9: =IF($D9="","",$E9+BB設定!$B$5*$F9) -> 4281.7566 | I9: =IF($D9="","",$E9-BB設定!$B$5*$F9) -> 4012.9434 | J9: =IF($D9="","",$E9-BB設定!$B$4*$F9) -> 3878.5368 | K9: =IF($D9="","",IFERROR(($D9-$J9)/($G9-$J9),"")) -> 1.0759577 | L9: =IF($D9="","",IFERROR(($G9-$J9)/$E9*100,"")) -> 12.963128 | M9: =IF($D9="","",IFERROR(MIN(BB_帯幅!B9:AP9)*100,"")) -> 11.110678 | N9: =IF($L9="","",IF($L9<=$M9*BB設定!$B$7,"スクイーズ★",IF($L9<=$M9*1.3,"収縮","－"))) -> 収縮 | O9: =IF($D9="","",IF(AND(BB_帯幅!B9>BB_帯幅!C9,BB_帯幅!C9>BB_帯幅!D9),"拡大↑","縮小↓")) -> 拡大↑ | P9: =IF($D9="","",IF($D9>$G9,"↑+2σ突破",IF($D9<$J9,"↓-2σ割れ",IF($D9>$H9,"+1σ上",IF($D9<$I9,"-1σ下","バンド内"))))) -> ↑+2σ突破 | Q9: =IF($D9="","",IFERROR(100-100/(1+SUMPRODUCT((終値!E9:R9>終値!F9:S9)*(終値!E9:R9-終値!F9:S9))/SUMPRODUCT((終値!E9:R9<終値!F9:S9)*(終値!F9:S9-終値!E9:R9))),100)) -> 58.128079 | R9: =IF($D9="","",IFERROR(100-100/(1+SUMPRODUCT((((高値!E9:R9+安値!E9:R9+終値!E9:R9)/3)>((高値!F9:S9+安値!F9:S9+終値!F9:S9)/3))*((高値!E9:R9+安値!E9:R9+終値!E9:R9)/3)*出来高!E9:R9)/SUMPRODUCT((((高値!E9:R9+安値!E9:R9+終値!E9:R9)/3)<((高値!F9:S9+安値!F9:S9+終値!F9:S9)/3))*((高値!E9:R9+安値!E9:R9+終値!E9:R9)/3)*出来高!E9:R9)),50)) -> 65.117569 | S9: =IF($D9="","",IF(AND(終値!E9<終値!O9,$Q9>(IFERROR(100-100/(1+SUMPRODUCT((終値!O9:AB9>終値!P9:AC9)*(終値!O9:AB9-終値!P9:AC9))/SUMPRODUCT((終値!O9:AB9<終値!P9:AC9)*(終値!P9:AC9-終値!O9:AB9))),100))),"強気div▲",IF(AND(終値!E9>終値!O9,$Q9<(IFERROR(100-100/(1+SUMPRODUCT((終値!O9:AB9>終値!P9:AC9)*(終値!O9:AB9-終値!P9:AC9))/SUMPRODUCT((終値!O9:AB9<終値!P9:AC9)*(終値!P9:AC9-終値!O9:AB9))),100))),"弱気div▼","－"))) -> － | T9: =IF($D9="","",IF($D9>=$H9,"上walk▲",IF($D9<=$I9,"下walk▼","－"))) -> 上walk▲ | U9: =IF(終値!A9="","",BB_スイング!BT9) -> 二番底W▲ | V9: =IF($D9="","",IFERROR(出来高!E9/AVERAGE(出来高!E9:I9),"")) -> 1.0483189 | W9: =IF($D9="","",IF(AND($D9>$G9,$O9="拡大↑",OR($N9="スクイーズ★",$N9="収縮")),"◎スクイーズブレイク買",IF(AND($D9>=$H9,$R9>=BB設定!$B$10),"○順張り継続(walk)",IF(AND($S9="強気div▲",$D9>$I9,LEFT($U9,4)<>"二番天井"),"○反発(ダイバ)買",IF($U9="二番底W▲","△二番底買(確)",IF($U9="二番底W形成","△二番底形成",IF(LEFT($U9,4)="二番天井","▼二番天井警戒",IF($D9<$J9,"▼-2σ割れ危険",IF(AND($D9>$E9,$K9<0.6,$R9>=50),"・押し目注目",IF($N9="スクイーズ★","☆スクイーズ監視","様子見")))))))))) -> ◎スクイーズブレイク買 | X9: =IF($D9="","",MAX(0,MIN(100,IF($L9<=$M9*1.15,20,IF($L9<=$M9*1.4,10,0))+IF($D9>$G9,20,IF($D9>$H9,12,IF($D9>$E9,5,0)))+IF($O9="拡大↑",10,0)+IF($R9>=80,15,IF($R9>=60,10,IF($R9>=50,5,0)))+IF(AND($Q9>=50,$Q9<=70),10,IF($Q9>70,3,IF($Q9>=40,5,0)))+IF(AND($S9="強気div▲",$T9<>"下walk▼"),15,IF(AND($S9="強気div▲",$T9="下walk▼"),5,0))+IF($T9="上walk▲",5,0)+IF($V9>=2,5,IF($V9>=1.5,3,0))+IF(LEFT($U9,4)="二番天井",-15,0)+IF($D9<$E9,-10,0)+IF($T9="下walk▼",-10,0)+IF($K9<0.2,-5,0)))) -> 65 | Y9: =IF($D9="","",$D9) -> 4457 | Z9: =IF($D9="","",$H9) -> 4281.7566 | AA9: =IF($D9="","",IF($D9>$E9,$E9,$AD9)) -> 4147.35 | AB9: =IF($D9="","",IF($D9>$G9,$E9+3*$F9,$G9)) -> 4550.5697 | AC9: =IF($D9="","",IF(($Y9-$AA9)<=0,"－",IFERROR(ROUND(MIN(20,($AB9-$Y9)/($Y9-$AA9)),2),"－"))) -> 0.3 | AD9: =IF($D9="","",MIN(終値!E9:I9)) -> 4144 | AE9: =IF($D9="","",$X9+(10000-ROW())/100000) -> 65.09991
A10: =IF(終値!A10="","",HYPERLINK("https://kabutan.jp/stock/?code="&終値!A10,"📈")) -> 📈 | B10: =IF(終値!A10="","",終値!A10) -> 5714 | C10: =IF(終値!A10="","",終値!B10) -> ＤＯＷＡホールディングス | D10: =IF(終値!A10="","",終値!E10) -> 8907 | E10: =IF($D10="","",AVERAGE(終値!E10:X10)) -> 8302.05 | F10: =IF($D10="","",STDEVP(終値!E10:X10)) -> 226.74181 | G10: =IF($D10="","",$E10+BB設定!$B$4*$F10) -> 8755.5336 | H10: =IF($D10="","",$E10+BB設定!$B$5*$F10) -> 8528.7918 | I10: =IF($D10="","",$E10-BB設定!$B$5*$F10) -> 8075.3082 | J10: =IF($D10="","",$E10-BB設定!$B$4*$F10) -> 7848.5664 | K10: =IF($D10="","",IFERROR(($D10-$J10)/($G10-$J10),"")) -> 1.1670031 | L10: =IF($D10="","",IFERROR(($G10-$J10)/$E10*100,"")) -> 10.924618 | M10: =IF($D10="","",IFERROR(MIN(BB_帯幅!B10:AP10)*100,"")) -> 8.8162778 | N10: =IF($L10="","",IF($L10<=$M10*BB設定!$B$7,"スクイーズ★",IF($L10<=$M10*1.3,"収縮","－"))) -> 収縮 | O10: =IF($D10="","",IF(AND(BB_帯幅!B10>BB_帯幅!C10,BB_帯幅!C10>BB_帯幅!D10),"拡大↑","縮小↓")) -> 縮小↓ | P10: =IF($D10="","",IF($D10>$G10,"↑+2σ突破",IF($D10<$J10,"↓-2σ割れ",IF($D10>$H10,"+1σ上",IF($D10<$I10,"-1σ下","バンド内"))))) -> ↑+2σ突破 | Q10: =IF($D10="","",IFERROR(100-100/(1+SUMPRODUCT((終値!E10:R10>終値!F10:S10)*(終値!E10:R10-終値!F10:S10))/SUMPRODUCT((終値!E10:R10<終値!F10:S10)*(終値!F10:S10-終値!E10:R10))),100)) -> 59.00581 | R10: =IF($D10="","",IFERROR(100-100/(1+SUMPRODUCT((((高値!E10:R10+安値!E10:R10+終値!E10:R10)/3)>((高値!F10:S10+安値!F10:S10+終値!F10:S10)/3))*((高値!E10:R10+安値!E10:R10+終値!E10:R10)/3)*出来高!E10:R10)/SUMPRODUCT((((高値!E10:R10+安値!E10:R10+終値!E10:R10)/3)<((高値!F10:S10+安値!F10:S10+終値!F10:S10)/3))*((高値!E10:R10+安値!E10:R10+終値!E10:R10)/3)*出来高!E10:R10)),50)) -> 65.398996 | S10: =IF($D10="","",IF(AND(終値!E10<終値!O10,$Q10>(IFERROR(100-100/(1+SUMPRODUCT((終値!O10:AB10>終値!P10:AC10)*(終値!O10:AB10-終値!P10:AC10))/SUMPRODUCT((終値!O10:AB10<終値!P10:AC10)*(終値!P10:AC10-終値!O10:AB10))),100))),"強気div▲",IF(AND(終値!E10>終値!O10,$Q10<(IFERROR(100-100/(1+SUMPRODUCT((終値!O10:AB10>終値!P10:AC10)*(終値!O10:AB10-終値!P10:AC10))/SUMPRODUCT((終値!O10:AB10<終値!P10:AC10)*(終値!P10:AC10-終値!O10:AB10))),100))),"弱気div▼","－"))) -> － | T10: =IF($D10="","",IF($D10>=$H10,"上walk▲",IF($D10<=$I10,"下walk▼","－"))) -> 上walk▲ | U10: =IF(終値!A10="","",BB_スイング!BT10) -> 二番底W▲ | V10: =IF($D10="","",IFERROR(出来高!E10/AVERAGE(出来高!E10:I10),"")) -> 1.5550805 | W10: =IF($D10="","",IF(AND($D10>$G10,$O10="拡大↑",OR($N10="スクイーズ★",$N10="収縮")),"◎スクイーズブレイク買",IF(AND($D10>=$H10,$R10>=BB設定!$B$10),"○順張り継続(walk)",IF(AND($S10="強気div▲",$D10>$I10,LEFT($U10,4)<>"二番天井"),"○反発(ダイバ)買",IF($U10="二番底W▲","△二番底買(確)",IF($U10="二番底W形成","△二番底形成",IF(LEFT($U10,4)="二番天井","▼二番天井警戒",IF($D10<$J10,"▼-2σ割れ危険",IF(AND($D10>$E10,$K10<0.6,$R10>=50),"・押し目注目",IF($N10="スクイーズ★","☆スクイーズ監視","様子見")))))))))) -> △二番底買(確) | X10: =IF($D10="","",MAX(0,MIN(100,IF($L10<=$M10*1.15,20,IF($L10<=$M10*1.4,10,0))+IF($D10>$G10,20,IF($D10>$H10,12,IF($D10>$E10,5,0)))+IF($O10="拡大↑",10,0)+IF($R10>=80,15,IF($R10>=60,10,IF($R10>=50,5,0)))+IF(AND($Q10>=50,$Q10<=70),10,IF($Q10>70,3,IF($Q10>=40,5,0)))+IF(AND($S10="強気div▲",$T10<>"下walk▼"),15,IF(AND($S10="強気div▲",$T10="下walk▼"),5,0))+IF($T10="上walk▲",5,0)+IF($V10>=2,5,IF($V10>=1.5,3,0))+IF(LEFT($U10,4)="二番天井",-15,0)+IF($D10<$E10,-10,0)+IF($T10="下walk▼",-10,0)+IF($K10<0.2,-5,0)))) -> 58 | Y10: =IF($D10="","",$D10) -> 8907 | Z10: =IF($D10="","",$H10) -> 8528.7918 | AA10: =IF($D10="","",IF($D10>$E10,$E10,$AD10)) -> 8302.05 | AB10: =IF($D10="","",IF($D10>$G10,$E10+3*$F10,$G10)) -> 8982.2754 | AC10: =IF($D10="","",IF(($Y10-$AA10)<=0,"－",IFERROR(ROUND(MIN(20,($AB10-$Y10)/($Y10-$AA10)),2),"－"))) -> 0.12 | AD10: =IF($D10="","",MIN(終値!E10:I10)) -> 8159 | AE10: =IF($D10="","",$X10+(10000-ROW())/100000) -> 58.0999
A11: =IF(終値!A11="","",HYPERLINK("https://kabutan.jp/stock/?code="&終値!A11,"📈")) -> 📈 | B11: =IF(終値!A11="","",終値!A11) -> 6701 | C11: =IF(終値!A11="","",終値!B11) -> 日本電気 | D11: =IF(終値!A11="","",終値!E11) -> 4690 | E11: =IF($D11="","",AVERAGE(終値!E11:X11)) -> 4488.8 | F11: =IF($D11="","",STDEVP(終値!E11:X11)) -> 193.28337 | G11: =IF($D11="","",$E11+BB設定!$B$4*$F11) -> 4875.3667 | H11: =IF($D11="","",$E11+BB設定!$B$5*$F11) -> 4682.0834 | I11: =IF($D11="","",$E11-BB設定!$B$5*$F11) -> 4295.5166 | J11: =IF($D11="","",$E11-BB設定!$B$4*$F11) -> 4102.2333 | K11: =IF($D11="","",IFERROR(($D11-$J11)/($G11-$J11),"")) -> 0.76023967 | L11: =IF($D11="","",IFERROR(($G11-$J11)/$E11*100,"")) -> 17.223611 | M11: =IF($D11="","",IFERROR(MIN(BB_帯幅!B11:AP11)*100,"")) -> 10.839877 | N11: =IF($L11="","",IF($L11<=$M11*BB設定!$B$7,"スクイーズ★",IF($L11<=$M11*1.3,"収縮","－"))) -> － | O11: =IF($D11="","",IF(AND(BB_帯幅!B11>BB_帯幅!C11,BB_帯幅!C11>BB_帯幅!D11),"拡大↑","縮小↓")) -> 拡大↑ | P11: =IF($D11="","",IF($D11>$G11,"↑+2σ突破",IF($D11<$J11,"↓-2σ割れ",IF($D11>$H11,"+1σ上",IF($D11<$I11,"-1σ下","バンド内"))))) -> +1σ上 | Q11: =IF($D11="","",IFERROR(100-100/(1+SUMPRODUCT((終値!E11:R11>終値!F11:S11)*(終値!E11:R11-終値!F11:S11))/SUMPRODUCT((終値!E11:R11<終値!F11:S11)*(終値!F11:S11-終値!E11:R11))),100)) -> 57.955272 | R11: =IF($D11="","",IFERROR(100-100/(1+SUMPRODUCT((((高値!E11:R11+安値!E11:R11+終値!E11:R11)/3)>((高値!F11:S11+安値!F11:S11+終値!F11:S11)/3))*((高値!E11:R11+安値!E11:R11+終値!E11:R11)/3)*出来高!E11:R11)/SUMPRODUCT((((高値!E11:R11+安値!E11:R11+終値!E11:R11)/3)<((高値!F11:S11+安値!F11:S11+終値!F11:S11)/3))*((高値!E11:R11+安値!E11:R11+終値!E11:R11)/3)*出来高!E11:R11)),50)) -> 55.489095 | S11: =IF($D11="","",IF(AND(終値!E11<終値!O11,$Q11>(IFERROR(100-100/(1+SUMPRODUCT((終値!O11:AB11>終値!P11:AC11)*(終値!O11:AB11-終値!P11:AC11))/SUMPRODUCT((終値!O11:AB11<終値!P11:AC11)*(終値!P11:AC11-終値!O11:AB11))),100))),"強気div▲",IF(AND(終値!E11>終値!O11,$Q11<(IFERROR(100-100/(1+SUMPRODUCT((終値!O11:AB11>終値!P11:AC11)*(終値!O11:AB11-終値!P11:AC11))/SUMPRODUCT((終値!O11:AB11<終値!P11:AC11)*(終値!P11:AC11-終値!O11:AB11))),100))),"弱気div▼","－"))) -> － | T11: =IF($D11="","",IF($D11>=$H11,"上walk▲",IF($D11<=$I11,"下walk▼","－"))) -> 上walk▲ | U11: =IF(終値!A11="","",BB_スイング!BT11) -> － | V11: =IF($D11="","",IFERROR(出来高!E11/AVERAGE(出来高!E11:I11),"")) -> 0.75985058 | W11: =IF($D11="","",IF(AND($D11>$G11,$O11="拡大↑",OR($N11="スクイーズ★",$N11="収縮")),"◎スクイーズブレイク買",IF(AND($D11>=$H11,$R11>=BB設定!$B$10),"○順張り継続(walk)",IF(AND($S11="強気div▲",$D11>$I11,LEFT($U11,4)<>"二番天井"),"○反発(ダイバ)買",IF($U11="二番底W▲","△二番底買(確)",IF($U11="二番底W形成","△二番底形成",IF(LEFT($U11,4)="二番天井","▼二番天井警戒",IF($D11<$J11,"▼-2σ割れ危険",IF(AND($D11>$E11,$K11<0.6,$R11>=50),"・押し目注目",IF($N11="スクイーズ★","☆スクイーズ監視","様子見")))))))))) -> 様子見 | X11: =IF($D11="","",MAX(0,MIN(100,IF($L11<=$M11*1.15,20,IF($L11<=$M11*1.4,10,0))+IF($D11>$G11,20,IF($D11>$H11,12,IF($D11>$E11,5,0)))+IF($O11="拡大↑",10,0)+IF($R11>=80,15,IF($R11>=60,10,IF($R11>=50,5,0)))+IF(AND($Q11>=50,$Q11<=70),10,IF($Q11>70,3,IF($Q11>=40,5,0)))+IF(AND($S11="強気div▲",$T11<>"下walk▼"),15,IF(AND($S11="強気div▲",$T11="下walk▼"),5,0))+IF($T11="上walk▲",5,0)+IF($V11>=2,5,IF($V11>=1.5,3,0))+IF(LEFT($U11,4)="二番天井",-15,0)+IF($D11<$E11,-10,0)+IF($T11="下walk▼",-10,0)+IF($K11<0.2,-5,0)))) -> 42 | Y11: =IF($D11="","",$D11) -> 4690 | Z11: =IF($D11="","",$H11) -> 4682.0834 | AA11: =IF($D11="","",IF($D11>$E11,$E11,$AD11)) -> 4488.8 | AB11: =IF($D11="","",IF($D11>$G11,$E11+3*$F11,$G11)) -> 4875.3667 | AC11: =IF($D11="","",IF(($Y11-$AA11)<=0,"－",IFERROR(ROUND(MIN(20,($AB11-$Y11)/($Y11-$AA11)),2),"－"))) -> 0.92 | AD11: =IF($D11="","",MIN(終値!E11:I11)) -> 4598 | AE11: =IF($D11="","",$X11+(10000-ROW())/100000) -> 42.09989
A12: =IF(終値!A12="","",HYPERLINK("https://kabutan.jp/stock/?code="&終値!A12,"📈")) -> 📈 | B12: =IF(終値!A12="","",終値!A12) -> 1605 | C12: =IF(終値!A12="","",終値!B12) -> ＩＮＰＥＸ | D12: =IF(終値!A12="","",終値!E12) -> 3460 | E12: =IF($D12="","",AVERAGE(終値!E12:X12)) -> 3529.5 | F12: =IF($D12="","",STDEVP(終値!E12:X12)) -> 111.868 | G12: =IF($D12="","",$E12+BB設定!$B$4*$F12) -> 3753.236 | H12: =IF($D12="","",$E12+BB設定!$B$5*$F12) -> 3641.368 | I12: =IF($D12="","",$E12-BB設定!$B$5*$F12) -> 3417.632 | J12: =IF($D12="","",$E12-BB設定!$B$4*$F12) -> 3305.764 | K12: =IF($D12="","",IFERROR(($D12-$J12)/($G12-$J12),"")) -> 0.34468302 | L12: =IF($D12="","",IFERROR(($G12-$J12)/$E12*100,"")) -> 12.678057 | M12: =IF($D12="","",IFERROR(MIN(BB_帯幅!B12:AP12)*100,"")) -> 10.063584 | N12: =IF($L12="","",IF($L12<=$M12*BB設定!$B$7,"スクイーズ★",IF($L12<=$M12*1.3,"収縮","－"))) -> 収縮 | O12: =IF($D12="","",IF(AND(BB_帯幅!B12>BB_帯幅!C12,BB_帯幅!C12>BB_帯幅!D12),"拡大↑","縮小↓")) -> 縮小↓ | P12: =IF($D12="","",IF($D12>$G12,"↑+2σ突破",IF($D12<$J12,"↓-2σ割れ",IF($D12>$H12,"+1σ上",IF($D12<$I12,"-1σ下","バンド内"))))) -> バンド内 | Q12: =IF($D12="","",IFERROR(100-100/(1+SUMPRODUCT((終値!E12:R12>終値!F12:S12)*(終値!E12:R12-終値!F12:S12))/SUMPRODUCT((終値!E12:R12<終値!F12:S12)*(終値!F12:S12-終値!E12:R12))),100)) -> 51.640212 | R12: =IF($D12="","",IFERROR(100-100/(1+SUMPRODUCT((((高値!E12:R12+安値!E12:R12+終値!E12:R12)/3)>((高値!F12:S12+安値!F12:S12+終値!F12:S12)/3))*((高値!E12:R12+安値!E12:R12+終値!E12:R12)/3)*出来高!E12:R12)/SUMPRODUCT((((高値!E12:R12+安値!E12:R12+終値!E12:R12)/3)<((高値!F12:S12+安値!F12:S12+終値!F12:S12)/3))*((高値!E12:R12+安値!E12:R12+終値!E12:R12)/3)*出来高!E12:R12)),50)) -> 53.276343 | S12: =IF($D12="","",IF(AND(終値!E12<終値!O12,$Q12>(IFERROR(100-100/(1+SUMPRODUCT((終値!O12:AB12>終値!P12:AC12)*(終値!O12:AB12-終値!P12:AC12))/SUMPRODUCT((終値!O12:AB12<終値!P12:AC12)*(終値!P12:AC12-終値!O12:AB12))),100))),"強気div▲",IF(AND(終値!E12>終値!O12,$Q12<(IFERROR(100-100/(1+SUMPRODUCT((終値!O12:AB12>終値!P12:AC12)*(終値!O12:AB12-終値!P12:AC12))/SUMPRODUCT((終値!O12:AB12<終値!P12:AC12)*(終値!P12:AC12-終値!O12:AB12))),100))),"弱気div▼","－"))) -> － | T12: =IF($D12="","",IF($D12>=$H12,"上walk▲",IF($D12<=$I12,"下walk▼","－"))) -> － | U12: =IF(終値!A12="","",BB_スイング!BT12) -> 二番天井M▼ | V12: =IF($D12="","",IFERROR(出来高!E12/AVERAGE(出来高!E12:I12),"")) -> 0.94776591 | W12: =IF($D12="","",IF(AND($D12>$G12,$O12="拡大↑",OR($N12="スクイーズ★",$N12="収縮")),"◎スクイーズブレイク買",IF(AND($D12>=$H12,$R12>=BB設定!$B$10),"○順張り継続(walk)",IF(AND($S12="強気div▲",$D12>$I12,LEFT($U12,4)<>"二番天井"),"○反発(ダイバ)買",IF($U12="二番底W▲","△二番底買(確)",IF($U12="二番底W形成","△二番底形成",IF(LEFT($U12,4)="二番天井","▼二番天井警戒",IF($D12<$J12,"▼-2σ割れ危険",IF(AND($D12>$E12,$K12<0.6,$R12>=50),"・押し目注目",IF($N12="スクイーズ★","☆スクイーズ監視","様子見")))))))))) -> ▼二番天井警戒 | X12: =IF($D12="","",MAX(0,MIN(100,IF($L12<=$M12*1.15,20,IF($L12<=$M12*1.4,10,0))+IF($D12>$G12,20,IF($D12>$H12,12,IF($D12>$E12,5,0)))+IF($O12="拡大↑",10,0)+IF($R12>=80,15,IF($R12>=60,10,IF($R12>=50,5,0)))+IF(AND($Q12>=50,$Q12<=70),10,IF($Q12>70,3,IF($Q12>=40,5,0)))+IF(AND($S12="強気div▲",$T12<>"下walk▼"),15,IF(AND($S12="強気div▲",$T12="下walk▼"),5,0))+IF($T12="上walk▲",5,0)+IF($V12>=2,5,IF($V12>=1.5,3,0))+IF(LEFT($U12,4)="二番天井",-15,0)+IF($D12<$E12,-10,0)+IF($T12="下walk▼",-10,0)+IF($K12<0.2,-5,0)))) -> 0 | Y12: =IF($D12="","",$D12) -> 3460 | Z12: =IF($D12="","",$H12) -> 3641.368 | AA12: =IF($D12="","",IF($D12>$E12,$E12,$AD12)) -> 3394 | AB12: =IF($D12="","",IF($D12>$G12,$E12+3*$F12,$G12)) -> 3753.236 | AC12: =IF($D12="","",IF(($Y12-$AA12)<=0,"－",IFERROR(ROUND(MIN(20,($AB12-$Y12)/($Y12-$AA12)),2),"－"))) -> 4.44 | AD12: =IF($D12="","",MIN(終値!E12:I12)) -> 3394 | AE12: =IF($D12="","",$X12+(10000-ROW())/100000) -> 0.09988
A13: =IF(終値!A13="","",HYPERLINK("https://kabutan.jp/stock/?code="&終値!A13,"📈")) -> 📈 | B13: =IF(終値!A13="","",終値!A13) -> 5703 | C13: =IF(終値!A13="","",終値!B13) -> 日本軽金属ＨＤ | D13: =IF(終値!A13="","",終値!E13) -> 2936 | E13: =IF($D13="","",AVERAGE(終値!E13:X13)) -> 2717.3 | F13: =IF($D13="","",STDEVP(終値!E13:X13)) -> 93.442014 | G13: =IF($D13="","",$E13+BB設定!$B$4*$F13) -> 2904.184 | H13: =IF($D13="","",$E13+BB設定!$B$5*$F13) -> 2810.742 | I13: =IF($D13="","",$E13-BB設定!$B$5*$F13) -> 2623.858 | J13: =IF($D13="","",$E13-BB設定!$B$4*$F13) -> 2530.416 | K13: =IF($D13="","",IFERROR(($D13-$J13)/($G13-$J13),"")) -> 1.0851222 | L13: =IF($D13="","",IFERROR(($G13-$J13)/$E13*100,"")) -> 13.755127 | M13: =IF($D13="","",IFERROR(MIN(BB_帯幅!B13:AP13)*100,"")) -> 6.6889406 | N13: =IF($L13="","",IF($L13<=$M13*BB設定!$B$7,"スクイーズ★",IF($L13<=$M13*1.3,"収縮","－"))) -> － | O13: =IF($D13="","",IF(AND(BB_帯幅!B13>BB_帯幅!C13,BB_帯幅!C13>BB_帯幅!D13),"拡大↑","縮小↓")) -> 拡大↑ | P13: =IF($D13="","",IF($D13>$G13,"↑+2σ突破",IF($D13<$J13,"↓-2σ割れ",IF($D13>$H13,"+1σ上",IF($D13<$I13,"-1σ下","バンド内"))))) -> ↑+2σ突破 | Q13: =IF($D13="","",IFERROR(100-100/(1+SUMPRODUCT((終値!E13:R13>終値!F13:S13)*(終値!E13:R13-終値!F13:S13))/SUMPRODUCT((終値!E13:R13<終値!F13:S13)*(終値!F13:S13-終値!E13:R13))),100)) -> 62.139423 | R13: =IF($D13="","",IFERROR(100-100/(1+SUMPRODUCT((((高値!E13:R13+安値!E13:R13+終値!E13:R13)/3)>((高値!F13:S13+安値!F13:S13+終値!F13:S13)/3))*((高値!E13:R13+安値!E13:R13+終値!E13:R13)/3)*出来高!E13:R13)/SUMPRODUCT((((高値!E13:R13+安値!E13:R13+終値!E13:R13)/3)<((高値!F13:S13+安値!F13:S13+終値!F13:S13)/3))*((高値!E13:R13+安値!E13:R13+終値!E13:R13)/3)*出来高!E13:R13)),50)) -> 60.290027 | S13: =IF($D13="","",IF(AND(終値!E13<終値!O13,$Q13>(IFERROR(100-100/(1+SUMPRODUCT((終値!O13:AB13>終値!P13:AC13)*(終値!O13:AB13-終値!P13:AC13))/SUMPRODUCT((終値!O13:AB13<終値!P13:AC13)*(終値!P13:AC13-終値!O13:AB13))),100))),"強気div▲",IF(AND(終値!E13>終値!O13,$Q13<(IFERROR(100-100/(1+SUMPRODUCT((終値!O13:AB13>終値!P13:AC13)*(終値!O13:AB13-終値!P13:AC13))/SUMPRODUCT((終値!O13:AB13<終値!P13:AC13)*(終値!P13:AC13-終値!O13:AB13))),100))),"弱気div▼","－"))) -> － | T13: =IF($D13="","",IF($D13>=$H13,"上walk▲",IF($D13<=$I13,"下walk▼","－"))) -> 上walk▲ | U13: =IF(終値!A13="","",BB_スイング!BT13) -> 二番底W▲ | V13: =IF($D13="","",IFERROR(出来高!E13/AVERAGE(出来高!E13:I13),"")) -> 0.45241158 | W13: =IF($D13="","",IF(AND($D13>$G13,$O13="拡大↑",OR($N13="スクイーズ★",$N13="収縮")),"◎スクイーズブレイク買",IF(AND($D13>=$H13,$R13>=BB設定!$B$10),"○順張り継続(walk)",IF(AND($S13="強気div▲",$D13>$I13,LEFT($U13,4)<>"二番天井"),"○反発(ダイバ)買",IF($U13="二番底W▲","△二番底買(確)",IF($U13="二番底W形成","△二番底形成",IF(LEFT($U13,4)="二番天井","▼二番天井警戒",IF($D13<$J13,"▼-2σ割れ危険",IF(AND($D13>$E13,$K13<0.6,$R13>=50),"・押し目注目",IF($N13="スクイーズ★","☆スクイーズ監視","様子見")))))))))) -> △二番底買(確) | X13: =IF($D13="","",MAX(0,MIN(100,IF($L13<=$M13*1.15,20,IF($L13<=$M13*1.4,10,0))+IF($D13>$G13,20,IF($D13>$H13,12,IF($D13>$E13,5,0)))+IF($O13="拡大↑",10,0)+IF($R13>=80,15,IF($R13>=60,10,IF($R13>=50,5,0)))+IF(AND($Q13>=50,$Q13<=70),10,IF($Q13>70,3,IF($Q13>=40,5,0)))+IF(AND($S13="強気div▲",$T13<>"下walk▼"),15,IF(AND($S13="強気div▲",$T13="下walk▼"),5,0))+IF($T13="上walk▲",5,0)+IF($V13>=2,5,IF($V13>=1.5,3,0))+IF(LEFT($U13,4)="二番天井",-15,0)+IF($D13<$E13,-10,0)+IF($T13="下walk▼",-10,0)+IF($K13<0.2,-5,0)))) -> 55 | Y13: =IF($D13="","",$D13) -> 2936 | Z13: =IF($D13="","",$H13) -> 2810.742 | AA13: =IF($D13="","",IF($D13>$E13,$E13,$AD13)) -> 2717.3 | AB13: =IF($D13="","",IF($D13>$G13,$E13+3*$F13,$G13)) -> 2997.626 | AC13: =IF($D13="","",IF(($Y13-$AA13)<=0,"－",IFERROR(ROUND(MIN(20,($AB13-$Y13)/($Y13-$AA13)),2),"－"))) -> 0.28 | AD13: =IF($D13="","",MIN(終値!E13:I13)) -> 2715 | AE13: =IF($D13="","",$X13+(10000-ROW())/100000) -> 55.09987
A14: =IF(終値!A14="","",HYPERLINK("https://kabutan.jp/stock/?code="&終値!A14,"📈")) -> 📈 | B14: =IF(終値!A14="","",終値!A14) -> 8002 | C14: =IF(終値!A14="","",終値!B14) -> 丸紅 | D14: =IF(終値!A14="","",終値!E14) -> 4936 | E14: =IF($D14="","",AVERAGE(終値!E14:X14)) -> 5108.3 | F14: =IF($D14="","",STDEVP(終値!E14:X14)) -> 181.93875 | G14: =IF($D14="","",$E14+BB設定!$B$4*$F14) -> 5472.1775 | H14: =IF($D14="","",$E14+BB設定!$B$5*$F14) -> 5290.2388 | I14: =IF($D14="","",$E14-BB設定!$B$5*$F14) -> 4926.3612 | J14: =IF($D14="","",$E14-BB設定!$B$4*$F14) -> 4744.4225 | K14: =IF($D14="","",IFERROR(($D14-$J14)/($G14-$J14),"")) -> 0.2632445 | L14: =IF($D14="","",IFERROR(($G14-$J14)/$E14*100,"")) -> 14.246521 | M14: =IF($D14="","",IFERROR(MIN(BB_帯幅!B14:AP14)*100,"")) -> 9.1981323 | N14: =IF($L14="","",IF($L14<=$M14*BB設定!$B$7,"スクイーズ★",IF($L14<=$M14*1.3,"収縮","－"))) -> － | O14: =IF($D14="","",IF(AND(BB_帯幅!B14>BB_帯幅!C14,BB_帯幅!C14>BB_帯幅!D14),"拡大↑","縮小↓")) -> 拡大↑ | P14: =IF($D14="","",IF($D14>$G14,"↑+2σ突破",IF($D14<$J14,"↓-2σ割れ",IF($D14>$H14,"+1σ上",IF($D14<$I14,"-1σ下","バンド内"))))) -> バンド内 | Q14: =IF($D14="","",IFERROR(100-100/(1+SUMPRODUCT((終値!E14:R14>終値!F14:S14)*(終値!E14:R14-終値!F14:S14))/SUMPRODUCT((終値!E14:R14<終値!F14:S14)*(終値!F14:S14-終値!E14:R14))),100)) -> 44.117647 | R14: =IF($D14="","",IFERROR(100-100/(1+SUMPRODUCT((((高値!E14:R14+安値!E14:R14+終値!E14:R14)/3)>((高値!F14:S14+安値!F14:S14+終値!F14:S14)/3))*((高値!E14:R14+安値!E14:R14+終値!E14:R14)/3)*出来高!E14:R14)/SUMPRODUCT((((高値!E14:R14+安値!E14:R14+終値!E14:R14)/3)<((高値!F14:S14+安値!F14:S14+終値!F14:S14)/3))*((高値!E14:R14+安値!E14:R14+終値!E14:R14)/3)*出来高!E14:R14)),50)) -> 38.268576 | S14: =IF($D14="","",IF(AND(終値!E14<終値!O14,$Q14>(IFERROR(100-100/(1+SUMPRODUCT((終値!O14:AB14>終値!P14:AC14)*(終値!O14:AB14-終値!P14:AC14))/SUMPRODUCT((終値!O14:AB14<終値!P14:AC14)*(終値!P14:AC14-終値!O14:AB14))),100))),"強気div▲",IF(AND(終値!E14>終値!O14,$Q14<(IFERROR(100-100/(1+SUMPRODUCT((終値!O14:AB14>終値!P14:AC14)*(終値!O14:AB14-終値!P14:AC14))/SUMPRODUCT((終値!O14:AB14<終値!P14:AC14)*(終値!P14:AC14-終値!O14:AB14))),100))),"弱気div▼","－"))) -> － | T14: =IF($D14="","",IF($D14>=$H14,"上walk▲",IF($D14<=$I14,"下walk▼","－"))) -> － | U14: =IF(終値!A14="","",BB_スイング!BT14) -> 二番底W形成 | V14: =IF($D14="","",IFERROR(出来高!E14/AVERAGE(出来高!E14:I14),"")) -> 0.70353032 | W14: =IF($D14="","",IF(AND($D14>$G14,$O14="拡大↑",OR($N14="スクイーズ★",$N14="収縮")),"◎スクイーズブレイク買",IF(AND($D14>=$H14,$R14>=BB設定!$B$10),"○順張り継続(walk)",IF(AND($S14="強気div▲",$D14>$I14,LEFT($U14,4)<>"二番天井"),"○反発(ダイバ)買",IF($U14="二番底W▲","△二番底買(確)",IF($U14="二番底W形成","△二番底形成",IF(LEFT($U14,4)="二番天井","▼二番天井警戒",IF($D14<$J14,"▼-2σ割れ危険",IF(AND($D14>$E14,$K14<0.6,$R14>=50),"・押し目注目",IF($N14="スクイーズ★","☆スクイーズ監視","様子見")))))))))) -> △二番底形成 | X14: =IF($D14="","",MAX(0,MIN(100,IF($L14<=$M14*1.15,20,IF($L14<=$M14*1.4,10,0))+IF($D14>$G14,20,IF($D14>$H14,12,IF($D14>$E14,5,0)))+IF($O14="拡大↑",10,0)+IF($R14>=80,15,IF($R14>=60,10,IF($R14>=50,5,0)))+IF(AND($Q14>=50,$Q14<=70),10,IF($Q14>70,3,IF($Q14>=40,5,0)))+IF(AND($S14="強気div▲",$T14<>"下walk▼"),15,IF(AND($S14="強気div▲",$T14="下walk▼"),5,0))+IF($T14="上walk▲",5,0)+IF($V14>=2,5,IF($V14>=1.5,3,0))+IF(LEFT($U14,4)="二番天井",-15,0)+IF($D14<$E14,-10,0)+IF($T14="下walk▼",-10,0)+IF($K14<0.2,-5,0)))) -> 5 | Y14: =IF($D14="","",$D14) -> 4936 | Z14: =IF($D14="","",$H14) -> 5290.2388 | AA14: =IF($D14="","",IF($D14>$E14,$E14,$AD14)) -> 4862 | AB14: =IF($D14="","",IF($D14>$G14,$E14+3*$F14,$G14)) -> 5472.1775 | AC14: =IF($D14="","",IF(($Y14-$AA14)<=0,"－",IFERROR(ROUND(MIN(20,($AB14-$Y14)/($Y14-$AA14)),2),"－"))) -> 7.25 | AD14: =IF($D14="","",MIN(終値!E14:I14)) -> 4862 | AE14: =IF($D14="","",$X14+(10000-ROW())/100000) -> 5.09986
A15: =IF(終値!A15="","",HYPERLINK("https://kabutan.jp/stock/?code="&終値!A15,"📈")) -> 📈 | B15: =IF(終値!A15="","",終値!A15) -> 5021 | C15: =IF(終値!A15="","",終値!B15) -> コスモエネルギーＨＬＤＧＳ | D15: =IF(終値!A15="","",終値!E15) -> 3811 | E15: =IF($D15="","",AVERAGE(終値!E15:X15)) -> 3890.9 | F15: =IF($D15="","",STDEVP(終値!E15:X15)) -> 77.093385 | G15: =IF($D15="","",$E15+BB設定!$B$4*$F15) -> 4045.0868 | H15: =IF($D15="","",$E15+BB設定!$B$5*$F15) -> 3967.9934 | I15: =IF($D15="","",$E15-BB設定!$B$5*$F15) -> 3813.8066 | J15: =IF($D15="","",$E15-BB設定!$B$4*$F15) -> 3736.7132 | K15: =IF($D15="","",IFERROR(($D15-$J15)/($G15-$J15),"")) -> 0.24089865 | L15: =IF($D15="","",IFERROR(($G15-$J15)/$E15*100,"")) -> 7.9255067 | M15: =IF($D15="","",IFERROR(MIN(BB_帯幅!B15:AP15)*100,"")) -> 6.1448439 | N15: =IF($L15="","",IF($L15<=$M15*BB設定!$B$7,"スクイーズ★",IF($L15<=$M15*1.3,"収縮","－"))) -> 収縮 | O15: =IF($D15="","",IF(AND(BB_帯幅!B15>BB_帯幅!C15,BB_帯幅!C15>BB_帯幅!D15),"拡大↑","縮小↓")) -> 拡大↑ | P15: =IF($D15="","",IF($D15>$G15,"↑+2σ突破",IF($D15<$J15,"↓-2σ割れ",IF($D15>$H15,"+1σ上",IF($D15<$I15,"-1σ下","バンド内"))))) -> -1σ下 | Q15: =IF($D15="","",IFERROR(100-100/(1+SUMPRODUCT((終値!E15:R15>終値!F15:S15)*(終値!E15:R15-終値!F15:S15))/SUMPRODUCT((終値!E15:R15<終値!F15:S15)*(終値!F15:S15-終値!E15:R15))),100)) -> 50.082102 | R15: =IF($D15="","",IFERROR(100-100/(1+SUMPRODUCT((((高値!E15:R15+安値!E15:R15+終値!E15:R15)/3)>((高値!F15:S15+安値!F15:S15+終値!F15:S15)/3))*((高値!E15:R15+安値!E15:R15+終値!E15:R15)/3)*出来高!E15:R15)/SUMPRODUCT((((高値!E15:R15+安値!E15:R15+終値!E15:R15)/3)<((高値!F15:S15+安値!F15:S15+終値!F15:S15)/3))*((高値!E15:R15+安値!E15:R15+終値!E15:R15)/3)*出来高!E15:R15)),50)) -> 52.491576 | S15: =IF($D15="","",IF(AND(終値!E15<終値!O15,$Q15>(IFERROR(100-100/(1+SUMPRODUCT((終値!O15:AB15>終値!P15:AC15)*(終値!O15:AB15-終値!P15:AC15))/SUMPRODUCT((終値!O15:AB15<終値!P15:AC15)*(終値!P15:AC15-終値!O15:AB15))),100))),"強気div▲",IF(AND(終値!E15>終値!O15,$Q15<(IFERROR(100-100/(1+SUMPRODUCT((終値!O15:AB15>終値!P15:AC15)*(終値!O15:AB15-終値!P15:AC15))/SUMPRODUCT((終値!O15:AB15<終値!P15:AC15)*(終値!P15:AC15-終値!O15:AB15))),100))),"弱気div▼","－"))) -> － | T15: =IF($D15="","",IF($D15>=$H15,"上walk▲",IF($D15<=$I15,"下walk▼","－"))) -> 下walk▼ | U15: =IF(終値!A15="","",BB_スイング!BT15) -> 二番底W形成 | V15: =IF($D15="","",IFERROR(出来高!E15/AVERAGE(出来高!E15:I15),"")) -> 0.76096349 | W15: =IF($D15="","",IF(AND($D15>$G15,$O15="拡大↑",OR($N15="スクイーズ★",$N15="収縮")),"◎スクイーズブレイク買",IF(AND($D15>=$H15,$R15>=BB設定!$B$10),"○順張り継続(walk)",IF(AND($S15="強気div▲",$D15>$I15,LEFT($U15,4)<>"二番天井"),"○反発(ダイバ)買",IF($U15="二番底W▲","△二番底買(確)",IF($U15="二番底W形成","△二番底形成",IF(LEFT($U15,4)="二番天井","▼二番天井警戒",IF($D15<$J15,"▼-2σ割れ危険",IF(AND($D15>$E15,$K15<0.6,$R15>=50),"・押し目注目",IF($N15="スクイーズ★","☆スクイーズ監視","様子見")))))))))) -> △二番底形成 | X15: =IF($D15="","",MAX(0,MIN(100,IF($L15<=$M15*1.15,20,IF($L15<=$M15*1.4,10,0))+IF($D15>$G15,20,IF($D15>$H15,12,IF($D15>$E15,5,0)))+IF($O15="拡大↑",10,0)+IF($R15>=80,15,IF($R15>=60,10,IF($R15>=50,5,0)))+IF(AND($Q15>=50,$Q15<=70),10,IF($Q15>70,3,IF($Q15>=40,5,0)))+IF(AND($S15="強気div▲",$T15<>"下walk▼"),15,IF(AND($S15="強気div▲",$T15="下walk▼"),5,0))+IF($T15="上walk▲",5,0)+IF($V15>=2,5,IF($V15>=1.5,3,0))+IF(LEFT($U15,4)="二番天井",-15,0)+IF($D15<$E15,-10,0)+IF($T15="下walk▼",-10,0)+IF($K15<0.2,-5,0)))) -> 15 | Y15: =IF($D15="","",$D15) -> 3811 | Z15: =IF($D15="","",$H15) -> 3967.9934 | AA15: =IF($D15="","",IF($D15>$E15,$E15,$AD15)) -> 3753 | AB15: =IF($D15="","",IF($D15>$G15,$E15+3*$F15,$G15)) -> 4045.0868 | AC15: =IF($D15="","",IF(($Y15-$AA15)<=0,"－",IFERROR(ROUND(MIN(20,($AB15-$Y15)/($Y15-$AA15)),2),"－"))) -> 4.04 | AD15: =IF($D15="","",MIN(終値!E15:I15)) -> 3753 | AE15: =IF($D15="","",$X15+(10000-ROW())/100000) -> 15.09985
A16: =IF(終値!A16="","",HYPERLINK("https://kabutan.jp/stock/?code="&終値!A16,"📈")) -> 📈 | B16: =IF(終値!A16="","",終値!A16) -> 8058 | C16: =IF(終値!A16="","",終値!B16) -> 三菱商事 | D16: =IF(終値!A16="","",終値!E16) -> 4748 | E16: =IF($D16="","",AVERAGE(終値!E16:X16)) -> 4680.65 | F16: =IF($D16="","",STDEVP(終値!E16:X16)) -> 169.5483 | G16: =IF($D16="","",$E16+BB設定!$B$4*$F16) -> 5019.7466 | H16: =IF($D16="","",$E16+BB設定!$B$5*$F16) -> 4850.1983 | I16: =IF($D16="","",$E16-BB設定!$B$5*$F16) -> 4511.1017 | J16: =IF($D16="","",$E16-BB設定!$B$4*$F16) -> 4341.5534 | K16: =IF($D16="","",IFERROR(($D16-$J16)/($G16-$J16),"")) -> 0.59930798 | L16: =IF($D16="","",IFERROR(($G16-$J16)/$E16*100,"")) -> 14.489296 | M16: =IF($D16="","",IFERROR(MIN(BB_帯幅!B16:AP16)*100,"")) -> 6.8269208 | N16: =IF($L16="","",IF($L16<=$M16*BB設定!$B$7,"スクイーズ★",IF($L16<=$M16*1.3,"収縮","－"))) -> － | O16: =IF($D16="","",IF(AND(BB_帯幅!B16>BB_帯幅!C16,BB_帯幅!C16>BB_帯幅!D16),"拡大↑","縮小↓")) -> 縮小↓ | P16: =IF($D16="","",IF($D16>$G16,"↑+2σ突破",IF($D16<$J16,"↓-2σ割れ",IF($D16>$H16,"+1σ上",IF($D16<$I16,"-1σ下","バンド内"))))) -> バンド内 | Q16: =IF($D16="","",IFERROR(100-100/(1+SUMPRODUCT((終値!E16:R16>終値!F16:S16)*(終値!E16:R16-終値!F16:S16))/SUMPRODUCT((終値!E16:R16<終値!F16:S16)*(終値!F16:S16-終値!E16:R16))),100)) -> 60.42065 | R16: =IF($D16="","",IFERROR(100-100/(1+SUMPRODUCT((((高値!E16:R16+安値!E16:R16+終値!E16:R16)/3)>((高値!F16:S16+安値!F16:S16+終値!F16:S16)/3))*((高値!E16:R16+安値!E16:R16+終値!E16:R16)/3)*出来高!E16:R16)/SUMPRODUCT((((高値!E16:R16+安値!E16:R16+終値!E16:R16)/3)<((高値!F16:S16+安値!F16:S16+終値!F16:S16)/3))*((高値!E16:R16+安値!E16:R16+終値!E16:R16)/3)*出来高!E16:R16)),50)) -> 49.204082 | S16: =IF($D16="","",IF(AND(終値!E16<終値!O16,$Q16>(IFERROR(100-100/(1+SUMPRODUCT((終値!O16:AB16>終値!P16:AC16)*(終値!O16:AB16-終値!P16:AC16))/SUMPRODUCT((終値!O16:AB16<終値!P16:AC16)*(終値!P16:AC16-終値!O16:AB16))),100))),"強気div▲",IF(AND(終値!E16>終値!O16,$Q16<(IFERROR(100-100/(1+SUMPRODUCT((終値!O16:AB16>終値!P16:AC16)*(終値!O16:AB16-終値!P16:AC16))/SUMPRODUCT((終値!O16:AB16<終値!P16:AC16)*(終値!P16:AC16-終値!O16:AB16))),100))),"弱気div▼","－"))) -> － | T16: =IF($D16="","",IF($D16>=$H16,"上walk▲",IF($D16<=$I16,"下walk▼","－"))) -> － | U16: =IF(終値!A16="","",BB_スイング!BT16) -> － | V16: =IF($D16="","",IFERROR(出来高!E16/AVERAGE(出来高!E16:I16),"")) -> 0.6079884 | W16: =IF($D16="","",IF(AND($D16>$G16,$O16="拡大↑",OR($N16="スクイーズ★",$N16="収縮")),"◎スクイーズブレイク買",IF(AND($D16>=$H16,$R16>=BB設定!$B$10),"○順張り継続(walk)",IF(AND($S16="強気div▲",$D16>$I16,LEFT($U16,4)<>"二番天井"),"○反発(ダイバ)買",IF($U16="二番底W▲","△二番底買(確)",IF($U16="二番底W形成","△二番底形成",IF(LEFT($U16,4)="二番天井","▼二番天井警戒",IF($D16<$J16,"▼-2σ割れ危険",IF(AND($D16>$E16,$K16<0.6,$R16>=50),"・押し目注目",IF($N16="スクイーズ★","☆スクイーズ監視","様子見")))))))))) -> 様子見 | X16: =IF($D16="","",MAX(0,MIN(100,IF($L16<=$M16*1.15,20,IF($L16<=$M16*1.4,10,0))+IF($D16>$G16,20,IF($D16>$H16,12,IF($D16>$E16,5,0)))+IF($O16="拡大↑",10,0)+IF($R16>=80,15,IF($R16>=60,10,IF($R16>=50,5,0)))+IF(AND($Q16>=50,$Q16<=70),10,IF($Q16>70,3,IF($Q16>=40,5,0)))+IF(AND($S16="強気div▲",$T16<>"下walk▼"),15,IF(AND($S16="強気div▲",$T16="下walk▼"),5,0))+IF($T16="上walk▲",5,0)+IF($V16>=2,5,IF($V16>=1.5,3,0))+IF(LEFT($U16,4)="二番天井",-15,0)+IF($D16<$E16,-10,0)+IF($T16="下walk▼",-10,0)+IF($K16<0.2,-5,0)))) -> 15 | Y16: =IF($D16="","",$D16) -> 4748 | Z16: =IF($D16="","",$H16) -> 4850.1983 | AA16: =IF($D16="","",IF($D16>$E16,$E16,$AD16)) -> 4680.65 | AB16: =IF($D16="","",IF($D16>$G16,$E16+3*$F16,$G16)) -> 5019.7466 | AC16: =IF($D16="","",IF(($Y16-$AA16)<=0,"－",IFERROR(ROUND(MIN(20,($AB16-$Y16)/($Y16-$AA16)),2),"－"))) -> 4.03 | AD16: =IF($D16="","",MIN(終値!E16:I16)) -> 4641 | AE16: =IF($D16="","",$X16+(10000-ROW())/100000) -> 15.09984
A17: =IF(終値!A17="","",HYPERLINK("https://kabutan.jp/stock/?code="&終値!A17,"📈")) -> 📈 | B17: =IF(終値!A17="","",終値!A17) -> 5333 | C17: =IF(終値!A17="","",終値!B17) -> ＮＧＫ | D17: =IF(終値!A17="","",終値!E17) -> 5772 | E17: =IF($D17="","",AVERAGE(終値!E17:X17)) -> 6085.15 | F17: =IF($D17="","",STDEVP(終値!E17:X17)) -> 541.7628 | G17: =IF($D17="","",$E17+BB設定!$B$4*$F17) -> 7168.6756 | H17: =IF($D17="","",$E17+BB設定!$B$5*$F17) -> 6626.9128 | I17: =IF($D17="","",$E17-BB設定!$B$5*$F17) -> 5543.3872 | J17: =IF($D17="","",$E17-BB設定!$B$4*$F17) -> 5001.6244 | K17: =IF($D17="","",IFERROR(($D17-$J17)/($G17-$J17),"")) -> 0.35549488 | L17: =IF($D17="","",IFERROR(($G17-$J17)/$E17*100,"")) -> 35.612124 | M17: =IF($D17="","",IFERROR(MIN(BB_帯幅!B17:AP17)*100,"")) -> 17.194134 | N17: =IF($L17="","",IF($L17<=$M17*BB設定!$B$7,"スクイーズ★",IF($L17<=$M17*1.3,"収縮","－"))) -> － | O17: =IF($D17="","",IF(AND(BB_帯幅!B17>BB_帯幅!C17,BB_帯幅!C17>BB_帯幅!D17),"拡大↑","縮小↓")) -> 縮小↓ | P17: =IF($D17="","",IF($D17>$G17,"↑+2σ突破",IF($D17<$J17,"↓-2σ割れ",IF($D17>$H17,"+1σ上",IF($D17<$I17,"-1σ下","バンド内"))))) -> バンド内 | Q17: =IF($D17="","",IFERROR(100-100/(1+SUMPRODUCT((終値!E17:R17>終値!F17:S17)*(終値!E17:R17-終値!F17:S17))/SUMPRODUCT((終値!E17:R17<終値!F17:S17)*(終値!F17:S17-終値!E17:R17))),100)) -> 37.358628 | R17: =IF($D17="","",IFERROR(100-100/(1+SUMPRODUCT((((高値!E17:R17+安値!E17:R17+終値!E17:R17)/3)>((高値!F17:S17+安値!F17:S17+終値!F17:S17)/3))*((高値!E17:R17+安値!E17:R17+終値!E17:R17)/3)*出来高!E17:R17)/SUMPRODUCT((((高値!E17:R17+安値!E17:R17+終値!E17:R17)/3)<((高値!F17:S17+安値!F17:S17+終値!F17:S17)/3))*((高値!E17:R17+安値!E17:R17+終値!E17:R17)/3)*出来高!E17:R17)),50)) -> 30.183448 | S17: =IF($D17="","",IF(AND(終値!E17<終値!O17,$Q17>(IFERROR(100-100/(1+SUMPRODUCT((終値!O17:AB17>終値!P17:AC17)*(終値!O17:AB17-終値!P17:AC17))/SUMPRODUCT((終値!O17:AB17<終値!P17:AC17)*(終値!P17:AC17-終値!O17:AB17))),100))),"強気div▲",IF(AND(終値!E17>終値!O17,$Q17<(IFERROR(100-100/(1+SUMPRODUCT((終値!O17:AB17>終値!P17:AC17)*(終値!O17:AB17-終値!P17:AC17))/SUMPRODUCT((終値!O17:AB17<終値!P17:AC17)*(終値!P17:AC17-終値!O17:AB17))),100))),"弱気div▼","－"))) -> 強気div▲ | T17: =IF($D17="","",IF($D17>=$H17,"上walk▲",IF($D17<=$I17,"下walk▼","－"))) -> － | U17: =IF(終値!A17="","",BB_スイング!BT17) -> － | V17: =IF($D17="","",IFERROR(出来高!E17/AVERAGE(出来高!E17:I17),"")) -> 0.74301209 | W17: =IF($D17="","",IF(AND($D17>$G17,$O17="拡大↑",OR($N17="スクイーズ★",$N17="収縮")),"◎スクイーズブレイク買",IF(AND($D17>=$H17,$R17>=BB設定!$B$10),"○順張り継続(walk)",IF(AND($S17="強気div▲",$D17>$I17,LEFT($U17,4)<>"二番天井"),"○反発(ダイバ)買",IF($U17="二番底W▲","△二番底買(確)",IF($U17="二番底W形成","△二番底形成",IF(LEFT($U17,4)="二番天井","▼二番天井警戒",IF($D17<$J17,"▼-2σ割れ危険",IF(AND($D17>$E17,$K17<0.6,$R17>=50),"・押し目注目",IF($N17="スクイーズ★","☆スクイーズ監視","様子見")))))))))) -> ○反発(ダイバ)買 | X17: =IF($D17="","",MAX(0,MIN(100,IF($L17<=$M17*1.15,20,IF($L17<=$M17*1.4,10,0))+IF($D17>$G17,20,IF($D17>$H17,12,IF($D17>$E17,5,0)))+IF($O17="拡大↑",10,0)+IF($R17>=80,15,IF($R17>=60,10,IF($R17>=50,5,0)))+IF(AND($Q17>=50,$Q17<=70),10,IF($Q17>70,3,IF($Q17>=40,5,0)))+IF(AND($S17="強気div▲",$T17<>"下walk▼"),15,IF(AND($S17="強気div▲",$T17="下walk▼"),5,0))+IF($T17="上walk▲",5,0)+IF($V17>=2,5,IF($V17>=1.5,3,0))+IF(LEFT($U17,4)="二番天井",-15,0)+IF($D17<$E17,-10,0)+IF($T17="下walk▼",-10,0)+IF($K17<0.2,-5,0)))) -> 5 | Y17: =IF($D17="","",$D17) -> 5772 | Z17: =IF($D17="","",$H17) -> 6626.9128 | AA17: =IF($D17="","",IF($D17>$E17,$E17,$AD17)) -> 5532 | AB17: =IF($D17="","",IF($D17>$G17,$E17+3*$F17,$G17)) -> 7168.6756 | AC17: =IF($D17="","",IF(($Y17-$AA17)<=0,"－",IFERROR(ROUND(MIN(20,($AB17-$Y17)/($Y17-$AA17)),2),"－"))) -> 5.82 | AD17: =IF($D17="","",MIN(終値!E17:I17)) -> 5532 | AE17: =IF($D17="","",$X17+(10000-ROW())/100000) -> 5.09983
... A405: =IF(終値!A405="","",HYPERLINK("https://kabutan.jp/stock/?code="&終値!A405,"📈")) | B405: =IF(終値!A405="","",終値!A405) | C405: =IF(終値!A405="","",終値!B405) | D405: =IF(終値!A405="","",終値!E405) | E405: =IF($D405="","",AVERAGE(終値!E405:X405)) | F405: =IF($D405="","",STDEVP(終値!E405:X405)) | G405: =IF($D405="","",$E405+BB設定!$B$4*$F405) | H405: =IF($D405="","",$E405+BB設定!$B$5*$F405) | I405: =IF($D405="","",$E405-BB設定!$B$5*$F405) | J405: =IF($D405="","",$E405-BB設定!$B$4*$F405) | K405: =IF($D405="","",IFERROR(($D405-$J405)/($G405-$J405),"")) | L405: =IF($D405="","",IFERROR(($G405-$J405)/$E405*100,"")) | M405: =IF($D405="","",IFERROR(MIN(BB_帯幅!B405:AP405)*100,"")) | N405: =IF($L405="","",IF($L405<=$M405*BB設定!$B$7,"スクイーズ★",IF($L405<=$M405*1.3,"収縮","－"))) | O405: =IF($D405="","",IF(AND(BB_帯幅!B405>BB_帯幅!C405,BB_帯幅!C405>BB_帯幅!D405),"拡大↑","縮小↓")) | P405: =IF($D405="","",IF($D405>$G405,"↑+2σ突破",IF($D405<$J405,"↓-2σ割れ",IF($D405>$H405,"+1σ上",IF($D405<$I405,"-1σ下","バンド内"))))) | Q405: =IF($D405="","",IFERROR(100-100/(1+SUMPRODUCT((終値!E405:R405>終値!F405:S405)*(終値!E405:R405-終値!F405:S405))/SUMPRODUCT((終値!E405:R405<終値!F405:S405)*(終値!F405:S405-終値!E405:R405))),100)) | R405: =IF($D405="","",IFERROR(100-100/(1+SUMPRODUCT((((高値!E405:R405+安値!E405:R405+終値!E405:R405)/3)>((高値!F405:S405+安値!F405:S405+終値!F405:S405)/3))*((高値!E405:R405+安値!E405:R405+終値!E405:R405)/3)*出来高!E405:R405)/SUMPRODUCT((((高値!E405:R405+安値!E405:R405+終値!E405:R405)/3)<((高値!F405:S405+安値!F405:S405+終値!F405:S405)/3))*((高値!E405:R405+安値!E405:R405+終値!E405:R405)/3)*出来高!E405:R405)),50)) | S405: =IF($D405="","",IF(AND(終値!E405<終値!O405,$Q405>(IFERROR(100-100/(1+SUMPRODUCT((終値!O405:AB405>終値!P405:AC405)*(終値!O405:AB405-終値!P405:AC405))/SUMPRODUCT((終値!O405:AB405<終値!P405:AC405)*(終値!P405:AC405-終値!O405:AB405))),100))),"強気div▲",IF(AND(終値!E405>終値!O405,$Q405<(IFERROR(100-100/(1+SUMPRODUCT((終値!O405:AB405>終値!P405:AC405)*(終値!O405:AB405-終値!P405:AC405))/SUMPRODUCT((終値!O405:AB405<終値!P405:AC405)*(終値!P405:AC405-終値!O405:AB405))),100))),"弱気div▼","－"))) | T405: =IF($D405="","",IF($D405>=$H405,"上walk▲",IF($D405<=$I405,"下walk▼","－"))) | U405: =IF(終値!A405="","",BB_スイング!BT405) | V405: =IF($D405="","",IFERROR(出来高!E405/AVERAGE(出来高!E405:I405),"")) | W405: =IF($D405="","",IF(AND($D405>$G405,$O405="拡大↑",OR($N405="スクイーズ★",$N405="収縮")),"◎スクイーズブレイク買",IF(AND($D405>=$H405,$R405>=BB設定!$B$10),"○順張り継続(walk)",IF(AND($S405="強気div▲",$D405>$I405,LEFT($U405,4)<>"二番天井"),"○反発(ダイバ)買",IF($U405="二番底W▲","△二番底買(確)",IF($U405="二番底W形成","△二番底形成",IF(LEFT($U405,4)="二番天井","▼二番天井警戒",IF($D405<$J405,"▼-2σ割れ危険",IF(AND($D405>$E405,$K405<0.6,$R405>=50),"・押し目注目",IF($N405="スクイーズ★","☆スクイーズ監視","様子見")))))))))) | X405: =IF($D405="","",MAX(0,MIN(100,IF($L405<=$M405*1.15,20,IF($L405<=$M405*1.4,10,0))+IF($D405>$G405,20,IF($D405>$H405,12,IF($D405>$E405,5,0)))+IF($O405="拡大↑",10,0)+IF($R405>=80,15,IF($R405>=60,10,IF($R405>=50,5,0)))+IF(AND($Q405>=50,$Q405<=70),10,IF($Q405>70,3,IF($Q405>=40,5,0)))+IF(AND($S405="強気div▲",$T405<>"下walk▼"),15,IF(AND($S405="強気div▲",$T405="下walk▼"),5,0))+IF($T405="上walk▲",5,0)+IF($V405>=2,5,IF($V405>=1.5,3,0))+IF(LEFT($U405,4)="二番天井",-15,0)+IF($D405<$E405,-10,0)+IF($T405="下walk▼",-10,0)+IF($K405<0.2,-5,0)))) | Y405: =IF($D405="","",$D405) | Z405: =IF($D405="","",$H405) | AA405: =IF($D405="","",IF($D405>$E405,$E405,$AD405)) | AB405: =IF($D405="","",IF($D405>$G405,$E405+3*$F405,$G405)) | AC405: =IF($D405="","",IF(($Y405-$AA405)<=0,"－",IFERROR(ROUND(MIN(20,($AB405-$Y405)/($Y405-$AA405)),2),"－"))) | AD405: =IF($D405="","",MIN(終値!E405:I405)) | AE405: =IF($D405="","",$X405+(10000-ROW())/100000)

Sheet 終値
A1: 📈 終値シート｜60日履歴
A2: コード | B2: 銘 柄 名 | C2: RSS 現値 | D2: 差 分
A3: 日 付 | C3: 本日 | E3: 46240 | F3: 46239 | G3: 46238 | H3: 46237 | I3: 46234 | J3: 46233 | K3: 46232 | L3: 46231 | M3: 46230 | N3: 46227 | O3: 46226 | P3: 46225 | Q3: 46224 | R3: 46220 | S3: 46219 | T3: 46218 | U3: 46217 | V3: 46216 | W3: 46213 | X3: 46212 | Y3: 46211 | Z3: 46210 | AA3: 46209 | AB3: 46206 | AC3: 46205 | AD3: 46204 | AE3: 46203 | AF3: 46202 | AG3: 46199 | AH3: 46198 | AI3: 46197 | AJ3: 46196 | AK3: 46195 | AL3: 46192 | AM3: 46191 | AN3: 46190 | AO3: 46189 | AP3: 46188 | AQ3: 46185 | AR3: 46184 | AS3: 46183 | AT3: 46182 | AU3: 46181 | AV3: 46178 | AW3: 46177 | AX3: 46176 | AY3: 46175 | AZ3: 46174 | BA3: 46171 | BB3: 46170 | BC3: 46169 | BD3: 46168 | BE3: 46167 | BF3: 46164 | BG3: 46163 | BH3: 46162 | BI3: 46161 | BJ3: 46160 | BK3: 46157 | BL3: 46156 | BM3: 46155 | BN3: 46154 | BO3: 46153 | BP3: 46150 | BQ3: 46149 | BR3: 46143 | BS3: 46142 | BT3: 46140 | BU3: 46139 | BV3: 46136 | BW3: 46135 | BX3: 46134 | BY3: 46133 | BZ3: 46132 | CA3: 46129 | CB3: 46128 | CC3: 46127 | CD3: 46126 | CE3: 46125 | CF3: 46122 | CG3: 46121 | CH3: 46120 | CI3: 46119 | CJ3: 46118 | CK3: 46115 | CL3: 46114 | CM3: 46113 | CN3: 46112 | CO3: 46111 | CP3: 46108 | CQ3: 46107 | CR3: 46106 | CS3: 46105 | CT3: 46104 | CU3: 46100 | CV3: 46099 | CW3: 46098 | CX3: 46097 | CY3: 46094 | CZ3: 46093 | DA3: 46092 | DB3: 46091 | DC3: 46090 | DD3: 46087 | DE3: 46086 | DF3: 46085 | DG3: 46084 | DH3: 46083 | DI3: 46080 | DJ3: 46079 | DK3: 46078 | DL3: 46077 | DM3: 46073 | DN3: 46072 | DO3: 46071 | DP3: 46070 | DQ3: 46069 | DR3: 46066 | DS3: 46065 | DT3: 46063 | DU3: 46062 | DV3: 46059 | DW3: 46058 | DX3: 46057 | DY3: 46056 | DZ3: 46055 | EA3: 46052 | EB3: 46051 | EC3: 46050 | ED3: 46049 | EE3: 46048 | EF3: 46045 | EG3: 46044 | EH3: 46043 | EI3: 46042 | EJ3: 46041 | EK3: 46038 | EL3: 46037 | EM3: 46036 | EN3: 46035 | EO3: 46031 | EP3: 46030 | EQ3: 46029 | ER3: 46028 | ES3: 46027 | ET3: 46021 | EU3: 46020 | EV3: 46017 | EW3: 46016 | EX3: 46015 | EY3: 46014 | EZ3: 46013 | FA3: 46010 | FB3: 46009 | FC3: 46008 | FD3: 46007 | FE3: 46006 | FF3: 46003 | FG3: 46002 | FH3: 46001 | FI3: 46000 | FJ3: 45999 | FK3: 45996 | FL3: 45995 | FM3: 45994 | FN3: 45993 | FO3: 45992 | FP3: 45989 | FQ3: 45988 | FR3: 45987 | FS3: 45986 | FT3: 45982 | FU3: 45981 | FV3: 45980 | FW3: 45979 | FX3: 45978 | FY3: 45975 | FZ3: 45974 | GA3: 45973 | GB3: 45972 | GC3: 45971 | GD3: 45968 | GE3: 45967 | GF3: 45966 | GG3: 45965 | GH3: 45961 | GI3: 45960 | GJ3: 45959 | GK3: 45958 | GL3: 45957 | GM3: 45954 | GN3: 45953 | GO3: 45952 | GP3: 45951 | GQ3: 45950 | GR3: 45947 | GS3: 45946 | GT3: 45945 | GU3: 45944 | GV3: 45940 | GW3: 45939 | GX3: 45938 | GY3: 45937 | GZ3: 45936 | HA3: 45933 | HB3: 45932 | HC3: 45931 | HD3: 45930 | HE3: 45929 | HF3: 45926 | HG3: 45925 | HH3: 45924 | HI3: 45922 | HJ3: 45919 | HK3: 45918 | HL3: 45917 | HM3: 45916 | HN3: 45912 | HO3: 45911 | HP3: 45910 | HQ3: 45909 | HR3: 45908 | HS3: 45905 | HT3: 45904 | HU3: 45903 | HV3: 45902 | HW3: 45901 | HX3: 45898 | HY3: 45897 | HZ3: 45896 | IA3: 45895 | IB3: 45894 | IC3: 45891 | ID3: 45890 | IE3: 45889 | IF3: 45888 | IG3: 45887 | IH3: 45884 | II3: 45883 | IJ3: 45882 | IK3: 45881 | IL3: 45877 | IM3: 45876 | IN3: 45875 | IO3: 45874 | IP3: 45873 | IQ3: 45870 | IR3: 45869 | IS3: 45868 | IT3: 45867
A5: TOPX | B5: 4059.18 | C5: 4059.18 | D5: 3163.18 | E5: 896 | F5: 883.5 | G5: 889.1 | H5: 896.6 | I5: 902.2 | J5: 941.4 | K5: 964.6 | L5: 923.8 | M5: 894 | N5: 862.7 | O5: 856.2 | P5: 866.3 | Q5: 880.9 | R5: 889 | S5: 869 | T5: 858.5 | U5: 874 | V5: 872.7 | W5: 850.4 | X5: 870.9 | Y5: 873.2 | Z5: 866.7 | AA5: 852.7 | AB5: 818.3 | AC5: 820.7 | AD5: 793.6 | AE5: 823 | AF5: 826.4 | AG5: 823 | AH5: 820.7 | AI5: 818.5 | AJ5: 813.4 | AK5: 816.4 | AL5: 819 | AM5: 835.3 | AN5: 835.6 | AO5: 834.6 | AP5: 837.2 | AQ5: 855.3 | AR5: 867.8 | AS5: 849 | AT5: 833.2 | AU5: 839.3 | AV5: 831.9 | AW5: 826.1 | AX5: 824.6 | AY5: 826.7 | AZ5: 823.5 | BA5: 878.2 | BB5: 858.5 | BC5: 819 | BD5: 809.4 | BE5: 824.6 | BF5: 866.9 | BG5: 867.1 | BH5: 872.1 | BI5: 884.8 | BJ5: 871.3 | BK5: 871.3 | BL5: 858 | BM5: 883.6 | BN5: 893.8 | BO5: 907.3 | BP5: 883.5 | BQ5: 887.3 | BR5: 888 | BS5: 889.4 | BT5: 900.7 | BU5: 914.6 | BV5: 918.4 | BW5: 922 | BX5: 949.4 | BY5: 942 | BZ5: 959.3 | CA5: 940 | CB5: 963.2 | CC5: 961.5 | CD5: 962.6 | CE5: 954.1 | CF5: 938.5 | CG5: 956.5 | CH5: 975.2 | CI5: 977.8 | CJ5: 992.1 | CK5: 950.8 | CL5: 936.5 | CM5: 982.4 | CN5: 968.2 | CO5: 991.9 | CP5: 983 | CQ5: 970.9 | CR5: 974.5 | CS5: 971.5 | CT5: 973 | CU5: 989.6 | CV5: 1016 | CW5: 1012 | CX5: 1003.5 | CY5: 1010 | CZ5: 1000.5 | DA5: 1039 | DB5: 1037.5 | DC5: 1047.5 | DD5: 1058.5 | DE5: 1023.5 | DF5: 1012.5 | DG5: 988.7 | DH5: 1038 | DI5: 1040 | DJ5: 1017.5 | DK5: 1036 | DL5: 1023.5 | DM5: 1005 | DN5: 985.4 | DO5: 956.4 | DP5: 952.9 | DQ5: 968.4 | DR5: 977.3 | DS5: 975.4 | DT5: 975.3 | DU5: 975 | DV5: 965.6 | DW5: 960.6 | DX5: 938.8 | DY5: 928 | DZ5: 907.9 | EA5: 915.9 | EB5: 898.6 | EC5: 923.6 | ED5: 928.1 | EE5: 927.7 | EF5: 928.9 | EG5: 924.9 | EH5: 953.7 | EI5: 972.8 | EJ5: 928.6 | EK5: 889.7 | EL5: 904.5 | EM5: 896 | EN5: 911.7 | EO5: 925 | EP5: 912.7 | EQ5: 918.7 | ER5: 926.1 | ES5: 917.3 | ET5: 932.3 | EU5: 936.9 | EV5: 946.2 | EW5: 942.7 | EX5: 946.6 | EY5: 957.2 | EZ5: 955.5 | FA5: 974.2 | FB5: 969.7 | FC5: 938.9 | FD5: 945.7 | FE5: 967.7 | FF5: 964.9 | FG5: 950.2 | FH5: 949.1 | FI5: 938.5 | FJ5: 949 | FK5: 939.1 | FL5: 951.7 | FM5: 928.9 | FN5: 926.1 | FO5: 936.8 | FP5: 947.1 | FQ5: 966.3 | FR5: 946.2 | FS5: 924.9 | FT5: 916.6 | FU5: 908.8 | FV5: 908.6 | FW5: 918.9 | FX5: 903 | FY5: 953.2 | FZ5: 957.7 | GA5: 987.4 | GB5: 1000 | GC5: 1002.5 | GD5: 999.8 | GE5: 989.9 | GF5: 992 | GG5: 945.4 | GH5: 917.8 | GI5: 921.1 | GJ5: 923.3 | GK5: 942.4 | GL5: 963.5 | GM5: 964.5 | GN5: 972.3 | GO5: 945.2 | GP5: 943.4 | GQ5: 938 | GR5: 936.3 | GS5: 931.9 | GT5: 956.3 | GU5: 974.9 | GV5: 939.1 | GW5: 945.2 | GX5: 956.8 | GY5: 947.4 | GZ5: 952.8 | HA5: 935.8 | HB5: 933.5 | HC5: 953.6 | HD5: 975 | HE5: 984.1 | HF5: 1009 | HG5: 984.8 | HH5: 987.6 | HI5: 987.8 | HJ5: 986.8 | HK5: 1007.2 | HL5: 1009.4 | HM5: 1023.6 | HN5: 1048.8 | HO5: 1052.2 | HP5: 1067.4 | HQ5: 1066.8 | HR5: 1104.4 | HS5: 1102.2 | HT5: 1099.2 | HU5: 1076.6 | HV5: 1063.4 | HW5: 1069.4 | HX5: 1067.2 | HY5: 1093 | HZ5: 1087 | IA5: 1093.4 | IB5: 1095.6 | IC5: 1101.4 | ID5: 1100 | IE5: 1095 | IF5: 1065.6 | IG5: 1069.8 | IH5: 1048.2 | II5: 1050 | IJ5: 1071 | IK5: 1087.2 | IL5: 1075.4 | IM5: 1065 | IN5: 1060.6 | IO5: 1041 | IP5: 1035 | IQ5: 1026.2 | IR5: 1013.8 | IS5: 997.6 | IT5: 987.6
A6: 5706 | B6: 三井金属 | C6: 31650 | D6: -320 | E6: 31970 | F6: 35380 | G6: 31900 | H6: 30890 | I6: 30950 | J6: 27095 | K6: 25665 | L6: 28010 | M6: 31230 | N6: 31910 | O6: 33900 | P6: 33600 | Q6: 31290 | R6: 29980 | S6: 32280 | T6: 34980 | U6: 34390 | V6: 35280 | W6: 36460 | X6: 35090 | Y6: 33730 | Z6: 35930 | AA6: 37520 | AB6: 38740 | AC6: 38250 | AD6: 43160 | AE6: 42550 | AF6: 41940 | AG6: 42390 | AH6: 46390 | AI6: 46040 | AJ6: 46250 | AK6: 52930 | AL6: 48820 | AM6: 48100 | AN6: 47600 | AO6: 48500 | AP6: 44690 | AQ6: 43900 | AR6: 37330 | AS6: 36980 | AT6: 39460 | AU6: 41350 | AV6: 44490 | AW6: 46050 | AX6: 47600 | AY6: 49550 | AZ6: 53840 | BA6: 51630 | BB6: 48750 | BC6: 51800 | BD6: 53740 | BE6: 53330 | BF6: 49610 | BG6: 46670 | BH6: 44360 | BI6: 44790 | BJ6: 47320 | BK6: 46640 | BL6: 50660 | BM6: 54900 | BN6: 50850 | BO6: 51250 | BP6: 50000 | BQ6: 48060 | BR6: 41060 | BS6: 42350 | BT6: 41370 | BU6: 39300 | BV6: 38660 | BW6: 36830 | BX6: 38260 | BY6: 37390 | BZ6: 35480 | CA6: 36500 | CB6: 37750 | CC6: 35690 | CD6: 38260 | CE6: 36430 | CF6: 37200 | CG6: 34770 | CH6: 35000 | CI6: 31550 | CJ6: 31960 | CK6: 31520 | CL6: 29650 | CM6: 30730 | CN6: 28040 | CO6: 29565 | CP6: 31270 | CQ6: 30890 | CR6: 31630 | CS6: 30100 | CT6: 29190 | CU6: 31110 | CV6: 32400 | CW6: 30110 | CX6: 31600 | CY6: 31580 | CZ6: 31260 | DA6: 32380 | DB6: 30790 | DC6: 29485 | DD6: 32740 | DE6: 34170 | DF6: 32830 | DG6: 36130 | DH6: 38680 | DI6: 36910 | DJ6: 36200 | DK6: 35740 | DL6: 33040 | DM6: 31290 | DN6: 29675 | DO6: 28515 | DP6: 27460 | DQ6: 28360 | DR6: 26540 | DS6: 25990 | DT6: 23430 | DU6: 22595 | DV6: 20785 | DW6: 21085 | DX6: 22015 | DY6: 20815 | DZ6: 19795 | EA6: 20370 | EB6: 21630 | EC6: 21570 | ED6: 21900 | EE6: 21705 | EF6: 21815 | EG6: 21685 | EH6: 21970 | EI6: 22040 | EJ6: 22920 | EK6: 22220 | EL6: 21645 | EM6: 21445 | EN6: 20295 | EO6: 19900 | EP6: 20140 | EQ6: 19265 | ER6: 19175 | ES6: 18595 | ET6: 17635 | EU6: 17800 | EV6: 17325 | EW6: 17860 | EX6: 18045 | EY6: 18110 | EZ6: 18445 | FA6: 17150 | FB6: 17250 | FC6: 17200 | FD6: 16735 | FE6: 17310 | FF6: 18100 | FG6: 17580 | FH6: 18415 | FI6: 18000 | FJ6: 18385 | FK6: 17985 | FL6: 17525 | FM6: 17775 | FN6: 16975 | FO6: 16620 | FP6: 17830 | FQ6: 18220 | FR6: 17910 | FS6: 17480 | FT6: 18290 | FU6: 20850 | FV6: 19400 | FW6: 19425 | FX6: 21230 | FY6: 19500 | FZ6: 19400 | GA6: 19150 | GB6: 15535 | GC6: 15965 | GD6: 15650 | GE6: 16505 | GF6: 15340 | GG6: 16065 | GH6: 15760 | GI6: 15505 | GJ6: 15530 | GK6: 14365 | GL6: 14850 | GM6: 14080 | GN6: 13605 | GO6: 13735 | GP6: 13715 | GQ6: 14205 | GR6: 13675 | GS6: 13680 | GT6: 13615 | GU6: 13195 | GV6: 13660 | GW6: 14060 | GX6: 13685 | GY6: 13070 | GZ6: 13215 | HA6: 13180 | HB6: 12350 | HC6: 11630 | HD6: 11505 | HE6: 11585 | HF6: 11520 | HG6: 11805 | HH6: 11005 | HI6: 10630 | HJ6: 10810 | HK6: 10810 | HL6: 10205 | HM6: 10705 | HN6: 10325 | HO6: 10800 | HP6: 10300 | HQ6: 9961 | HR6: 10675 | HS6: 10550 | HT6: 10670 | HU6: 10725 | HV6: 10705 | HW6: 10215 | HX6: 10525 | HY6: 10400 | HZ6: 10120 | IA6: 9803 | IB6: 9848 | IC6: 9310 | ID6: 9230 | IE6: 8570 | IF6: 9141 | IG6: 9037 | IH6: 8461 | II6: 7686 | IJ6: 7850 | IK6: 7556 | IL6: 6693 | IM6: 6846 | IN6: 6830 | IO6: 6700 | IP6: 6607 | IQ6: 6605 | IR6: 6450 | IS6: 6130 | IT6: 5990
A7: 5423 | B7: 東京製鐵 | C7: 1765 | D7: 13 | E7: 1752 | F7: 1723 | G7: 1689 | H7: 1695 | I7: 1772 | J7: 1761 | K7: 1782 | L7: 1784 | M7: 1742 | N7: 1687 | O7: 1715 | P7: 1708 | Q7: 1721 | R7: 1748 | S7: 1770 | T7: 1767 | U7: 1763 | V7: 1726 | W7: 1717 | X7: 1722 | Y7: 1744 | Z7: 1750 | AA7: 1749 | AB7: 1750 | AC7: 1714 | AD7: 1705 | AE7: 1685 | AF7: 1691 | AG7: 1679 | AH7: 1678 | AI7: 1715 | AJ7: 1739 | AK7: 1799 | AL7: 1761 | AM7: 1776 | AN7: 1771 | AO7: 1742 | AP7: 1760 | AQ7: 1717 | AR7: 1689 | AS7: 1671 | AT7: 1671 | AU7: 1699 | AV7: 1698 | AW7: 1703 | AX7: 1703 | AY7: 1702 | AZ7: 1705 | BA7: 1756 | BB7: 1712 | BC7: 1707 | BD7: 1720 | BE7: 1708 | BF7: 1725 | BG7: 1745 | BH7: 1704 | BI7: 1758 | BJ7: 1798 | BK7: 1825 | BL7: 1844 | BM7: 1701 | BN7: 1663 | BO7: 1656 | BP7: 1657 | BQ7: 1682 | BR7: 1677 | BS7: 1697 | BT7: 1693 | BU7: 1697 | BV7: 1703 | BW7: 1736 | BX7: 1805 | BY7: 1827 | BZ7: 1780 | CA7: 1768 | CB7: 1782 | CC7: 1733 | CD7: 1725 | CE7: 1723 | CF7: 1745 | CG7: 1777 | CH7: 1826 | CI7: 1784 | CJ7: 1871 | CK7: 1902 | CL7: 1627 | CM7: 1630 | CN7: 1618 | CO7: 1633 | CP7: 1656 | CQ7: 1641 | CR7: 1606 | CS7: 1590 | CT7: 1563 | CU7: 1608 | CV7: 1650 | CW7: 1631 | CX7: 1612 | CY7: 1629 | CZ7: 1623 | DA7: 1635 | DB7: 1619 | DC7: 1542 | DD7: 1560 | DE7: 1580 | DF7: 1535 | DG7: 1614 | DH7: 1616 | DI7: 1620 | DJ7: 1575 | DK7: 1569 | DL7: 1584 | DM7: 1581 | DN7: 1601 | DO7: 1582 | DP7: 1566 | DQ7: 1587 | DR7: 1546 | DS7: 1628 | DT7: 1627 | DU7: 1615 | DV7: 1577 | DW7: 1573 | DX7: 1570 | DY7: 1544 | DZ7: 1512 | EA7: 1510 | EB7: 1497 | EC7: 1483 | ED7: 1517 | EE7: 1545 | EF7: 1527 | EG7: 1641 | EH7: 1619 | EI7: 1630 | EJ7: 1639 | EK7: 1616 | EL7: 1622 | EM7: 1596 | EN7: 1578 | EO7: 1555 | EP7: 1512 | EQ7: 1504 | ER7: 1497 | ES7: 1479 | ET7: 1476 | EU7: 1488 | EV7: 1489 | EW7: 1481 | EX7: 1481 | EY7: 1462 | EZ7: 1431 | FA7: 1416 | FB7: 1423 | FC7: 1420 | FD7: 1415 | FE7: 1439 | FF7: 1442 | FG7: 1424 | FH7: 1436 | FI7: 1426 | FJ7: 1441 | FK7: 1410 | FL7: 1437 | FM7: 1425 | FN7: 1427 | FO7: 1429 | FP7: 1443 | FQ7: 1427 | FR7: 1435 | FS7: 1420 | FT7: 1430 | FU7: 1409 | FV7: 1398 | FW7: 1404 | FX7: 1415 | FY7: 1404 | FZ7: 1408 | GA7: 1414 | GB7: 1382 | GC7: 1382 | GD7: 1375 | GE7: 1355 | GF7: 1370 | GG7: 1354 | GH7: 1361 | GI7: 1334 | GJ7: 1334 | GK7: 1356 | GL7: 1389 | GM7: 1379 | GN7: 1381 | GO7: 1399 | GP7: 1422 | GQ7: 1385 | GR7: 1359 | GS7: 1482 | GT7: 1465 | GU7: 1433 | GV7: 1441 | GW7: 1502 | GX7: 1495 | GY7: 1492 | GZ7: 1476 | HA7: 1454 | HB7: 1455 | HC7: 1459 | HD7: 1458 | HE7: 1483 | HF7: 1509 | HG7: 1522 | HH7: 1515 | HI7: 1525 | HJ7: 1534 | HK7: 1554 | HL7: 1568 | HM7: 1597 | HN7: 1618 | HO7: 1606 | HP7: 1624 | HQ7: 1625 | HR7: 1662 | HS7: 1643 | HT7: 1655 | HU7: 1670 | HV7: 1674 | HW7: 1642 | HX7: 1660 | HY7: 1671 | HZ7: 1659 | IA7: 1650 | IB7: 1657 | IC7: 1648 | ID7: 1643 | IE7: 1638 | IF7: 1618 | IG7: 1598 | IH7: 1585 | II7: 1594 | IJ7: 1621 | IK7: 1616 | IL7: 1627 | IM7: 1611 | IN7: 1623 | IO7: 1620 | IP7: 1596 | IQ7: 1600 | IR7: 1581 | IS7: 1580 | IT7: 1566
A8: 5713 | B8: 住友鉱山 | C8: 9212 | D8: 124 | E8: 9088 | F8: 8563 | G8: 8058 | H8: 7961 | I8: 8185 | J8: 7430 | K8: 7315 | L8: 7364 | M8: 7785 | N8: 7460 | O8: 7902 | P8: 7521 | Q8: 7317 | R8: 6794 | S8: 7276 | T8: 7404 | U8: 7329 | V8: 7156 | W8: 7275 | X8: 7190 | Y8: 7305 | Z8: 7462 | AA8: 7924 | AB8: 7930 | AC8: 7521 | AD8: 7336 | AE8: 7469 | AF8: 7492 | AG8: 7635 | AH8: 7653 | AI8: 7955 | AJ8: 8251 | AK8: 8834 | AL8: 8607 | AM8: 9273 | AN8: 9155 | AO8: 8863 | AP8: 9200 | AQ8: 8638 | AR8: 7735 | AS8: 7844 | AT8: 7718 | AU8: 7996 | AV8: 8578 | AW8: 8654 | AX8: 9099 | AY8: 8779 | AZ8: 8989 | BA8: 9093 | BB8: 8910 | BC8: 9608 | BD8: 9800 | BE8: 9800 | BF8: 9504 | BG8: 9193 | BH8: 8980 | BI8: 9280 | BJ8: 9560 | BK8: 10275 | BL8: 10565 | BM8: 10820 | BN8: 10725 | BO8: 10155 | BP8: 10615 | BQ8: 10085 | BR8: 9532 | BS8: 9423 | BT8: 9664 | BU8: 9599 | BV8: 9713 | BW8: 9740 | BX8: 10030 | BY8: 10290 | BZ8: 10070 | CA8: 10150 | CB8: 11020 | CC8: 10645 | CD8: 10400 | CE8: 9867 | CF8: 9986 | CG8: 9922 | CH8: 10355 | CI8: 9544 | CJ8: 9476 | CK8: 9440 | CL8: 9214 | CM8: 9593 | CN8: 8855 | CO8: 9250 | CP8: 9478 | CQ8: 9337 | CR8: 9240 | CS8: 8827 | CT8: 8372 | CU8: 9137 | CV8: 10015 | CW8: 9567 | CX8: 9711 | CY8: 9929 | CZ8: 10060 | DA8: 10485 | DB8: 10075 | DC8: 9566 | DD8: 10125 | DE8: 10535 | DF8: 10735 | DG8: 11995 | DH8: 13050 | DI8: 12625 | DJ8: 11345 | DK8: 11650 | DL8: 10810 | DM8: 10010 | DN8: 9925 | DO8: 9678 | DP8: 9320 | DQ8: 9667 | DR8: 9886 | DS8: 10795 | DT8: 10230 | DU8: 9458 | DV8: 8755 | DW8: 8825 | DX8: 9300 | DY8: 8749 | DZ8: 8291 | EA8: 9360 | EB8: 9855 | EC8: 9004 | ED8: 8788 | EE8: 8509 | EF8: 8488 | EG8: 8180 | EH8: 8380 | EI8: 8082 | EJ8: 7868 | EK8: 7770 | EL8: 7850 | EM8: 7846 | EN8: 7510 | EO8: 7171 | EP8: 7039 | EQ8: 7174 | ER8: 7059 | ES8: 6638 | ET8: 6357 | EU8: 6675 | EV8: 6421 | EW8: 6331 | EX8: 6488 | EY8: 6049 | EZ8: 6090 | FA8: 5792 | FB8: 5799 | FC8: 5882 | FD8: 5614 | FE8: 5706 | FF8: 5952 | FG8: 5454 | FH8: 5388 | FI8: 5351 | FJ8: 5469 | FK8: 5499 | FL8: 5325 | FM8: 5119 | FN8: 5086 | FO8: 5127 | FP8: 5132 | FQ8: 5025 | FR8: 4885 | FS8: 4820 | FT8: 4721 | FU8: 4945 | FV8: 4842 | FW8: 4792 | FX8: 5091 | FY8: 5197 | FZ8: 5205 | GA8: 5120 | GB8: 4988 | GC8: 5027 | GD8: 4910 | GE8: 4932 | GF8: 4824 | GG8: 4954 | GH8: 5077 | GI8: 5084 | GJ8: 4920 | GK8: 4907 | GL8: 5197 | GM8: 5094 | GN8: 5086 | GO8: 4927 | GP8: 5300 | GQ8: 5348 | GR8: 5448 | GS8: 5321 | GT8: 5279 | GU8: 5100 | GV8: 5018 | GW8: 5242 | GX8: 5133 | GY8: 4877 | GZ8: 4963 | HA8: 4905 | HB8: 4926 | HC8: 4690 | HD8: 4767 | HE8: 4730 | HF8: 4673 | HG8: 4818 | HH8: 4329 | HI8: 4258 | HJ8: 4150 | HK8: 4320 | HL8: 4327 | HM8: 4415 | HN8: 4331 | HO8: 4288 | HP8: 4209 | HQ8: 4224 | HR8: 4264 | HS8: 4194 | HT8: 4207 | HU8: 4181 | HV8: 4147 | HW8: 4019 | HX8: 4035 | HY8: 4044 | HZ8: 4011 | IA8: 3956 | IB8: 3946 | IC8: 3767 | ID8: 3754 | IE8: 3726 | IF8: 3757 | IG8: 3788 | IH8: 3690 | II8: 3596 | IJ8: 3624 | IK8: 3660 | IL8: 3646 | IM8: 3663 | IN8: 3550 | IO8: 3513 | IP8: 3447 | IQ8: 3385 | IR8: 3355 | IS8: 3466 | IT8: 3445
A9: 5711 | B9: 三菱マテリアル | C9: 0 | D9: -4457 | E9: 4457 | F9: 4382 | G9: 4144 | H9: 4151 | I9: 4193 | J9: 3971 | K9: 3944 | L9: 4034 | M9: 4224 | N9: 4166 | O9: 4294 | P9: 4204 | Q9: 4124 | R9: 3970 | S9: 4193 | T9: 4242 | U9: 4160 | V9: 4047 | W9: 4087 | X9: 3960 | Y9: 4254 | Z9: 4359 | AA9: 4626 | AB9: 4555 | AC9: 4452 | AD9: 4387 | AE9: 4315 | AF9: 4322 | AG9: 4363 | AH9: 4424 | AI9: 4559 | AJ9: 4630 | AK9: 4889 | AL9: 4836 | AM9: 4901 | AN9: 4882 | AO9: 4898 | AP9: 5005 | AQ9: 4640 | AR9: 4443 | AS9: 4471 | AT9: 4536 | AU9: 4595 | AV9: 4904 | AW9: 4973 | AX9: 5187 | AY9: 5050 | AZ9: 5089 | BA9: 5153 | BB9: 5128 | BC9: 5271 | BD9: 5430 | BE9: 5255 | BF9: 5038 | BG9: 4890 | BH9: 4786 | BI9: 4959 | BJ9: 5057 | BK9: 5428 | BL9: 5362 | BM9: 6100 | BN9: 5817 | BO9: 5584 | BP9: 5562 | BQ9: 5340 | BR9: 5080 | BS9: 5092 | BT9: 5215 | BU9: 5157 | BV9: 5261 | BW9: 5292 | BX9: 5419 | BY9: 5548 | BZ9: 5500 | CA9: 5528 | CB9: 5774 | CC9: 5652 | CD9: 5688 | CE9: 5460 | CF9: 5560 | CG9: 5562 | CH9: 5637 | CI9: 5203 | CJ9: 5168 | CK9: 5189 | CL9: 4995 | CM9: 5186 | CN9: 4815 | CO9: 4944 | CP9: 5130 | CQ9: 5144 | CR9: 5185 | CS9: 4965 | CT9: 4733 | CU9: 5221 | CV9: 5603 | CW9: 4903 | CX9: 4930 | CY9: 5039 | CZ9: 5091 | DA9: 5260 | DB9: 5165 | DC9: 4863 | DD9: 5179 | DE9: 5270 | DF9: 5200 | DG9: 5648 | DH9: 6103 | DI9: 6006 | DJ9: 5562 | DK9: 5662 | DL9: 5437 | DM9: 5237 | DN9: 5264 | DO9: 5136 | DP9: 5038 | DQ9: 5223 | DR9: 5397 | DS9: 5250 | DT9: 4939 | DU9: 4776 | DV9: 4539 | DW9: 4495 | DX9: 4676 | DY9: 4434 | DZ9: 4179 | EA9: 4448 | EB9: 4585 | EC9: 4456 | ED9: 4467 | EE9: 4422 | EF9: 4465 | EG9: 4365 | EH9: 4345 | EI9: 4301 | EJ9: 4359 | EK9: 4350 | EL9: 4402 | EM9: 4387 | EN9: 4205 | EO9: 3997 | EP9: 3957 | EQ9: 3984 | ER9: 3959 | ES9: 3690 | ET9: 3670 | EU9: 3750 | EV9: 3654 | EW9: 3673 | EX9: 3652 | EY9: 3530 | EZ9: 3505 | FA9: 3405 | FB9: 3312 | FC9: 3336 | FD9: 3303 | FE9: 3387 | FF9: 3474 | FG9: 3294 | FH9: 3342 | FI9: 3216 | FJ9: 3248 | FK9: 3222 | FL9: 3189 | FM9: 3128 | FN9: 3116 | FO9: 3154 | FP9: 3131 | FQ9: 3085 | FR9: 3160 | FS9: 3102 | FT9: 2992 | FU9: 3063 | FV9: 2997 | FW9: 3012 | FX9: 3123 | FY9: 3115 | FZ9: 3117 | GA9: 3042 | GB9: 2973.5 | GC9: 2940.5 | GD9: 2867 | GE9: 2876 | GF9: 2875 | GG9: 2939 | GH9: 2970 | GI9: 3019 | GJ9: 2954 | GK9: 2897.5 | GL9: 3041 | GM9: 3000 | GN9: 2930 | GO9: 2890.5 | GP9: 2914 | GQ9: 2946.5 | GR9: 2915 | GS9: 2919 | GT9: 2928.5 | GU9: 2827.5 | GV9: 2867 | GW9: 2995.5 | GX9: 2969.5 | GY9: 2833 | GZ9: 2829 | HA9: 2802.5 | HB9: 2765 | HC9: 2701.5 | HD9: 2778 | HE9: 2754 | HF9: 2784 | HG9: 2869.5 | HH9: 2645.5 | HI9: 2636.5 | HJ9: 2590.5 | HK9: 2621 | HL9: 2607 | HM9: 2638 | HN9: 2589.5 | HO9: 2583.5 | HP9: 2564 | HQ9: 2582 | HR9: 2600 | HS9: 2598.5 | HT9: 2613 | HU9: 2574.5 | HV9: 2571 | HW9: 2526 | HX9: 2552 | HY9: 2546 | HZ9: 2564 | IA9: 2540.5 | IB9: 2568.5 | IC9: 2527.5 | ID9: 2541.5 | IE9: 2520.5 | IF9: 2547 | IG9: 2562 | IH9: 2515.5 | II9: 2462.5 | IJ9: 2497 | IK9: 2475 | IL9: 2446.5 | IM9: 2437 | IN9: 2402.5 | IO9: 2374 | IP9: 2338 | IQ9: 2347.5 | IR9: 2322.5 | IS9: 2320 | IT9: 2304.5
A10: 5714 | B10: ＤＯＷＡホールディングス | C10: 9198 | D10: 291 | E10: 8907 | F10: 8559 | G10: 8197 | H10: 8159 | I10: 8235 | J10: 7990 | K10: 7907 | L10: 8089 | M10: 8432 | N10: 8276 | O10: 8542 | P10: 8457 | Q10: 8271 | R10: 7946 | S10: 8349 | T10: 8443 | U10: 8369 | V10: 8280 | W10: 8376 | X10: 8257 | Y10: 8425 | Z10: 8586 | AA10: 8963 | AB10: 8834 | AC10: 8790 | AD10: 8602 | AE10: 8666 | AF10: 8770 | AG10: 8744 | AH10: 8735 | AI10: 8984 | AJ10: 9184 | AK10: 9670 | AL10: 9480 | AM10: 9745 | AN10: 9839 | AO10: 9685 | AP10: 9870 | AQ10: 9377 | AR10: 8905 | AS10: 8997 | AT10: 9104 | AU10: 9257 | AV10: 10005 | AW10: 9834 | AX10: 10370 | AY10: 10150 | AZ10: 10430 | BA10: 10300 | BB10: 10530 | BC10: 10845 | BD10: 10890 | BE10: 10935 | BF10: 10390 | BG10: 10165 | BH10: 10125 | BI10: 10370 | BJ10: 11125 | BK10: 11640 | BL10: 10025 | BM10: 10655 | BN10: 10350 | BO10: 10360 | BP10: 10180 | BQ10: 9848 | BR10: 9492 | BS10: 9476 | BT10: 9730 | BU10: 9500 | BV10: 9640 | BW10: 9667 | BX10: 9782 | BY10: 9937 | BZ10: 9792 | CA10: 9962 | CB10: 10355 | CC10: 10055 | CD10: 10055 | CE10: 9677 | CF10: 9758 | CG10: 9769 | CH10: 9891 | CI10: 9309 | CJ10: 9117 | CK10: 9094 | CL10: 8913 | CM10: 9271 | CN10: 8735 | CO10: 8882 | CP10: 9390 | CQ10: 9466 | CR10: 9394 | CS10: 9018 | CT10: 8710 | CU10: 9271 | CV10: 10050 | CW10: 9613 | CX10: 9629 | CY10: 9858 | CZ10: 9924 | DA10: 10245 | DB10: 10055 | DC10: 9511 | DD10: 10165 | DE10: 10005 | DF10: 9842 | DG10: 11005 | DH10: 11830 | DI10: 11550 | DJ10: 10440 | DK10: 10495 | DL10: 10590 | DM10: 10140 | DN10: 9885 | DO10: 9637 | DP10: 9377 | DQ10: 9481 | DR10: 9461 | DS10: 10170 | DT10: 9872 | DU10: 9429 | DV10: 9015 | DW10: 9212 | DX10: 9586 | DY10: 9186 | DZ10: 8624 | EA10: 9214 | EB10: 9564 | EC10: 9249 | ED10: 9315 | EE10: 9207 | EF10: 9126 | EG10: 8958 | EH10: 9085 | EI10: 8927 | EJ10: 8950 | EK10: 8668 | EL10: 8783 | EM10: 8824 | EN10: 8676 | EO10: 8064 | EP10: 7950 | EQ10: 8081 | ER10: 8021 | ES10: 7538 | ET10: 7432 | EU10: 7578 | EV10: 7404 | EW10: 7398 | EX10: 7360 | EY10: 7085 | EZ10: 7034 | FA10: 6878 | FB10: 6897 | FC10: 6998 | FD10: 6537 | FE10: 6645 | FF10: 6736 | FG10: 6454 | FH10: 6500 | FI10: 6116 | FJ10: 6150 | FK10: 6106 | FL10: 6080 | FM10: 6050 | FN10: 5979 | FO10: 5993 | FP10: 6081 | FQ10: 6058 | FR10: 5963 | FS10: 5930 | FT10: 5872 | FU10: 5990 | FV10: 5824 | FW10: 5772 | FX10: 6015 | FY10: 6041 | FZ10: 6109 | GA10: 5928 | GB10: 5592 | GC10: 5680 | GD10: 5468 | GE10: 5443 | GF10: 5502 | GG10: 5599 | GH10: 5600 | GI10: 5645 | GJ10: 5557 | GK10: 5472 | GL10: 5807 | GM10: 5737 | GN10: 5642 | GO10: 5581 | GP10: 5606 | GQ10: 5669 | GR10: 5691 | GS10: 5606 | GT10: 5649 | GU10: 5489 | GV10: 5443 | GW10: 5666 | GX10: 5623 | GY10: 5462 | GZ10: 5421 | HA10: 5370 | HB10: 5369 | HC10: 5308 | HD10: 5398 | HE10: 5455 | HF10: 5446 | HG10: 5521 | HH10: 5293 | HI10: 5290 | HJ10: 5225 | HK10: 5382 | HL10: 5381 | HM10: 5502 | HN10: 5479 | HO10: 5453 | HP10: 5409 | HQ10: 5430 | HR10: 5512 | HS10: 5427 | HT10: 5412 | HU10: 5312 | HV10: 5286 | HW10: 5213 | HX10: 5222 | HY10: 5219 | HZ10: 5224 | IA10: 5176 | IB10: 5218 | IC10: 5195 | ID10: 5201 | IE10: 5120 | IF10: 5075 | IG10: 5085 | IH10: 5014 | II10: 4947 | IJ10: 5100 | IK10: 5046 | IL10: 4981 | IM10: 5185 | IN10: 5138 | IO10: 5069 | IP10: 5030 | IQ10: 5041 | IR10: 4958 | IS10: 5006 | IT10: 4975
A11: 6701 | B11: 日本電気 | C11: 4793 | D11: 103 | E11: 4690 | F11: 4631 | G11: 4598 | H11: 4733 | I11: 4740 | J11: 5002 | K11: 4613 | L11: 4490 | M11: 4445 | N11: 4249 | O11: 4240 | P11: 4352 | Q11: 4407 | R11: 4354 | S11: 4441 | T11: 4270 | U11: 4463 | V11: 4339 | W11: 4333 | X11: 4386 | Y11: 4349 | Z11: 4348 | AA11: 4347 | AB11: 4168 | AC11: 4200 | AD11: 3981 | AE11: 3925 | AF11: 4047 | AG11: 3795 | AH11: 3757 | AI11: 3838 | AJ11: 3683 | AK11: 3752 | AL11: 3756 | AM11: 3973 | AN11: 3852 | AO11: 3849 | AP11: 3847 | AQ11: 3879 | AR11: 4000 | AS11: 4010 | AT11: 4065 | AU11: 4096 | AV11: 4253 | AW11: 4224 | AX11: 4273 | AY11: 4434 | AZ11: 4369 | BA11: 4103 | BB11: 4086 | BC11: 4146 | BD11: 4113 | BE11: 4106 | BF11: 4105 | BG11: 4125 | BH11: 4140 | BI11: 4297 | BJ11: 4162 | BK11: 4004 | BL11: 4049 | BM11: 4190 | BN11: 4130 | BO11: 4101 | BP11: 4200 | BQ11: 4028 | BR11: 4035 | BS11: 4101 | BT11: 4444 | BU11: 4625 | BV11: 4513 | BW11: 4292 | BX11: 4524 | BY11: 4431 | BZ11: 4327 | CA11: 4328 | CB11: 4328 | CC11: 4269 | CD11: 4083 | CE11: 3882 | CF11: 3860 | CG11: 4048 | CH11: 4188 | CI11: 4074 | CJ11: 4011 | CK11: 4046 | CL11: 4023 | CM11: 4025 | CN11: 3846 | CO11: 3789 | CP11: 3990 | CQ11: 3940 | CR11: 4042 | CS11: 4049 | CT11: 3928 | CU11: 4124 | CV11: 4188 | CW11: 4200 | CX11: 4267 | CY11: 4257 | CZ11: 4207 | DA11: 4311 | DB11: 4500 | DC11: 4419 | DD11: 4445 | DE11: 4224 | DF11: 4192 | DG11: 4168 | DH11: 4278 | DI11: 4334 | DJ11: 4115 | DK11: 3760 | DL11: 3673 | DM11: 3916 | DN11: 4052 | DO11: 4041 | DP11: 4004 | DQ11: 4200 | DR11: 4099 | DS11: 4503 | DT11: 4835 | DU11: 4508 | DV11: 4311 | DW11: 4397 | DX11: 4722 | DY11: 5353 | DZ11: 5222 | EA11: 5210 | EB11: 5537 | EC11: 5681 | ED11: 5687 | EE11: 5611 | EF11: 5835 | EG11: 5700 | EH11: 5807 | EI11: 5895 | EJ11: 5999 | EK11: 5899 | EL11: 5922 | EM11: 5938 | EN11: 5838 | EO11: 5612 | EP11: 5642 | EQ11: 5600 | ER11: 5686 | ES11: 5434 | ET11: 5310 | EU11: 5315 | EV11: 5379 | EW11: 5422 | EX11: 5400 | EY11: 5433 | EZ11: 5392 | FA11: 5436 | FB11: 5314 | FC11: 5465 | FD11: 5409 | FE11: 5492 | FF11: 5526 | FG11: 5489 | FH11: 5576 | FI11: 5625 | FJ11: 5683 | FK11: 5723 | FL11: 5727 | FM11: 5761 | FN11: 5883 | FO11: 5697 | FP11: 5891 | FQ11: 5989 | FR11: 6009 | FS11: 6018 | FT11: 6074 | FU11: 5980 | FV11: 5759 | FW11: 5616 | FX11: 5879 | FY11: 5980 | FZ11: 5990 | GA11: 5880 | GB11: 5732 | GC11: 5612 | GD11: 5483 | GE11: 5597 | GF11: 5647 | GG11: 5583 | GH11: 5618 | GI11: 5775 | GJ11: 5104 | GK11: 5094 | GL11: 5161 | GM11: 5079 | GN11: 5046 | GO11: 5018 | GP11: 4888 | GQ11: 4965 | GR11: 4778 | GS11: 4823 | GT11: 4803 | GU11: 4636 | GV11: 4809 | GW11: 4931 | GX11: 5033 | GY11: 4944 | GZ11: 5093 | HA11: 4510 | HB11: 4490 | HC11: 4595 | HD11: 4739 | HE11: 4596 | HF11: 4705 | HG11: 4743 | HH11: 4766 | HI11: 4675 | HJ11: 4685 | HK11: 4649 | HL11: 4532 | HM11: 4627 | HN11: 4625 | HO11: 4577 | HP11: 4518 | HQ11: 4407 | HR11: 4458 | HS11: 4423 | HT11: 4430 | HU11: 4335 | HV11: 4400 | HW11: 4414 | HX11: 4537 | HY11: 4483 | HZ11: 4556 | IA11: 4606 | IB11: 4582 | IC11: 4636 | ID11: 4543 | IE11: 4612 | IF11: 4642 | IG11: 4720 | IH11: 4580 | II11: 4532 | IJ11: 4605 | IK11: 4621 | IL11: 4626 | IM11: 4682 | IN11: 4540 | IO11: 4458 | IP11: 4471 | IQ11: 4529 | IR11: 4399 | IS11: 4340 | IT11: 4090
A12: 1605 | B12: ＩＮＰＥＸ | C12: 3499 | D12: 39 | E12: 3460 | F12: 3394 | G12: 3492 | H12: 3519 | I12: 3627 | J12: 3628 | K12: 3616 | L12: 3566 | M12: 3652 | N12: 3761 | O12: 3697 | P12: 3615 | Q12: 3580 | R12: 3401 | S12: 3429 | T12: 3450 | U12: 3524 | V12: 3391 | W12: 3361 | X12: 3427 | Y12: 3388 | Z12: 3281 | AA12: 3309 | AB12: 3242 | AC12: 3204 | AD12: 3205 | AE12: 3265 | AF12: 3278 | AG12: 3351 | AH12: 3287 | AI12: 3401 | AJ12: 3456 | AK12: 3448 | AL12: 3500 | AM12: 3429 | AN12: 3406 | AO12: 3378 | AP12: 3495 | AQ12: 3559 | AR12: 3607 | AS12: 3483 | AT12: 3592 | AU12: 3641 | AV12: 3685 | AW12: 3648 | AX12: 3707 | AY12: 3567 | AZ12: 3416 | BA12: 3604 | BB12: 3693 | BC12: 3689 | BD12: 3668 | BE12: 3658 | BF12: 3839 | BG12: 3885 | BH12: 3990 | BI12: 3993 | BJ12: 3934 | BK12: 3921 | BL12: 3920 | BM12: 3930 | BN12: 3944 | BO12: 3848 | BP12: 3788 | BQ12: 3850 | BR12: 4118 | BS12: 4150 | BT12: 4123 | BU12: 3930 | BV12: 4074 | BW12: 3969 | BX12: 3807 | BY12: 3830 | BZ12: 3843 | CA12: 3985 | CB12: 3948 | CC12: 4035 | CD12: 4190 | CE12: 4277 | CF12: 4147 | CG12: 4230 | CH12: 4201 | CI12: 4480 | CJ12: 4512 | CK12: 4675 | CL12: 4567 | CM12: 4701 | CN12: 4678 | CO12: 4892 | CP12: 4900 | CQ12: 4687 | CR12: 4444 | CS12: 4519 | CT12: 4483 | CU12: 4700 | CV12: 4675 | CW12: 4507 | CX12: 4370 | CY12: 4383 | CZ12: 4299 | DA12: 4171 | DB12: 4091 | DC12: 4101 | DD12: 4091 | DE12: 4161 | DF12: 3872 | DG12: 4017 | DH12: 4031 | DI12: 3800 | DJ12: 3685 | DK12: 3620 | DL12: 3708 | DM12: 3677 | DN12: 3719 | DO12: 3598 | DP12: 3567 | DQ12: 3543 | DR12: 3473 | DS12: 3998 | DT12: 3845 | DU12: 3726 | DV12: 3665 | DW12: 3558 | DX12: 3561 | DY12: 3437 | DZ12: 3344 | EA12: 3443 | EB12: 3434 | EC12: 3355 | ED12: 3258 | EE12: 3226 | EF12: 3230 | EG12: 3222 | EH12: 3185 | EI12: 3172 | EJ12: 3200 | EK12: 3195 | EL12: 3286 | EM12: 3266 | EN12: 3161 | EO12: 3120 | EP12: 3048 | EQ12: 3020 | ER12: 3189 | ES12: 3116 | ET12: 3127 | EU12: 3096 | EV12: 3145 | EW12: 3158 | EX12: 3170 | EY12: 3199 | EZ12: 3193 | FA12: 3150 | FB12: 3115 | FC12: 3105 | FD12: 3121 | FE12: 3226 | FF12: 3184 | FG12: 3207 | FH12: 3217 | FI12: 3199 | FJ12: 3209 | FK12: 3173 | FL12: 3210 | FM12: 3133 | FN12: 3172 | FO12: 3223 | FP12: 3331 | FQ12: 3330 | FR12: 3290 | FS12: 3215 | FT12: 3170 | FU12: 3135 | FV12: 3075 | FW12: 3080 | FX12: 3177 | FY12: 3175 | FZ12: 3016 | GA12: 3020 | GB12: 2964 | GC12: 2981 | GD12: 2895.5 | GE12: 2896.5 | GF12: 2838.5 | GG12: 2871 | GH12: 2841 | GI12: 2854 | GJ12: 2787 | GK12: 2833 | GL12: 2896 | GM12: 2849 | GN12: 2798.5 | GO12: 2727.5 | GP12: 2694.5 | GQ12: 2706 | GR12: 2653.5 | GS12: 2688.5 | GT12: 2661.5 | GU12: 2630 | GV12: 2675 | GW12: 2786 | GX12: 2743 | GY12: 2707 | GZ12: 2677.5 | HA12: 2598 | HB12: 2665.5 | HC12: 2641 | HD12: 2673 | HE12: 2738 | HF12: 2775 | HG12: 2740 | HH12: 2714.5 | HI12: 2638 | HJ12: 2613 | HK12: 2630 | HL12: 2640 | HM12: 2654.5 | HN12: 2646.5 | HO12: 2657.5 | HP12: 2615 | HQ12: 2575 | HR12: 2618.5 | HS12: 2605.5 | HT12: 2565.5 | HU12: 2570 | HV12: 2582 | HW12: 2543 | HX12: 2518 | HY12: 2532.5 | HZ12: 2427.5 | IA12: 2433 | IB12: 2452.5 | IC12: 2428.5 | ID12: 2391 | IE12: 2374 | IF12: 2350 | IG12: 2330.5 | IH12: 2342 | II12: 2310.5 | IJ12: 2342 | IK12: 2388 | IL12: 2230 | IM12: 2189 | IN12: 2175 | IO12: 2117 | IP12: 2097 | IQ12: 2158.5 | IR12: 2147.5 | IS12: 2125 | IT12: 2111.5
A13: 5703 | B13: 日本軽金属ＨＤ | C13: 2892 | D13: -44 | E13: 2936 | F13: 2917 | G13: 2793 | H13: 2835 | I13: 2715 | J13: 2589 | K13: 2584 | L13: 2621 | M13: 2685 | N13: 2644 | O13: 2711 | P13: 2702 | Q13: 2711 | R13: 2638 | S13: 2734 | T13: 2750 | U13: 2756 | V13: 2682 | W13: 2707 | X13: 2636 | Y13: 2622 | Z13: 2693 | AA13: 2752 | AB13: 2764 | AC13: 2726 | AD13: 2742 | AE13: 2721 | AF13: 2795 | AG13: 2819 | AH13: 2822 | AI13: 2869 | AJ13: 2910 | AK13: 3010 | AL13: 2983 | AM13: 2970 | AN13: 2958 | AO13: 3010 | AP13: 3105 | AQ13: 3040 | AR13: 2986 | AS13: 3065 | AT13: 3095 | AU13: 3135 | AV13: 3255 | AW13: 3175 | AX13: 3270 | AY13: 3165 | AZ13: 3130 | BA13: 3165 | BB13: 3190 | BC13: 3200 | BD13: 3290 | BE13: 3245 | BF13: 3050 | BG13: 3065 | BH13: 3050 | BI13: 3085 | BJ13: 3150 | BK13: 3120 | BL13: 3040 | BM13: 2951 | BN13: 2960 | BO13: 2902 | BP13: 2928 | BQ13: 2930 | BR13: 2823 | BS13: 2853 | BT13: 2868 | BU13: 2886 | BV13: 2858 | BW13: 2855 | BX13: 2908 | BY13: 2963 | BZ13: 2948 | CA13: 2982 | CB13: 3045 | CC13: 3010 | CD13: 3040 | CE13: 2999 | CF13: 2983 | CG13: 2945 | CH13: 2978 | CI13: 2893 | CJ13: 2867 | CK13: 2873 | CL13: 2774 | CM13: 2839 | CN13: 2776 | CO13: 2656 | CP13: 2732 | CQ13: 2718 | CR13: 2735 | CS13: 2640 | CT13: 2544 | CU13: 2736 | CV13: 2906 | CW13: 2812 | CX13: 2811 | CY13: 2884 | CZ13: 2884 | DA13: 2940 | DB13: 2919 | DC13: 2805 | DD13: 2993 | DE13: 2940 | DF13: 2839 | DG13: 3030 | DH13: 3175 | DI13: 3120 | DJ13: 3060 | DK13: 3105 | DL13: 3030 | DM13: 2968 | DN13: 2971 | DO13: 2989 | DP13: 2980 | DQ13: 2979 | DR13: 2892 | DS13: 3130 | DT13: 3050 | DU13: 3055 | DV13: 2930 | DW13: 2868 | DX13: 2866 | DY13: 2789 | DZ13: 2769 | EA13: 2732 | EB13: 2816 | EC13: 2808 | ED13: 2855 | EE13: 2822 | EF13: 2821 | EG13: 2773 | EH13: 2747 | EI13: 2772 | EJ13: 2754 | EK13: 2771 | EL13: 2747 | EM13: 2749 | EN13: 2699 | EO13: 2629 | EP13: 2629 | EQ13: 2634 | ER13: 2619 | ES13: 2561 | ET13: 2550 | EU13: 2578 | EV13: 2500 | EW13: 2490 | EX13: 2492 | EY13: 2485 | EZ13: 2479 | FA13: 2453 | FB13: 2450 | FC13: 2475 | FD13: 2434 | FE13: 2471 | FF13: 2480 | FG13: 2458 | FH13: 2505 | FI13: 2481 | FJ13: 2463 | FK13: 2425 | FL13: 2423 | FM13: 2403 | FN13: 2432 | FO13: 2428 | FP13: 2454 | FQ13: 2415 | FR13: 2421 | FS13: 2384 | FT13: 2338 | FU13: 2349 | FV13: 2271 | FW13: 2292 | FX13: 2321 | FY13: 2298 | FZ13: 2271 | GA13: 2283 | GB13: 2223 | GC13: 2229 | GD13: 2181 | GE13: 2185 | GF13: 2137 | GG13: 2171 | GH13: 2250 | GI13: 2143 | GJ13: 2109 | GK13: 2093 | GL13: 2186 | GM13: 2170 | GN13: 2131 | GO13: 2104 | GP13: 2083 | GQ13: 2100 | GR13: 2080 | GS13: 2086 | GT13: 2079 | GU13: 2019 | GV13: 2076 | GW13: 2175 | GX13: 2136 | GY13: 2117 | GZ13: 2130 | HA13: 2168 | HB13: 2098 | HC13: 2044 | HD13: 2100 | HE13: 2122 | HF13: 2157 | HG13: 2150 | HH13: 2125 | HI13: 2119 | HJ13: 2105 | HK13: 2117 | HL13: 2116 | HM13: 2163 | HN13: 2167 | HO13: 2149 | HP13: 2112 | HQ13: 2137 | HR13: 2157 | HS13: 2186 | HT13: 2133 | HU13: 2081 | HV13: 2052 | HW13: 2063 | HX13: 2064 | HY13: 2041 | HZ13: 2013 | IA13: 1952 | IB13: 1998 | IC13: 1975 | ID13: 1946 | IE13: 1882 | IF13: 1872 | IG13: 1874 | IH13: 1879 | II13: 1834 | IJ13: 1840 | IK13: 1817 | IL13: 1809 | IM13: 1797 | IN13: 1802 | IO13: 1807 | IP13: 1775 | IQ13: 1775 | IR13: 1764 | IS13: 1726 | IT13: 1715
A14: 8002 | B14: 丸紅 | C14: 5018 | D14: 82 | E14: 4936 | F14: 4862 | G14: 4937 | H14: 5132 | I14: 5201 | J14: 5196 | K14: 5205 | L14: 5272 | M14: 5450 | N14: 5370 | O14: 5384 | P14: 5260 | Q14: 5194 | R14: 4988 | S14: 5084 | T14: 5110 | U14: 4920 | V14: 4862 | W14: 4879 | X14: 4924 | Y14: 4961 | Z14: 5048 | AA14: 5026 | AB14: 4963 | AC14: 4806 | AD14: 4668 | AE14: 4690 | AF14: 4713 | AG14: 4692 | AH14: 4607 | AI14: 4687 | AJ14: 4793 | AK14: 4913 | AL14: 4895 | AM14: 4909 | AN14: 4949 | AO14: 4921 | AP14: 5042 | AQ14: 4899 | AR14: 4812 | AS14: 4795 | AT14: 4894 | AU14: 4870 | AV14: 5044 | AW14: 4968 | AX14: 4993 | AY14: 4910 | AZ14: 4918 | BA14: 5196 | BB14: 5224 | BC14: 5220 | BD14: 5348 | BE14: 5312 | BF14: 5271 | BG14: 5325 | BH14: 5374 | BI14: 5553 | BJ14: 5638 | BK14: 5856 | BL14: 5898 | BM14: 5740 | BN14: 5520 | BO14: 5418 | BP14: 5418 | BQ14: 5495 | BR14: 5755 | BS14: 6072 | BT14: 6084 | BU14: 5910 | BV14: 5936 | BW14: 5929 | BX14: 5908 | BY14: 6001 | BZ14: 5885 | CA14: 5853 | CB14: 6040 | CC14: 5909 | CD14: 6018 | CE14: 5932 | CF14: 5950 | CG14: 6088 | CH14: 6119 | CI14: 5919 | CJ14: 5890 | CK14: 5988 | CL14: 5890 | CM14: 5993 | CN14: 5618 | CO14: 5763 | CP14: 5751 | CQ14: 5661 | CR14: 5610 | CS14: 5356 | CT14: 5189 | CU14: 5495 | CV14: 5835 | CW14: 5694 | CX14: 5633 | CY14: 5591 | CZ14: 5375 | DA14: 5469 | DB14: 5413 | DC14: 5150 | DD14: 5383 | DE14: 5452 | DF14: 5251 | DG14: 5757 | DH14: 5925 | DI14: 6008 | DJ14: 5965 | DK14: 6010 | DL14: 5798 | DM14: 5710 | DN14: 5828 | DO14: 5786 | DP14: 5748 | DQ14: 5848 | DR14: 6033 | DS14: 6301 | DT14: 6186 | DU14: 5957 | DV14: 5657 | DW14: 5400 | DX14: 5406 | DY14: 5306 | DZ14: 4963 | EA14: 5115 | EB14: 5129 | EC14: 5063 | ED14: 5076 | EE14: 4915 | EF14: 5126 | EG14: 5129 | EH14: 5095 | EI14: 5119 | EJ14: 5197 | EK14: 5199 | EL14: 5143 | EM14: 5055 | EN14: 4949 | EO14: 4603 | EP14: 4608 | EQ14: 4582 | ER14: 4556 | ES14: 4448 | ET14: 4353 | EU14: 4362 | EV14: 4331 | EW14: 4351 | EX14: 4331 | EY14: 4368 | EZ14: 4358 | FA14: 4344 | FB14: 4240 | FC14: 4312 | FD14: 4392 | FE14: 4550 | FF14: 4578 | FG14: 4435 | FH14: 4426 | FI14: 4362 | FJ14: 4333 | FK14: 4243 | FL14: 4259 | FM14: 4114 | FN14: 4054 | FO14: 4059 | FP14: 4119 | FQ14: 4086 | FR14: 4036 | FS14: 3912 | FT14: 3825 | FU14: 3790 | FV14: 3761 | FW14: 3791 | FX14: 3950 | FY14: 4037 | FZ14: 4041 | GA14: 3994 | GB14: 3900 | GC14: 3934 | GD14: 3955 | GE14: 3928 | GF14: 3874 | GG14: 3839 | GH14: 3800 | GI14: 3771 | GJ14: 3698 | GK14: 3765 | GL14: 3848 | GM14: 3770 | GN14: 3762 | GO14: 3735 | GP14: 3681 | GQ14: 3652 | GR14: 3598 | GS14: 3604 | GT14: 3670 | GU14: 3620 | GV14: 3805 | GW14: 3852 | GX14: 3841 | GY14: 3844 | GZ14: 3866 | HA14: 3745 | HB14: 3724 | HC14: 3657 | HD14: 3698 | HE14: 3624 | HF14: 3723 | HG14: 3703 | HH14: 3656 | HI14: 3645 | HJ14: 3616 | HK14: 3599 | HL14: 3557 | HM14: 3598 | HN14: 3514 | HO14: 3496 | HP14: 3518 | HQ14: 3503 | HR14: 3543 | HS14: 3467 | HT14: 3428 | HU14: 3410 | HV14: 3459 | HW14: 3372 | HX14: 3382 | HY14: 3375 | HZ14: 3336 | IA14: 3326 | IB14: 3322 | IC14: 3305 | ID14: 3279 | IE14: 3276 | IF14: 3292 | IG14: 3248 | IH14: 3236 | II14: 3191 | IJ14: 3278 | IK14: 3292 | IL14: 3233 | IM14: 3169 | IN14: 3144 | IO14: 3060 | IP14: 3022 | IQ14: 3046 | IR14: 3113 | IS14: 3060 | IT14: 3032
A15: 5021 | B15: コスモエネルギーＨＬＤＧＳ | C15: 4038 | D15: 227 | E15: 3811 | F15: 3753 | G15: 3786 | H15: 3836 | I15: 3984 | J15: 3988 | K15: 3988 | L15: 3947 | M15: 3976 | N15: 3969 | O15: 3975 | P15: 3944 | Q15: 3930 | R15: 3776 | S15: 3810 | T15: 3867 | U15: 3904 | V15: 3845 | W15: 3861 | X15: 3868 | Y15: 3869 | Z15: 3885 | AA15: 3964 | AB15: 3889 | AC15: 3875 | AD15: 3813 | AE15: 3788 | AF15: 3775 | AG15: 3757 | AH15: 3674 | AI15: 3706 | AJ15: 3688 | AK15: 3721 | AL15: 3775 | AM15: 3729 | AN15: 3669 | AO15: 3676 | AP15: 3684 | AQ15: 3571 | AR15: 3503 | AS15: 3462 | AT15: 3509 | AU15: 3586 | AV15: 3611 | AW15: 3663 | AX15: 3833 | AY15: 3717 | AZ15: 3671 | BA15: 3739 | BB15: 3700 | BC15: 3685 | BD15: 3656 | BE15: 3680 | BF15: 3701 | BG15: 3700 | BH15: 3739 | BI15: 3774 | BJ15: 3733 | BK15: 3832 | BL15: 3867 | BM15: 3760 | BN15: 3969 | BO15: 3958 | BP15: 3951 | BQ15: 3909 | BR15: 3982 | BS15: 4003 | BT15: 3985 | BU15: 3906 | BV15: 3943 | BW15: 4021 | BX15: 4067 | BY15: 4197 | BZ15: 4267 | CA15: 4355 | CB15: 4357 | CC15: 4374 | CD15: 4357 | CE15: 4385 | CF15: 4431 | CG15: 4507 | CH15: 4449 | CI15: 4509 | CJ15: 4461 | CK15: 4530 | CL15: 4442 | CM15: 4545 | CN15: 4432 | CO15: 4534 | CP15: 4585 | CQ15: 4603 | CR15: 4494 | CS15: 4516 | CT15: 4341 | CU15: 4588 | CV15: 4688 | CW15: 4547 | CX15: 4452 | CY15: 4460 | CZ15: 4469 | DA15: 4573 | DB15: 4476 | DC15: 4384 | DD15: 4506 | DE15: 4602 | DF15: 4423 | DG15: 4652 | DH15: 4940 | DI15: 4817 | DJ15: 4664 | DK15: 4664 | DL15: 4740 | DM15: 4793 | DN15: 4850 | DO15: 4763 | DP15: 4681 | DQ15: 4629 | DR15: 4572 | DS15: 4688 | DT15: 4582 | DU15: 4558 | DV15: 4718 | DW15: 4769 | DX15: 4766 | DY15: 4606 | DZ15: 4479 | EA15: 4614 | EB15: 4553 | EC15: 4422 | ED15: 4525 | EE15: 4511 | EF15: 4550 | EG15: 4541 | EH15: 4471 | EI15: 4449 | EJ15: 4485 | EK15: 4505 | EL15: 4549 | EM15: 4530 | EN15: 4412 | EO15: 4341 | EP15: 4268 | EQ15: 4298 | ER15: 4392 | ES15: 4228 | ET15: 4175 | EU15: 4165 | EV15: 4170 | EW15: 4207 | EX15: 4195 | EY15: 4197 | EZ15: 4219 | FA15: 4139 | FB15: 4153 | FC15: 4141 | FD15: 4199 | FE15: 4242 | FF15: 4115 | FG15: 4098 | FH15: 4176 | FI15: 4134 | FJ15: 4106 | FK15: 4077 | FL15: 4090 | FM15: 4028 | FN15: 4032 | FO15: 4077 | FP15: 4055 | FQ15: 4026 | FR15: 4052 | FS15: 3983 | FT15: 3991 | FU15: 3990 | FV15: 3927 | FW15: 3898 | FX15: 3947 | FY15: 3882 | FZ15: 3758 | GA15: 3795 | GB15: 3581 | GC15: 3605 | GD15: 3508 | GE15: 3492 | GF15: 3502 | GG15: 3555 | GH15: 3518 | GI15: 3524 | GJ15: 3476 | GK15: 3527 | GL15: 3620 | GM15: 3617 | GN15: 3659 | GO15: 3581 | GP15: 3489 | GQ15: 3501 | GR15: 3444 | GS15: 3483 | GT15: 3507 | GU15: 3433 | GV15: 3486 | GW15: 3666 | GX15: 3580 | GY15: 3533 | GZ15: 3536 | HA15: 3452 | HB15: 3498 | HC15: 3486 | HD15: 3581 | HE15: 3555 | HF15: 3678.5 | HG15: 3684.5 | HH15: 3641.5 | HI15: 3630 | HJ15: 3600 | HK15: 3645.5 | HL15: 3671.5 | HM15: 3692.5 | HN15: 3596 | HO15: 3594 | HP15: 3582.5 | HQ15: 3597 | HR15: 3648.5 | HS15: 3606 | HT15: 3612.5 | HU15: 3592 | HV15: 3633.5 | HW15: 3588.5 | HX15: 3567.5 | HY15: 3635.5 | HZ15: 3565 | IA15: 3526.5 | IB15: 3561.5 | IC15: 3572 | ID15: 3551.5 | IE15: 3552.5 | IF15: 3531 | IG15: 3516.5 | IH15: 3545 | II15: 3486 | IJ15: 3546.5 | IK15: 3469.5 | IL15: 3479 | IM15: 3427 | IN15: 3417 | IO15: 3351 | IP15: 3322.5 | IQ15: 3382.5 | IR15: 3358.5 | IS15: 3336.5 | IT15: 3284
A16: 8058 | B16: 三菱商事 | C16: 4846 | D16: 98 | E16: 4748 | F16: 4641 | G16: 4738 | H16: 4787 | I16: 4776 | J16: 4777 | K16: 4819 | L16: 4776 | M16: 4847 | N16: 4918 | O16: 4916 | P16: 4888 | Q16: 4664 | R16: 4447 | S16: 4530 | T16: 4585 | U16: 4496 | V16: 4440 | W16: 4409 | X16: 4411 | Y16: 4464 | Z16: 4500 | AA16: 4507 | AB16: 4457 | AC16: 4385 | AD16: 4344 | AE16: 4347 | AF16: 4414 | AG16: 4403 | AH16: 4400 | AI16: 4530 | AJ16: 4591 | AK16: 4609 | AL16: 4540 | AM16: 4570 | AN16: 4610 | AO16: 4595 | AP16: 4728 | AQ16: 4683 | AR16: 4605 | AS16: 4615 | AT16: 4805 | AU16: 4833 | AV16: 4859 | AW16: 4896 | AX16: 4979 | AY16: 4924 | AZ16: 4921 | BA16: 5065 | BB16: 5038 | BC16: 5124 | BD16: 5186 | BE16: 5320 | BF16: 5432 | BG16: 5411 | BH16: 5436 | BI16: 5519 | BJ16: 5500 | BK16: 5849 | BL16: 5882 | BM16: 5864 | BN16: 5500 | BO16: 5252 | BP16: 5249 | BQ16: 5398 | BR16: 5219 | BS16: 4990 | BT16: 4913 | BU16: 4810 | BV16: 4950 | BW16: 4792 | BX16: 4746 | BY16: 4844 | BZ16: 4910 | CA16: 4952 | CB16: 5086 | CC16: 4989 | CD16: 5193 | CE16: 5275 | CF16: 5307 | CG16: 5413 | CH16: 5436 | CI16: 5425 | CJ16: 5405 | CK16: 5475 | CL16: 5397 | CM16: 5490 | CN16: 5317 | CO16: 5669 | CP16: 5762 | CQ16: 5655 | CR16: 5556 | CS16: 5426 | CT16: 5272 | CU16: 5397 | CV16: 5712 | CW16: 5297 | CX16: 5175 | CY16: 5211 | CZ16: 5120 | DA16: 5220 | DB16: 5177 | DC16: 4918 | DD16: 5073 | DE16: 5114 | DF16: 4953 | DG16: 5315 | DH16: 5324 | DI16: 5290 | DJ16: 5161 | DK16: 5161 | DL16: 5132 | DM16: 4991 | DN16: 4977 | DO16: 4900 | DP16: 4890 | DQ16: 4928 | DR16: 5058 | DS16: 5164 | DT16: 5137 | DU16: 4925 | DV16: 4723 | DW16: 4625 | DX16: 4337 | DY16: 4209 | DZ16: 4081 | EA16: 4097 | EB16: 4057 | EC16: 4088 | ED16: 4008 | EE16: 3910 | EF16: 4031 | EG16: 4082 | EH16: 4046 | EI16: 4090 | EJ16: 4118 | EK16: 4055 | EL16: 4138 | EM16: 4055 | EN16: 3979 | EO16: 3782 | EP16: 3739 | EQ16: 3770 | ER16: 3787 | ES16: 3653 | ET16: 3586 | EU16: 3569 | EV16: 3529 | EW16: 3523 | EX16: 3512 | EY16: 3568 | EZ16: 3605 | FA16: 3617 | FB16: 3628 | FC16: 3600 | FD16: 3617 | FE16: 3780 | FF16: 3763 | FG16: 3721 | FH16: 3742 | FI16: 3810 | FJ16: 3819 | FK16: 3744 | FL16: 3838 | FM16: 3670 | FN16: 3678 | FO16: 3666 | FP16: 3702 | FQ16: 3674 | FR16: 3684 | FS16: 3638 | FT16: 3658 | FU16: 3618 | FV16: 3591 | FW16: 3596 | FX16: 3673 | FY16: 3750 | FZ16: 3731 | GA16: 3704 | GB16: 3638 | GC16: 3672 | GD16: 3637 | GE16: 3639 | GF16: 3572 | GG16: 3568 | GH16: 3712 | GI16: 3681 | GJ16: 3659 | GK16: 3679 | GL16: 3772 | GM16: 3682 | GN16: 3697 | GO16: 3673 | GP16: 3628 | GQ16: 3638 | GR16: 3569 | GS16: 3561 | GT16: 3598 | GU16: 3518 | GV16: 3577 | GW16: 3603 | GX16: 3583 | GY16: 3555 | GZ16: 3526 | HA16: 3492 | HB16: 3469 | HC16: 3465 | HD16: 3531 | HE16: 3512 | HF16: 3613 | HG16: 3563 | HH16: 3534 | HI16: 3600 | HJ16: 3571 | HK16: 3505 | HL16: 3460 | HM16: 3472 | HN16: 3441 | HO16: 3441 | HP16: 3453 | HQ16: 3462 | HR16: 3497 | HS16: 3445 | HT16: 3385 | HU16: 3359 | HV16: 3453 | HW16: 3353 | HX16: 3354 | HY16: 3311 | HZ16: 3251 | IA16: 3263 | IB16: 3290 | IC16: 3233 | ID16: 3215 | IE16: 3200 | IF16: 3205 | IG16: 3203 | IH16: 3167 | II16: 3110 | IJ16: 3179 | IK16: 3173 | IL16: 3126 | IM16: 3082 | IN16: 3095 | IO16: 3002 | IP16: 2986.5 | IQ16: 3028 | IR16: 2988 | IS16: 2966 | IT16: 2944
A17: 5333 | B17: ＮＧＫ | C17: 5605 | D17: -167 | E17: 5772 | F17: 5928 | G17: 5603 | H17: 5532 | I17: 5594 | J17: 5245 | K17: 5180 | L17: 5538 | M17: 6063 | N17: 6085 | O17: 6213 | P17: 6219 | Q17: 6109 | R17: 6005 | S17: 6465 | T17: 6759 | U17: 6617 | V17: 6664 | W17: 7061 | X17: 7051 | Y17: 6856 | Z17: 7125 | AA17: 7391 | AB17: 7473 | AC17: 7392 | AD17: 7660 | AE17: 7532 | AF17: 7441 | AG17: 7509 | AH17: 7853 | AI17: 7478 | AJ17: 7424 | AK17: 7695 | AL17: 7332 | AM17: 7308 | AN17: 6972 | AO17: 6747 | AP17: 6635 | AQ17: 6117 | AR17: 5957 | AS17: 5933 | AT17: 6128 | AU17: 6092 | AV17: 6575 | AW17: 6356 | AX17: 6483 | AY17: 6170 | AZ17: 6355 | BA17: 6316 | BB17: 6120 | BC17: 6069 | BD17: 6336 | BE17: 6210 | BF17: 5861 | BG17: 5700 | BH17: 5456 | BI17: 5493 | BJ17: 5609 | BK17: 5696 | BL17: 5787 | BM17: 5731 | BN17: 5614 | BO17: 5550 | BP17: 5374 | BQ17: 5345 | BR17: 5121 | BS17: 4961 | BT17: 4670 | BU17: 4613 | BV17: 4428 | BW17: 4379 | BX17: 4481 | BY17: 4543 | BZ17: 4521 | CA17: 4473 | CB17: 4561 | CC17: 4444 | CD17: 4449 | CE17: 4412 | CF17: 4441 | CG17: 4399 | CH17: 4375 | CI17: 4145 | CJ17: 4120 | CK17: 4135 | CL17: 4059 | CM17: 4206 | CN17: 3977 | CO17: 4014 | CP17: 4144 | CQ17: 4155 | CR17: 4162 | CS17: 3937 | CT17: 3792 | CU17: 3976 | CV17: 4180 | CW17: 4046 | CX17: 4038 | CY17: 4055 | CZ17: 4070 | DA17: 4142 | DB17: 4030 | DC17: 3907 | DD17: 4191 | DE17: 4232 | DF17: 4152 | DG17: 4413 | DH17: 4549 | DI17: 4587 | DJ17: 4448 | DK17: 4484 | DL17: 4471 | DM17: 4321 | DN17: 4388 | DO17: 4288 | DP17: 4198 | DQ17: 4152 | DR17: 4131 | DS17: 4184 | DT17: 4132 | DU17: 4106 | DV17: 3987 | DW17: 3949 | DX17: 3940 | DY17: 3826 | DZ17: 3620 | EA17: 3689 | EB17: 3750 | EC17: 3748 | ED17: 3786 | EE17: 3707 | EF17: 3824 | EG17: 3727 | EH17: 3672 | EI17: 3685 | EJ17: 3776 | EK17: 3783 | EL17: 3742 | EM17: 3755 | EN17: 3641 | EO17: 3490 | EP17: 3535 | EQ17: 3469 | ER17: 3410 | ES17: 3415 | ET17: 3351 | EU17: 3368 | EV17: 3344 | EW17: 3378 | EX17: 3379 | EY17: 3390 | EZ17: 3367 | FA17: 3362 | FB17: 3272 | FC17: 3295 | FD17: 3322 | FE17: 3381 | FF17: 3433 | FG17: 3390 | FH17: 3451 | FI17: 3402 | FJ17: 3356 | FK17: 3297 | FL17: 3315 | FM17: 3234 | FN17: 3291 | FO17: 3070 | FP17: 3081 | FQ17: 3052 | FR17: 3014 | FS17: 2964.5 | FT17: 2951.5 | FU17: 2996 | FV17: 2963 | FW17: 2996.5 | FX17: 3003 | FY17: 3051 | FZ17: 3118 | GA17: 3018 | GB17: 2993.5 | GC17: 2917 | GD17: 2902 | GE17: 2916 | GF17: 2790 | GG17: 2776.5 | GH17: 2606 | GI17: 2588 | GJ17: 2553.5 | GK17: 2577 | GL17: 2631 | GM17: 2586 | GN17: 2550 | GO17: 2547 | GP17: 2518 | GQ17: 2504.5 | GR17: 2458.5 | GS17: 2496 | GT17: 2502.5 | GU17: 2430 | GV17: 2514.5 | GW17: 2588.5 | GX17: 2542.5 | GY17: 2565.5 | GZ17: 2536 | HA17: 2497 | HB17: 2461.5 | HC17: 2449 | HD17: 2479.5 | HE17: 2458 | HF17: 2511 | HG17: 2515 | HH17: 2447 | HI17: 2496 | HJ17: 2449.5 | HK17: 2458.5 | HL17: 2481 | HM17: 2468.5 | HN17: 2458.5 | HO17: 2458.5 | HP17: 2461 | HQ17: 2437.5 | HR17: 2416.5 | HS17: 2401.5 | HT17: 2352.5 | HU17: 2335 | HV17: 2325 | HW17: 2345 | HX17: 2345 | HY17: 2320 | HZ17: 2289 | IA17: 2288.5 | IB17: 2303.5 | IC17: 2299.5 | ID17: 2262 | IE17: 2252 | IF17: 2260.5 | IG17: 2257 | IH17: 2258.5 | II17: 2228 | IJ17: 2241 | IK17: 2217.5 | IL17: 2177 | IM17: 2138 | IN17: 2113.5 | IO17: 2063.5 | IP17: 2028 | IQ17: 2055.5 | IR17: 1917 | IS17: 1902.5 | IT17: 1895
... A105: 6925 | B105: ウシオ電機 | C105: 3954 | D105: -139 | E105: 4093 | F105: 4360 | G105: 4013 | H105: 3798 | I105: 3786 | J105: 3604 | K105: 3582 | L105: 3823 | M105: 4142 | N105: 4164 | O105: 4234 | P105: 4104 | Q105: 4048 | R105: 3824 | S105: 4076 | T105: 4235 | U105: 4086 | V105: 4195 | W105: 4363 | X105: 4268 | Y105: 4151 | Z105: 4368 | AA105: 4492 | AB105: 4700 | AC105: 4684 | AD105: 4828 | AE105: 4488 | AF105: 4296 | AG105: 4361 | AH105: 4508 | AI105: 4399 | AJ105: 4540 | AK105: 4765 | AL105: 4631 | AM105: 4651 | AN105: 4596 | AO105: 4302 | AP105: 4235 | AQ105: 4088 | AR105: 3918 | AS105: 3978 | AT105: 4046 | AU105: 3976 | AV105: 4260 | AW105: 4310 | AX105: 4116 | AY105: 4063 | AZ105: 4060 | BA105: 4156 | BB105: 4114 | BC105: 4199 | BD105: 4133 | BE105: 4214 | BF105: 4081 | BG105: 4040 | BH105: 3779 | BI105: 3928 | BJ105: 4179 | BK105: 4239 | BL105: 3539 | BM105: 3439 | BN105: 3492 | BO105: 3406 | BP105: 3366 | BQ105: 3385 | BR105: 3175 | BS105: 3160 | BT105: 3090 | BU105: 3148 | BV105: 3220 | BW105: 3142 | BX105: 3166 | BY105: 3191 | BZ105: 3207 | CA105: 3153 | CB105: 3323 | CC105: 3291 | CD105: 3285 | CE105: 3247 | CF105: 3259 | CG105: 3197 | CH105: 3178 | CI105: 3068 | CJ105: 3067 | CK105: 3079 | CL105: 3033 | CM105: 3058 | CN105: 2815.5 | CO105: 2844 | CP105: 2926 | CQ105: 2946.5 | CR105: 2949.5 | CS105: 2866 | CT105: 2782 | CU105: 2860 | CV105: 2925 | CW105: 2831.5 | CX105: 2825 | CY105: 2817 | CZ105: 2823.5 | DA105: 2909 | DB105: 2868.5 | DC105: 2749 | DD105: 2950 | DE105: 2986.5 | DF105: 2916 | DG105: 3111 | DH105: 3158 | DI105: 3216 | DJ105: 3162 | DK105: 3176 | DL105: 3136 | DM105: 3084 | DN105: 3095 | DO105: 3023 | DP105: 3008 | DQ105: 3006 | DR105: 2978 | DS105: 3037 | DT105: 3012 | DU105: 2973 | DV105: 2901 | DW105: 2866 | DX105: 2889.5 | DY105: 2788 | DZ105: 2706.5 | EA105: 2770 | EB105: 2765 | EC105: 2775 | ED105: 2820 | EE105: 2781 | EF105: 2854 | EG105: 2886.5 | EH105: 2796.5 | EI105: 2801.5 | EJ105: 2866.5 | EK105: 2900.5 | EL105: 2804.5 | EM105: 2784 | EN105: 2774 | EO105: 2742 | EP105: 2824 | EQ105: 2871.5 | ER105: 2825.5 | ES105: 2584.5 | ET105: 2505 | EU105: 2530 | EV105: 2532.5 | EW105: 2507 | EX105: 2494.5 | EY105: 2494 | EZ105: 2496 | FA105: 2494 | FB105: 2439 | FC105: 2443 | FD105: 2485 | FE105: 2485 | FF105: 2469 | FG105: 2426.5 | FH105: 2476 | FI105: 2478 | FJ105: 2483 | FK105: 2434.5 | FL105: 2434 | FM105: 2422.5 | FN105: 2433 | FO105: 2434 | FP105: 2454.5 | FQ105: 2429 | FR105: 2393.5 | FS105: 2360 | FT105: 2326.5 | FU105: 2323.5 | FV105: 2292.5 | FW105: 2303 | FX105: 2378.5 | FY105: 2367 | FZ105: 2412 | GA105: 2402 | GB105: 2362.5 | GC105: 2337 | GD105: 2290.5 | GE105: 2503 | GF105: 2465 | GG105: 2513.5 | GH105: 2560.5 | GI105: 2556.5 | GJ105: 2512.5 | GK105: 2512 | GL105: 2554 | GM105: 2478 | GN105: 2444.5 | GO105: 2407.5 | GP105: 2401.5 | GQ105: 2378.5 | GR105: 2340 | GS105: 2358 | GT105: 2329 | GU105: 2299.5 | GV105: 2348 | GW105: 2383 | GX105: 2337 | GY105: 2373.5 | GZ105: 2348.5 | HA105: 2320 | HB105: 2322 | HC105: 2306 | HD105: 2329.5 | HE105: 2348.5 | HF105: 2345.5 | HG105: 2315 | HH105: 2283 | HI105: 2328 | HJ105: 2266.5 | HK105: 2256.5 | HL105: 2239 | HM105: 2268 | HN105: 2254 | HO105: 2240 | HP105: 2237.5 | HQ105: 2228 | HR105: 2232 | HS105: 2219 | HT105: 2205 | HU105: 2163.5 | HV105: 2191.5 | HW105: 2162 | HX105: 2154 | HY105: 2133.5 | HZ105: 2142.5 | IA105: 2119 | IB105: 2137 | IC105: 2121 | ID105: 2100 | IE105: 2086 | IF105: 2113 | IG105: 2114 | IH105: 2119 | II105: 2110 | IJ105: 2143 | IK105: 2121.5 | IL105: 2107.5 | IM105: 2105 | IN105: 2026.5 | IO105: 1839 | IP105: 1822 | IQ105: 1850 | IR105: 1857 | IS105: 1829.5 | IT105: 1846
A106: 7021 | B106: ニッチツ | C106: 2033 | D106: -56 | E106: 2089 | F106: 2050 | G106: 2060 | H106: 2030 | I106: 2009 | J106: 1972 | K106: 1994 | L106: 1977 | M106: 1966 | N106: 1941 | O106: 1940 | P106: 1879 | Q106: 1878 | R106: 1868 | S106: 1878 | T106: 1846 | U106: 1849 | V106: 1830 | W106: 1857 | X106: 1829 | Y106: 1826 | Z106: 1839 | AA106: 1819 | AB106: 1808 | AC106: 1791 | AD106: 1799 | AE106: 1795 | AF106: 1800 | AG106: 1775 | AH106: 1791 | AI106: 1774 | AJ106: 1800 | AK106: 1760 | AL106: 1787 | AM106: 1762 | AN106: 1800 | AO106: 1809 | AP106: 1780 | AQ106: 1805 | AR106: 1769 | AS106: 1806 | AT106: 1800 | AU106: 1765 | AV106: 1810 | AW106: 1770 | AX106: 1754 | AY106: 1800 | AZ106: 1803 | BA106: 1854 | BB106: 1854 | BC106: 1894 | BD106: 1854 | BE106: 1815 | BF106: 1803 | BG106: 1822 | BH106: 1848 | BI106: 1878 | BJ106: 1916 | BK106: 1998 | BL106: 2161 | BM106: 2190 | BN106: 2156 | BO106: 2146 | BP106: 2141 | BQ106: 2166 | BR106: 2138 | BS106: 2171 | BT106: 2230 | BU106: 2226 | BV106: 2258 | BW106: 2280 | BX106: 2294 | BY106: 2312 | BZ106: 2333 | CA106: 2341 | CB106: 2334 | CC106: 2350 | CD106: 2350 | CE106: 2340 | CF106: 2322 | CG106: 2312 | CH106: 2296 | CI106: 2291 | CJ106: 2290 | CK106: 2295 | CL106: 2240 | CM106: 2257 | CN106: 2228 | CO106: 2203 | CP106: 2250 | CQ106: 2266 | CR106: 2271 | CS106: 2261 | CT106: 2264 | CU106: 2255 | CV106: 2314 | CW106: 2258 | CX106: 2241 | CY106: 2224 | CZ106: 2250 | DA106: 2280 | DB106: 2251 | DC106: 2175 | DD106: 2214 | DE106: 2235 | DF106: 2161 | DG106: 2290 | DH106: 2335 | DI106: 2356 | DJ106: 2367 | DK106: 2357 | DL106: 2350 | DM106: 2350 | DN106: 2343 | DO106: 2336 | DP106: 2255 | DQ106: 2317 | DR106: 2470 | DS106: 2503 | DT106: 2494 | DU106: 2464 | DV106: 2435 | DW106: 2451 | DX106: 2475 | DY106: 2427 | DZ106: 2405 | EA106: 2425 | EB106: 2448 | EC106: 2475 | ED106: 2400 | EE106: 2354 | EF106: 2451 | EG106: 2479 | EH106: 2479 | EI106: 2489 | EJ106: 2505 | EK106: 2495 | EL106: 2438 | EM106: 2435 | EN106: 2456 | EO106: 2481 | EP106: 2412 | EQ106: 2347 | ER106: 2290 | ES106: 2285 | ET106: 2252 | EU106: 2234 | EV106: 2222 | EW106: 2249 | EX106: 2277 | EY106: 2255 | EZ106: 2300 | FA106: 2269 | FB106: 2259 | FC106: 2258 | FD106: 2213 | FE106: 2212 | FF106: 2225 | FG106: 2166 | FH106: 2218 | FI106: 2204 | FJ106: 2206 | FK106: 2172 | FL106: 2152 | FM106: 2151 | FN106: 2146 | FO106: 2187 | FP106: 2248 | FQ106: 2215 | FR106: 2140 | FS106: 2172 | FT106: 2104 | FU106: 2136 | FV106: 2150 | FW106: 2132 | FX106: 2198 | FY106: 2269 | FZ106: 2427 | GA106: 2326 | GB106: 2345 | GC106: 2388 | GD106: 2330 | GE106: 2431 | GF106: 2489 | GG106: 2470 | GH106: 2311 | GI106: 2459 | GJ106: 2552 | GK106: 2770 | GL106: 2751 | GM106: 2251 | GN106: 1992 | GO106: 1990 | GP106: 1985 | GQ106: 1956 | GR106: 1973 | GS106: 1963 | GT106: 1933 | GU106: 1900 | GV106: 1979 | GW106: 1995 | GX106: 1990 | GY106: 1985 | GZ106: 1980 | HA106: 1960 | HB106: 1969 | HC106: 1941 | HD106: 2010 | HE106: 2012 | HF106: 2012 | HG106: 2019 | HH106: 2019 | HI106: 2014 | HJ106: 1982 | HK106: 1962 | HL106: 1939 | HM106: 1951 | HN106: 1971 | HO106: 1968 | HP106: 1979 | HQ106: 1955 | HR106: 1959 | HS106: 1971 | HT106: 1955 | HU106: 1951 | HV106: 1939 | HW106: 1936 | HX106: 1970 | HY106: 1930 | HZ106: 1917 | IA106: 1911 | IB106: 1940 | IC106: 1929 | ID106: 1924 | IE106: 1903 | IF106: 1957 | IG106: 1915 | IH106: 1929 | II106: 1903 | IJ106: 1918 | IK106: 1895 | IL106: 1885 | IM106: 1991 | IN106: 1980 | IO106: 1979 | IP106: 1959 | IR106: 1980 | IS106: 1950 | IT106: 1973
A107: 7729 | B107: 東京精密 | C107: 17485 | D107: -505 | E107: 17990 | F107: 18755 | G107: 18060 | H107: 17235 | I107: 17160 | J107: 15445 | K107: 14760 | L107: 16120 | M107: 17865 | N107: 17520 | O107: 18445 | P107: 18255 | Q107: 18185 | R107: 17055 | S107: 18850 | T107: 19210 | U107: 18325 | V107: 18815 | W107: 18905 | X107: 18105 | Y107: 17330 | Z107: 17740 | AA107: 18830 | AB107: 19370 | AC107: 19110 | AD107: 20920 | AE107: 20130 | AF107: 19275 | AG107: 19320 | AH107: 20060 | AI107: 18730 | AJ107: 18900 | AK107: 20160 | AL107: 20075 | AM107: 20145 | AN107: 19255 | AO107: 19190 | AP107: 19760 | AQ107: 18655 | AR107: 17480 | AS107: 16925 | AT107: 17520 | AU107: 16640 | AV107: 17910 | AW107: 18325 | AX107: 17715 | AY107: 16910 | AZ107: 16820 | BA107: 17385 | BB107: 17570 | BC107: 17705 | BD107: 17445 | BE107: 18350 | BF107: 16915 | BG107: 16395 | BH107: 15630 | BI107: 15915 | BJ107: 16395 | BK107: 16515 | BL107: 17765 | BM107: 18690 | BN107: 18985 | BO107: 18860 | BP107: 18765 | BQ107: 18305 | BR107: 17355 | BS107: 17130 | BT107: 17355 | BU107: 17350 | BV107: 17430 | BW107: 16900 | BX107: 16650 | BY107: 16720 | BZ107: 16250 | CA107: 16420 | CB107: 16945 | CC107: 16545 | CD107: 16035 | CE107: 15700 | CF107: 15890 | CG107: 15395 | CH107: 15200 | CI107: 14035 | CJ107: 14150 | CK107: 14065 | CL107: 13795 | CM107: 14165 | CN107: 13210 | CO107: 13420 | CP107: 14190 | CQ107: 14630 | CR107: 14735 | CS107: 14150 | CT107: 13755 | CU107: 14280 | CV107: 14875 | CW107: 14305 | CX107: 14685 | CY107: 14415 | CZ107: 14955 | DA107: 15525 | DB107: 14995 | DC107: 14240 | DD107: 16155 | DE107: 16340 | DF107: 15605 | DG107: 16715 | DH107: 17260 | DI107: 17300 | DJ107: 18235 | DK107: 17890 | DL107: 17035 | DM107: 16895 | DN107: 17025 | DO107: 16500 | DP107: 16220 | DQ107: 16450 | DR107: 16630 | DS107: 17120 | DT107: 16700 | DU107: 15820 | DV107: 13845 | DW107: 13560 | DX107: 13995 | DY107: 14165 | DZ107: 13415 | EA107: 13950 | EB107: 14045 | EC107: 13945 | ED107: 13565 | EE107: 13095 | EF107: 13595 | EG107: 13535 | EH107: 12650 | EI107: 12425 | EJ107: 12655 | EK107: 12795 | EL107: 12335 | EM107: 12500 | EN107: 12380 | EO107: 11760 | EP107: 11720 | EQ107: 11790 | ER107: 11705 | ES107: 11535 | ET107: 11105 | EU107: 11210 | EV107: 11425 | EW107: 11290 | EX107: 11100 | EY107: 10970 | EZ107: 11050 | FA107: 10385 | FB107: 10305 | FC107: 10500 | FD107: 10205 | FE107: 10340 | FF107: 10910 | FG107: 10915 | FH107: 11110 | FI107: 10965 | FJ107: 10850 | FK107: 10695 | FL107: 10830 | FM107: 10695 | FN107: 10300 | FO107: 10340 | FP107: 10375 | FQ107: 10385 | FR107: 10365 | FS107: 10230 | FT107: 10295 | FU107: 10835 | FV107: 10085 | FW107: 10300 | FX107: 10415 | FY107: 10275 | FZ107: 10670 | GA107: 10605 | GB107: 10770 | GC107: 10945 | GD107: 10785 | GE107: 10860 | GF107: 10980 | GG107: 11140 | GH107: 10660 | GI107: 10310 | GJ107: 10725 | GK107: 10350 | GL107: 10490 | GM107: 10270 | GN107: 10045 | GO107: 10215 | GP107: 10265 | GQ107: 10260 | GR107: 9982 | GS107: 10185 | GT107: 10140 | GU107: 9972 | GV107: 10260 | GW107: 10455 | GX107: 10655 | GY107: 10915 | GZ107: 11020 | HA107: 10720 | HB107: 10835 | HC107: 9932 | HD107: 10055 | HE107: 10100 | HF107: 10000 | HG107: 10705 | HH107: 10580 | HI107: 10200 | HJ107: 10140 | HK107: 9549 | HL107: 9107 | HM107: 9000 | HN107: 8704 | HO107: 8565 | HP107: 8410 | HQ107: 8368 | HR107: 8435 | HS107: 8297 | HT107: 8098 | HU107: 7998 | HV107: 8023 | HW107: 8115 | HX107: 8413 | HY107: 8429 | HZ107: 8414 | IA107: 8372 | IB107: 8402 | IC107: 8372 | ID107: 8166 | IE107: 8214 | IF107: 8400 | IG107: 8416 | IH107: 8375 | II107: 8421 | IJ107: 8450 | IK107: 8396 | IL107: 8255 | IM107: 8323 | IN107: 8407 | IO107: 8543 | IP107: 9255 | IQ107: 9443 | IR107: 9550 | IS107: 9365 | IT107: 9294
A108: 8424 | B108: 芙蓉総合リース | C108: 4465 | D108: 52 | E108: 4413 | F108: 4365 | G108: 4375 | H108: 4464 | I108: 4543 | J108: 4517 | K108: 4591 | L108: 4482 | M108: 4520 | N108: 4432 | O108: 4422 | P108: 4432 | Q108: 4425 | R108: 4345 | S108: 4352 | T108: 4361 | U108: 4333 | V108: 4271 | W108: 4267 | X108: 4272 | Y108: 4260 | Z108: 4279 | AA108: 4241 | AB108: 4189 | AC108: 4181 | AD108: 4163 | AE108: 4220 | AF108: 4226 | AG108: 4235 | AH108: 4194 | AI108: 4180 | AJ108: 4176 | AK108: 4216 | AL108: 4256 | AM108: 4240 | AN108: 4236 | AO108: 4281 | AP108: 4311 | AQ108: 4284 | AR108: 4272 | AS108: 4314 | AT108: 4218 | AU108: 4192 | AV108: 4137 | AW108: 4070 | AX108: 4089 | AY108: 4081 | AZ108: 4094 | BA108: 4194 | BB108: 4182 | BC108: 4184 | BD108: 4198 | BE108: 4234 | BF108: 4287 | BG108: 4375 | BH108: 4333 | BI108: 4387 | BJ108: 4315 | BK108: 4378 | BL108: 4394 | BM108: 4348 | BN108: 4403 | BO108: 4293 | BP108: 4272 | BQ108: 4328 | BR108: 4295 | BS108: 4334 | BT108: 4350 | BU108: 4263 | BV108: 4279 | BW108: 4268 | BX108: 4265 | BY108: 4261 | BZ108: 4307 | CA108: 4336 | CB108: 4330 | CC108: 4333 | CD108: 4310 | CE108: 4326 | CF108: 4338 | CG108: 4395 | CH108: 4443 | CI108: 4379 | CJ108: 4341 | CK108: 4356 | CL108: 4336 | CM108: 4341 | CN108: 4258 | CO108: 4259 | CP108: 4403 | CQ108: 4405 | CR108: 4430 | CS108: 4347 | CT108: 4299 | CU108: 4386 | CV108: 4447 | CW108: 4404 | CX108: 4389 | CY108: 4382 | CZ108: 4385 | DA108: 4459 | DB108: 4429 | DC108: 4355 | DD108: 4431 | DE108: 4421 | DF108: 4344 | DG108: 4536 | DH108: 4636 | DI108: 4646 | DJ108: 4577 | DK108: 4522 | DL108: 4541 | DM108: 4583 | DN108: 4642 | DO108: 4616 | DP108: 4526 | DQ108: 4552 | DR108: 4529 | DS108: 4579 | DT108: 4587 | DU108: 4542 | DV108: 4460 | DW108: 4414 | DX108: 4394 | DY108: 4385 | DZ108: 4322 | EA108: 4343 | EB108: 4313 | EC108: 4302 | ED108: 4380 | EE108: 4389 | EF108: 4459 | EG108: 4448 | EH108: 4357 | EI108: 4423 | EJ108: 4445 | EK108: 4443 | EL108: 4503 | EM108: 4439 | EN108: 4426 | EO108: 4390 | EP108: 4400 | EQ108: 4405 | ER108: 4446 | ES108: 4344 | ET108: 4293 | EU108: 4331 | EV108: 4327 | EW108: 4300 | EX108: 4306 | EY108: 4298 | EZ108: 4241 | FA108: 4247 | FB108: 4234 | FC108: 4180 | FD108: 4206 | FE108: 4237 | FF108: 4213 | FG108: 4127 | FH108: 4190 | FI108: 4165 | FJ108: 4149 | FK108: 4103 | FL108: 4186 | FM108: 4148 | FN108: 4162 | FO108: 4168 | FP108: 4182 | FQ108: 4126 | FR108: 4146 | FS108: 4099 | FT108: 4098 | FU108: 4007 | FV108: 3999 | FW108: 4005 | FX108: 4010 | FY108: 4041 | FZ108: 4034 | GA108: 4032 | GB108: 3996 | GC108: 3994 | GD108: 4005 | GE108: 4034 | GF108: 4023 | GG108: 4055 | GH108: 4035 | GI108: 4053 | GJ108: 3992 | GK108: 4078 | GL108: 4127 | GM108: 4126 | GN108: 4460 | GO108: 4409 | GP108: 4374 | GQ108: 4360 | GR108: 4304 | GS108: 4333 | GT108: 4328 | GU108: 4281 | GV108: 4284 | GW108: 4365 | GX108: 4359 | GY108: 4301 | GZ108: 4324 | HA108: 4268 | HB108: 4254 | HC108: 4304 | HD108: 4425 | HE108: 4432 | HF108: 4541 | HG108: 4484 | HH108: 4464 | HI108: 4467 | HJ108: 4452 | HK108: 4441 | HL108: 4450 | HM108: 4498 | HN108: 4483 | HO108: 4489 | HP108: 4487 | HQ108: 4451 | HR108: 4460 | HS108: 4458 | HT108: 4459 | HU108: 4438 | HV108: 4426 | HW108: 4377 | HX108: 4382 | HY108: 4426 | HZ108: 4386 | IA108: 4364 | IB108: 4382 | IC108: 4378 | ID108: 4341 | IE108: 4359 | IF108: 4347 | IG108: 4327 | IH108: 4287 | II108: 4246 | IJ108: 4276 | IK108: 4254 | IL108: 4210 | IM108: 4180 | IN108: 4178 | IO108: 4142 | IP108: 4133 | IQ108: 4147 | IR108: 4088 | IS108: 4068 | IT108: 4050
A109: 9020 | B109: 東日本旅客鉄道 | C109: 3485 | D109: 57 | E109: 3428 | F109: 3369 | G109: 3408 | H109: 3422 | I109: 3676 | J109: 3820 | K109: 3935 | L109: 3829 | M109: 3756 | N109: 3632 | O109: 3566 | P109: 3617 | Q109: 3650 | R109: 3624 | S109: 3601 | T109: 3580 | U109: 3564 | V109: 3531 | W109: 3478 | X109: 3517 | Y109: 3541 | Z109: 3554 | AA109: 3502 | AB109: 3459 | AC109: 3410 | AD109: 3295 | AE109: 3408 | AF109: 3452 | AG109: 3386 | AH109: 3343 | AI109: 3363 | AJ109: 3351 | AK109: 3324 | AL109: 3415 | AM109: 3393 | AN109: 3345 | AO109: 3398 | AP109: 3377 | AQ109: 3404 | AR109: 3460 | AS109: 3460 | AT109: 3383 | AU109: 3380 | AV109: 3366 | AW109: 3280 | AX109: 3313 | AY109: 3345 | AZ109: 3354 | BA109: 3412 | BB109: 3444 | BC109: 3528 | BD109: 3551 | BE109: 3570 | BF109: 3606 | BG109: 3692 | BH109: 3775 | BI109: 3788 | BJ109: 3682 | BK109: 3766 | BL109: 3680 | BM109: 3764 | BN109: 3693 | BO109: 3639 | BP109: 3645 | BQ109: 3610 | BR109: 3700 | BS109: 3388 | BT109: 3451 | BU109: 3427 | BV109: 3461 | BW109: 3501 | BX109: 3522 | BY109: 3544 | BZ109: 3517 | CA109: 3478 | CB109: 3525 | CC109: 3582 | CD109: 3514 | CE109: 3602 | CF109: 3559 | CG109: 3579 | CH109: 3608 | CI109: 3574 | CJ109: 3576 | CK109: 3640 | CL109: 3675 | CM109: 3684 | CN109: 3625 | CO109: 3620 | CP109: 3671 | CQ109: 3647 | CR109: 3635 | CS109: 3589 | CT109: 3557 | CU109: 3611 | CV109: 3702 | CW109: 3756 | CX109: 3721 | CY109: 3721 | CZ109: 3762 | DA109: 3817 | DB109: 3754 | DC109: 3789 | DD109: 3709 | DE109: 3730 | DF109: 3705 | DG109: 3768 | DH109: 3880 | DI109: 3860 | DJ109: 3844 | DK109: 3819 | DL109: 3828 | DM109: 3814 | DN109: 3834 | DO109: 3836 | DP109: 3761 | DQ109: 3789 | DR109: 3810 | DS109: 3772 | DT109: 3887 | DU109: 3927 | DV109: 3978 | DW109: 3860 | DX109: 3764 | DY109: 3742 | DZ109: 3796 | EA109: 3893 | EB109: 3838 | EC109: 3806 | ED109: 3922 | EE109: 3968 | EF109: 3961 | EG109: 3968 | EH109: 3991 | EI109: 4009 | EJ109: 3929 | EK109: 3960 | EL109: 4070 | EM109: 4137 | EN109: 4194 | EO109: 4146 | EP109: 4133 | EQ109: 4121 | ER109: 4185 | ES109: 4157 | ET109: 4132 | EU109: 4152 | EV109: 4159 | EW109: 4149 | EX109: 4129 | EY109: 4080 | EZ109: 4020 | FA109: 4116 | FB109: 4100 | FC109: 4043 | FD109: 4139 | FE109: 4200 | FF109: 4006 | FG109: 3921 | FH109: 3977 | FI109: 3949 | FJ109: 3939 | FK109: 3861 | FL109: 3951 | FM109: 3939 | FN109: 4037 | FO109: 4002 | FP109: 4046 | FQ109: 4077 | FR109: 4041 | FS109: 4000 | FT109: 3962 | FU109: 3818 | FV109: 3812 | FW109: 3800 | FX109: 3768 | FY109: 3804 | FZ109: 3803 | GA109: 3763 | GB109: 3794 | GC109: 3878 | GD109: 3858 | GE109: 3783 | GF109: 3768 | GG109: 3673 | GH109: 3756 | GI109: 3596 | GJ109: 3630 | GK109: 3662 | GL109: 3687 | GM109: 3672 | GN109: 3692 | GO109: 3693 | GP109: 3640 | GQ109: 3634 | GR109: 3595 | GS109: 3598 | GT109: 3613 | GU109: 3607 | GV109: 3561 | GW109: 3584 | GX109: 3597 | GY109: 3591 | GZ109: 3621 | HA109: 3595 | HB109: 3529 | HC109: 3600 | HD109: 3620 | HE109: 3634 | HF109: 3727 | HG109: 3692 | HH109: 3716 | HI109: 3629 | HJ109: 3638 | HK109: 3661 | HL109: 3683 | HM109: 3694 | HN109: 3680 | HO109: 3696 | HP109: 3727 | HQ109: 3749 | HR109: 3795 | HS109: 3749 | HT109: 3735 | HU109: 3719 | HV109: 3689 | HW109: 3675 | HX109: 3614 | HY109: 3645 | HZ109: 3562 | IA109: 3533 | IB109: 3593 | IC109: 3651 | ID109: 3600 | IE109: 3650 | IF109: 3621 | IG109: 3583 | IH109: 3567 | II109: 3503 | IJ109: 3522 | IK109: 3544 | IL109: 3516 | IM109: 3468 | IN109: 3455 | IO109: 3368 | IP109: 3305 | IQ109: 3344 | IR109: 3218 | IS109: 3206 | IT109: 3151
A110: 9069 | B110: センコーグループＨＬＤＧＳ | C110: 2237 | D110: 21.5 | E110: 2215.5 | F110: 2196 | G110: 2195 | H110: 2219.5 | I110: 2205.5 | J110: 2237 | K110: 2261.5 | L110: 2196 | M110: 2205.5 | N110: 2187.5 | O110: 2186.5 | P110: 2200.5 | Q110: 2225.5 | R110: 2195 | S110: 2121 | T110: 2132 | U110: 2114 | V110: 2103.5 | W110: 2052 | X110: 2042 | Y110: 2018 | Z110: 2015 | AA110: 1994 | AB110: 1974 | AC110: 1906.5 | AD110: 1900 | AE110: 1958 | AF110: 1935 | AG110: 1921.5 | AH110: 1900 | AI110: 1891 | AJ110: 1899.5 | AK110: 1901 | AL110: 1883.5 | AM110: 1898 | AN110: 1907.5 | AO110: 1932.5 | AP110: 1964 | AQ110: 1922.5 | AR110: 1945 | AS110: 1954 | AT110: 1947.5 | AU110: 1952.5 | AV110: 1907.5 | AW110: 1902.5 | AX110: 1917 | AY110: 1893.5 | AZ110: 1892 | BA110: 1906.5 | BB110: 1919.5 | BC110: 1918 | BD110: 1917.5 | BE110: 1935 | BF110: 1966.5 | BG110: 2032 | BH110: 2012 | BI110: 2027 | BJ110: 2005 | BK110: 2031.5 | BL110: 2006 | BM110: 1849.5 | BN110: 1828.5 | BO110: 1858 | BP110: 1869 | BQ110: 1864.5 | BR110: 1828 | BS110: 1845.5 | BT110: 1868 | BU110: 1827.5 | BV110: 1854.5 | BW110: 1875 | BX110: 1899 | BY110: 1915 | BZ110: 1906.5 | CA110: 1886 | CB110: 1901 | CC110: 1887 | CD110: 1877.5 | CE110: 1867 | CF110: 1876 | CG110: 1917 | CH110: 1903.5 | CI110: 1872.5 | CJ110: 1855 | CK110: 1867 | CL110: 1875 | CM110: 1869.5 | CN110: 1795.5 | CO110: 1783 | CP110: 1808 | CQ110: 1806.5 | CR110: 1809 | CS110: 1789.5 | CT110: 1738.5 | CU110: 1793 | CV110: 1836.5 | CW110: 1800.5 | CX110: 1785 | CY110: 1794 | CZ110: 1824.5 | DA110: 1881 | DB110: 1865.5 | DC110: 1836.5 | DD110: 1866.5 | DE110: 1876.5 | DF110: 1835 | DG110: 1867 | DH110: 1936.5 | DI110: 1969 | DJ110: 1926.5 | DK110: 1914 | DL110: 1921 | DM110: 1926.5 | DN110: 1960.5 | DO110: 1974.5 | DP110: 1933.5 | DQ110: 1925 | DR110: 1943.5 | DS110: 1997.5 | DT110: 1998 | DU110: 1974.5 | DV110: 1966 | DW110: 1960 | DX110: 1925 | DY110: 1940.5 | DZ110: 1924.5 | EA110: 1923.5 | EB110: 1938 | EC110: 1957 | ED110: 1998.5 | EE110: 2026.5 | EF110: 2072.5 | EG110: 2068 | EH110: 2051 | EI110: 2073 | EJ110: 2126.5 | EK110: 2137 | EL110: 2094 | EM110: 2066 | EN110: 2063 | EO110: 2026.5 | EP110: 2031 | EQ110: 2038.5 | ER110: 2019 | ES110: 1976 | ET110: 1953.5 | EU110: 1976 | EV110: 1964.5 | EW110: 1958.5 | EX110: 1922 | EY110: 1923 | EZ110: 1929.5 | FA110: 1933 | FB110: 1922 | FC110: 1930.5 | FD110: 1934 | FE110: 1885 | FF110: 1866 | FG110: 1840 | FH110: 1836.5 | FI110: 1862 | FJ110: 1862 | FK110: 1862 | FL110: 1904 | FM110: 1912 | FN110: 1912 | FO110: 1931 | FP110: 1949.5 | FQ110: 1938 | FR110: 1907 | FS110: 1883 | FT110: 1868 | FU110: 1839 | FV110: 1808.5 | FW110: 1823.5 | FX110: 1822.5 | FY110: 1760.5 | FZ110: 1989.5 | GA110: 1997.5 | GB110: 2000.5 | GC110: 2009 | GD110: 2032 | GE110: 2042 | GF110: 2022 | GG110: 1999 | GH110: 2012 | GI110: 2018 | GJ110: 1971 | GK110: 2025 | GL110: 2118 | GM110: 2068 | GN110: 2108 | GO110: 2087 | GP110: 2037 | GQ110: 2046 | GR110: 2031 | GS110: 2003 | GT110: 2017 | GU110: 1988 | GV110: 2023 | GW110: 2027 | GX110: 2017 | GY110: 2035 | GZ110: 2025 | HA110: 1992 | HB110: 1978 | HC110: 2004 | HD110: 2034 | HE110: 2066 | HF110: 2108 | HG110: 2052 | HH110: 2051 | HI110: 2058 | HJ110: 2080 | HK110: 2078 | HL110: 2062 | HM110: 2095 | HN110: 2112 | HO110: 2102 | HP110: 2100 | HQ110: 2099 | HR110: 2092 | HS110: 2044 | HT110: 2069 | HU110: 2030 | HV110: 2020 | HW110: 2029 | HX110: 2021 | HY110: 2034 | HZ110: 2055 | IA110: 2040 | IB110: 2028 | IC110: 2034 | ID110: 2038 | IE110: 2039 | IF110: 2029 | IG110: 2019 | IH110: 2021 | II110: 2025 | IJ110: 2026 | IK110: 2032 | IL110: 2052 | IM110: 2083 | IN110: 2078 | IO110: 2044 | IP110: 2042 | IQ110: 2038 | IR110: 2036 | IS110: 2021 | IT110: 2014
A111: 9227 | B111: マイクロ波化学 | C111: 901 | D111: 2 | E111: 899 | F111: 893 | G111: 880 | H111: 850 | I111: 857 | J111: 887 | K111: 922 | L111: 817 | M111: 823 | N111: 790 | O111: 808 | P111: 811 | Q111: 811 | R111: 769 | S111: 820 | T111: 844 | U111: 838 | V111: 835 | W111: 875 | X111: 862 | Y111: 904 | Z111: 966 | AA111: 953 | AB111: 938 | AC111: 947 | AD111: 940 | AE111: 907 | AF111: 876 | AG111: 876 | AH111: 897 | AI111: 896 | AJ111: 892 | AK111: 946 | AL111: 887 | AM111: 887 | AN111: 881 | AO111: 865 | AP111: 882 | AQ111: 865 | AR111: 864 | AS111: 865 | AT111: 927 | AU111: 915 | AV111: 930 | AW111: 887 | AX111: 904 | AY111: 912 | AZ111: 996 | BA111: 1031 | BB111: 1120 | BC111: 1209 | BD111: 1115 | BE111: 1093 | BF111: 943 | BG111: 793 | BH111: 770 | BI111: 799 | BJ111: 813 | BK111: 822 | BL111: 806 | BM111: 854 | BN111: 962 | BO111: 980 | BP111: 1015 | BQ111: 1006 | BR111: 1027 | BS111: 1024 | BT111: 1040 | BU111: 1034 | BV111: 1063 | BW111: 1095 | BX111: 1133 | BY111: 1181 | BZ111: 1196 | CA111: 1061 | CB111: 1043 | CC111: 1017 | CD111: 1002 | CE111: 1000 | CF111: 948 | CG111: 972 | CH111: 998 | CI111: 928 | CJ111: 948 | CK111: 956 | CL111: 975 | CM111: 1020 | CN111: 950 | CO111: 960 | CP111: 978 | CQ111: 972 | CR111: 1017 | CS111: 999 | CT111: 978 | CU111: 1074 | CV111: 1144 | CW111: 994 | CX111: 1009 | CY111: 998 | CZ111: 1001 | DA111: 1028 | DB111: 1050 | DC111: 969 | DD111: 1037 | DE111: 1028 | DF111: 946 | DG111: 995 | DH111: 1062 | DI111: 1104 | DJ111: 1068 | DK111: 1121 | DL111: 983 | DM111: 1012 | DN111: 1096 | DO111: 1046 | DP111: 1065 | DQ111: 1284 | DR111: 1203 | DS111: 1320 | DT111: 1238 | DU111: 1180 | DV111: 1300 | DW111: 1239 | DX111: 1368 | DY111: 1276 | DZ111: 1050 | EA111: 1010 | EB111: 959 | EC111: 992 | ED111: 1066 | EE111: 1091 | EF111: 1107 | EG111: 1096 | EH111: 1224 | EI111: 1289 | EJ111: 1398 | EK111: 1204 | EL111: 1350 | EM111: 1320 | EN111: 1020 | EO111: 870 | EP111: 765 | EQ111: 665 | ER111: 624 | ES111: 607 | ET111: 588 | EU111: 613 | EV111: 600 | EW111: 610 | EX111: 603 | EY111: 622 | EZ111: 608 | FA111: 616 | FB111: 621 | FC111: 622 | FD111: 647 | FE111: 675 | FF111: 677 | FG111: 688 | FH111: 707 | FI111: 709 | FJ111: 713 | FK111: 696 | FL111: 730 | FM111: 698 | FN111: 667 | FO111: 672 | FP111: 712 | FQ111: 698 | FR111: 710 | FS111: 737 | FT111: 713 | FU111: 722 | FV111: 742 | FW111: 731 | FX111: 770 | FY111: 729 | FZ111: 736 | GA111: 750 | GB111: 731 | GC111: 752 | GD111: 721 | GE111: 717 | GF111: 723 | GG111: 738 | GH111: 740 | GI111: 720 | GJ111: 755 | GK111: 773 | GL111: 779 | GM111: 771 | GN111: 798 | GO111: 816 | GP111: 832 | GQ111: 826 | GR111: 772 | GS111: 819 | GT111: 843 | GU111: 745 | GV111: 700 | GW111: 739 | GX111: 750 | GY111: 771 | GZ111: 733 | HA111: 706 | HB111: 677 | HC111: 759 | HD111: 720 | HE111: 647 | HF111: 644 | HG111: 625 | HH111: 638 | HI111: 669 | HJ111: 648 | HK111: 638 | HL111: 650 | HM111: 630 | HN111: 621 | HO111: 670 | HP111: 694 | HQ111: 711 | HR111: 704 | HS111: 664 | HT111: 670 | HU111: 674 | HV111: 668 | HW111: 655 | HX111: 649 | HY111: 670 | HZ111: 671 | IA111: 702 | IB111: 720 | IC111: 702 | ID111: 727 | IE111: 627 | IF111: 675 | IG111: 680 | IH111: 647 | II111: 618 | IJ111: 592 | IK111: 616 | IL111: 607 | IM111: 611 | IN111: 566 | IO111: 617 | IP111: 591 | IQ111: 570 | IR111: 543 | IS111: 543 | IT111: 529
A112: 9348 | B112: ｉｓｐａｃｅ | C112: 414 | D112: -3 | E112: 417 | F112: 422 | G112: 413 | H112: 403 | I112: 405 | J112: 406 | K112: 400 | L112: 408 | M112: 419 | N112: 413 | O112: 416 | P112: 415 | Q112: 413 | R112: 411 | S112: 421 | T112: 449 | U112: 440 | V112: 442 | W112: 445 | X112: 508 | Y112: 428 | Z112: 441 | AA112: 448 | AB112: 450 | AC112: 441 | AD112: 440 | AE112: 449 | AF112: 439 | AG112: 430 | AH112: 443 | AI112: 441 | AJ112: 435 | AK112: 455 | AL112: 434 | AM112: 468 | AN112: 473 | AO112: 468 | AP112: 503 | AQ112: 551 | AR112: 576 | AS112: 577 | AT112: 581 | AU112: 598 | AV112: 615 | AW112: 555 | AX112: 587 | AY112: 583 | AZ112: 588 | BA112: 671 | BB112: 699 | BC112: 600 | BD112: 597 | BE112: 580 | BF112: 568 | BG112: 507 | BH112: 494 | BI112: 534 | BJ112: 496 | BK112: 506 | BL112: 499 | BM112: 498 | BN112: 497 | BO112: 510 | BP112: 503 | BQ112: 484 | BR112: 470 | BS112: 468 | BT112: 476 | BU112: 466 | BV112: 476 | BW112: 482 | BX112: 492 | BY112: 488 | BZ112: 496 | CA112: 496 | CB112: 489 | CC112: 512 | CD112: 510 | CE112: 500 | CF112: 515 | CG112: 457 | CH112: 456 | CI112: 434 | CJ112: 432 | CK112: 424 | CL112: 472 | CM112: 444 | CN112: 435 | CO112: 466 | CP112: 566 | CQ112: 566 | CR112: 577 | CS112: 549 | CT112: 537 | CU112: 584 | CV112: 603 | CW112: 575 | CX112: 578 | CY112: 577 | CZ112: 575 | DA112: 571 | DB112: 567 | DC112: 550 | DD112: 570 | DE112: 586 | DF112: 554 | DG112: 581 | DH112: 602 | DI112: 617 | DJ112: 581 | DK112: 570 | DL112: 575 | DM112: 601 | DN112: 599 | DO112: 602 | DP112: 573 | DQ112: 552 | DR112: 548 | DS112: 572 | DT112: 649 | DU112: 633 | DV112: 645 | DW112: 612 | DX112: 635 | DY112: 597 | DZ112: 582 | EA112: 587 | EB112: 590 | EC112: 548 | ED112: 562 | EE112: 545 | EF112: 550 | EG112: 528 | EH112: 543 | EI112: 555 | EJ112: 604 | EK112: 552 | EL112: 549 | EM112: 509 | EN112: 519 | EO112: 519 | EP112: 516 | EQ112: 479 | ER112: 487 | ES112: 468 | ET112: 448 | EU112: 458 | EV112: 435 | EW112: 436 | EX112: 426 | EY112: 425 | EZ112: 415 | FA112: 426 | FB112: 409 | FC112: 415 | FD112: 422 | FE112: 442 | FF112: 427 | FG112: 422 | FH112: 428 | FI112: 431 | FJ112: 435 | FK112: 437 | FL112: 432 | FM112: 425 | FN112: 438 | FO112: 444 | FP112: 461 | FQ112: 460 | FR112: 456 | FS112: 439 | FT112: 443 | FU112: 449 | FV112: 451 | FW112: 449 | FX112: 457 | FY112: 467 | FZ112: 472 | GA112: 476 | GB112: 470 | GC112: 469 | GD112: 470 | GE112: 466 | GF112: 466 | GG112: 471 | GH112: 482 | GI112: 479 | GJ112: 467 | GK112: 480 | GL112: 496 | GM112: 478 | GN112: 480 | GO112: 475 | GP112: 471 | GQ112: 491 | GR112: 493 | GS112: 500 | GT112: 520 | GU112: 516 | GV112: 533 | GW112: 539 | GX112: 540 | GY112: 560 | GZ112: 554 | HA112: 529 | HB112: 527 | HC112: 526 | HD112: 529 | HE112: 531 | HF112: 534 | HG112: 539 | HH112: 538 | HI112: 541 | HJ112: 545 | HK112: 539 | HL112: 539 | HM112: 545 | HN112: 526 | HO112: 525 | HP112: 527 | HQ112: 525 | HR112: 531 | HS112: 529 | HT112: 526 | HU112: 534 | HV112: 550 | HW112: 528 | HX112: 531 | HY112: 528 | HZ112: 531 | IA112: 530 | IB112: 525 | IC112: 520 | ID112: 521 | IE112: 530 | IF112: 536 | IG112: 538 | IH112: 533 | II112: 542 | IJ112: 538 | IK112: 538 | IL112: 554 | IM112: 546 | IN112: 550 | IO112: 554 | IP112: 560 | IQ112: 555 | IR112: 551 | IS112: 558 | IT112: 558
A113: 9449 | B113: ＧＭＯインターネットグループ | C113: 4203 | D113: 7 | E113: 4196 | F113: 4184 | G113: 4148 | H113: 4151 | I113: 4254 | J113: 4212 | K113: 4258 | L113: 4100 | M113: 4120 | N113: 3916 | O113: 3963 | P113: 3950 | Q113: 4058 | R113: 4056 | S113: 4075 | T113: 4038 | U113: 3992 | V113: 3912 | W113: 3908 | X113: 3807 | Y113: 3838 | Z113: 3675 | AA113: 3646 | AB113: 3609 | AC113: 3534 | AD113: 3370 | AE113: 3342 | AF113: 3388 | AG113: 3283 | AH113: 3227 | AI113: 3275 | AJ113: 3242 | AK113: 3542 | AL113: 3000 | AM113: 3124 | AN113: 3098 | AO113: 3083 | AP113: 3101 | AQ113: 3083 | AR113: 3146 | AS113: 3171 | AT113: 3198 | AU113: 3162 | AV113: 3230 | AW113: 3245 | AX113: 3307 | AY113: 3327 | AZ113: 3355 | BA113: 3285 | BB113: 3283 | BC113: 3330 | BD113: 3413 | BE113: 3438 | BF113: 3396 | BG113: 3317 | BH113: 3307 | BI113: 3348 | BJ113: 3310 | BK113: 3079 | BL113: 3091 | BM113: 3172 | BN113: 3114 | BO113: 3161 | BP113: 3183 | BQ113: 3054 | BR113: 3045 | BS113: 3080 | BT113: 3108 | BU113: 3092 | BV113: 3153 | BW113: 3168 | BX113: 3261 | BY113: 3309 | BZ113: 3236 | CA113: 3276 | CB113: 3258 | CC113: 3083 | CD113: 3026 | CE113: 2975 | CF113: 2964.5 | CG113: 3053 | CH113: 3131 | CI113: 3023 | CJ113: 3008 | CK113: 2997.5 | CL113: 2901 | CM113: 2988 | CN113: 2866.5 | CO113: 2796.5 | CP113: 2863.5 | CQ113: 2837.5 | CR113: 2860.5 | CS113: 2840.5 | CT113: 2758 | CU113: 2827.5 | CV113: 2927.5 | CW113: 2835.5 | CX113: 2827.5 | CY113: 2810 | CZ113: 2860.5 | DA113: 2878.5 | DB113: 2894.5 | DC113: 2874 | DD113: 2908 | DE113: 2818 | DF113: 2783 | DG113: 2848 | DH113: 2939 | DI113: 2997 | DJ113: 2960 | DK113: 2839.5 | DL113: 2816 | DM113: 2930 | DN113: 3057 | DO113: 3048 | DP113: 3046 | DQ113: 3111 | DR113: 3158 | DS113: 3676 | DT113: 3687 | DU113: 3588 | DV113: 3550 | DW113: 3642 | DX113: 3654 | DY113: 3818 | DZ113: 3799 | EA113: 3851 | EB113: 3823 | EC113: 3849 | ED113: 3933 | EE113: 3951 | EF113: 4050 | EG113: 3957 | EH113: 3983 | EI113: 4050 | EJ113: 4073 | EK113: 4088 | EL113: 4100 | EM113: 4055 | EN113: 4008 | EO113: 3995 | EP113: 3995 | EQ113: 4032 | ER113: 4047 | ES113: 3901 | ET113: 3918 | EU113: 4044 | EV113: 4005 | EW113: 3971 | EX113: 3929 | EY113: 3961 | EZ113: 3964 | FA113: 3923 | FB113: 3829 | FC113: 3838 | FD113: 3795 | FE113: 3880 | FF113: 3884 | FG113: 3805 | FH113: 3898 | FI113: 3882 | FJ113: 3910 | FK113: 3876 | FL113: 3922 | FM113: 3872 | FN113: 3930 | FO113: 3960 | FP113: 4011 | FQ113: 4061 | FR113: 4027 | FS113: 3584 | FT113: 3613 | FU113: 3472 | FV113: 3433 | FW113: 3416 | FX113: 3540 | FY113: 3602 | FZ113: 3444 | GA113: 3485 | GB113: 3454 | GC113: 3456 | GD113: 3389 | GE113: 3370 | GF113: 3403 | GG113: 3420 | GH113: 3451 | GI113: 3400 | GJ113: 3392 | GK113: 3455 | GL113: 3540 | GM113: 3499 | GN113: 3485 | GO113: 3524 | GP113: 3483 | GQ113: 3435 | GR113: 3376 | GS113: 3415 | GT113: 3451 | GU113: 3447 | GV113: 3490 | GW113: 3493 | GX113: 3524 | GY113: 3511 | GZ113: 3530 | HA113: 3460 | HB113: 3392 | HC113: 3519 | HD113: 3620 | HE113: 3640 | HF113: 3692 | HG113: 3700 | HH113: 3691 | HI113: 3760 | HJ113: 3816 | HK113: 3895 | HL113: 3914 | HM113: 3867 | HN113: 3959 | HO113: 3892 | HP113: 3909 | HQ113: 3855 | HR113: 3880 | HS113: 3839 | HT113: 3935 | HU113: 3863 | HV113: 3928 | HW113: 3931 | HX113: 3955 | HY113: 3925 | HZ113: 3938 | IA113: 3958 | IB113: 3870 | IC113: 3903 | ID113: 3904 | IE113: 3812 | IF113: 3825 | IG113: 3869 | IH113: 3809 | II113: 3786 | IJ113: 3820 | IK113: 3969 | IL113: 3964 | IM113: 3958 | IN113: 3931 | IO113: 3866 | IP113: 3818 | IQ113: 3786 | IR113: 3894 | IS113: 3684 | IT113: 3633
A114: 9501 | B114: 東京電力ＨＤ | C114: 526.4 | D114: -10.6 | E114: 537 | F114: 526 | G114: 522.8 | H114: 526.1 | I114: 520 | J114: 524 | K114: 533.7 | L114: 523.6 | M114: 537 | N114: 516.7 | O114: 516.6 | P114: 505.3 | Q114: 503.4 | R114: 506.6 | S114: 501.6 | T114: 508.7 | U114: 503.1 | V114: 485.3 | W114: 480.4 | X114: 479.1 | Y114: 479.9 | Z114: 462.3 | AA114: 468.8 | AB114: 465 | AC114: 457.4 | AD114: 455.1 | AE114: 461.3 | AF114: 462 | AG114: 456.6 | AH114: 481.2 | AI114: 470.7 | AJ114: 470.6 | AK114: 477.5 | AL114: 514 | AM114: 510.3 | AN114: 508.1 | AO114: 513.5 | AP114: 531.3 | AQ114: 509.3 | AR114: 494.8 | AS114: 512.2 | AT114: 519.2 | AU114: 535.4 | AV114: 528.4 | AW114: 541 | AX114: 572.9 | AY114: 560 | AZ114: 558.9 | BA114: 564.7 | BB114: 557.3 | BC114: 572.3 | BD114: 576.6 | BE114: 567.2 | BF114: 549 | BG114: 557.4 | BH114: 547.9 | BI114: 580.7 | BJ114: 558.5 | BK114: 592.7 | BL114: 609 | BM114: 612.6 | BN114: 645.2 | BO114: 651.1 | BP114: 632.8 | BQ114: 624 | BR114: 612.7 | BS114: 592.2 | BT114: 611.1 | BU114: 580.5 | BV114: 584.7 | BW114: 584.8 | BX114: 625.3 | BY114: 603.2 | BZ114: 611.5 | CA114: 624 | CB114: 638 | CC114: 632.5 | CD114: 650 | CE114: 651.3 | CF114: 665.1 | CG114: 657.3 | CH114: 640.4 | CI114: 624.1 | CJ114: 636.3 | CK114: 646 | CL114: 648.3 | CM114: 661.3 | CN114: 638.9 | CO114: 634.5 | CP114: 635.2 | CQ114: 623.4 | CR114: 636.6 | CS114: 626.3 | CT114: 617.3 | CU114: 653.4 | CV114: 713.4 | CW114: 613.4 | CX114: 610 | CY114: 640.5 | CZ114: 645 | DA114: 624 | DB114: 599.5 | DC114: 598.2 | DD114: 642.7 | DE114: 650.1 | DF114: 637.6 | DG114: 637.4 | DH114: 667.8 | DI114: 700.4 | DJ114: 675.2 | DK114: 689 | DL114: 686.1 | DM114: 703.3 | DN114: 715 | DO114: 713.7 | DP114: 701 | DQ114: 703.9 | DR114: 690.3 | DS114: 666.9 | DT114: 635.4 | DU114: 636.6 | DV114: 634 | DW114: 592.1 | DX114: 610 | DY114: 592.1 | DZ114: 581.1 | EA114: 580.9 | EB114: 570.5 | EC114: 557.4 | ED114: 609.6 | EE114: 662 | EF114: 688 | EG114: 695.5 | EH114: 720.6 | EI114: 685.5 | EJ114: 694.1 | EK114: 681.5 | EL114: 705 | EM114: 717.8 | EN114: 722 | EO114: 718 | EP114: 727.3 | EQ114: 704.7 | ER114: 760 | ES114: 718 | ET114: 657.3 | EU114: 650 | EV114: 645.8 | EW114: 659 | EX114: 652.3 | EY114: 665 | EZ114: 649.5 | FA114: 636.5 | FB114: 642.1 | FC114: 626 | FD114: 636.9 | FE114: 657.1 | FF114: 661 | FG114: 626.3 | FH114: 648 | FI114: 640.4 | FJ114: 627.5 | FK114: 644.6 | FL114: 655.6 | FM114: 659.5 | FN114: 668.2 | FO114: 716 | FP114: 793 | FQ114: 791.3 | FR114: 800.6 | FS114: 765.5 | FT114: 817.9 | FU114: 834 | FV114: 868 | FW114: 880.6 | FX114: 900 | FY114: 878 | FZ114: 934.1 | GA114: 880 | GB114: 868 | GC114: 855 | GD114: 844 | GE114: 841.5 | GF114: 818.5 | GG114: 764.7 | GH114: 772.1 | GI114: 748.2 | GJ114: 705.9 | GK114: 723 | GL114: 747.9 | GM114: 748.9 | GN114: 769.8 | GO114: 783 | GP114: 790.6 | GQ114: 811.4 | GR114: 790 | GS114: 822.3 | GT114: 782.5 | GU114: 749.4 | GV114: 763.5 | GW114: 796.5 | GX114: 759 | GY114: 743.7 | GZ114: 723.6 | HA114: 697.5 | HB114: 643.1 | HC114: 698 | HD114: 694.2 | HE114: 682.2 | HF114: 679.6 | HG114: 660.7 | HH114: 627.8 | HI114: 659.9 | HJ114: 685.6 | HK114: 652.7 | HL114: 707 | HM114: 739 | HN114: 749.5 | HO114: 759.9 | HP114: 750 | HQ114: 754.2 | HR114: 761.5 | HS114: 731.2 | HT114: 738.5 | HU114: 716.4 | HV114: 770.2 | HW114: 760.7 | HX114: 755.1 | HY114: 748.9 | HZ114: 730.1 | IA114: 705.2 | IB114: 746.1 | IC114: 761.8 | ID114: 748.7 | IE114: 735.7 | IF114: 739.4 | IG114: 713.3 | IH114: 740 | II114: 723.9 | IJ114: 716.3 | IK114: 668.6 | IL114: 666 | IM114: 647.9 | IN114: 630 | IO114: 618.5 | IP114: 584.7 | IQ114: 595 | IR114: 575 | IS114: 590.1 | IT114: 582.1
A115: 9531 | B115: 東京瓦斯 | C115: 5979 | D115: 12 | E115: 5967 | F115: 5937 | G115: 6038 | H115: 6181 | I115: 6219 | J115: 6263 | K115: 6290 | L115: 6235 | M115: 6273 | N115: 6226 | O115: 6160 | P115: 6151 | Q115: 6127 | R115: 6087 | S115: 6066 | T115: 6072 | U115: 6030 | V115: 5905 | W115: 5966 | X115: 6089 | Y115: 6143 | Z115: 6120 | AA115: 6156 | AB115: 6037 | AC115: 6006 | AD115: 5987 | AE115: 6121 | AF115: 6163 | AG115: 6111 | AH115: 6068 | AI115: 6110 | AJ115: 6138 | AK115: 6210 | AL115: 6178 | AM115: 6174 | AN115: 6151 | AO115: 6223 | AP115: 6261 | AQ115: 6303 | AR115: 6395 | AS115: 6305 | AT115: 6349 | AU115: 6311 | AV115: 6190 | AW115: 6219 | AX115: 6292 | AY115: 6220 | AZ115: 6175 | BA115: 6380 | BB115: 6294 | BC115: 6471 | BD115: 6480 | BE115: 6436 | BF115: 6522 | BG115: 6656 | BH115: 6639 | BI115: 6699 | BJ115: 6565 | BK115: 6722 | BL115: 6625 | BM115: 6607 | BN115: 6670 | BO115: 6745 | BP115: 6600 | BQ115: 6812 | BR115: 6614 | BS115: 6670 | BT115: 6937 | BU115: 6473 | BV115: 6454 | BW115: 6471 | BX115: 6487 | BY115: 6596 | BZ115: 6644 | CA115: 6914 | CB115: 7117 | CC115: 6955 | CD115: 7007 | CE115: 7072 | CF115: 7286 | CG115: 7297 | CH115: 7302 | CI115: 7369 | CJ115: 7224 | CK115: 7356 | CL115: 7297 | CM115: 7645 | CN115: 7417 | CO115: 7604 | CP115: 7757 | CQ115: 7636 | CR115: 7544 | CS115: 7260 | CT115: 7080 | CU115: 7319 | CV115: 7687 | CW115: 7538 | CX115: 7459 | CY115: 7584 | CZ115: 7655 | DA115: 7657 | DB115: 7447 | DC115: 7454 | DD115: 7816 | DE115: 7783 | DF115: 7684 | DG115: 7861 | DH115: 7689 | DI115: 7656 | DJ115: 7637 | DK115: 7598 | DL115: 7625 | DM115: 7575 | DN115: 7639 | DO115: 7551 | DP115: 7541 | DQ115: 7440 | DR115: 7769 | DS115: 7780 | DT115: 7721 | DU115: 7568 | DV115: 7236 | DW115: 7282 | DX115: 7294 | DY115: 7141 | DZ115: 7018 | EA115: 6846 | EB115: 6719 | EC115: 6654 | ED115: 6584 | EE115: 6705 | EF115: 6752 | EG115: 6706 | EH115: 6560 | EI115: 6554 | EJ115: 6580 | EK115: 6544 | EL115: 6514 | EM115: 6503 | EN115: 6396 | EO115: 6238 | EP115: 6232 | EQ115: 6163 | ER115: 6326 | ES115: 6259 | ET115: 6205 | EU115: 6164 | EV115: 6198 | EW115: 6161 | EX115: 6189 | EY115: 6220 | EZ115: 6206 | FA115: 6415 | FB115: 6356 | FC115: 6275 | FD115: 6205 | FE115: 6370 | FF115: 6273 | FG115: 6197 | FH115: 6216 | FI115: 6114 | FJ115: 6013 | FK115: 5907 | FL115: 6030 | FM115: 6001 | FN115: 6130 | FO115: 6178 | FP115: 6332 | FQ115: 6423 | FR115: 6459 | FS115: 6189 | FT115: 6081 | FU115: 6060 | FV115: 5942 | FW115: 5933 | FX115: 6147 | FY115: 6077 | FZ115: 6106 | GA115: 5889 | GB115: 5936 | GC115: 5820 | GD115: 5663 | GE115: 5743 | GF115: 5653 | GG115: 5620 | GH115: 5402 | GI115: 5324 | GJ115: 5363 | GK115: 5380 | GL115: 5344 | GM115: 5274 | GN115: 5313 | GO115: 5264 | GP115: 5235 | GQ115: 5232 | GR115: 5199 | GS115: 5332 | GT115: 5285 | GU115: 5255 | GV115: 5261 | GW115: 5335 | GX115: 5377 | GY115: 5190 | GZ115: 5185 | HA115: 5153 | HB115: 5111 | HC115: 5119 | HD115: 5264 | HE115: 5321 | HF115: 5390 | HG115: 5429 | HH115: 5364 | HI115: 5338 | HJ115: 5389 | HK115: 5431 | HL115: 5727 | HM115: 5849 | HN115: 5780 | HO115: 5792 | HP115: 5756 | HQ115: 5671 | HR115: 5715 | HS115: 5723 | HT115: 5757 | HU115: 5733 | HV115: 5817 | HW115: 5740 | HX115: 5632 | HY115: 5733 | HZ115: 5697 | IA115: 5637 | IB115: 5694 | IC115: 5814 | ID115: 5719 | IE115: 5735 | IF115: 5616 | IG115: 5724 | IH115: 5696 | II115: 5640 | IJ115: 5602 | IK115: 5623 | IL115: 5535 | IM115: 5551 | IN115: 5453 | IO115: 5359 | IP115: 5317 | IQ115: 5321 | IR115: 5049 | IS115: 5008 | IT115: 4880
A116: 9882 | B116: イエローハット | C116: 1741 | D116: 3 | E116: 1738 | F116: 1714 | G116: 1720 | H116: 1745 | I116: 1809 | J116: 1870 | K116: 1881 | L116: 1845 | M116: 1829 | N116: 1787 | O116: 1788 | P116: 1803 | Q116: 1825 | R116: 1821 | S116: 1827 | T116: 1812 | U116: 1817 | V116: 1813 | W116: 1820 | X116: 1827 | Y116: 1849 | Z116: 1815 | AA116: 1817 | AB116: 1780 | AC116: 1765 | AD116: 1741 | AE116: 1760 | AF116: 1772 | AG116: 1763 | AH116: 1763 | AI116: 1749 | AJ116: 1745 | AK116: 1752 | AL116: 1773 | AM116: 1745 | AN116: 1736 | AO116: 1743 | AP116: 1732 | AQ116: 1733 | AR116: 1727 | AS116: 1709 | AT116: 1683 | AU116: 1674 | AV116: 1663 | AW116: 1652 | AX116: 1687 | AY116: 1634 | AZ116: 1621 | BA116: 1655 | BB116: 1627 | BC116: 1625 | BD116: 1626 | BE116: 1616 | BF116: 1630 | BG116: 1631 | BH116: 1620 | BI116: 1634 | BJ116: 1621 | BK116: 1637 | BL116: 1595 | BM116: 1613 | BN116: 1633 | BO116: 1650 | BP116: 1497 | BQ116: 1503 | BR116: 1506 | BS116: 1517 | BT116: 1515 | BU116: 1507 | BV116: 1520 | BW116: 1533 | BX116: 1539 | BY116: 1566 | BZ116: 1562 | CA116: 1561 | CB116: 1550 | CC116: 1553 | CD116: 1562 | CE116: 1575 | CF116: 1596 | CG116: 1597 | CH116: 1627 | CI116: 1605 | CJ116: 1568 | CK116: 1546 | CL116: 1557 | CM116: 1567 | CN116: 1545 | CO116: 1538 | CP116: 1595 | CQ116: 1586 | CR116: 1580 | CS116: 1556 | CT116: 1523 | CU116: 1542 | CV116: 1598 | CW116: 1581 | CX116: 1575 | CY116: 1580 | CZ116: 1611 | DA116: 1650 | DB116: 1657 | DC116: 1646 | DD116: 1672 | DE116: 1680 | DF116: 1655 | DG116: 1694 | DH116: 1746 | DI116: 1759 | DJ116: 1733 | DK116: 1736 | DL116: 1732 | DM116: 1717 | DN116: 1719 | DO116: 1710 | DP116: 1670 | DQ116: 1695 | DR116: 1679 | DS116: 1693 | DT116: 1659 | DU116: 1660 | DV116: 1651 | DW116: 1643 | DX116: 1640 | DY116: 1626 | DZ116: 1616 | EA116: 1687 | EB116: 1683 | EC116: 1673 | ED116: 1701 | EE116: 1699 | EF116: 1710 | EG116: 1698 | EH116: 1670 | EI116: 1674 | EJ116: 1662 | EK116: 1643 | EL116: 1647 | EM116: 1649 | EN116: 1655 | EO116: 1664 | EP116: 1654 | EQ116: 1647 | ER116: 1647 | ES116: 1650 | ET116: 1640 | EU116: 1653 | EV116: 1653 | EW116: 1642 | EX116: 1644 | EY116: 1673 | EZ116: 1656 | FA116: 1665 | FB116: 1659 | FC116: 1632 | FD116: 1626 | FE116: 1648 | FF116: 1634 | FG116: 1606 | FH116: 1601 | FI116: 1604 | FJ116: 1616 | FK116: 1613 | FL116: 1639 | FM116: 1614 | FN116: 1636 | FO116: 1637 | FP116: 1668 | FQ116: 1660 | FR116: 1643 | FS116: 1642 | FT116: 1652 | FU116: 1606 | FV116: 1581 | FW116: 1568 | FX116: 1589 | FY116: 1575 | FZ116: 1560 | GA116: 1549 | GB116: 1535 | GC116: 1550 | GD116: 1510 | GE116: 1484 | GF116: 1476 | GG116: 1455 | GH116: 1554 | GI116: 1587 | GJ116: 1569 | GK116: 1595 | GL116: 1638 | GM116: 1633 | GN116: 1664 | GO116: 1634 | GP116: 1608 | GQ116: 1608 | GR116: 1588 | GS116: 1606 | GT116: 1613 | GU116: 1591 | GV116: 1586 | GW116: 1608 | GX116: 1627 | GY116: 1627 | GZ116: 1616 | HA116: 1601 | HB116: 1587 | HC116: 1603 | HD116: 1690 | HE116: 1746 | HF116: 1735 | HG116: 1695 | HH116: 1693 | HI116: 1699 | HJ116: 1715 | HK116: 1725 | HL116: 1714 | HM116: 1723 | HN116: 1707 | HO116: 1707 | HP116: 1715 | HQ116: 1717 | HR116: 1730 | HS116: 1708 | HT116: 1670 | HU116: 1664 | HV116: 1641 | HW116: 1643 | HX116: 1657 | HY116: 1672 | HZ116: 1650 | IA116: 1653 | IB116: 1648 | IC116: 1666 | ID116: 1667 | IE116: 1672 | IF116: 1661 | IG116: 1640 | IH116: 1656 | II116: 1616 | IJ116: 1630 | IK116: 1620 | IL116: 1618 | IM116: 1609 | IN116: 1591 | IO116: 1533 | IP116: 1525 | IQ116: 1527 | IR116: 1595 | IS116: 1586 | IT116: 1591
A117: 5838 | B117: 楽天銀行 | C117: 5664 | D117: 144 | E117: 5520 | F117: 5552 | G117: 5406 | H117: 5304 | I117: 5473 | J117: 5312 | K117: 5447 | L117: 5559 | M117: 5648 | N117: 5576 | O117: 5714 | P117: 5486 | Q117: 5340 | R117: 5221 | S117: 5553 | T117: 5680 | U117: 5800 | V117: 5809 | W117: 5735 | X117: 5712 | Y117: 5787 | Z117: 5646 | AA117: 5425 | AB117: 5395 | AC117: 5328 | AD117: 5123 | AE117: 5170 | AF117: 5097 | AG117: 5039 | AH117: 5000 | AI117: 5000 | AJ117: 5020 | AK117: 5037 | AL117: 5124 | AM117: 5299 | AN117: 5161 | AO117: 5244 | AP117: 5119 | AQ117: 5260 | AR117: 5104 | AS117: 4762 | AT117: 5113 | AU117: 4869 | AV117: 4950 | AW117: 4955 | AX117: 4899 | AY117: 4562 | AZ117: 4498 | BA117: 4653 | BB117: 4793 | BC117: 4798 | BD117: 4996 | BE117: 5096 | BF117: 4847 | BG117: 5480 | BH117: 6480 | BI117: 6767 | BJ117: 6601 | BK117: 6000 | BL117: 6039 | BM117: 6156 | BN117: 6422 | BO117: 6267 | BP117: 6291 | BQ117: 6294 | BR117: 6238 | BS117: 6305 | BT117: 6415 | BU117: 6132 | BV117: 6156 | BW117: 6250 | BX117: 6131 | BY117: 6431 | BZ117: 6549 | CA117: 6552 | CB117: 6750 | CC117: 6795 | CD117: 6759 | CE117: 6700 | CF117: 6700 | CG117: 6700 | CH117: 6548 | CI117: 6231 | CJ117: 6065 | CK117: 6009 | CL117: 6002 | CM117: 6105 | CN117: 5640 | CO117: 5788 | CP117: 6065 | CQ117: 6022 | CR117: 6236 | CS117: 6181 | CT117: 6088 | CU117: 6136 | CV117: 6203 | CW117: 6042 | CX117: 6100 | CY117: 6133 | CZ117: 6050 | DA117: 6088 | DB117: 6259 | DC117: 6090 | DD117: 6017 | DE117: 6047 | DF117: 5585 | DG117: 5948 | DH117: 6235 | DI117: 6363 | DJ117: 6878 | DK117: 7958 | DL117: 8367 | DM117: 8962 | DN117: 9087 | DO117: 8789 | DP117: 8440 | DQ117: 8716 | DR117: 8518 | DS117: 8922 | DT117: 8400 | DU117: 7678 | DV117: 7727 | DW117: 7632 | DX117: 7501 | DY117: 7304 | DZ117: 7061 | EA117: 7364 | EB117: 7109 | EC117: 7181 | ED117: 6878 | EE117: 6723 | EF117: 7133 | EG117: 6936 | EH117: 7141 | EI117: 7377 | EJ117: 7315 | EK117: 7042 | EL117: 7102 | EM117: 6848 | EN117: 6892 | EO117: 6710 | EP117: 6685 | EQ117: 6780 | ER117: 6974 | ES117: 6971 | ET117: 6912 | EU117: 7036 | EV117: 6903 | EW117: 6944 | EX117: 7006 | EY117: 7018 | EZ117: 6982 | FA117: 7049 | FB117: 6850 | FC117: 7006 | FD117: 7197 | FE117: 7253 | FF117: 7009 | FG117: 6929 | FH117: 7374 | FI117: 7326 | FJ117: 7452 | FK117: 7544 | FL117: 7294 | FM117: 7127 | FN117: 7206 | FO117: 7409 | FP117: 7412 | FQ117: 7328 | FR117: 7165 | FS117: 6800 | FT117: 6758 | FU117: 6733 | FV117: 6560 | FW117: 6925 | FX117: 7452 | FY117: 7605 | FZ117: 7615 | GA117: 7654 | GB117: 8080 | GC117: 8003 | GD117: 8084 | GE117: 8172 | GF117: 8133 | GG117: 8371 | GH117: 8485 | GI117: 8569 | GJ117: 8304 | GK117: 8277 | GL117: 8203 | GM117: 8126 | GN117: 8204 | GO117: 8372 | GP117: 8500 | GQ117: 8178 | GR117: 7779 | GS117: 8025 | GT117: 7945 | GU117: 7815 | GV117: 8075 | GW117: 8269 | GX117: 8223 | GY117: 7718 | GZ117: 7900 | HA117: 8368 | HB117: 8009 | HC117: 8010 | HD117: 8269 | HE117: 8259 | HF117: 8140 | HG117: 8088 | HH117: 7939 | HI117: 7998 | HJ117: 7610 | HK117: 7615 | HL117: 7601 | HM117: 7807 | HN117: 7665 | HO117: 7630 | HP117: 7948 | HQ117: 7660 | HR117: 7774 | HS117: 7926 | HT117: 8051 | HU117: 7942 | HV117: 8333 | HW117: 8280 | HX117: 8398 | HY117: 8426 | HZ117: 8170 | IA117: 8331 | IB117: 8344 | IC117: 8155 | ID117: 8326 | IE117: 8098 | IF117: 8022 | IG117: 8780 | IH117: 8626 | II117: 8572 | IJ117: 8285 | IK117: 7977 | IL117: 7475 | IM117: 7200 | IN117: 6635 | IO117: 6730 | IP117: 6678 | IQ117: 6933 | IR117: 7080 | IS117: 6998 | IT117: 6924
A118: 5844 | B118: 京都フィナンシャルＧ | C118: 4632 | D118: 2 | E118: 4630 | F118: 4677 | G118: 4574 | H118: 4490 | I118: 4437 | J118: 4473 | K118: 4533 | L118: 4603 | M118: 4687 | N118: 4634 | O118: 4665 | P118: 4618 | Q118: 4500 | R118: 4384 | S118: 4649 | T118: 4770 | U118: 4700 | V118: 4660 | W118: 4654 | X118: 4782 | Y118: 4758 | Z118: 4719 | AA118: 4805 | AB118: 4710 | AC118: 4643 | AD118: 4573 | AE118: 4494 | AF118: 4511 | AG118: 4477 | AH118: 4532 | AI118: 4540 | AJ118: 4628 | AK118: 4821 | AL118: 4726 | AM118: 4658 | AN118: 4535 | AO118: 4656 | AP118: 4500 | AQ118: 4462 | AR118: 4442 | AS118: 4494 | AT118: 4690 | AU118: 4575 | AV118: 4622 | AW118: 4482 | AX118: 4347 | AY118: 4373 | AZ118: 4341 | BA118: 4419 | BB118: 4420 | BC118: 4502 | BD118: 4530 | BE118: 4575 | BF118: 4479 | BG118: 4495 | BH118: 4385 | BI118: 4407 | BJ118: 4374 | BK118: 4413 | BL118: 4400 | BM118: 4484 | BN118: 4419 | BO118: 4401 | BP118: 4395 | BQ118: 4499 | BR118: 4373 | BS118: 4336 | BT118: 4352 | BU118: 4200 | BV118: 4295 | BW118: 4264 | BX118: 4258 | BY118: 4333 | BZ118: 4307 | CA118: 4393 | CB118: 4421 | CC118: 4393 | CD118: 4336 | CE118: 4373 | CF118: 4330 | CG118: 4412 | CH118: 4490 | CI118: 4410 | CJ118: 4388 | CK118: 4337 | CL118: 4283 | CM118: 4376 | CN118: 4061 | CO118: 4210 | CP118: 4477 | CQ118: 4385 | CR118: 4403 | CS118: 4289 | CT118: 4294 | CU118: 4396 | CV118: 4400 | CW118: 4309 | CX118: 4374 | CY118: 4468 | CZ118: 4352 | DA118: 4051 | DB118: 4027 | DC118: 3951 | DD118: 4169 | DE118: 3988 | DF118: 3708 | DG118: 3920 | DH118: 3832 | DI118: 3877 | DJ118: 3538 | DK118: 3471 | DL118: 3562 | DM118: 3698 | DN118: 3733 | DO118: 3679 | DP118: 3625 | DQ118: 3780 | DR118: 3878 | DS118: 3983 | DT118: 3957 | DU118: 3938 | DV118: 3826 | DW118: 3822 | DX118: 3843 | DY118: 3791 | DZ118: 3726 | EA118: 3727 | EB118: 3727 | EC118: 3678 | ED118: 3725 | EE118: 3693 | EF118: 3772 | EG118: 3690 | EH118: 3588 | EI118: 3637 | EJ118: 3672 | EK118: 3694 | EL118: 3616 | EM118: 3568 | EN118: 3566 | EO118: 3511 | EP118: 3475 | EQ118: 3532 | ER118: 3539 | ES118: 3470 | ET118: 3427 | EU118: 3468 | EV118: 3436 | EW118: 3435 | EX118: 3443 | EY118: 3439 | EZ118: 3451 | FA118: 3471 | FB118: 3375 | FC118: 3334 | FD118: 3385 | FE118: 3521 | FF118: 3444 | FG118: 3357 | FH118: 3427 | FI118: 3397 | FJ118: 3405 | FK118: 3413 | FL118: 3427 | FM118: 3324 | FN118: 3361 | FO118: 3387 | FP118: 3400 | FQ118: 3340 | FR118: 3332 | FS118: 3259 | FT118: 3238 | FU118: 3232 | FV118: 3200 | FW118: 3207 | FX118: 3365 | FY118: 3252 | FZ118: 3325 | GA118: 3271 | GB118: 3204 | GC118: 3205 | GD118: 3187 | GE118: 3276 | GF118: 3196 | GG118: 3177 | GH118: 3124 | GI118: 3113 | GJ118: 3019 | GK118: 3115 | GL118: 3252 | GM118: 3127 | GN118: 3145 | GO118: 3141 | GP118: 3117 | GQ118: 3108 | GR118: 2998 | GS118: 3063 | GT118: 3061 | GU118: 3014 | GV118: 3057 | GW118: 3177 | GX118: 3144 | GY118: 3149 | GZ118: 3134 | HA118: 3140 | HB118: 3103 | HC118: 3122 | HD118: 3146 | HE118: 3114 | HF118: 3223 | HG118: 3080 | HH118: 3047 | HI118: 3084 | HJ118: 3040 | HK118: 3015 | HL118: 2993 | HM118: 2986.5 | HN118: 2949 | HO118: 2937 | HP118: 2992 | HQ118: 2927 | HR118: 2907.5 | HS118: 2903 | HT118: 2872.5 | HU118: 2878.5 | HV118: 2960 | HW118: 2910.5 | HX118: 2936.5 | HY118: 2942 | HZ118: 2898.5 | IA118: 2906.5 | IB118: 2940 | IC118: 2938.5 | ID118: 2873.5 | IE118: 2887.5 | IF118: 2863 | IG118: 2870 | IH118: 2914.5 | II118: 2827 | IJ118: 2821.5 | IK118: 2839 | IL118: 2792.5 | IM118: 2759 | IN118: 2734 | IO118: 2728 | IP118: 2675 | IQ118: 2706 | IR118: 2743 | IS118: 2710 | IT118: 2709.5
... A138: 3103 | B138: ユニチカ | C138: 1051 | D138: -207 | E138: 1258 | F138: 1009 | G138: 876 | H138: 838 | I138: 830 | J138: 774 | K138: 762 | L138: 826 | M138: 859 | N138: 836 | O138: 890 | P138: 906 | Q138: 884 | R138: 850 | S138: 945 | T138: 971 | U138: 912 | V138: 879 | W138: 934 | X138: 930 | Y138: 940 | Z138: 982 | AA138: 1004 | AB138: 1031 | AC138: 1001 | AD138: 1006 | AE138: 1034 | AF138: 1035 | AG138: 1032 | AH138: 1070 | AI138: 1046 | AJ138: 1111 | AK138: 1220 | AL138: 1107 | AM138: 1168 | AN138: 1236 | AO138: 1129 | AP138: 1145 | AQ138: 1150 | AR138: 1133 | AS138: 1216 | AT138: 1264 | AU138: 1196 | AV138: 1227 | AW138: 1187 | AX138: 1265 | AY138: 1223 | AZ138: 1312 | BA138: 1411 | BB138: 1385 | BC138: 1440 | BD138: 1506 | BE138: 1575 | BF138: 1574 | BG138: 1274 | BH138: 1284 | BI138: 1412 | BJ138: 1315 | BK138: 1415 | BL138: 1815 | BM138: 2315 | BN138: 2261 | BO138: 2308 | BP138: 2569 | BQ138: 2535 | BR138: 2382 | BS138: 2438 | BT138: 2234 | BU138: 2482 | BV138: 2565 | BW138: 2851 | BX138: 2835 | BY138: 3045 | BZ138: 3745 | CA138: 3085 | CB138: 2581 | CC138: 2081 | CD138: 2163 | CE138: 1763 | CF138: 1463 | CG138: 1163 | CH138: 1152 | CI138: 1046 | CJ138: 1081 | CK138: 1113 | CL138: 1194 | CM138: 1228 | CN138: 1147 | CO138: 1215 | CP138: 1189 | CQ138: 1145 | CR138: 1397 | CS138: 1317 | CT138: 1327 | CU138: 1490 | CV138: 1549 | CW138: 1249 | CX138: 1295 | CY138: 1336 | CZ138: 1299 | DA138: 1436 | DB138: 1486 | DC138: 1512 | DD138: 1661 | DE138: 1722 | DF138: 1765 | DG138: 1649 | DH138: 1951 | DI138: 1918 | DJ138: 1617 | DK138: 1428 | DL138: 1377 | DM138: 1236 | DN138: 1296 | DO138: 1692 | DP138: 2192 | DQ138: 1792 | DR138: 1492 | DS138: 1372 | DT138: 1072 | DU138: 922 | DV138: 772 | DW138: 672 | DX138: 716 | DY138: 667 | DZ138: 582 | EA138: 629 | EB138: 529 | EC138: 564 | ED138: 484 | EE138: 404 | EF138: 390 | EG138: 356 | EH138: 364 | EI138: 347 | EJ138: 380 | EK138: 391 | EL138: 399 | EM138: 379 | EN138: 342 | EO138: 330 | EP138: 316 | EQ138: 311 | ER138: 296 | ES138: 291 | ET138: 289 | EU138: 293 | EV138: 277 | EW138: 274 | EX138: 260 | EY138: 261 | EZ138: 258 | FA138: 257 | FB138: 255 | FC138: 255 | FD138: 256 | FE138: 269 | FF138: 257 | FG138: 253 | FH138: 260 | FI138: 256 | FJ138: 272 | FK138: 281 | FL138: 295 | FM138: 288 | FN138: 292 | FO138: 325 | FP138: 369 | FQ138: 345 | FR138: 326 | FS138: 313 | FT138: 304 | FU138: 277 | FV138: 283 | FW138: 269 | FX138: 270 | FY138: 273 | FZ138: 267 | GA138: 275 | GB138: 247 | GC138: 197 | GD138: 193 | GE138: 192 | GF138: 189 | GG138: 195 | GH138: 199 | GI138: 200 | GJ138: 201 | GK138: 199 | GL138: 207 | GM138: 202 | GN138: 203 | GO138: 206 | GP138: 202 | GQ138: 203 | GR138: 196 | GS138: 202 | GT138: 197 | GU138: 195 | GV138: 201 | GW138: 204 | GX138: 204 | GY138: 209 | GZ138: 216 | HA138: 209 | HB138: 203 | HC138: 202 | HD138: 211 | HE138: 211 | HF138: 212 | HG138: 206 | HH138: 204 | HI138: 209 | HJ138: 212 | HK138: 213 | HL138: 214 | HM138: 213 | HN138: 221 | HO138: 222 | HP138: 223 | HQ138: 223 | HR138: 217 | HS138: 214 | HT138: 206 | HU138: 205 | HV138: 207 | HW138: 208 | HX138: 216 | HY138: 213 | HZ138: 222 | IA138: 224 | IB138: 237 | IC138: 234 | ID138: 217 | IE138: 200 | IF138: 205 | IG138: 211 | IH138: 216 | II138: 213 | IJ138: 209 | IK138: 207 | IL138: 199 | IM138: 197 | IN138: 210 | IO138: 184 | IP138: 180 | IQ138: 179 | IR138: 180 | IS138: 184 | IT138: 181
